Workbook

Sheet README
A1: Dissertation data compilation
A2: Capital Requirements and Credit Supply: The Effect of the RBI's November 2023 Risk-Weight Measures on Bank Consumer Credit and Bank Funding of NBFCs in India, 2021–2026
A4: Sheet | B4: Contents | C4: Frequency / coverage | D4: Source
A5: RBI_Levels | B5: Outstanding bank credit by sector (₹ crore): non-food credit, NBFCs, HFCs, housing, credit cards, education, vehicle loans, gold loans, other personal loans; NBFCs excl. HFCs and the alternative H2 benchmark by formula | C5: Monthly, Jan 2019 to Jul 2026 (91 observations) | D5: RBI DBIE Table 15
A6: RBI_Levels_ExMerger | B6: The same series excluding the impact of the HDFC merger, as published by the RBI | C6: Monthly, Jul 2023 to Jun 2025 | D6: RBI DBIE Table 15 (figures in parentheses)
A7: RBI_Growth | B7: Monthly growth (100 × log change) of each series and the growth gaps used for H1 and H2, with window, post-policy and period flags (all formulas) | C7: Monthly | D7: Calculated
A8: Share_Prices | B8: Daily closing prices of the 16 sample companies and the Nifty 50 and Nifty 500 | C8: Daily, 1 Sep 2022 to 28 Mar 2025 (641 trading days) | D8: Investing.com
A9: Share_Returns | B9: Daily simple returns (formulas) | C9: Daily | D9: Calculated
A10: Firm_Sample | B10: Company list, NSE symbol, type, groups used in the tests and pre-policy bank dependence | C10: 30 Sep 2023 | D10: Q2 FY2024 investor presentations
A11: Firm_Cost_of_Funds | B11: Cost of funds by company and quarter, with source presentation and page, and the pre/post period (formula) | C11: Quarterly, Q1 FY2021 to Q4 FY2026 | D11: Investor presentations
A12: Firm_Bank_Share | B12: Bank share of borrowings by company and quarter, with source presentation and page, definition and period | C12: Quarterly, Q1 FY2021 to Q4 FY2026 | D12: Investor presentations
A13: Bajaj_Segments | B13: Bajaj Finance assets under management by segment, and the share in segments affected by the circular (formula) | C13: Quarterly, Q1 FY2021 to Q4 FY2026 | D13: Bajaj Finance investor presentations
A14: Company_Disclosures | B14: Verbatim company statements on the effect of the measures | C14: Q3 FY2024 | D14: Investor presentations
A15: Event_Dates | B15: Policy and firm events, release times and the dates and windows used in the analysis | D15: RBI circulars, news reports, NSE
A17: Colour code: blue = data as published or as compiled from the source; black = formula.
A18: Units: bank credit in ₹ crore (1 lakh crore = 100,000 crore); growth in percentage points per month; returns in per cent.
A19: Merger adjustment: HDFC Ltd merged into HDFC Bank on 1 July 2023. The merger month (28 Jul 2023) is excluded from growth for affected series, and growth from Aug 2023 to Jun 2025 uses the RBI figures that exclude the merger.

Sheet RBI_Levels
A1: Outstanding bank credit by sector, ₹ crore (reported figures)
A2: Source: RBI, Database on Indian Economy, Table 15 'Deployment of Gross Bank Credit by Major Sectors'. Each observation is the last reporting Friday of the month. Blue = data as published; black = formula.
A4: Date | B4: Non-food credit (RBI item III) | C4: NBFCs (incl. HFCs) (RBI item 3.9) | D4: HFCs (RBI item 3.9.1) | E4: Housing (RBI item 4.2) | F4: Credit cards (RBI item 4.5) | G4: Education (RBI item 4.6) | H4: Vehicle loans (RBI item 4.7) | I4: Gold loans (RBI item 4.8) | J4: Other personal loans (RBI item 4.9) | K4: NBFCs excl. HFCs (formula) | L4: Non-food excl. NBFCs, cards and other PL (formula)
A5: 43483 | B5: 9261605.7 | C5: 662551.6 | D5: 206996.49 | E5: 1141732.8 | F5: 83645.81 | G5: 76750.07 | H5: 281694.44 | I5: 24444.88 | J5: 531456.84 | K5: =C5-D5 -> 455555.11 | L5: =B5-C5-F5-J5 -> 7983951.4
A6: 43511 | B6: 9378625.8 | C6: 707143.7 | D6: 213566.14 | E6: 1153719.3 | F6: 82798.71 | G6: 76824.4 | H6: 282226.51 | I6: 24600.01 | J6: 540192.16 | K6: =C6-D6 -> 493577.56 | L6: =B6-C6-F6-J6 -> 8048491.2
A7: 43553 | B7: 9730112.1 | C7: 751146.21 | D7: 225504.5 | E7: 1176510.1 | F7: 87685.62 | G7: 76375.8 | H7: 285257.82 | I7: 24670.77 | J7: 552616.58 | K7: =C7-D7 -> 525641.71 | L7: =B7-C7-F7-J7 -> 8338663.7
A8: 43581 | B8: 9577783.8 | C8: 725245.92 | D8: 223161.97 | E8: 1187097.8 | F8: 91931.27 | G8: 75923.45 | H8: 285567.84 | I8: 24577.71 | J8: 557876.95 | K8: =C8-D8 -> 502083.95 | L8: =B8-C8-F8-J8 -> 8202729.6
A9: 43609 | B9: 9555822.4 | C9: 705605.83 | D9: 219000.37 | E9: 1192750.2 | F9: 93038.7 | G9: 75854.42 | H9: 287246.09 | I9: 25849.01 | J9: 562248.45 | K9: =C9-D9 -> 486605.46 | L9: =B9-C9-F9-J9 -> 8194929.4
A10: 43637 | B10: 9577348.8 | C10: 708269.67 | D10: 219824.91 | E10: 1208164.1 | F10: 94292.74 | G10: 76430.59 | H10: 286279.3 | I10: 27102.28 | J10: 563497.35 | K10: =C10-D10 -> 488444.76 | L10: =B10-C10-F10-J10 -> 8211289
A11: 43665 | B11: 9592376.2 | C11: 735161.49 | D11: 223112.6 | E11: 1222853.7 | F11: 93377.19 | G11: 76982.24 | H11: 287772.52 | I11: 27214.94 | J11: 576465.66 | K11: =C11-D11 -> 512048.89 | L11: =B11-C11-F11-J11 -> 8187371.8
A12: 43707 | B12: 9617761.8 | C12: 770593.19 | D12: 237205.49 | E12: 1236210.9 | F12: 96972.74 | G12: 78532.42 | H12: 289025.36 | I12: 27598.38 | J12: 582919.99 | K12: =C12-D12 -> 533387.7 | L12: =B12-C12-F12-J12 -> 8167275.9
A13: 43735 | B13: 9706768.8 | C13: 799158.88 | D13: 237097.79 | E13: 1255411.2 | F13: 98607.5 | G13: 79031.06 | H13: 289152.97 | I13: 28828.15 | J13: 592686.02 | K13: =C13-D13 -> 562061.09 | L13: =B13-C13-F13-J13 -> 8216316.4
A14: 43763 | B14: 9770783.7 | C14: 814566.33 | D14: 236725.99 | E14: 1295242.2 | F14: 113798.86 | G14: 78159.44 | H14: 322367.84 | I14: 28926.07 | J14: 638002.26 | K14: =C14-D14 -> 577840.34 | L14: =B14-C14-F14-J14 -> 8204416.3
A15: 43791 | B15: 9768998.6 | C15: 836140.62 | D15: 234586.59 | E15: 1302222.9 | F15: 114898.72 | G15: 77620.36 | H15: 323778.44 | I15: 29276.84 | J15: 646255.22 | K15: =C15-D15 -> 601554.03 | L15: =B15-C15-F15-J15 -> 8171704
A16: 43819 | B16: 9952589.6 | C16: 846292.74 | D16: 245396.5 | E16: 1303749.9 | F16: 115188.48 | G16: 78324.08 | H16: 325253.36 | I16: 29104.55 | J16: 663953.27 | K16: =C16-D16 -> 600896.24 | L16: =B16-C16-F16-J16 -> 8327155.1
... A95: 46234 | B95: 21960264 | C95: 2127531 | D95: 382151.44 | E95: 3428452.6 | F95: 297756.08 | G95: 160946.79 | H95: 764554.47 | I95: 552261 | J95: 1784253.1 | K95: =C95-D95 -> 1745379.6 | L95: =B95-C95-F95-J95 -> 17750724

Sheet RBI_Levels_ExMerger
A1: Bank credit excluding the impact of the HDFC merger, ₹ crore (July 2023 to June 2025)
A2: Source: RBI DBIE Table 15, figures shown in parentheses (note 5: 'Data since July 28, 2023 include the impact of the merger of a non-bank with a bank. Figures in parentheses exclude the impact of the merger.'). Blank where not published.
A4: Date | B4: Non-food credit (excl. merger) | C4: Housing (excl. merger) | D4: Other personal loans (excl. merger) | E4: Non-food excl. NBFCs, cards and other PL (excl. merger, formula)
A5: 43483 | E5: =IF(B5="","",B5-RBI_Levels!C5-RBI_Levels!F5-D5)
A6: 43511 | E6: =IF(B6="","",B6-RBI_Levels!C6-RBI_Levels!F6-D6)
A7: 43553 | E7: =IF(B7="","",B7-RBI_Levels!C7-RBI_Levels!F7-D7)
A8: 43581 | E8: =IF(B8="","",B8-RBI_Levels!C8-RBI_Levels!F8-D8)
A9: 43609 | E9: =IF(B9="","",B9-RBI_Levels!C9-RBI_Levels!F9-D9)
A10: 43637 | E10: =IF(B10="","",B10-RBI_Levels!C10-RBI_Levels!F10-D10)
A11: 43665 | E11: =IF(B11="","",B11-RBI_Levels!C11-RBI_Levels!F11-D11)
A12: 43707 | E12: =IF(B12="","",B12-RBI_Levels!C12-RBI_Levels!F12-D12)
A13: 43735 | E13: =IF(B13="","",B13-RBI_Levels!C13-RBI_Levels!F13-D13)
A14: 43763 | E14: =IF(B14="","",B14-RBI_Levels!C14-RBI_Levels!F14-D14)
A15: 43791 | E15: =IF(B15="","",B15-RBI_Levels!C15-RBI_Levels!F15-D15)
A16: 43819 | E16: =IF(B16="","",B16-RBI_Levels!C16-RBI_Levels!F16-D16)
... A58: 45107 | E58: =IF(B58="","",B58-RBI_Levels!C58-RBI_Levels!F58-D58)
A59: 45135 | B59: 14156007 | C59: 2052115 | D59: 1216369 | E59: =IF(B59="","",B59-RBI_Levels!C59-RBI_Levels!F59-D59) -> 11357579
A60: 45163 | B60: 14295755 | C60: 2081117 | D60: 1227512 | E60: =IF(B60="","",B60-RBI_Levels!C60-RBI_Levels!F60-D60) -> 11477504
A61: 45191 | B61: 14540009 | C61: 2105971 | D61: 1253324 | E61: =IF(B61="","",B61-RBI_Levels!C61-RBI_Levels!F61-D61) -> 11659746
A62: 45219 | B62: 14977628 | C62: 2144052.3 | D62: 1305788.5 | E62: =IF(B62="","",B62-RBI_Levels!C62-RBI_Levels!F62-D62) -> 11981573
A63: 45247 | B63: 15205570 | C63: 2176906.4 | D63: 1316795.7 | E63: =IF(B63="","",B63-RBI_Levels!C63-RBI_Levels!F63-D63) -> 12179254
A64: 45289 | B64: 15345733 | C64: 2228350 | D64: 1352880 | E64: =IF(B64="","",B64-RBI_Levels!C64-RBI_Levels!F64-D64) -> 12219486
A65: 45317 | B65: 15444737 | C65: 2263917.6 | D65: 1369940.3 | E65: =IF(B65="","",B65-RBI_Levels!C65-RBI_Levels!F65-D65) -> 12320876
A66: 45345 | B66: 15637228 | C66: 2289954.3 | D66: 1386678.7 | E66: =IF(B66="","",B66-RBI_Levels!C66-RBI_Levels!F66-D66) -> 12501737
A67: 45373 | B67: 15878397 | C67: 2331931.6 | D67: 1403063.2 | E67: =IF(B67="","",B67-RBI_Levels!C67-RBI_Levels!F67-D67) -> 12695263
A68: 45401 | B68: 15952888 | C68: 2358296.4 | D68: 1392427.3 | E68: =IF(B68="","",B68-RBI_Levels!C68-RBI_Levels!F68-D68) -> 12760758
A69: 45443 | B69: 16232739 | C69: 2409156.2 | D69: 1421323.6 | E69: =IF(B69="","",B69-RBI_Levels!C69-RBI_Levels!F69-D69) -> 12996152
A70: 45471 | B70: 16351894 | C70: 2427444.2 | D70: 1421630.7 | E70: =IF(B70="","",B70-RBI_Levels!C70-RBI_Levels!F70-D70) -> 13109554
... A82: 45835 | B82: 18024223 | C82: 2776336.4 | D82: 1528637.5 | E82: =IF(B82="","",B82-RBI_Levels!C82-RBI_Levels!F82-D82) -> 14607034
A83: 45863 | E83: =IF(B83="","",B83-RBI_Levels!C83-RBI_Levels!F83-D83)
A84: 45891 | E84: =IF(B84="","",B84-RBI_Levels!C84-RBI_Levels!F84-D84)
A85: 45919 | E85: =IF(B85="","",B85-RBI_Levels!C85-RBI_Levels!F85-D85)
A86: 45961 | E86: =IF(B86="","",B86-RBI_Levels!C86-RBI_Levels!F86-D86)
A87: 45989 | E87: =IF(B87="","",B87-RBI_Levels!C87-RBI_Levels!F87-D87)
A88: 46022 | E88: =IF(B88="","",B88-RBI_Levels!C88-RBI_Levels!F88-D88)
A89: 46053 | E89: =IF(B89="","",B89-RBI_Levels!C89-RBI_Levels!F89-D89)
A90: 46081 | E90: =IF(B90="","",B90-RBI_Levels!C90-RBI_Levels!F90-D90)
A91: 46112 | E91: =IF(B91="","",B91-RBI_Levels!C91-RBI_Levels!F91-D91)
A92: 46142 | E92: =IF(B92="","",B92-RBI_Levels!C92-RBI_Levels!F92-D92)
A93: 46173 | E93: =IF(B93="","",B93-RBI_Levels!C93-RBI_Levels!F93-D93)
A94: 46203 | E94: =IF(B94="","",B94-RBI_Levels!C94-RBI_Levels!F94-D94)
A95: 46234 | E95: =IF(B95="","",B95-RBI_Levels!C95-RBI_Levels!F95-D95)

Sheet RBI_Growth
A1: Monthly growth of bank credit (100 × change in natural log) and the growth gaps used in the tests
A2: Formulas. Merger month (28-Jul-2023) left blank for merger-affected series. From Aug-2023 to Jun-2025, growth of non-food credit, housing, other personal loans and the alternative benchmark uses the figures excluding the merger.
A4: Date | B4: Credit cards | C4: Other personal loans | D4: Housing | E4: Vehicle loans | F4: Education | G4: Gold loans | H4: NBFCs ex-HFC | I4: HFCs | J4: NBFCs (incl. HFCs) | K4: Non-food credit | L4: Non-food excl. NBFCs, cards, other PL | M4: Gap1: (cards + other PL)/2 minus (housing + vehicle + education)/3 | N4: Gap2: NBFCs ex-HFC minus non-food credit | O4: Gap2 (alt.): NBFCs ex-HFC minus non-food excl. NBFCs, cards, PL | P4: Test window (Apr-21 to Jan-25) | Q4: Post (1 from 29-Dec-2023) | R4: Period
A5: 43483
A6: 43511 | B6: =100*LN(RBI_Levels!F6/RBI_Levels!F5) -> -1.0178855 | C6: =100*LN(RBI_Levels!J6/RBI_Levels!J5) -> 1.6302938 | D6: =100*LN(RBI_Levels!E6/RBI_Levels!E5) -> 1.0443833 | E6: =100*LN(RBI_Levels!H6/RBI_Levels!H5) -> 0.18870381 | F6: =100*LN(RBI_Levels!G6/RBI_Levels!G5) -> 0.096799951 | G6: =100*LN(RBI_Levels!I6/RBI_Levels!I5) -> 0.63260624 | H6: =100*LN(RBI_Levels!K6/RBI_Levels!K5) -> 8.0163312 | I6: =100*LN(RBI_Levels!D6/RBI_Levels!D5) -> 3.1244737 | J6: =100*LN(RBI_Levels!C6/RBI_Levels!C5) -> 6.5135457 | K6: =100*LN(RBI_Levels!B6/RBI_Levels!B5) -> 1.2555815 | L6: =100*LN(RBI_Levels!L6/RBI_Levels!L5) -> 0.80511925 | M6: =AVERAGE(B6,C6)-AVERAGE(D6,E6,F6) -> -0.13709153 | N6: =IF(OR(H6="",K6=""),"",H6-K6) -> 6.7607497 | O6: =IF(OR(H6="",L6=""),"",H6-L6) -> 7.211212 | P6: =IF(AND(A6>=DATE(2021,4,1),A6<=DATE(2025,1,31)),1,0) -> 0 | Q6: =IF(A6>=DATE(2023,12,1),1,0) -> 0 | R6: =IF(A6<DATE(2021,4,1),"Before sample",IF(A6<=DATE(2023,11,17),"Pre-policy",IF(A6<=DATE(2025,3,31),"Post-policy","After rollback"))) -> Before sample
A7: 43553 | B7: =100*LN(RBI_Levels!F7/RBI_Levels!F6) -> 5.7345436 | C7: =100*LN(RBI_Levels!J7/RBI_Levels!J6) -> 2.2739488 | D7: =100*LN(RBI_Levels!E7/RBI_Levels!E6) -> 1.9561548 | E7: =100*LN(RBI_Levels!H7/RBI_Levels!H6) -> 1.0683427 | F7: =100*LN(RBI_Levels!G7/RBI_Levels!G6) -> -0.5856406 | G7: =100*LN(RBI_Levels!I7/RBI_Levels!I6) -> 0.28722926 | H7: =100*LN(RBI_Levels!K7/RBI_Levels!K6) -> 6.2939811 | I7: =100*LN(RBI_Levels!D7/RBI_Levels!D6) -> 5.439354 | J7: =100*LN(RBI_Levels!C7/RBI_Levels!C6) -> 6.0366421 | K7: =100*LN(RBI_Levels!B7/RBI_Levels!B6) -> 3.6792173 | L7: =100*LN(RBI_Levels!L7/RBI_Levels!L6) -> 3.5418331 | M7: =AVERAGE(B7,C7)-AVERAGE(D7,E7,F7) -> 3.1912939 | N7: =IF(OR(H7="",K7=""),"",H7-K7) -> 2.6147639 | O7: =IF(OR(H7="",L7=""),"",H7-L7) -> 2.752148 | P7: =IF(AND(A7>=DATE(2021,4,1),A7<=DATE(2025,1,31)),1,0) -> 0 | Q7: =IF(A7>=DATE(2023,12,1),1,0) -> 0 | R7: =IF(A7<DATE(2021,4,1),"Before sample",IF(A7<=DATE(2023,11,17),"Pre-policy",IF(A7<=DATE(2025,3,31),"Post-policy","After rollback"))) -> Before sample
A8: 43581 | B8: =100*LN(RBI_Levels!F8/RBI_Levels!F7) -> 4.7283315 | C8: =100*LN(RBI_Levels!J8/RBI_Levels!J7) -> 0.94740027 | D8: =100*LN(RBI_Levels!E8/RBI_Levels!E7) -> 0.89590165 | E8: =100*LN(RBI_Levels!H8/RBI_Levels!H7) -> 0.10862162 | F8: =100*LN(RBI_Levels!G8/RBI_Levels!G7) -> -0.59402962 | G8: =100*LN(RBI_Levels!I8/RBI_Levels!I7) -> -0.37792074 | H8: =100*LN(RBI_Levels!K8/RBI_Levels!K7) -> -4.5852484 | I8: =100*LN(RBI_Levels!D8/RBI_Levels!D7) -> -1.0442284 | J8: =100*LN(RBI_Levels!C8/RBI_Levels!C7) -> -3.5089523 | K8: =100*LN(RBI_Levels!B8/RBI_Levels!B7) -> -1.5779193 | L8: =100*LN(RBI_Levels!L8/RBI_Levels!L7) -> -1.6435996 | M8: =AVERAGE(B8,C8)-AVERAGE(D8,E8,F8) -> 2.7010347 | N8: =IF(OR(H8="",K8=""),"",H8-K8) -> -3.0073292 | O8: =IF(OR(H8="",L8=""),"",H8-L8) -> -2.9416489 | P8: =IF(AND(A8>=DATE(2021,4,1),A8<=DATE(2025,1,31)),1,0) -> 0 | Q8: =IF(A8>=DATE(2023,12,1),1,0) -> 0 | R8: =IF(A8<DATE(2021,4,1),"Before sample",IF(A8<=DATE(2023,11,17),"Pre-policy",IF(A8<=DATE(2025,3,31),"Post-policy","After rollback"))) -> Before sample
A9: 43609 | B9: =100*LN(RBI_Levels!F9/RBI_Levels!F8) -> 1.1974303 | C9: =100*LN(RBI_Levels!J9/RBI_Levels!J8) -> 0.78054157 | D9: =100*LN(RBI_Levels!E9/RBI_Levels!E8) -> 0.47502199 | E9: =100*LN(RBI_Levels!H9/RBI_Levels!H8) -> 0.58596857 | F9: =100*LN(RBI_Levels!G9/RBI_Levels!G8) -> -0.090961884 | G9: =100*LN(RBI_Levels!I9/RBI_Levels!I8) -> 5.0432368 | H9: =100*LN(RBI_Levels!K9/RBI_Levels!K8) -> -3.1313686 | I9: =100*LN(RBI_Levels!D9/RBI_Levels!D8) -> -1.8824411 | J9: =100*LN(RBI_Levels!C9/RBI_Levels!C8) -> -2.745403 | K9: =100*LN(RBI_Levels!B9/RBI_Levels!B8) -> -0.22955811 | L9: =100*LN(RBI_Levels!L9/RBI_Levels!L8) -> -0.095138013 | M9: =AVERAGE(B9,C9)-AVERAGE(D9,E9,F9) -> 0.66564304 | N9: =IF(OR(H9="",K9=""),"",H9-K9) -> -2.9018105 | O9: =IF(OR(H9="",L9=""),"",H9-L9) -> -3.0362306 | P9: =IF(AND(A9>=DATE(2021,4,1),A9<=DATE(2025,1,31)),1,0) -> 0 | Q9: =IF(A9>=DATE(2023,12,1),1,0) -> 0 | R9: =IF(A9<DATE(2021,4,1),"Before sample",IF(A9<=DATE(2023,11,17),"Pre-policy",IF(A9<=DATE(2025,3,31),"Post-policy","After rollback"))) -> Before sample
A10: 43637 | B10: =100*LN(RBI_Levels!F10/RBI_Levels!F9) -> 1.3388663 | C10: =100*LN(RBI_Levels!J10/RBI_Levels!J9) -> 0.22187967 | D10: =100*LN(RBI_Levels!E10/RBI_Levels!E9) -> 1.2840243 | E10: =100*LN(RBI_Levels!H10/RBI_Levels!H9) -> -0.33713971 | F10: =100*LN(RBI_Levels!G10/RBI_Levels!G9) -> 0.75670317 | G10: =100*LN(RBI_Levels!I10/RBI_Levels!I9) -> 4.7345555 | H10: =100*LN(RBI_Levels!K10/RBI_Levels!K9) -> 0.37727332 | I10: =100*LN(RBI_Levels!D10/RBI_Levels!D9) -> 0.37579465 | J10: =100*LN(RBI_Levels!C10/RBI_Levels!C9) -> 0.37681439 | K10: =100*LN(RBI_Levels!B10/RBI_Levels!B9) -> 0.22501646 | L10: =100*LN(RBI_Levels!L10/RBI_Levels!L9) -> 0.1994318 | M10: =AVERAGE(B10,C10)-AVERAGE(D10,E10,F10) -> 0.21251038 | N10: =IF(OR(H10="",K10=""),"",H10-K10) -> 0.15225687 | O10: =IF(OR(H10="",L10=""),"",H10-L10) -> 0.17784153 | P10: =IF(AND(A10>=DATE(2021,4,1),A10<=DATE(2025,1,31)),1,0) -> 0 | Q10: =IF(A10>=DATE(2023,12,1),1,0) -> 0 | R10: =IF(A10<DATE(2021,4,1),"Before sample",IF(A10<=DATE(2023,11,17),"Pre-policy",IF(A10<=DATE(2025,3,31),"Post-policy","After rollback"))) -> Before sample
A11: 43665 | B11: =100*LN(RBI_Levels!F11/RBI_Levels!F10) -> -0.97571013 | C11: =100*LN(RBI_Levels!J11/RBI_Levels!J10) -> 2.2753141 | D11: =100*LN(RBI_Levels!E11/RBI_Levels!E10) -> 1.2085258 | E11: =100*LN(RBI_Levels!H11/RBI_Levels!H10) -> 0.52023992 | F11: =100*LN(RBI_Levels!G11/RBI_Levels!G10) -> 0.71917372 | G11: =100*LN(RBI_Levels!I11/RBI_Levels!I10) -> 0.414823 | H11: =100*LN(RBI_Levels!K11/RBI_Levels!K10) -> 4.7193725 | I11: =100*LN(RBI_Levels!D11/RBI_Levels!D10) -> 1.4845211 | J11: =100*LN(RBI_Levels!C11/RBI_Levels!C10) -> 3.7265278 | K11: =100*LN(RBI_Levels!B11/RBI_Levels!B10) -> 0.15678238 | L11: =100*LN(RBI_Levels!L11/RBI_Levels!L10) -> -0.29169729 | M11: =AVERAGE(B11,C11)-AVERAGE(D11,E11,F11) -> -0.16617784 | N11: =IF(OR(H11="",K11=""),"",H11-K11) -> 4.5625901 | O11: =IF(OR(H11="",L11=""),"",H11-L11) -> 5.0110697 | P11: =IF(AND(A11>=DATE(2021,4,1),A11<=DATE(2025,1,31)),1,0) -> 0 | Q11: =IF(A11>=DATE(2023,12,1),1,0) -> 0 | R11: =IF(A11<DATE(2021,4,1),"Before sample",IF(A11<=DATE(2023,11,17),"Pre-policy",IF(A11<=DATE(2025,3,31),"Post-policy","After rollback"))) -> Before sample
A12: 43707 | B12: =100*LN(RBI_Levels!F12/RBI_Levels!F11) -> 3.7782811 | C12: =100*LN(RBI_Levels!J12/RBI_Levels!J11) -> 1.1134167 | D12: =100*LN(RBI_Levels!E12/RBI_Levels!E11) -> 1.0863758 | E12: =100*LN(RBI_Levels!H12/RBI_Levels!H11) -> 0.43441282 | F12: =100*LN(RBI_Levels!G12/RBI_Levels!G11) -> 1.9936787 | G12: =100*LN(RBI_Levels!I12/RBI_Levels!I11) -> 1.3990988 | H12: =100*LN(RBI_Levels!K12/RBI_Levels!K11) -> 4.0828443 | I12: =100*LN(RBI_Levels!D12/RBI_Levels!D11) -> 6.1250235 | J12: =100*LN(RBI_Levels!C12/RBI_Levels!C11) -> 4.7070406 | K12: =100*LN(RBI_Levels!B12/RBI_Levels!B11) -> 0.26429477 | L12: =100*LN(RBI_Levels!L12/RBI_Levels!L11) -> -0.24575167 | M12: =AVERAGE(B12,C12)-AVERAGE(D12,E12,F12) -> 1.2743598 | N12: =IF(OR(H12="",K12=""),"",H12-K12) -> 3.8185495 | O12: =IF(OR(H12="",L12=""),"",H12-L12) -> 4.328596 | P12: =IF(AND(A12>=DATE(2021,4,1),A12<=DATE(2025,1,31)),1,0) -> 0 | Q12: =IF(A12>=DATE(2023,12,1),1,0) -> 0 | R12: =IF(A12<DATE(2021,4,1),"Before sample",IF(A12<=DATE(2023,11,17),"Pre-policy",IF(A12<=DATE(2025,3,31),"Post-policy","After rollback"))) -> Before sample
A13: 43735 | B13: =100*LN(RBI_Levels!F13/RBI_Levels!F12) -> 1.6717416 | C13: =100*LN(RBI_Levels!J13/RBI_Levels!J12) -> 1.6614843 | D13: =100*LN(RBI_Levels!E13/RBI_Levels!E12) -> 1.5412169 | E13: =100*LN(RBI_Levels!H13/RBI_Levels!H12) -> 0.044142091 | F13: =100*LN(RBI_Levels!G13/RBI_Levels!G12) -> 0.63294066 | G13: =100*LN(RBI_Levels!I13/RBI_Levels!I12) -> 4.3595265 | H13: =100*LN(RBI_Levels!K13/RBI_Levels!K12) -> 5.2361993 | I13: =100*LN(RBI_Levels!D13/RBI_Levels!D12) -> -0.045413981 | J13: =100*LN(RBI_Levels!C13/RBI_Levels!C12) -> 3.639918 | K13: =100*LN(RBI_Levels!B13/RBI_Levels!B12) -> 0.92118752 | L13: =100*LN(RBI_Levels!L13/RBI_Levels!L12) -> 0.59865527 | M13: =AVERAGE(B13,C13)-AVERAGE(D13,E13,F13) -> 0.92717972 | N13: =IF(OR(H13="",K13=""),"",H13-K13) -> 4.3150118 | O13: =IF(OR(H13="",L13=""),"",H13-L13) -> 4.6375441 | P13: =IF(AND(A13>=DATE(2021,4,1),A13<=DATE(2025,1,31)),1,0) -> 0 | Q13: =IF(A13>=DATE(2023,12,1),1,0) -> 0 | R13: =IF(A13<DATE(2021,4,1),"Before sample",IF(A13<=DATE(2023,11,17),"Pre-policy",IF(A13<=DATE(2025,3,31),"Post-policy","After rollback"))) -> Before sample
A14: 43763 | B14: =100*LN(RBI_Levels!F14/RBI_Levels!F13) -> 14.328518 | C14: =100*LN(RBI_Levels!J14/RBI_Levels!J13) -> 7.3677044 | D14: =100*LN(RBI_Levels!E14/RBI_Levels!E13) -> 3.1234583 | E14: =100*LN(RBI_Levels!H14/RBI_Levels!H13) -> 10.87374 | F14: =100*LN(RBI_Levels!G14/RBI_Levels!G13) -> -1.1090097 | G14: =100*LN(RBI_Levels!I14/RBI_Levels!I13) -> 0.33909243 | H14: =100*LN(RBI_Levels!K14/RBI_Levels!K13) -> 2.7687057 | I14: =100*LN(RBI_Levels!D14/RBI_Levels!D13) -> -0.15693601 | J14: =100*LN(RBI_Levels!C14/RBI_Levels!C13) -> 1.9096087 | K14: =100*LN(RBI_Levels!B14/RBI_Levels!B13) -> 0.6573223 | L14: =100*LN(RBI_Levels!L14/RBI_Levels!L13) -> -0.14494036 | M14: =AVERAGE(B14,C14)-AVERAGE(D14,E14,F14) -> 6.5520484 | N14: =IF(OR(H14="",K14=""),"",H14-K14) -> 2.1113834 | O14: =IF(OR(H14="",L14=""),"",H14-L14) -> 2.9136461 | P14: =IF(AND(A14>=DATE(2021,4,1),A14<=DATE(2025,1,31)),1,0) -> 0 | Q14: =IF(A14>=DATE(2023,12,1),1,0) -> 0 | R14: =IF(A14<DATE(2021,4,1),"Before sample",IF(A14<=DATE(2023,11,17),"Pre-policy",IF(A14<=DATE(2025,3,31),"Post-policy","After rollback"))) -> Before sample
A15: 43791 | B15: =100*LN(RBI_Levels!F15/RBI_Levels!F14) -> 0.96185406 | C15: =100*LN(RBI_Levels!J15/RBI_Levels!J14) -> 1.2852678 | D15: =100*LN(RBI_Levels!E15/RBI_Levels!E14) -> 0.53749994 | E15: =100*LN(RBI_Levels!H15/RBI_Levels!H14) -> 0.43662009 | F15: =100*LN(RBI_Levels!G15/RBI_Levels!G14) -> -0.6921079 | G15: =100*LN(RBI_Levels!I15/RBI_Levels!I14) -> 1.2053495 | H15: =100*LN(RBI_Levels!K15/RBI_Levels!K14) -> 4.0218755 | I15: =100*LN(RBI_Levels!D15/RBI_Levels!D14) -> -0.90785385 | J15: =100*LN(RBI_Levels!C15/RBI_Levels!C14) -> 2.6140943 | K15: =100*LN(RBI_Levels!B15/RBI_Levels!B14) -> -0.01827189 | L15: =100*LN(RBI_Levels!L15/RBI_Levels!L14) -> -0.39951218 | M15: =AVERAGE(B15,C15)-AVERAGE(D15,E15,F15) -> 1.0295569 | N15: =IF(OR(H15="",K15=""),"",H15-K15) -> 4.0401474 | O15: =IF(OR(H15="",L15=""),"",H15-L15) -> 4.4213876 | P15: =IF(AND(A15>=DATE(2021,4,1),A15<=DATE(2025,1,31)),1,0) -> 0 | Q15: =IF(A15>=DATE(2023,12,1),1,0) -> 0 | R15: =IF(A15<DATE(2021,4,1),"Before sample",IF(A15<=DATE(2023,11,17),"Pre-policy",IF(A15<=DATE(2025,3,31),"Post-policy","After rollback"))) -> Before sample
A16: 43819 | B16: =100*LN(RBI_Levels!F16/RBI_Levels!F15) -> 0.25186986 | C16: =100*LN(RBI_Levels!J16/RBI_Levels!J15) -> 2.7017267 | D16: =100*LN(RBI_Levels!E16/RBI_Levels!E15) -> 0.11719003 | E16: =100*LN(RBI_Levels!H16/RBI_Levels!H15) -> 0.45449931 | F16: =100*LN(RBI_Levels!G16/RBI_Levels!G15) -> 0.90253269 | G16: =100*LN(RBI_Levels!I16/RBI_Levels!I15) -> -0.59022404 | H16: =100*LN(RBI_Levels!K16/RBI_Levels!K15) -> -0.10940828 | I16: =100*LN(RBI_Levels!D16/RBI_Levels!D15) -> 4.5050496 | J16: =100*LN(RBI_Levels!C16/RBI_Levels!C15) -> 1.2068523 | K16: =100*LN(RBI_Levels!B16/RBI_Levels!B15) -> 1.8618821 | L16: =100*LN(RBI_Levels!L16/RBI_Levels!L15) -> 1.8844421 | M16: =AVERAGE(B16,C16)-AVERAGE(D16,E16,F16) -> 0.98539095 | N16: =IF(OR(H16="",K16=""),"",H16-K16) -> -1.9712904 | O16: =IF(OR(H16="",L16=""),"",H16-L16) -> -1.9938504 | P16: =IF(AND(A16>=DATE(2021,4,1),A16<=DATE(2025,1,31)),1,0) -> 0 | Q16: =IF(A16>=DATE(2023,12,1),1,0) -> 0 | R16: =IF(A16<DATE(2021,4,1),"Before sample",IF(A16<=DATE(2023,11,17),"Pre-policy",IF(A16<=DATE(2025,3,31),"Post-policy","After rollback"))) -> Before sample
A17: 43861 | B17: =100*LN(RBI_Levels!F17/RBI_Levels!F16) -> 5.8480034 | C17: =100*LN(RBI_Levels!J17/RBI_Levels!J16) -> 2.8088707 | D17: =100*LN(RBI_Levels!E17/RBI_Levels!E16) -> 2.8351661 | E17: =100*LN(RBI_Levels!H17/RBI_Levels!H16) -> 3.371387 | F17: =100*LN(RBI_Levels!G17/RBI_Levels!G16) -> 1.4898283 | G17: =100*LN(RBI_Levels!I17/RBI_Levels!I16) -> 9.054341 | H17: =100*LN(RBI_Levels!K17/RBI_Levels!K16) -> 1.2366761 | I17: =100*LN(RBI_Levels!D17/RBI_Levels!D16) -> -4.5305701 | J17: =100*LN(RBI_Levels!C17/RBI_Levels!C16) -> -0.40167045 | K17: =100*LN(RBI_Levels!B17/RBI_Levels!B16) -> 0.73765053 | L17: =100*LN(RBI_Levels!L17/RBI_Levels!L16) -> 0.6133098 | M17: =AVERAGE(B17,C17)-AVERAGE(D17,E17,F17) -> 1.7629766 | N17: =IF(OR(H17="",K17=""),"",H17-K17) -> 0.49902561 | O17: =IF(OR(H17="",L17=""),"",H17-L17) -> 0.62336634 | P17: =IF(AND(A17>=DATE(2021,4,1),A17<=DATE(2025,1,31)),1,0) -> 0 | Q17: =IF(A17>=DATE(2023,12,1),1,0) -> 0 | R17: =IF(A17<DATE(2021,4,1),"Before sample",IF(A17<=DATE(2023,11,17),"Pre-policy",IF(A17<=DATE(2025,3,31),"Post-policy","After rollback"))) -> Before sample
... A58: 45107 | B58: =100*LN(RBI_Levels!F58/RBI_Levels!F57) -> 4.1319236 | C58: =100*LN(RBI_Levels!J58/RBI_Levels!J57) -> 3.538621 | D58: =100*LN(RBI_Levels!E58/RBI_Levels!E57) -> 2.121341 | E58: =100*LN(RBI_Levels!H58/RBI_Levels!H57) -> 2.8405796 | F58: =100*LN(RBI_Levels!G58/RBI_Levels!G57) -> 4.2183022 | G58: =100*LN(RBI_Levels!I58/RBI_Levels!I57) -> 5.2311497 | H58: =100*LN(RBI_Levels!K58/RBI_Levels!K57) -> 6.4387213 | I58: =100*LN(RBI_Levels!D58/RBI_Levels!D57) -> 4.411552 | J58: =100*LN(RBI_Levels!C58/RBI_Levels!C57) -> 5.9636485 | K58: =100*LN(RBI_Levels!B58/RBI_Levels!B57) -> 2.7032153 | L58: =100*LN(RBI_Levels!L58/RBI_Levels!L57) -> 2.1880272 | M58: =AVERAGE(B58,C58)-AVERAGE(D58,E58,F58) -> 0.77519798 | N58: =IF(OR(H58="",K58=""),"",H58-K58) -> 3.735506 | O58: =IF(OR(H58="",L58=""),"",H58-L58) -> 4.2506941 | P58: =IF(AND(A58>=DATE(2021,4,1),A58<=DATE(2025,1,31)),1,0) -> 1 | Q58: =IF(A58>=DATE(2023,12,1),1,0) -> 0 | R58: =IF(A58<DATE(2021,4,1),"Before sample",IF(A58<=DATE(2023,11,17),"Pre-policy",IF(A58<=DATE(2025,3,31),"Post-policy","After rollback"))) -> Pre-policy
A59: 45135 | B59: =100*LN(RBI_Levels!F59/RBI_Levels!F58) -> 2.0479055 | E59: =100*LN(RBI_Levels!H59/RBI_Levels!H58) -> 1.1406359 | F59: =100*LN(RBI_Levels!G59/RBI_Levels!G58) -> 1.6656711 | G59: =100*LN(RBI_Levels!I59/RBI_Levels!I58) -> 0.49647073 | M59: =AVERAGE(B59,C59)-AVERAGE(D59,E59,F59) -> 0.64475199 | N59: =IF(OR(H59="",K59=""),"",H59-K59) | O59: =IF(OR(H59="",L59=""),"",H59-L59) | P59: =IF(AND(A59>=DATE(2021,4,1),A59<=DATE(2025,1,31)),1,0) -> 1 | Q59: =IF(A59>=DATE(2023,12,1),1,0) -> 0 | R59: =IF(A59<DATE(2021,4,1),"Before sample",IF(A59<=DATE(2023,11,17),"Pre-policy",IF(A59<=DATE(2025,3,31),"Post-policy","After rollback"))) -> Pre-policy
A60: 45163 | B60: =100*LN(RBI_Levels!F60/RBI_Levels!F59) -> 2.0617214 | C60: =100*LN(RBI_Levels_ExMerger!D60/RBI_Levels_ExMerger!D59) -> 0.91191651 | D60: =100*LN(RBI_Levels_ExMerger!C60/RBI_Levels_ExMerger!C59) -> 1.40338 | E60: =100*LN(RBI_Levels!H60/RBI_Levels!H59) -> 0.87416948 | F60: =100*LN(RBI_Levels!G60/RBI_Levels!G59) -> 3.0261702 | G60: =100*LN(RBI_Levels!I60/RBI_Levels!I59) -> 4.3927457 | H60: =100*LN(RBI_Levels!K60/RBI_Levels!K59) -> 1.2203055 | I60: =100*LN(RBI_Levels!D60/RBI_Levels!D59) -> -2.769978 | J60: =100*LN(RBI_Levels!C60/RBI_Levels!C59) -> 0.29258736 | K60: =100*LN(RBI_Levels_ExMerger!B60/RBI_Levels_ExMerger!B59) -> 0.98235831 | L60: =100*LN(RBI_Levels_ExMerger!E60/RBI_Levels_ExMerger!E59) -> 1.0503633 | M60: =AVERAGE(B60,C60)-AVERAGE(D60,E60,F60) -> -0.28108759 | N60: =IF(OR(H60="",K60=""),"",H60-K60) -> 0.23794724 | O60: =IF(OR(H60="",L60=""),"",H60-L60) -> 0.16994222 | P60: =IF(AND(A60>=DATE(2021,4,1),A60<=DATE(2025,1,31)),1,0) -> 1 | Q60: =IF(A60>=DATE(2023,12,1),1,0) -> 0 | R60: =IF(A60<DATE(2021,4,1),"Before sample",IF(A60<=DATE(2023,11,17),"Pre-policy",IF(A60<=DATE(2025,3,31),"Post-policy","After rollback"))) -> Pre-policy
A61: 45191 | B61: =100*LN(RBI_Levels!F61/RBI_Levels!F60) -> -0.17256589 | C61: =100*LN(RBI_Levels_ExMerger!D61/RBI_Levels_ExMerger!D60) -> 2.0809865 | D61: =100*LN(RBI_Levels_ExMerger!C61/RBI_Levels_ExMerger!C60) -> 1.1871875 | E61: =100*LN(RBI_Levels!H61/RBI_Levels!H60) -> 1.5516481 | F61: =100*LN(RBI_Levels!G61/RBI_Levels!G60) -> 2.9532695 | G61: =100*LN(RBI_Levels!I61/RBI_Levels!I60) -> -2.232373 | H61: =100*LN(RBI_Levels!K61/RBI_Levels!K60) -> 3.676551 | I61: =100*LN(RBI_Levels!D61/RBI_Levels!D60) -> -0.86302014 | J61: =100*LN(RBI_Levels!C61/RBI_Levels!C60) -> 2.6552703 | K61: =100*LN(RBI_Levels_ExMerger!B61/RBI_Levels_ExMerger!B60) -> 1.6941451 | L61: =100*LN(RBI_Levels_ExMerger!E61/RBI_Levels_ExMerger!E60) -> 1.5753461 | M61: =AVERAGE(B61,C61)-AVERAGE(D61,E61,F61) -> -0.94315801 | N61: =IF(OR(H61="",K61=""),"",H61-K61) -> 1.9824059 | O61: =IF(OR(H61="",L61=""),"",H61-L61) -> 2.101205 | P61: =IF(AND(A61>=DATE(2021,4,1),A61<=DATE(2025,1,31)),1,0) -> 1 | Q61: =IF(A61>=DATE(2023,12,1),1,0) -> 0 | R61: =IF(A61<DATE(2021,4,1),"Before sample",IF(A61<=DATE(2023,11,17),"Pre-policy",IF(A61<=DATE(2025,3,31),"Post-policy","After rollback"))) -> Pre-policy
A62: 45219 | B62: =100*LN(RBI_Levels!F62/RBI_Levels!F61) -> 4.407656 | C62: =100*LN(RBI_Levels_ExMerger!D62/RBI_Levels_ExMerger!D61) -> 4.1007869 | D62: =100*LN(RBI_Levels_ExMerger!C62/RBI_Levels_ExMerger!C61) -> 1.7920977 | E62: =100*LN(RBI_Levels!H62/RBI_Levels!H61) -> -1.3506285 | F62: =100*LN(RBI_Levels!G62/RBI_Levels!G61) -> 0.98402719 | G62: =100*LN(RBI_Levels!I62/RBI_Levels!I61) -> -8.4331444 | H62: =100*LN(RBI_Levels!K62/RBI_Levels!K61) -> 3.2541018 | I62: =100*LN(RBI_Levels!D62/RBI_Levels!D61) -> 5.3498789 | J62: =100*LN(RBI_Levels!C62/RBI_Levels!C61) -> 3.7211314 | K62: =100*LN(RBI_Levels_ExMerger!B62/RBI_Levels_ExMerger!B61) -> 2.9653503 | L62: =100*LN(RBI_Levels_ExMerger!E62/RBI_Levels_ExMerger!E61) -> 2.7227462 | M62: =AVERAGE(B62,C62)-AVERAGE(D62,E62,F62) -> 3.779056 | N62: =IF(OR(H62="",K62=""),"",H62-K62) -> 0.28875143 | O62: =IF(OR(H62="",L62=""),"",H62-L62) -> 0.53135552 | P62: =IF(AND(A62>=DATE(2021,4,1),A62<=DATE(2025,1,31)),1,0) -> 1 | Q62: =IF(A62>=DATE(2023,12,1),1,0) -> 0 | R62: =IF(A62<DATE(2021,4,1),"Before sample",IF(A62<=DATE(2023,11,17),"Pre-policy",IF(A62<=DATE(2025,3,31),"Post-policy","After rollback"))) -> Pre-policy
A63: 45247 | B63: =100*LN(RBI_Levels!F63/RBI_Levels!F62) -> 1.6619825 | C63: =100*LN(RBI_Levels_ExMerger!D63/RBI_Levels_ExMerger!D62) -> 0.83941745 | D63: =100*LN(RBI_Levels_ExMerger!C63/RBI_Levels_ExMerger!C62) -> 1.5207166 | E63: =100*LN(RBI_Levels!H63/RBI_Levels!H62) -> 2.1180935 | F63: =100*LN(RBI_Levels!G63/RBI_Levels!G62) -> 1.0653222 | G63: =100*LN(RBI_Levels!I63/RBI_Levels!I62) -> 0.23347396 | H63: =100*LN(RBI_Levels!K63/RBI_Levels!K62) -> 3.2976321 | I63: =100*LN(RBI_Levels!D63/RBI_Levels!D62) -> -7.1458524 | J63: =100*LN(RBI_Levels!C63/RBI_Levels!C62) -> 1.0445503 | K63: =100*LN(RBI_Levels_ExMerger!B63/RBI_Levels_ExMerger!B62) -> 1.5104238 | L63: =100*LN(RBI_Levels_ExMerger!E63/RBI_Levels_ExMerger!E62) -> 1.6364159 | M63: =AVERAGE(B63,C63)-AVERAGE(D63,E63,F63) -> -0.31734416 | N63: =IF(OR(H63="",K63=""),"",H63-K63) -> 1.7872083 | O63: =IF(OR(H63="",L63=""),"",H63-L63) -> 1.6612162 | P63: =IF(AND(A63>=DATE(2021,4,1),A63<=DATE(2025,1,31)),1,0) -> 1 | Q63: =IF(A63>=DATE(2023,12,1),1,0) -> 0 | R63: =IF(A63<DATE(2021,4,1),"Before sample",IF(A63<=DATE(2023,11,17),"Pre-policy",IF(A63<=DATE(2025,3,31),"Post-policy","After rollback"))) -> Pre-policy
A64: 45289 | B64: =100*LN(RBI_Levels!F64/RBI_Levels!F63) -> 2.8902004 | C64: =100*LN(RBI_Levels_ExMerger!D64/RBI_Levels_ExMerger!D63) -> 2.703442 | D64: =100*LN(RBI_Levels_ExMerger!C64/RBI_Levels_ExMerger!C63) -> 2.3356598 | E64: =100*LN(RBI_Levels!H64/RBI_Levels!H63) -> 2.6386302 | F64: =100*LN(RBI_Levels!G64/RBI_Levels!G63) -> 2.5643439 | G64: =100*LN(RBI_Levels!I64/RBI_Levels!I63) -> 1.485201 | H64: =100*LN(RBI_Levels!K64/RBI_Levels!K63) -> 2.8365211 | I64: =100*LN(RBI_Levels!D64/RBI_Levels!D63) -> 7.3878758 | J64: =100*LN(RBI_Levels!C64/RBI_Levels!C63) -> 3.7957777 | K64: =100*LN(RBI_Levels_ExMerger!B64/RBI_Levels_ExMerger!B63) -> 0.91756134 | L64: =100*LN(RBI_Levels_ExMerger!E64/RBI_Levels_ExMerger!E63) -> 0.32978982 | M64: =AVERAGE(B64,C64)-AVERAGE(D64,E64,F64) -> 0.2839432 | N64: =IF(OR(H64="",K64=""),"",H64-K64) -> 1.9189598 | O64: =IF(OR(H64="",L64=""),"",H64-L64) -> 2.5067313 | P64: =IF(AND(A64>=DATE(2021,4,1),A64<=DATE(2025,1,31)),1,0) -> 1 | Q64: =IF(A64>=DATE(2023,12,1),1,0) -> 1 | R64: =IF(A64<DATE(2021,4,1),"Before sample",IF(A64<=DATE(2023,11,17),"Pre-policy",IF(A64<=DATE(2025,3,31),"Post-policy","After rollback"))) -> Post-policy
A65: 45317 | B65: =100*LN(RBI_Levels!F65/RBI_Levels!F64) -> 2.6103403 | C65: =100*LN(RBI_Levels_ExMerger!D65/RBI_Levels_ExMerger!D64) -> 1.2531485 | D65: =100*LN(RBI_Levels_ExMerger!C65/RBI_Levels_ExMerger!C64) -> 1.5835366 | E65: =100*LN(RBI_Levels!H65/RBI_Levels!H64) -> -0.44576735 | F65: =100*LN(RBI_Levels!G65/RBI_Levels!G64) -> 1.9217348 | G65: =100*LN(RBI_Levels!I65/RBI_Levels!I64) -> 0.39310985 | H65: =100*LN(RBI_Levels!K65/RBI_Levels!K64) -> -2.8761555 | I65: =100*LN(RBI_Levels!D65/RBI_Levels!D64) -> 2.3539668 | J65: =100*LN(RBI_Levels!C65/RBI_Levels!C64) -> -1.7306766 | K65: =100*LN(RBI_Levels_ExMerger!B65/RBI_Levels_ExMerger!B64) -> 0.64308581 | L65: =100*LN(RBI_Levels_ExMerger!E65/RBI_Levels_ExMerger!E64) -> 0.82631322 | M65: =AVERAGE(B65,C65)-AVERAGE(D65,E65,F65) -> 0.91190972 | N65: =IF(OR(H65="",K65=""),"",H65-K65) -> -3.5192413 | O65: =IF(OR(H65="",L65=""),"",H65-L65) -> -3.7024687 | P65: =IF(AND(A65>=DATE(2021,4,1),A65<=DATE(2025,1,31)),1,0) -> 1 | Q65: =IF(A65>=DATE(2023,12,1),1,0) -> 1 | R65: =IF(A65<DATE(2021,4,1),"Before sample",IF(A65<=DATE(2023,11,17),"Pre-policy",IF(A65<=DATE(2025,3,31),"Post-policy","After rollback"))) -> Post-policy
A66: 45345 | B66: =100*LN(RBI_Levels!F66/RBI_Levels!F65) -> -0.15327131 | C66: =100*LN(RBI_Levels_ExMerger!D66/RBI_Levels_ExMerger!D65) -> 1.2144304 | D66: =100*LN(RBI_Levels_ExMerger!C66/RBI_Levels_ExMerger!C65) -> 1.1435108 | E66: =100*LN(RBI_Levels!H66/RBI_Levels!H65) -> 0.84704989 | F66: =100*LN(RBI_Levels!G66/RBI_Levels!G65) -> 1.2897816 | G66: =100*LN(RBI_Levels!I66/RBI_Levels!I65) -> 1.0408314 | H66: =100*LN(RBI_Levels!K66/RBI_Levels!K65) -> 0.32836987 | I66: =100*LN(RBI_Levels!D66/RBI_Levels!D65) -> -2.5856184 | J66: =100*LN(RBI_Levels!C66/RBI_Levels!C65) -> -0.31560803 | K66: =100*LN(RBI_Levels_ExMerger!B66/RBI_Levels_ExMerger!B65) -> 1.2386184 | L66: =100*LN(RBI_Levels_ExMerger!E66/RBI_Levels_ExMerger!E65) -> 1.4572514 | M66: =AVERAGE(B66,C66)-AVERAGE(D66,E66,F66) -> -0.56286789 | N66: =IF(OR(H66="",K66=""),"",H66-K66) -> -0.91024854 | O66: =IF(OR(H66="",L66=""),"",H66-L66) -> -1.1288815 | P66: =IF(AND(A66>=DATE(2021,4,1),A66<=DATE(2025,1,31)),1,0) -> 1 | Q66: =IF(A66>=DATE(2023,12,1),1,0) -> 1 | R66: =IF(A66<DATE(2021,4,1),"Before sample",IF(A66<=DATE(2023,11,17),"Pre-policy",IF(A66<=DATE(2025,3,31),"Post-policy","After rollback"))) -> Post-policy
A67: 45373 | B67: =100*LN(RBI_Levels!F67/RBI_Levels!F66) -> -0.42371658 | C67: =100*LN(RBI_Levels_ExMerger!D67/RBI_Levels_ExMerger!D66) -> 1.1746347 | D67: =100*LN(RBI_Levels_ExMerger!C67/RBI_Levels_ExMerger!C66) -> 1.8165079 | E67: =100*LN(RBI_Levels!H67/RBI_Levels!H66) -> 1.3444606 | F67: =100*LN(RBI_Levels!G67/RBI_Levels!G66) -> 0.56480423 | G67: =100*LN(RBI_Levels!I67/RBI_Levels!I66) -> 0.954563 | H67: =100*LN(RBI_Levels!K67/RBI_Levels!K66) -> 3.1011756 | I67: =100*LN(RBI_Levels!D67/RBI_Levels!D66) -> -1.3431369 | J67: =100*LN(RBI_Levels!C67/RBI_Levels!C66) -> 2.1468434 | K67: =100*LN(RBI_Levels_ExMerger!B67/RBI_Levels_ExMerger!B66) -> 1.5304996 | L67: =100*LN(RBI_Levels_ExMerger!E67/RBI_Levels_ExMerger!E66) -> 1.5361362 | M67: =AVERAGE(B67,C67)-AVERAGE(D67,E67,F67) -> -0.86646523 | N67: =IF(OR(H67="",K67=""),"",H67-K67) -> 1.5706761 | O67: =IF(OR(H67="",L67=""),"",H67-L67) -> 1.5650394 | P67: =IF(AND(A67>=DATE(2021,4,1),A67<=DATE(2025,1,31)),1,0) -> 1 | Q67: =IF(A67>=DATE(2023,12,1),1,0) -> 1 | R67: =IF(A67<DATE(2021,4,1),"Before sample",IF(A67<=DATE(2023,11,17),"Pre-policy",IF(A67<=DATE(2025,3,31),"Post-policy","After rollback"))) -> Post-policy
A68: 45401 | B68: =100*LN(RBI_Levels!F68/RBI_Levels!F67) -> 1.0162605 | C68: =100*LN(RBI_Levels_ExMerger!D68/RBI_Levels_ExMerger!D67) -> -0.76093642 | D68: =100*LN(RBI_Levels_ExMerger!C68/RBI_Levels_ExMerger!C67) -> 1.124255 | E68: =100*LN(RBI_Levels!H68/RBI_Levels!H67) -> 0.88656362 | F68: =100*LN(RBI_Levels!G68/RBI_Levels!G67) -> -0.21376286 | G68: =100*LN(RBI_Levels!I68/RBI_Levels!I67) -> -0.50392754 | H68: =100*LN(RBI_Levels!K68/RBI_Levels!K67) -> 1.2124968 | I68: =100*LN(RBI_Levels!D68/RBI_Levels!D67) -> 0.72789974 | J68: =100*LN(RBI_Levels!C68/RBI_Levels!C67) -> 1.1104421 | K68: =100*LN(RBI_Levels_ExMerger!B68/RBI_Levels_ExMerger!B67) -> 0.46803965 | L68: =100*LN(RBI_Levels_ExMerger!E68/RBI_Levels_ExMerger!E67) -> 0.51457584 | M68: =AVERAGE(B68,C68)-AVERAGE(D68,E68,F68) -> -0.47135655 | N68: =IF(OR(H68="",K68=""),"",H68-K68) -> 0.74445714 | O68: =IF(OR(H68="",L68=""),"",H68-L68) -> 0.69792095 | P68: =IF(AND(A68>=DATE(2021,4,1),A68<=DATE(2025,1,31)),1,0) -> 1 | Q68: =IF(A68>=DATE(2023,12,1),1,0) -> 1 | R68: =IF(A68<DATE(2021,4,1),"Before sample",IF(A68<=DATE(2023,11,17),"Pre-policy",IF(A68<=DATE(2025,3,31),"Post-policy","After rollback"))) -> Post-policy
A69: 45443 | B69: =100*LN(RBI_Levels!F69/RBI_Levels!F68) -> 3.1607142 | C69: =100*LN(RBI_Levels_ExMerger!D69/RBI_Levels_ExMerger!D68) -> 2.0540118 | D69: =100*LN(RBI_Levels_ExMerger!C69/RBI_Levels_ExMerger!C68) -> 2.133707 | E69: =100*LN(RBI_Levels!H69/RBI_Levels!H68) -> 1.4287682 | F69: =100*LN(RBI_Levels!G69/RBI_Levels!G68) -> 1.6465901 | G69: =100*LN(RBI_Levels!I69/RBI_Levels!I68) -> 14.710501 | H69: =100*LN(RBI_Levels!K69/RBI_Levels!K68) -> 0.47384468 | I69: =100*LN(RBI_Levels!D69/RBI_Levels!D68) -> 0.44562712 | J69: =100*LN(RBI_Levels!C69/RBI_Levels!C68) -> 0.46791417 | K69: =100*LN(RBI_Levels_ExMerger!B69/RBI_Levels_ExMerger!B68) -> 1.7390227 | L69: =100*LN(RBI_Levels_ExMerger!E69/RBI_Levels_ExMerger!E68) -> 1.8278604 | M69: =AVERAGE(B69,C69)-AVERAGE(D69,E69,F69) -> 0.87100787 | N69: =IF(OR(H69="",K69=""),"",H69-K69) -> -1.2651781 | O69: =IF(OR(H69="",L69=""),"",H69-L69) -> -1.3540157 | P69: =IF(AND(A69>=DATE(2021,4,1),A69<=DATE(2025,1,31)),1,0) -> 1 | Q69: =IF(A69>=DATE(2023,12,1),1,0) -> 1 | R69: =IF(A69<DATE(2021,4,1),"Before sample",IF(A69<=DATE(2023,11,17),"Pre-policy",IF(A69<=DATE(2025,3,31),"Post-policy","After rollback"))) -> Post-policy
A70: 45471 | B70: =100*LN(RBI_Levels!F70/RBI_Levels!F69) -> 1.8725475 | C70: =100*LN(RBI_Levels_ExMerger!D70/RBI_Levels_ExMerger!D69) -> 0.021599081 | D70: =100*LN(RBI_Levels_ExMerger!C70/RBI_Levels_ExMerger!C69) -> 0.75623965 | E70: =100*LN(RBI_Levels!H70/RBI_Levels!H69) -> 0.29713037 | F70: =100*LN(RBI_Levels!G70/RBI_Levels!G69) -> 0.72950389 | G70: =100*LN(RBI_Levels!I70/RBI_Levels!I69) -> 6.4147638 | H70: =100*LN(RBI_Levels!K70/RBI_Levels!K69) -> 0.15666232 | I70: =100*LN(RBI_Levels!D70/RBI_Levels!D69) -> -0.47314346 | J70: =100*LN(RBI_Levels!C70/RBI_Levels!C69) -> 0.024638976 | K70: =100*LN(RBI_Levels_ExMerger!B70/RBI_Levels_ExMerger!B69) -> 0.73136378 | L70: =100*LN(RBI_Levels_ExMerger!E70/RBI_Levels_ExMerger!E69) -> 0.86879603 | M70: =AVERAGE(B70,C70)-AVERAGE(D70,E70,F70) -> 0.352782 | N70: =IF(OR(H70="",K70=""),"",H70-K70) -> -0.57470146 | O70: =IF(OR(H70="",L70=""),"",H70-L70) -> -0.71213371 | P70: =IF(AND(A70>=DATE(2021,4,1),A70<=DATE(2025,1,31)),1,0) -> 1 | Q70: =IF(A70>=DATE(2023,12,1),1,0) -> 1 | R70: =IF(A70<DATE(2021,4,1),"Before sample",IF(A70<=DATE(2023,11,17),"Pre-policy",IF(A70<=DATE(2025,3,31),"Post-policy","After rollback"))) -> Post-policy
A71: 45499 | B71: =100*LN(RBI_Levels!F71/RBI_Levels!F70) -> 0.93220759 | C71: =100*LN(RBI_Levels_ExMerger!D71/RBI_Levels_ExMerger!D70) -> 0.088194001 | D71: =100*LN(RBI_Levels_ExMerger!C71/RBI_Levels_ExMerger!C70) -> 0.66031687 | E71: =100*LN(RBI_Levels!H71/RBI_Levels!H70) -> 0.40796007 | F71: =100*LN(RBI_Levels!G71/RBI_Levels!G70) -> 0.87801833 | G71: =100*LN(RBI_Levels!I71/RBI_Levels!I70) -> 7.9603271 | H71: =100*LN(RBI_Levels!K71/RBI_Levels!K70) -> -1.521373 | I71: =100*LN(RBI_Levels!D71/RBI_Levels!D70) -> -2.2111585 | J71: =100*LN(RBI_Levels!C71/RBI_Levels!C70) -> -1.665217 | K71: =100*LN(RBI_Levels_ExMerger!B71/RBI_Levels_ExMerger!B70) -> -0.36629122 | L71: =100*LN(RBI_Levels_ExMerger!E71/RBI_Levels_ExMerger!E70) -> -0.29058405 | M71: =AVERAGE(B71,C71)-AVERAGE(D71,E71,F71) -> -0.1385643 | N71: =IF(OR(H71="",K71=""),"",H71-K71) -> -1.1550818 | O71: =IF(OR(H71="",L71=""),"",H71-L71) -> -1.2307889 | P71: =IF(AND(A71>=DATE(2021,4,1),A71<=DATE(2025,1,31)),1,0) -> 1 | Q71: =IF(A71>=DATE(2023,12,1),1,0) -> 1 | R71: =IF(A71<DATE(2021,4,1),"Before sample",IF(A71<=DATE(2023,11,17),"Pre-policy",IF(A71<=DATE(2025,3,31),"Post-policy","After rollback"))) -> Post-policy
... A82: 45835 | B82: =100*LN(RBI_Levels!F82/RBI_Levels!F81) -> 0.65970049 | C82: =100*LN(RBI_Levels_ExMerger!D82/RBI_Levels_ExMerger!D81) -> -0.1244776 | D82: =100*LN(RBI_Levels_ExMerger!C82/RBI_Levels_ExMerger!C81) -> 1.2169817 | E82: =100*LN(RBI_Levels!H82/RBI_Levels!H81) -> 0.77801415 | F82: =100*LN(RBI_Levels!G82/RBI_Levels!G81) -> 1.0483729 | G82: =100*LN(RBI_Levels!I82/RBI_Levels!I81) -> 9.8932885 | H82: =100*LN(RBI_Levels!K82/RBI_Levels!K81) -> 0.89489796 | I82: =100*LN(RBI_Levels!D82/RBI_Levels!D81) -> 7.0637812 | J82: =100*LN(RBI_Levels!C82/RBI_Levels!C81) -> 2.1448363 | K82: =100*LN(RBI_Levels_ExMerger!B82/RBI_Levels_ExMerger!B81) -> 1.1504982 | L82: =100*LN(RBI_Levels_ExMerger!E82/RBI_Levels_ExMerger!E81) -> 1.1865397 | M82: =AVERAGE(B82,C82)-AVERAGE(D82,E82,F82) -> -0.74684479 | N82: =IF(OR(H82="",K82=""),"",H82-K82) -> -0.25560025 | O82: =IF(OR(H82="",L82=""),"",H82-L82) -> -0.29164172 | P82: =IF(AND(A82>=DATE(2021,4,1),A82<=DATE(2025,1,31)),1,0) -> 0 | Q82: =IF(A82>=DATE(2023,12,1),1,0) -> 1 | R82: =IF(A82<DATE(2021,4,1),"Before sample",IF(A82<=DATE(2023,11,17),"Pre-policy",IF(A82<=DATE(2025,3,31),"Post-policy","After rollback"))) -> After rollback
A83: 45863 | B83: =100*LN(RBI_Levels!F83/RBI_Levels!F82) -> -0.51867492 | C83: =100*LN(RBI_Levels!J83/RBI_Levels!J82) -> 0.51784668 | D83: =100*LN(RBI_Levels!E83/RBI_Levels!E82) -> 0.45645728 | E83: =100*LN(RBI_Levels!H83/RBI_Levels!H82) -> 0.12248402 | F83: =100*LN(RBI_Levels!G83/RBI_Levels!G82) -> 1.3875511 | G83: =100*LN(RBI_Levels!I83/RBI_Levels!I82) -> 6.0664363 | H83: =100*LN(RBI_Levels!K83/RBI_Levels!K82) -> -0.95246367 | I83: =100*LN(RBI_Levels!D83/RBI_Levels!D82) -> -4.8153473 | J83: =100*LN(RBI_Levels!C83/RBI_Levels!C82) -> -1.7423451 | K83: =100*LN(RBI_Levels!B83/RBI_Levels!B82) -> 0.1241886 | L83: =100*LN(RBI_Levels!L83/RBI_Levels!L82) -> 0.29276667 | M83: =AVERAGE(B83,C83)-AVERAGE(D83,E83,F83) -> -0.65591157 | N83: =IF(OR(H83="",K83=""),"",H83-K83) -> -1.0766523 | O83: =IF(OR(H83="",L83=""),"",H83-L83) -> -1.2452303 | P83: =IF(AND(A83>=DATE(2021,4,1),A83<=DATE(2025,1,31)),1,0) -> 0 | Q83: =IF(A83>=DATE(2023,12,1),1,0) -> 1 | R83: =IF(A83<DATE(2021,4,1),"Before sample",IF(A83<=DATE(2023,11,17),"Pre-policy",IF(A83<=DATE(2025,3,31),"Post-policy","After rollback"))) -> After rollback
A84: 45891 | B84: =100*LN(RBI_Levels!F84/RBI_Levels!F83) -> -0.8268715 | C84: =100*LN(RBI_Levels!J84/RBI_Levels!J83) -> 0.42956627 | D84: =100*LN(RBI_Levels!E84/RBI_Levels!E83) -> 0.89300299 | E84: =100*LN(RBI_Levels!H84/RBI_Levels!H83) -> 0.64639144 | F84: =100*LN(RBI_Levels!G84/RBI_Levels!G83) -> 2.09882 | G84: =100*LN(RBI_Levels!I84/RBI_Levels!I83) -> 3.932306 | H84: =100*LN(RBI_Levels!K84/RBI_Levels!K83) -> 0.21277215 | I84: =100*LN(RBI_Levels!D84/RBI_Levels!D83) -> 0.88054909 | J84: =100*LN(RBI_Levels!C84/RBI_Levels!C83) -> 0.347588 | K84: =100*LN(RBI_Levels!B84/RBI_Levels!B83) -> 0.80908355 | L84: =100*LN(RBI_Levels!L84/RBI_Levels!L83) -> 0.92768836 | M84: =AVERAGE(B84,C84)-AVERAGE(D84,E84,F84) -> -1.4113908 | N84: =IF(OR(H84="",K84=""),"",H84-K84) -> -0.59631141 | O84: =IF(OR(H84="",L84=""),"",H84-L84) -> -0.71491622 | P84: =IF(AND(A84>=DATE(2021,4,1),A84<=DATE(2025,1,31)),1,0) -> 0 | Q84: =IF(A84>=DATE(2023,12,1),1,0) -> 1 | R84: =IF(A84<DATE(2021,4,1),"Before sample",IF(A84<=DATE(2023,11,17),"Pre-policy",IF(A84<=DATE(2025,3,31),"Post-policy","After rollback"))) -> After rollback
A85: 45919 | B85: =100*LN(RBI_Levels!F85/RBI_Levels!F84) -> -2.4077698 | C85: =100*LN(RBI_Levels!J85/RBI_Levels!J84) -> 0.75984549 | D85: =100*LN(RBI_Levels!E85/RBI_Levels!E84) -> 0.7715296 | E85: =100*LN(RBI_Levels!H85/RBI_Levels!H84) -> -0.24511824 | F85: =100*LN(RBI_Levels!G85/RBI_Levels!G84) -> 1.8079782 | G85: =100*LN(RBI_Levels!I85/RBI_Levels!I84) -> 3.3308031 | H85: =100*LN(RBI_Levels!K85/RBI_Levels!K84) -> 0.67154578 | I85: =100*LN(RBI_Levels!D85/RBI_Levels!D84) -> 1.9874203 | J85: =100*LN(RBI_Levels!C85/RBI_Levels!C84) -> 0.93931429 | K85: =100*LN(RBI_Levels!B85/RBI_Levels!B84) -> 1.4050574 | L85: =100*LN(RBI_Levels!L85/RBI_Levels!L84) -> 1.5905146 | M85: =AVERAGE(B85,C85)-AVERAGE(D85,E85,F85) -> -1.602092 | N85: =IF(OR(H85="",K85=""),"",H85-K85) -> -0.73351162 | O85: =IF(OR(H85="",L85=""),"",H85-L85) -> -0.91896886 | P85: =IF(AND(A85>=DATE(2021,4,1),A85<=DATE(2025,1,31)),1,0) -> 0 | Q85: =IF(A85>=DATE(2023,12,1),1,0) -> 1 | R85: =IF(A85<DATE(2021,4,1),"Before sample",IF(A85<=DATE(2023,11,17),"Pre-policy",IF(A85<=DATE(2025,3,31),"Post-policy","After rollback"))) -> After rollback
A86: 45961 | B86: =100*LN(RBI_Levels!F86/RBI_Levels!F85) -> 7.2694486 | C86: =100*LN(RBI_Levels!J86/RBI_Levels!J85) -> 2.697761 | D86: =100*LN(RBI_Levels!E86/RBI_Levels!E85) -> 1.7280188 | E86: =100*LN(RBI_Levels!H86/RBI_Levels!H85) -> 4.7012603 | F86: =100*LN(RBI_Levels!G86/RBI_Levels!G85) -> 1.5279208 | G86: =100*LN(RBI_Levels!I86/RBI_Levels!I85) -> 6.7060614 | H86: =100*LN(RBI_Levels!K86/RBI_Levels!K85) -> 8.1806154 | I86: =100*LN(RBI_Levels!D86/RBI_Levels!D85) -> 2.1741608 | J86: =100*LN(RBI_Levels!C86/RBI_Levels!C85) -> 6.9809475 | K86: =100*LN(RBI_Levels!B86/RBI_Levels!B85) -> 2.4228836 | L86: =100*LN(RBI_Levels!L86/RBI_Levels!L85) -> 1.8214754 | M86: =AVERAGE(B86,C86)-AVERAGE(D86,E86,F86) -> 2.3312048 | N86: =IF(OR(H86="",K86=""),"",H86-K86) -> 5.7577318 | O86: =IF(OR(H86="",L86=""),"",H86-L86) -> 6.35914 | P86: =IF(AND(A86>=DATE(2021,4,1),A86<=DATE(2025,1,31)),1,0) -> 0 | Q86: =IF(A86>=DATE(2023,12,1),1,0) -> 1 | R86: =IF(A86<DATE(2021,4,1),"Before sample",IF(A86<=DATE(2023,11,17),"Pre-policy",IF(A86<=DATE(2025,3,31),"Post-policy","After rollback"))) -> After rollback
A87: 45989 | B87: =100*LN(RBI_Levels!F87/RBI_Levels!F86) -> -2.3377788 | C87: =100*LN(RBI_Levels!J87/RBI_Levels!J86) -> 0.55999374 | D87: =100*LN(RBI_Levels!E87/RBI_Levels!E86) -> 0.24647441 | E87: =100*LN(RBI_Levels!H87/RBI_Levels!H86) -> 0.46940733 | F87: =100*LN(RBI_Levels!G87/RBI_Levels!G86) -> 0.23927134 | G87: =100*LN(RBI_Levels!I87/RBI_Levels!I86) -> 6.0530522 | H87: =100*LN(RBI_Levels!K87/RBI_Levels!K86) -> 0.41701063 | I87: =100*LN(RBI_Levels!D87/RBI_Levels!D86) -> 4.1851799 | J87: =100*LN(RBI_Levels!C87/RBI_Levels!C86) -> 1.1628757 | K87: =100*LN(RBI_Levels!B87/RBI_Levels!B86) -> 0.65716715 | L87: =100*LN(RBI_Levels!L87/RBI_Levels!L86) -> 0.66911827 | M87: =AVERAGE(B87,C87)-AVERAGE(D87,E87,F87) -> -1.2072769 | N87: =IF(OR(H87="",K87=""),"",H87-K87) -> -0.24015652 | O87: =IF(OR(H87="",L87=""),"",H87-L87) -> -0.25210764 | P87: =IF(AND(A87>=DATE(2021,4,1),A87<=DATE(2025,1,31)),1,0) -> 0 | Q87: =IF(A87>=DATE(2023,12,1),1,0) -> 1 | R87: =IF(A87<DATE(2021,4,1),"Before sample",IF(A87<=DATE(2023,11,17),"Pre-policy",IF(A87<=DATE(2025,3,31),"Post-policy","After rollback"))) -> After rollback
A88: 46022 | B88: =100*LN(RBI_Levels!F88/RBI_Levels!F87) -> -0.73631445 | C88: =100*LN(RBI_Levels!J88/RBI_Levels!J87) -> 2.800406 | D88: =100*LN(RBI_Levels!E88/RBI_Levels!E87) -> 1.8927558 | E88: =100*LN(RBI_Levels!H88/RBI_Levels!H87) -> 5.0306306 | F88: =100*LN(RBI_Levels!G88/RBI_Levels!G87) -> 1.9756814 | G88: =100*LN(RBI_Levels!I88/RBI_Levels!I87) -> 5.8379084 | H88: =100*LN(RBI_Levels!K88/RBI_Levels!K87) -> 9.3541955 | I88: =100*LN(RBI_Levels!D88/RBI_Levels!D87) -> 1.9036863 | J88: =100*LN(RBI_Levels!C88/RBI_Levels!C87) -> 7.9009879 | K88: =100*LN(RBI_Levels!B88/RBI_Levels!B87) -> 3.9672048 | L88: =100*LN(RBI_Levels!L88/RBI_Levels!L87) -> 3.7347933 | M88: =AVERAGE(B88,C88)-AVERAGE(D88,E88,F88) -> -1.9343101 | N88: =IF(OR(H88="",K88=""),"",H88-K88) -> 5.3869907 | O88: =IF(OR(H88="",L88=""),"",H88-L88) -> 5.6194021 | P88: =IF(AND(A88>=DATE(2021,4,1),A88<=DATE(2025,1,31)),1,0) -> 0 | Q88: =IF(A88>=DATE(2023,12,1),1,0) -> 1 | R88: =IF(A88<DATE(2021,4,1),"Before sample",IF(A88<=DATE(2023,11,17),"Pre-policy",IF(A88<=DATE(2025,3,31),"Post-policy","After rollback"))) -> After rollback
A89: 46053 | B89: =100*LN(RBI_Levels!F89/RBI_Levels!F88) -> 0.85344783 | C89: =100*LN(RBI_Levels!J89/RBI_Levels!J88) -> 0.76751833 | D89: =100*LN(RBI_Levels!E89/RBI_Levels!E88) -> 0.67402296 | E89: =100*LN(RBI_Levels!H89/RBI_Levels!H88) -> 0.68513735 | F89: =100*LN(RBI_Levels!G89/RBI_Levels!G88) -> 1.3715407 | G89: =100*LN(RBI_Levels!I89/RBI_Levels!I88) -> 5.2044087 | H89: =100*LN(RBI_Levels!K89/RBI_Levels!K88) -> 2.584139 | I89: =100*LN(RBI_Levels!D89/RBI_Levels!D88) -> 0.12174717 | J89: =100*LN(RBI_Levels!C89/RBI_Levels!C88) -> 2.122774 | K89: =100*LN(RBI_Levels!B89/RBI_Levels!B88) -> 0.74614424 | L89: =100*LN(RBI_Levels!L89/RBI_Levels!L88) -> 0.58429189 | M89: =AVERAGE(B89,C89)-AVERAGE(D89,E89,F89) -> -0.099750584 | N89: =IF(OR(H89="",K89=""),"",H89-K89) -> 1.8379947 | O89: =IF(OR(H89="",L89=""),"",H89-L89) -> 1.9998471 | P89: =IF(AND(A89>=DATE(2021,4,1),A89<=DATE(2025,1,31)),1,0) -> 0 | Q89: =IF(A89>=DATE(2023,12,1),1,0) -> 1 | R89: =IF(A89<DATE(2021,4,1),"Before sample",IF(A89<=DATE(2023,11,17),"Pre-policy",IF(A89<=DATE(2025,3,31),"Post-policy","After rollback"))) -> After rollback
A90: 46081 | B90: =100*LN(RBI_Levels!F90/RBI_Levels!F89) -> -1.4784019 | C90: =100*LN(RBI_Levels!J90/RBI_Levels!J89) -> 1.030549 | D90: =100*LN(RBI_Levels!E90/RBI_Levels!E89) -> 0.82839296 | E90: =100*LN(RBI_Levels!H90/RBI_Levels!H89) -> 0.75625756 | F90: =100*LN(RBI_Levels!G90/RBI_Levels!G89) -> 0.44510507 | G90: =100*LN(RBI_Levels!I90/RBI_Levels!I89) -> 6.7716539 | H90: =100*LN(RBI_Levels!K90/RBI_Levels!K89) -> 2.3284586 | I90: =100*LN(RBI_Levels!D90/RBI_Levels!D89) -> 1.6334179 | J90: =100*LN(RBI_Levels!C90/RBI_Levels!C89) -> 2.1998966 | K90: =100*LN(RBI_Levels!B90/RBI_Levels!B89) -> 1.3900137 | L90: =100*LN(RBI_Levels!L90/RBI_Levels!L89) -> 1.383565 | M90: =AVERAGE(B90,C90)-AVERAGE(D90,E90,F90) -> -0.90051164 | N90: =IF(OR(H90="",K90=""),"",H90-K90) -> 0.93844493 | O90: =IF(OR(H90="",L90=""),"",H90-L90) -> 0.94489362 | P90: =IF(AND(A90>=DATE(2021,4,1),A90<=DATE(2025,1,31)),1,0) -> 0 | Q90: =IF(A90>=DATE(2023,12,1),1,0) -> 1 | R90: =IF(A90<DATE(2021,4,1),"Before sample",IF(A90<=DATE(2023,11,17),"Pre-policy",IF(A90<=DATE(2025,3,31),"Post-policy","After rollback"))) -> After rollback
A91: 46112 | B91: =100*LN(RBI_Levels!F91/RBI_Levels!F90) -> 0.81625896 | C91: =100*LN(RBI_Levels!J91/RBI_Levels!J90) -> 1.6970852 | D91: =100*LN(RBI_Levels!E91/RBI_Levels!E90) -> 1.5093092 | E91: =100*LN(RBI_Levels!H91/RBI_Levels!H90) -> 1.7260696 | F91: =100*LN(RBI_Levels!G91/RBI_Levels!G90) -> 0.1501472 | G91: =100*LN(RBI_Levels!I91/RBI_Levels!I90) -> 7.3734075 | H91: =100*LN(RBI_Levels!K91/RBI_Levels!K90) -> 6.5803383 | I91: =100*LN(RBI_Levels!D91/RBI_Levels!D90) -> 3.8535459 | J91: =100*LN(RBI_Levels!C91/RBI_Levels!C90) -> 6.08295 | K91: =100*LN(RBI_Levels!B91/RBI_Levels!B90) -> 2.9539349 | L91: =100*LN(RBI_Levels!L91/RBI_Levels!L90) -> 2.7477336 | M91: =AVERAGE(B91,C91)-AVERAGE(D91,E91,F91) -> 0.1281634 | N91: =IF(OR(H91="",K91=""),"",H91-K91) -> 3.6264035 | O91: =IF(OR(H91="",L91=""),"",H91-L91) -> 3.8326048 | P91: =IF(AND(A91>=DATE(2021,4,1),A91<=DATE(2025,1,31)),1,0) -> 0 | Q91: =IF(A91>=DATE(2023,12,1),1,0) -> 1 | R91: =IF(A91<DATE(2021,4,1),"Before sample",IF(A91<=DATE(2023,11,17),"Pre-policy",IF(A91<=DATE(2025,3,31),"Post-policy","After rollback"))) -> After rollback
A92: 46142 | B92: =100*LN(RBI_Levels!F92/RBI_Levels!F91) -> 1.2001359 | C92: =100*LN(RBI_Levels!J92/RBI_Levels!J91) -> 0.061200975 | D92: =100*LN(RBI_Levels!E92/RBI_Levels!E91) -> -0.12554266 | E92: =100*LN(RBI_Levels!H92/RBI_Levels!H91) -> 0.56593892 | F92: =100*LN(RBI_Levels!G92/RBI_Levels!G91) -> -0.080758079 | G92: =100*LN(RBI_Levels!I92/RBI_Levels!I91) -> 5.7666791 | H92: =100*LN(RBI_Levels!K92/RBI_Levels!K91) -> -0.43835096 | I92: =100*LN(RBI_Levels!D92/RBI_Levels!D91) -> -1.5929857 | J92: =100*LN(RBI_Levels!C92/RBI_Levels!C91) -> -0.64564137 | K92: =100*LN(RBI_Levels!B92/RBI_Levels!B91) -> -0.8644127 | L92: =100*LN(RBI_Levels!L92/RBI_Levels!L91) -> -1.0202756 | M92: =AVERAGE(B92,C92)-AVERAGE(D92,E92,F92) -> 0.51078903 | N92: =IF(OR(H92="",K92=""),"",H92-K92) -> 0.42606174 | O92: =IF(OR(H92="",L92=""),"",H92-L92) -> 0.58192464 | P92: =IF(AND(A92>=DATE(2021,4,1),A92<=DATE(2025,1,31)),1,0) -> 0 | Q92: =IF(A92>=DATE(2023,12,1),1,0) -> 1 | R92: =IF(A92<DATE(2021,4,1),"Before sample",IF(A92<=DATE(2023,11,17),"Pre-policy",IF(A92<=DATE(2025,3,31),"Post-policy","After rollback"))) -> After rollback
A93: 46173 | B93: =100*LN(RBI_Levels!F93/RBI_Levels!F92) -> -1.1749335 | C93: =100*LN(RBI_Levels!J93/RBI_Levels!J92) -> 0.60501083 | D93: =100*LN(RBI_Levels!E93/RBI_Levels!E92) -> 0.51428622 | E93: =100*LN(RBI_Levels!H93/RBI_Levels!H92) -> 0.74833383 | F93: =100*LN(RBI_Levels!G93/RBI_Levels!G92) -> 1.1615155 | G93: =100*LN(RBI_Levels!I93/RBI_Levels!I92) -> 5.0896191 | H93: =100*LN(RBI_Levels!K93/RBI_Levels!K92) -> 1.7475467 | I93: =100*LN(RBI_Levels!D93/RBI_Levels!D92) -> 0.59911777 | J93: =100*LN(RBI_Levels!C93/RBI_Levels!C92) -> 1.5433112 | K93: =100*LN(RBI_Levels!B93/RBI_Levels!B92) -> 1.2759247 | L93: =100*LN(RBI_Levels!L93/RBI_Levels!L92) -> 1.3540148 | M93: =AVERAGE(B93,C93)-AVERAGE(D93,E93,F93) -> -1.0930065 | N93: =IF(OR(H93="",K93=""),"",H93-K93) -> 0.47162201 | O93: =IF(OR(H93="",L93=""),"",H93-L93) -> 0.39353191 | P93: =IF(AND(A93>=DATE(2021,4,1),A93<=DATE(2025,1,31)),1,0) -> 0 | Q93: =IF(A93>=DATE(2023,12,1),1,0) -> 1 | R93: =IF(A93<DATE(2021,4,1),"Before sample",IF(A93<=DATE(2023,11,17),"Pre-policy",IF(A93<=DATE(2025,3,31),"Post-policy","After rollback"))) -> After rollback
A94: 46203 | B94: =100*LN(RBI_Levels!F94/RBI_Levels!F93) -> 1.2636145 | C94: =100*LN(RBI_Levels!J94/RBI_Levels!J93) -> 1.3698228 | D94: =100*LN(RBI_Levels!E94/RBI_Levels!E93) -> 1.026802 | E94: =100*LN(RBI_Levels!H94/RBI_Levels!H93) -> 0.78785523 | F94: =100*LN(RBI_Levels!G94/RBI_Levels!G93) -> 0.37954887 | G94: =100*LN(RBI_Levels!I94/RBI_Levels!I93) -> 4.0513244 | H94: =100*LN(RBI_Levels!K94/RBI_Levels!K93) -> 1.1428757 | I94: =100*LN(RBI_Levels!D94/RBI_Levels!D93) -> 0.59962918 | J94: =100*LN(RBI_Levels!C94/RBI_Levels!C93) -> 1.0469355 | K94: =100*LN(RBI_Levels!B94/RBI_Levels!B93) -> 1.9333697 | L94: =100*LN(RBI_Levels!L94/RBI_Levels!L93) -> 2.1082269 | M94: =AVERAGE(B94,C94)-AVERAGE(D94,E94,F94) -> 0.58531663 | N94: =IF(OR(H94="",K94=""),"",H94-K94) -> -0.79049402 | O94: =IF(OR(H94="",L94=""),"",H94-L94) -> -0.96535124 | P94: =IF(AND(A94>=DATE(2021,4,1),A94<=DATE(2025,1,31)),1,0) -> 0 | Q94: =IF(A94>=DATE(2023,12,1),1,0) -> 1 | R94: =IF(A94<DATE(2021,4,1),"Before sample",IF(A94<=DATE(2023,11,17),"Pre-policy",IF(A94<=DATE(2025,3,31),"Post-policy","After rollback"))) -> After rollback
A95: 46234 | B95: =100*LN(RBI_Levels!F95/RBI_Levels!F94) -> -0.17593595 | C95: =100*LN(RBI_Levels!J95/RBI_Levels!J94) -> 0.94564052 | D95: =100*LN(RBI_Levels!E95/RBI_Levels!E94) -> 0.72149324 | E95: =100*LN(RBI_Levels!H95/RBI_Levels!H94) -> 1.3410319 | F95: =100*LN(RBI_Levels!G95/RBI_Levels!G94) -> 1.7744918 | G95: =100*LN(RBI_Levels!I95/RBI_Levels!I94) -> 3.0737708 | H95: =100*LN(RBI_Levels!K95/RBI_Levels!K94) -> 0.39471694 | I95: =100*LN(RBI_Levels!D95/RBI_Levels!D94) -> 2.7272182 | J95: =100*LN(RBI_Levels!C95/RBI_Levels!C94) -> 0.80969695 | K95: =100*LN(RBI_Levels!B95/RBI_Levels!B94) -> 0.74937094 | L95: =100*LN(RBI_Levels!L95/RBI_Levels!L94) -> 0.73802763 | M95: =AVERAGE(B95,C95)-AVERAGE(D95,E95,F95) -> -0.89415334 | N95: =IF(OR(H95="",K95=""),"",H95-K95) -> -0.35465401 | O95: =IF(OR(H95="",L95=""),"",H95-L95) -> -0.34331069 | P95: =IF(AND(A95>=DATE(2021,4,1),A95<=DATE(2025,1,31)),1,0) -> 0 | Q95: =IF(A95>=DATE(2023,12,1),1,0) -> 1 | R95: =IF(A95<DATE(2021,4,1),"Before sample",IF(A95<=DATE(2023,11,17),"Pre-policy",IF(A95<=DATE(2025,3,31),"Post-policy","After rollback"))) -> After rollback

Sheet Share_Prices
A1: Daily closing prices (₹; index points for Nifty), 1 September 2022 to 28 March 2025
A2: Source: Investing.com historical data (NSE listings), adjusted for splits and bonus issues. 26-Feb-2025 was a market holiday (Mahashivratri).
A4: Date | B4: NIFTY50 | C4: NIFTY500 | D4: AAVAS | E4: CANFINHOME | F4: HOMEFIRST | G4: LICHSGFIN | H4: PNBHOUSING | I4: REPCOHOME | J4: ARMANFIN | K4: BAJFINANCE | L4: CHOLAFIN | M4: CREDITACC | N4: IIFL | O4: MMFIN | P4: MUTHOOTFIN | Q4: POONAWALLA | R4: SBICARD | S4: SHRIRAMFIN
A5: 44805 | B5: 17542.8 | C5: 15211.2 | D5: 2307.1 | E5: 643.45 | F5: 936.1 | G5: 417.05 | H5: 298.29 | I5: 243.8 | J5: 1401.5 | K5: 717.15 | L5: 789.3 | M5: 982.6 | N5: 334.39 | O5: 206.85 | P5: 1044.75 | Q5: 305.8 | R5: 928.05 | S5: 265.85
A6: 44806 | B6: 17539.45 | C6: 15201.6 | D6: 2276.9 | E6: 635.9 | F6: 929.45 | G6: 418.05 | H6: 314.61 | I6: 242.45 | J6: 1423.85 | K6: 718.06 | L6: 790.5 | M6: 995.5 | N6: 333.76 | O6: 209.1 | P6: 1030 | Q6: 305.35 | R6: 932.5 | S6: 261.72
A7: 44809 | B7: 17665.8 | C7: 15294.4 | D7: 2287.95 | E7: 638.6 | F7: 913.4 | G7: 425.55 | H7: 311.17 | I7: 237.1 | J7: 1419.4 | K7: 718.64 | L7: 799.75 | M7: 1017.15 | N7: 328.85 | O7: 214.9 | P7: 1030.6 | Q7: 303.6 | R7: 936.35 | S7: 264.16
A8: 44810 | B8: 17655.6 | C8: 15313.05 | D8: 2283.35 | E8: 644.75 | F8: 886.2 | G8: 422.35 | H8: 304.67 | I8: 232.95 | J8: 1414.6 | K8: 710.97 | L8: 801.8 | M8: 1052.75 | N8: 323.17 | O8: 219.8 | P8: 1030.6 | Q8: 299.5 | R8: 950.25 | S8: 276.95
A9: 44811 | B9: 17624.4 | C9: 15319.4 | D9: 2286.3 | E9: 641.6 | F9: 859.15 | G9: 423.6 | H9: 307.61 | I9: 238 | J9: 1404.55 | K9: 715.68 | L9: 802.2 | M9: 1038.9 | N9: 323.51 | O9: 222.3 | P9: 1035.9 | Q9: 299.65 | R9: 958.15 | S9: 273.32
A10: 44812 | B10: 17798.75 | C10: 15440.7 | D10: 2290.7 | E10: 646.75 | F10: 887.15 | G10: 432.8 | H10: 306.86 | I10: 235.3 | J10: 1406.45 | K10: 724.78 | L10: 801.4 | M10: 1039.25 | N10: 325.65 | O10: 220.9 | P10: 1040.35 | Q10: 303.1 | R10: 963.2 | S10: 272.29
A11: 44813 | B11: 17833.35 | C11: 15467.4 | D11: 2313.25 | E11: 647.05 | F11: 873.85 | G11: 436.7 | H11: 308.68 | I11: 231.5 | J11: 1402.35 | K11: 717.11 | L11: 790.75 | M11: 1029.7 | N11: 326.23 | O11: 224.65 | P11: 1045.35 | Q11: 305.25 | R11: 943.25 | S11: 264.82
A12: 44816 | B12: 17936.35 | C12: 15577.4 | D12: 2308.15 | E12: 656.4 | F12: 879.55 | G12: 437.55 | H12: 308.23 | I12: 254.65 | J12: 1420.35 | K12: 727.7 | L12: 798.2 | M12: 1044.05 | N12: 327.15 | O12: 225.45 | P12: 1046.15 | Q12: 303.25 | R12: 949.75 | S12: 265.7
A13: 44817 | B13: 18070.05 | C13: 15669.85 | D13: 2280.85 | E13: 651.65 | F13: 861.4 | G13: 437.25 | H13: 333.37 | I13: 250 | J13: 1418.2 | K13: 739.34 | L13: 797.9 | M13: 1030.4 | N13: 337.21 | O13: 225.85 | P13: 1050.2 | Q13: 301.5 | R13: 952.75 | S13: 266.52
A14: 44818 | B14: 18003.75 | C14: 15630.7 | D14: 2264.4 | E14: 653.5 | F14: 864.9 | G14: 438.95 | H14: 336.22 | I14: 258.6 | J14: 1408 | K14: 747.33 | L14: 794.85 | M14: 1025.35 | N14: 339.49 | O14: 229.55 | P14: 1041.6 | Q14: 296.55 | R14: 957.85 | S14: 266.93
A15: 44819 | B15: 17877.4 | C15: 15580.35 | D15: 2211.65 | E15: 664.35 | F15: 890.6 | G15: 440.35 | H15: 342.68 | I15: 255.9 | J15: 1504.35 | K15: 737.63 | L15: 792.8 | M15: 1000.6 | N15: 352.46 | O15: 229.9 | P15: 1059.55 | Q15: 314.8 | R15: 958.65 | S15: 265.19
A16: 44820 | B16: 17530.85 | C16: 15243.95 | D16: 2164.4 | E16: 635 | F16: 868.05 | G16: 430.6 | H16: 340.41 | I16: 231.95 | J16: 1466.95 | K16: 726.42 | L16: 768.6 | M16: 1012.65 | N16: 351.54 | O16: 226.1 | P16: 1033.4 | Q16: 313.6 | R16: 934.05 | S16: 256.81
... A645: 45744 | B645: 23519.35 | C645: 21339.55 | D645: 2084.05 | E645: 669.45 | F645: 1014.15 | G645: 563.85 | H645: 881.5 | I645: 335.1 | J645: 1289.4 | K645: 893.34 | L645: 1519.95 | M645: 951.95 | N645: 327.65 | O645: 283 | P645: 2382.9 | Q645: 350.45 | R645: 881.1 | S645: 656

Sheet Share_Returns
A1: Daily simple returns (formula: today's close / previous close − 1)
A2: Formulas referencing Share_Prices. Used in the event study.
A4: Date | B4: NIFTY50 | C4: NIFTY500 | D4: AAVAS | E4: CANFINHOME | F4: HOMEFIRST | G4: LICHSGFIN | H4: PNBHOUSING | I4: REPCOHOME | J4: ARMANFIN | K4: BAJFINANCE | L4: CHOLAFIN | M4: CREDITACC | N4: IIFL | O4: MMFIN | P4: MUTHOOTFIN | Q4: POONAWALLA | R4: SBICARD | S4: SHRIRAMFIN
A5: =Share_Prices!A5 -> 44805
A6: =Share_Prices!A6 -> 44806 | B6: =Share_Prices!B6/Share_Prices!B5-1 -> -0.00019096153 | C6: =Share_Prices!C6/Share_Prices!C5-1 -> -0.00063111392 | D6: =Share_Prices!D6/Share_Prices!D5-1 -> -0.013090026 | E6: =Share_Prices!E6/Share_Prices!E5-1 -> -0.011733623 | F6: =Share_Prices!F6/Share_Prices!F5-1 -> -0.0071039419 | G6: =Share_Prices!G6/Share_Prices!G5-1 -> 0.002397794 | H6: =Share_Prices!H6/Share_Prices!H5-1 -> 0.054711858 | I6: =Share_Prices!I6/Share_Prices!I5-1 -> -0.0055373257 | ... S6: =Share_Prices!S6/Share_Prices!S5-1 -> -0.015535076
A7: =Share_Prices!A7 -> 44809 | B7: =Share_Prices!B7/Share_Prices!B6-1 -> 0.0072037607 | C7: =Share_Prices!C7/Share_Prices!C6-1 -> 0.0061046206 | D7: =Share_Prices!D7/Share_Prices!D6-1 -> 0.0048530897 | E7: =Share_Prices!E7/Share_Prices!E6-1 -> 0.0042459506 | F7: =Share_Prices!F7/Share_Prices!F6-1 -> -0.017268277 | G7: =Share_Prices!G7/Share_Prices!G6-1 -> 0.017940438 | H7: =Share_Prices!H7/Share_Prices!H6-1 -> -0.010934172 | I7: =Share_Prices!I7/Share_Prices!I6-1 -> -0.022066405 | ... S7: =Share_Prices!S7/Share_Prices!S6-1 -> 0.0093229405
A8: =Share_Prices!A8 -> 44810 | B8: =Share_Prices!B8/Share_Prices!B7-1 -> -0.00057738682 | C8: =Share_Prices!C8/Share_Prices!C7-1 -> 0.0012194006 | D8: =Share_Prices!D8/Share_Prices!D7-1 -> -0.0020105334 | E8: =Share_Prices!E8/Share_Prices!E7-1 -> 0.0096304416 | F8: =Share_Prices!F8/Share_Prices!F7-1 -> -0.029778848 | G8: =Share_Prices!G8/Share_Prices!G7-1 -> -0.0075196804 | H8: =Share_Prices!H8/Share_Prices!H7-1 -> -0.020888903 | I8: =Share_Prices!I8/Share_Prices!I7-1 -> -0.017503163 | ... S8: =Share_Prices!S8/Share_Prices!S7-1 -> 0.048417626
A9: =Share_Prices!A9 -> 44811 | B9: =Share_Prices!B9/Share_Prices!B8-1 -> -0.0017671447 | C9: =Share_Prices!C9/Share_Prices!C8-1 -> 0.00041467898 | D9: =Share_Prices!D9/Share_Prices!D8-1 -> 0.0012919614 | E9: =Share_Prices!E9/Share_Prices!E8-1 -> -0.0048856146 | F9: =Share_Prices!F9/Share_Prices!F8-1 -> -0.030523584 | G9: =Share_Prices!G9/Share_Prices!G8-1 -> 0.0029596306 | H9: =Share_Prices!H9/Share_Prices!H8-1 -> 0.009649785 | I9: =Share_Prices!I9/Share_Prices!I8-1 -> 0.021678472 | ... S9: =Share_Prices!S9/Share_Prices!S8-1 -> -0.013107059
A10: =Share_Prices!A10 -> 44812 | B10: =Share_Prices!B10/Share_Prices!B9-1 -> 0.0098925353 | C10: =Share_Prices!C10/Share_Prices!C9-1 -> 0.0079180647 | D10: =Share_Prices!D10/Share_Prices!D9-1 -> 0.0019245068 | E10: =Share_Prices!E10/Share_Prices!E9-1 -> 0.008026808 | F10: =Share_Prices!F10/Share_Prices!F9-1 -> 0.032590351 | G10: =Share_Prices!G10/Share_Prices!G9-1 -> 0.021718602 | H10: =Share_Prices!H10/Share_Prices!H9-1 -> -0.0024381522 | I10: =Share_Prices!I10/Share_Prices!I9-1 -> -0.011344538 | ... S10: =Share_Prices!S10/Share_Prices!S9-1 -> -0.0037684765
A11: =Share_Prices!A11 -> 44813 | B11: =Share_Prices!B11/Share_Prices!B10-1 -> 0.0019439567 | C11: =Share_Prices!C11/Share_Prices!C10-1 -> 0.0017291962 | D11: =Share_Prices!D11/Share_Prices!D10-1 -> 0.0098441524 | E11: =Share_Prices!E11/Share_Prices!E10-1 -> 0.00046385775 | F11: =Share_Prices!F11/Share_Prices!F10-1 -> -0.014991828 | G11: =Share_Prices!G11/Share_Prices!G10-1 -> 0.0090110906 | H11: =Share_Prices!H11/Share_Prices!H10-1 -> 0.0059310435 | I11: =Share_Prices!I11/Share_Prices!I10-1 -> -0.016149596 | ... S11: =Share_Prices!S11/Share_Prices!S10-1 -> -0.027433986
A12: =Share_Prices!A12 -> 44816 | B12: =Share_Prices!B12/Share_Prices!B11-1 -> 0.0057756955 | C12: =Share_Prices!C12/Share_Prices!C11-1 -> 0.0071117318 | D12: =Share_Prices!D12/Share_Prices!D11-1 -> -0.0022046904 | E12: =Share_Prices!E12/Share_Prices!E11-1 -> 0.014450197 | F12: =Share_Prices!F12/Share_Prices!F11-1 -> 0.0065228586 | G12: =Share_Prices!G12/Share_Prices!G11-1 -> 0.0019464163 | H12: =Share_Prices!H12/Share_Prices!H11-1 -> -0.0014578204 | I12: =Share_Prices!I12/Share_Prices!I11-1 -> 0.1 | ... S12: =Share_Prices!S12/Share_Prices!S11-1 -> 0.0033230119
A13: =Share_Prices!A13 -> 44817 | B13: =Share_Prices!B13/Share_Prices!B12-1 -> 0.0074541364 | C13: =Share_Prices!C13/Share_Prices!C12-1 -> 0.00593488 | D13: =Share_Prices!D13/Share_Prices!D12-1 -> -0.011827654 | E13: =Share_Prices!E13/Share_Prices!E12-1 -> -0.0072364412 | F13: =Share_Prices!F13/Share_Prices!F12-1 -> -0.020635552 | G13: =Share_Prices!G13/Share_Prices!G12-1 -> -0.00068563593 | H13: =Share_Prices!H13/Share_Prices!H12-1 -> 0.08156247 | I13: =Share_Prices!I13/Share_Prices!I12-1 -> -0.018260357 | ... S13: =Share_Prices!S13/Share_Prices!S12-1 -> 0.0030861874
A14: =Share_Prices!A14 -> 44818 | B14: =Share_Prices!B14/Share_Prices!B13-1 -> -0.0036690546 | C14: =Share_Prices!C14/Share_Prices!C13-1 -> -0.0024984285 | D14: =Share_Prices!D14/Share_Prices!D13-1 -> -0.0072122235 | E14: =Share_Prices!E14/Share_Prices!E13-1 -> 0.0028389473 | F14: =Share_Prices!F14/Share_Prices!F13-1 -> 0.004063153 | G14: =Share_Prices!G14/Share_Prices!G13-1 -> 0.003887936 | H14: =Share_Prices!H14/Share_Prices!H13-1 -> 0.0085490596 | I14: =Share_Prices!I14/Share_Prices!I13-1 -> 0.0344 | ... S14: =Share_Prices!S14/Share_Prices!S13-1 -> 0.0015383461
A15: =Share_Prices!A15 -> 44819 | B15: =Share_Prices!B15/Share_Prices!B14-1 -> -0.0070179824 | C15: =Share_Prices!C15/Share_Prices!C14-1 -> -0.0032212249 | D15: =Share_Prices!D15/Share_Prices!D14-1 -> -0.023295354 | E15: =Share_Prices!E15/Share_Prices!E14-1 -> 0.016602907 | F15: =Share_Prices!F15/Share_Prices!F14-1 -> 0.029714418 | G15: =Share_Prices!G15/Share_Prices!G14-1 -> 0.0031894293 | H15: =Share_Prices!H15/Share_Prices!H14-1 -> 0.01921361 | I15: =Share_Prices!I15/Share_Prices!I14-1 -> -0.010440835 | ... S15: =Share_Prices!S15/Share_Prices!S14-1 -> -0.0065185629
A16: =Share_Prices!A16 -> 44820 | B16: =Share_Prices!B16/Share_Prices!B15-1 -> -0.01938481 | C16: =Share_Prices!C16/Share_Prices!C15-1 -> -0.021591299 | D16: =Share_Prices!D16/Share_Prices!D15-1 -> -0.02136414 | E16: =Share_Prices!E16/Share_Prices!E15-1 -> -0.04417852 | F16: =Share_Prices!F16/Share_Prices!F15-1 -> -0.025320009 | G16: =Share_Prices!G16/Share_Prices!G15-1 -> -0.022141478 | H16: =Share_Prices!H16/Share_Prices!H15-1 -> -0.0066242559 | I16: =Share_Prices!I16/Share_Prices!I15-1 -> -0.093591247 | ... S16: =Share_Prices!S16/Share_Prices!S15-1 -> -0.031599985
A17: =Share_Prices!A17 -> 44823 | B17: =Share_Prices!B17/Share_Prices!B16-1 -> 0.0052136662 | C17: =Share_Prices!C17/Share_Prices!C16-1 -> 0.0032537498 | D17: =Share_Prices!D17/Share_Prices!D16-1 -> 0.032664942 | E17: =Share_Prices!E17/Share_Prices!E16-1 -> -0.071023622 | F17: =Share_Prices!F17/Share_Prices!F16-1 -> 0.023328149 | G17: =Share_Prices!G17/Share_Prices!G16-1 -> -0.03971203 | H17: =Share_Prices!H17/Share_Prices!H16-1 -> 0.082224376 | I17: =Share_Prices!I17/Share_Prices!I16-1 -> 0.0094848028 | ... S17: =Share_Prices!S17/Share_Prices!S16-1 -> 0.0022195397
... A645: =Share_Prices!A645 -> 45744 | B645: =Share_Prices!B645/Share_Prices!B644-1 -> -0.0030773209 | C645: =Share_Prices!C645/Share_Prices!C644-1 -> -0.0031950747 | D645: =Share_Prices!D645/Share_Prices!D644-1 -> -0.0015091989 | E645: =Share_Prices!E645/Share_Prices!E644-1 -> 0.0038236617 | F645: =Share_Prices!F645/Share_Prices!F644-1 -> -0.033636667 | G645: =Share_Prices!G645/Share_Prices!G644-1 -> -0.0099209833 | H645: =Share_Prices!H645/Share_Prices!H644-1 -> 0.012055109 | I645: =Share_Prices!I645/Share_Prices!I644-1 -> -0.0013410818 | ... S645: =Share_Prices!S645/Share_Prices!S644-1 -> -0.033161385

Sheet Firm_Sample
A1: Sample of 16 listed NBFCs and HFCs
A2: Bank share at 30-Sep-2023 from each company's Q2 FY2024 investor presentation (Poonawalla does not disclose its borrowing mix).
A4: Company | B4: NSE symbol | C4: Type | D4: Group used in tests | E4: Consumer lender | F4: Microfinance lender | G4: Bank share of borrowings, 30-Sep-2023 (%) | H4: Definition in filing
A5: AAVAS Financiers Ltd. | B5: AAVAS | C5: HFC | D5: HFC (exempt) | E5: No | F5: No | G5: 49.6 | H5: Term loans (share of funding mix)
A6: Arman Financial Services Ltd. | B6: ARMANFIN | C6: NBFC (MFI) | D6: Non-HFC NBFC | E6: No | F6: Yes | G6: 32.3 | H6: Banks & SFBs
A7: Bajaj Finance Ltd. | B7: BAJFINANCE | C7: NBFC | D7: Non-HFC NBFC | E7: Yes | F7: No | G7: 23 | H7: Banks (standalone borrowing mix)
A8: Can Fin Homes Ltd. | B8: CANFINHOME | C8: HFC | D8: HFC (exempt) | E8: No | F8: No | G8: 57 | H8: Banks (funding mix)
A9: Cholamandalam Investment & Finance Company Ltd. | B9: CHOLAFIN | C9: NBFC | D9: Non-HFC NBFC | E9: No | F9: No | G9: 60 | H9: Banks (borrowing mix by investor type)
A10: CreditAccess Grameen Ltd. | B10: CREDITACC | C10: NBFC (MFI) | D10: Non-HFC NBFC | E10: No | F10: Yes | G10: 52.9 | H10: Banks - term loans
A11: Home First Finance Company India Ltd. | B11: HOMEFIRST | C11: HFC | D11: HFC (exempt) | E11: No | F11: No | G11: 54 | H11: Public sector banks 21% + private sector banks 33%
A12: IIFL Finance Ltd. | B12: IIFL | C12: NBFC | D12: Non-HFC NBFC | E12: No | F12: No | G12: 55.3 | H12: Bank borrowings 22,345 / total borrowings 40,375 (consolidated)
A13: LIC Housing Finance Ltd. | B13: LICHSGFIN | C13: HFC | D13: HFC (exempt) | E13: No | F13: No | G13: 33 | H13: Bank (excluding NHB 4%)
A14: Mahindra & Mahindra Financial Services Ltd. | B14: MMFIN | C14: NBFC | D14: Non-HFC NBFC | E14: No | F14: No | G14: 57.2 | H14: Banks / financial institutions (investor category)
A15: Muthoot Finance Ltd. | B15: MUTHOOTFIN | C15: NBFC (gold) | D15: Non-HFC NBFC | E15: No | F15: No | G15: 65.4 | H15: Borrowings from banks/FIs 361,740 / total 553,486 (Rs mn)
A16: PNB Housing Finance Ltd. | B16: PNBHOUSING | C16: HFC | D16: HFC (exempt) | E16: No | F16: No | G16: 40.2 | H16: Term loans
A17: Poonawalla Fincorp Ltd. | B17: POONAWALLA | C17: NBFC | D17: Non-HFC NBFC | E17: Yes | F17: No | H17: Not disclosed
A18: Repco Home Finance Ltd. | B18: REPCOHOME | C18: HFC | D18: HFC (exempt) | E18: No | F18: No | G18: 75.5 | H18: Commercial banks 75,905 / total 100,470 (Rs mn)
A19: SBI Cards and Payment Services Ltd. | B19: SBICARD | C19: NBFC (cards) | D19: Non-HFC NBFC | E19: Yes | F19: No | G19: 77 | H19: WCDL 65% + term loans 12% (both bank facilities)
A20: Shriram Finance Ltd. | B20: SHRIRAMFIN | C20: NBFC | D20: Non-HFC NBFC | E20: No | F20: No | G20: 25.6 | H20: Term loans (Q2 FY24 column)

Sheet Firm_Cost_of_Funds
A1: Cost of funds by company and quarter (%)
A2: Source: company quarterly investor presentations. 'Source' gives the presentation (FY-quarter) and page. Period: Pre = up to Q2 FY2024; Post = Q3 FY2024 to Q4 FY2025 (before the rollback); Later = FY2026.
A4: Company | B4: NSE symbol | C4: Group | D4: Financial year | E4: Quarter | F4: Value (%) | G4: Period | H4: Source (presentation, page) | I4: Note / definition
A5: AAVAS Financiers Ltd. | B5: AAVAS | C5: HFC (exempt) | D5: FY21 | E5: Q1 | F5: 8.1 | G5: =IF(VALUE(MID(D5,3,2))*10+VALUE(MID(E5,2,1))<=242,"Pre",IF(VALUE(MID(D5,3,2))*10+VALUE(MID(E5,2,1))<=254,"Post","Later")) -> Pre | H5: 22-2 p.20 | I5: Reported cost of borrowings (quarter-end) from chart
A6: AAVAS Financiers Ltd. | B6: AAVAS | C6: HFC (exempt) | D6: FY21 | E6: Q2 | F6: 7.9 | G6: =IF(VALUE(MID(D6,3,2))*10+VALUE(MID(E6,2,1))<=242,"Pre",IF(VALUE(MID(D6,3,2))*10+VALUE(MID(E6,2,1))<=254,"Post","Later")) -> Pre | H6: 22-2 p.20 | I6: Reported cost of borrowings (quarter-end) from chart
A7: AAVAS Financiers Ltd. | B7: AAVAS | C7: HFC (exempt) | D7: FY21 | E7: Q3 | F7: 7.68 | G7: =IF(VALUE(MID(D7,3,2))*10+VALUE(MID(E7,2,1))<=242,"Pre",IF(VALUE(MID(D7,3,2))*10+VALUE(MID(E7,2,1))<=254,"Post","Later")) -> Pre | H7: 22-2 p.20 | I7: Reported cost of borrowings (quarter-end) from chart
A8: AAVAS Financiers Ltd. | B8: AAVAS | C8: HFC (exempt) | D8: FY21 | E8: Q4 | F8: 7.4 | G8: =IF(VALUE(MID(D8,3,2))*10+VALUE(MID(E8,2,1))<=242,"Pre",IF(VALUE(MID(D8,3,2))*10+VALUE(MID(E8,2,1))<=254,"Post","Later")) -> Pre | H8: 22-2 p.20 | I8: Reported cost of borrowings (quarter-end) from chart
A9: AAVAS Financiers Ltd. | B9: AAVAS | C9: HFC (exempt) | D9: FY22 | E9: Q1 | F9: 7.25 | G9: =IF(VALUE(MID(D9,3,2))*10+VALUE(MID(E9,2,1))<=242,"Pre",IF(VALUE(MID(D9,3,2))*10+VALUE(MID(E9,2,1))<=254,"Post","Later")) -> Pre | H9: 22-2 p.20 | I9: Reported cost of borrowings (quarter-end) from chart
A10: AAVAS Financiers Ltd. | B10: AAVAS | C10: HFC (exempt) | D10: FY22 | E10: Q2 | F10: 7.17 | G10: =IF(VALUE(MID(D10,3,2))*10+VALUE(MID(E10,2,1))<=242,"Pre",IF(VALUE(MID(D10,3,2))*10+VALUE(MID(E10,2,1))<=254,"Post","Later")) -> Pre | H10: 22-2 p.20 | I10: Reported cost of borrowings (quarter-end) from chart
A11: AAVAS Financiers Ltd. | B11: AAVAS | C11: HFC (exempt) | D11: FY22 | E11: Q3 | F11: 7.03 | G11: =IF(VALUE(MID(D11,3,2))*10+VALUE(MID(E11,2,1))<=242,"Pre",IF(VALUE(MID(D11,3,2))*10+VALUE(MID(E11,2,1))<=254,"Post","Later")) -> Pre | H11: 24-2 p.21 | I11: Reported cost of borrowings (quarter-end) from chart
A12: AAVAS Financiers Ltd. | B12: AAVAS | C12: HFC (exempt) | D12: FY22 | E12: Q4 | F12: 6.88 | G12: =IF(VALUE(MID(D12,3,2))*10+VALUE(MID(E12,2,1))<=242,"Pre",IF(VALUE(MID(D12,3,2))*10+VALUE(MID(E12,2,1))<=254,"Post","Later")) -> Pre | H12: 24-2 p.21 | I12: Reported cost of borrowings (quarter-end) from chart
A13: AAVAS Financiers Ltd. | B13: AAVAS | C13: HFC (exempt) | D13: FY23 | E13: Q1 | F13: 6.86 | G13: =IF(VALUE(MID(D13,3,2))*10+VALUE(MID(E13,2,1))<=242,"Pre",IF(VALUE(MID(D13,3,2))*10+VALUE(MID(E13,2,1))<=254,"Post","Later")) -> Pre | H13: 24-2 p.21 | I13: Reported cost of borrowings (quarter-end) from chart
A14: AAVAS Financiers Ltd. | B14: AAVAS | C14: HFC (exempt) | D14: FY23 | E14: Q2 | F14: 6.99 | G14: =IF(VALUE(MID(D14,3,2))*10+VALUE(MID(E14,2,1))<=242,"Pre",IF(VALUE(MID(D14,3,2))*10+VALUE(MID(E14,2,1))<=254,"Post","Later")) -> Pre | H14: 24-2 p.21 | I14: Reported cost of borrowings (quarter-end) from chart
A15: AAVAS Financiers Ltd. | B15: AAVAS | C15: HFC (exempt) | D15: FY23 | E15: Q3 | F15: 7.29 | G15: =IF(VALUE(MID(D15,3,2))*10+VALUE(MID(E15,2,1))<=242,"Pre",IF(VALUE(MID(D15,3,2))*10+VALUE(MID(E15,2,1))<=254,"Post","Later")) -> Pre | H15: 24-2 p.21 | I15: Reported cost of borrowings (quarter-end) from chart
A16: AAVAS Financiers Ltd. | B16: AAVAS | C16: HFC (exempt) | D16: FY23 | E16: Q4 | F16: 7.61 | G16: =IF(VALUE(MID(D16,3,2))*10+VALUE(MID(E16,2,1))<=242,"Pre",IF(VALUE(MID(D16,3,2))*10+VALUE(MID(E16,2,1))<=254,"Post","Later")) -> Pre | H16: 24-2 p.21 | I16: Reported cost of borrowings (quarter-end) from chart
... A332: SBI Cards and Payment Services Ltd. | B332: SBICARD | C332: Non-HFC NBFC | D332: FY21 | E332: Q2 | F332: 6.6 | G332: =IF(VALUE(MID(D332,3,2))*10+VALUE(MID(E332,2,1))<=242,"Pre",IF(VALUE(MID(D332,3,2))*10+VALUE(MID(E332,2,1))<=254,"Post","Later")) -> Pre | H332: 21-2 | I332: Key metrics table
A333: SBI Cards and Payment Services Ltd. | B333: SBICARD | C333: Non-HFC NBFC | D333: FY21 | E333: Q3 | F333: 6.1 | G333: =IF(VALUE(MID(D333,3,2))*10+VALUE(MID(E333,2,1))<=242,"Pre",IF(VALUE(MID(D333,3,2))*10+VALUE(MID(E333,2,1))<=254,"Post","Later")) -> Pre | H333: 21-3 / 21-4 p.15
A334: SBI Cards and Payment Services Ltd. | B334: SBICARD | C334: Non-HFC NBFC | D334: FY21 | E334: Q4 | F334: 5.5 | G334: =IF(VALUE(MID(D334,3,2))*10+VALUE(MID(E334,2,1))<=242,"Pre",IF(VALUE(MID(D334,3,2))*10+VALUE(MID(E334,2,1))<=254,"Post","Later")) -> Pre | H334: 21-4 p.15
A335: SBI Cards and Payment Services Ltd. | B335: SBICARD | C335: Non-HFC NBFC | D335: FY22 | E335: Q1 | F335: 5.2 | G335: =IF(VALUE(MID(D335,3,2))*10+VALUE(MID(E335,2,1))<=242,"Pre",IF(VALUE(MID(D335,3,2))*10+VALUE(MID(E335,2,1))<=254,"Post","Later")) -> Pre | H335: 22-1
A336: SBI Cards and Payment Services Ltd. | B336: SBICARD | C336: Non-HFC NBFC | D336: FY22 | E336: Q2 | F336: 5.5 | G336: =IF(VALUE(MID(D336,3,2))*10+VALUE(MID(E336,2,1))<=242,"Pre",IF(VALUE(MID(D336,3,2))*10+VALUE(MID(E336,2,1))<=254,"Post","Later")) -> Pre | H336: 22-2
A337: SBI Cards and Payment Services Ltd. | B337: SBICARD | C337: Non-HFC NBFC | D337: FY22 | E337: Q3 | F337: 5.4 | G337: =IF(VALUE(MID(D337,3,2))*10+VALUE(MID(E337,2,1))<=242,"Pre",IF(VALUE(MID(D337,3,2))*10+VALUE(MID(E337,2,1))<=254,"Post","Later")) -> Pre | H337: 22-4 p.14
A338: SBI Cards and Payment Services Ltd. | B338: SBICARD | C338: Non-HFC NBFC | D338: FY22 | E338: Q4 | F338: 4.9 | G338: =IF(VALUE(MID(D338,3,2))*10+VALUE(MID(E338,2,1))<=242,"Pre",IF(VALUE(MID(D338,3,2))*10+VALUE(MID(E338,2,1))<=254,"Post","Later")) -> Pre | H338: 22-4 p.14 / 23-4 p.17
A339: SBI Cards and Payment Services Ltd. | B339: SBICARD | C339: Non-HFC NBFC | D339: FY23 | E339: Q1 | F339: 5.1 | G339: =IF(VALUE(MID(D339,3,2))*10+VALUE(MID(E339,2,1))<=242,"Pre",IF(VALUE(MID(D339,3,2))*10+VALUE(MID(E339,2,1))<=254,"Post","Later")) -> Pre | H339: 23-4 p.17 | I339: COF trend chart
A340: SBI Cards and Payment Services Ltd. | B340: SBICARD | C340: Non-HFC NBFC | D340: FY23 | E340: Q2 | F340: 5.4 | G340: =IF(VALUE(MID(D340,3,2))*10+VALUE(MID(E340,2,1))<=242,"Pre",IF(VALUE(MID(D340,3,2))*10+VALUE(MID(E340,2,1))<=254,"Post","Later")) -> Pre | H340: 23-4 p.17
A341: SBI Cards and Payment Services Ltd. | B341: SBICARD | C341: Non-HFC NBFC | D341: FY23 | E341: Q3 | F341: 6.3 | G341: =IF(VALUE(MID(D341,3,2))*10+VALUE(MID(E341,2,1))<=242,"Pre",IF(VALUE(MID(D341,3,2))*10+VALUE(MID(E341,2,1))<=254,"Post","Later")) -> Pre | H341: 23-4 p.17
A342: SBI Cards and Payment Services Ltd. | B342: SBICARD | C342: Non-HFC NBFC | D342: FY23 | E342: Q4 | F342: 6.7 | G342: =IF(VALUE(MID(D342,3,2))*10+VALUE(MID(E342,2,1))<=242,"Pre",IF(VALUE(MID(D342,3,2))*10+VALUE(MID(E342,2,1))<=254,"Post","Later")) -> Pre | H342: 23-4 p.17
A343: SBI Cards and Payment Services Ltd. | B343: SBICARD | C343: Non-HFC NBFC | D343: FY24 | E343: Q1 | F343: 7.1 | G343: =IF(VALUE(MID(D343,3,2))*10+VALUE(MID(E343,2,1))<=242,"Pre",IF(VALUE(MID(D343,3,2))*10+VALUE(MID(E343,2,1))<=254,"Post","Later")) -> Pre | H343: 24-1 / 24-3
A344: SBI Cards and Payment Services Ltd. | B344: SBICARD | C344: Non-HFC NBFC | D344: FY24 | E344: Q2 | F344: 7.1 | G344: =IF(VALUE(MID(D344,3,2))*10+VALUE(MID(E344,2,1))<=242,"Pre",IF(VALUE(MID(D344,3,2))*10+VALUE(MID(E344,2,1))<=254,"Post","Later")) -> Pre | H344: 24-2 / 24-3
A345: SBI Cards and Payment Services Ltd. | B345: SBICARD | C345: Non-HFC NBFC | D345: FY24 | E345: Q3 | F345: 7.6 | G345: =IF(VALUE(MID(D345,3,2))*10+VALUE(MID(E345,2,1))<=242,"Pre",IF(VALUE(MID(D345,3,2))*10+VALUE(MID(E345,2,1))<=254,"Post","Later")) -> Post | H345: 24-3 (5-quarter series)
A346: SBI Cards and Payment Services Ltd. | B346: SBICARD | C346: Non-HFC NBFC | D346: FY24 | E346: Q4 | F346: 7.4 | G346: =IF(VALUE(MID(D346,3,2))*10+VALUE(MID(E346,2,1))<=242,"Pre",IF(VALUE(MID(D346,3,2))*10+VALUE(MID(E346,2,1))<=254,"Post","Later")) -> Post | H346: 24-4 key metrics
A347: SBI Cards and Payment Services Ltd. | B347: SBICARD | C347: Non-HFC NBFC | D347: FY25 | E347: Q1 | F347: 7.5 | G347: =IF(VALUE(MID(D347,3,2))*10+VALUE(MID(E347,2,1))<=242,"Pre",IF(VALUE(MID(D347,3,2))*10+VALUE(MID(E347,2,1))<=254,"Post","Later")) -> Post | H347: 25-1 / 25-4 p.17
A348: SBI Cards and Payment Services Ltd. | B348: SBICARD | C348: Non-HFC NBFC | D348: FY25 | E348: Q2 | F348: 7.4 | G348: =IF(VALUE(MID(D348,3,2))*10+VALUE(MID(E348,2,1))<=242,"Pre",IF(VALUE(MID(D348,3,2))*10+VALUE(MID(E348,2,1))<=254,"Post","Later")) -> Post | H348: 25-4 p.17
A349: SBI Cards and Payment Services Ltd. | B349: SBICARD | C349: Non-HFC NBFC | D349: FY25 | E349: Q3 | F349: 7.4 | G349: =IF(VALUE(MID(D349,3,2))*10+VALUE(MID(E349,2,1))<=242,"Pre",IF(VALUE(MID(D349,3,2))*10+VALUE(MID(E349,2,1))<=254,"Post","Later")) -> Post | H349: 25-4 p.17
A350: SBI Cards and Payment Services Ltd. | B350: SBICARD | C350: Non-HFC NBFC | D350: FY25 | E350: Q4 | F350: 7.2 | G350: =IF(VALUE(MID(D350,3,2))*10+VALUE(MID(E350,2,1))<=242,"Pre",IF(VALUE(MID(D350,3,2))*10+VALUE(MID(E350,2,1))<=254,"Post","Later")) -> Post | H350: 25-4 p.17 | I350: Reported (7.3% excl. one-off lease modification)
A351: SBI Cards and Payment Services Ltd. | B351: SBICARD | C351: Non-HFC NBFC | D351: FY26 | E351: Q1 | F351: 7.1 | G351: =IF(VALUE(MID(D351,3,2))*10+VALUE(MID(E351,2,1))<=242,"Pre",IF(VALUE(MID(D351,3,2))*10+VALUE(MID(E351,2,1))<=254,"Post","Later")) -> Later | H351: 26-2 (prior-quarter column)
A352: SBI Cards and Payment Services Ltd. | B352: SBICARD | C352: Non-HFC NBFC | D352: FY26 | E352: Q2 | F352: 6.4 | G352: =IF(VALUE(MID(D352,3,2))*10+VALUE(MID(E352,2,1))<=242,"Pre",IF(VALUE(MID(D352,3,2))*10+VALUE(MID(E352,2,1))<=254,"Post","Later")) -> Later | H352: 26-2 key metrics
A353: SBI Cards and Payment Services Ltd. | B353: SBICARD | C353: Non-HFC NBFC | D353: FY26 | E353: Q3 | F353: 6.5 | G353: =IF(VALUE(MID(D353,3,2))*10+VALUE(MID(E353,2,1))<=242,"Pre",IF(VALUE(MID(D353,3,2))*10+VALUE(MID(E353,2,1))<=254,"Post","Later")) -> Later | H353: 26-3 / 26-4
A354: SBI Cards and Payment Services Ltd. | B354: SBICARD | C354: Non-HFC NBFC | D354: FY26 | E354: Q4 | F354: 6.4 | G354: =IF(VALUE(MID(D354,3,2))*10+VALUE(MID(E354,2,1))<=242,"Pre",IF(VALUE(MID(D354,3,2))*10+VALUE(MID(E354,2,1))<=254,"Post","Later")) -> Later | H354: 26-4 key metrics
A355: Shriram Finance Ltd. | B355: SHRIRAMFIN | C355: Non-HFC NBFC | D355: FY23 | E355: Q1 | F355: 7.85 | G355: =IF(VALUE(MID(D355,3,2))*10+VALUE(MID(E355,2,1))<=242,"Pre",IF(VALUE(MID(D355,3,2))*10+VALUE(MID(E355,2,1))<=254,"Post","Later")) -> Pre | H355: 23-4/24-4/25-4/26-4 P&L + borrowing profile | I355: COMPUTED: annualised interest expended / avg borrowings; merged entity (STFC+SCUF) from FY23; FY23 Q1-Q2 restated; FY23Q1 uses closing borrowings
A356: Shriram Finance Ltd. | B356: SHRIRAMFIN | C356: Non-HFC NBFC | D356: FY23 | E356: Q2 | F356: 8.45 | G356: =IF(VALUE(MID(D356,3,2))*10+VALUE(MID(E356,2,1))<=242,"Pre",IF(VALUE(MID(D356,3,2))*10+VALUE(MID(E356,2,1))<=254,"Post","Later")) -> Pre | H356: 23-4/24-4/25-4/26-4 P&L + borrowing profile | I356: COMPUTED: annualised interest expended / avg borrowings; merged entity (STFC+SCUF) from FY23; FY23 Q1-Q2 restated; FY23Q1 uses closing borrowings
A357: Shriram Finance Ltd. | B357: SHRIRAMFIN | C357: Non-HFC NBFC | D357: FY23 | E357: Q3 | F357: 8.07 | G357: =IF(VALUE(MID(D357,3,2))*10+VALUE(MID(E357,2,1))<=242,"Pre",IF(VALUE(MID(D357,3,2))*10+VALUE(MID(E357,2,1))<=254,"Post","Later")) -> Pre | H357: 23-4/24-4/25-4/26-4 P&L + borrowing profile | I357: COMPUTED: annualised interest expended / avg borrowings; merged entity (STFC+SCUF) from FY23; FY23 Q1-Q2 restated; FY23Q1 uses closing borrowings
A358: Shriram Finance Ltd. | B358: SHRIRAMFIN | C358: Non-HFC NBFC | D358: FY23 | E358: Q4 | F358: 8.41 | G358: =IF(VALUE(MID(D358,3,2))*10+VALUE(MID(E358,2,1))<=242,"Pre",IF(VALUE(MID(D358,3,2))*10+VALUE(MID(E358,2,1))<=254,"Post","Later")) -> Pre | H358: 23-4/24-4/25-4/26-4 P&L + borrowing profile | I358: COMPUTED: annualised interest expended / avg borrowings; merged entity (STFC+SCUF) from FY23; FY23 Q1-Q2 restated; FY23Q1 uses closing borrowings
A359: Shriram Finance Ltd. | B359: SHRIRAMFIN | C359: Non-HFC NBFC | D359: FY24 | E359: Q1 | F359: 8.8 | G359: =IF(VALUE(MID(D359,3,2))*10+VALUE(MID(E359,2,1))<=242,"Pre",IF(VALUE(MID(D359,3,2))*10+VALUE(MID(E359,2,1))<=254,"Post","Later")) -> Pre | H359: 23-4/24-4/25-4/26-4 P&L + borrowing profile | I359: COMPUTED: annualised interest expended / avg borrowings; merged entity (STFC+SCUF) from FY23; FY23 Q1-Q2 restated; FY23Q1 uses closing borrowings
A360: Shriram Finance Ltd. | B360: SHRIRAMFIN | C360: Non-HFC NBFC | D360: FY24 | E360: Q2 | F360: 8.95 | G360: =IF(VALUE(MID(D360,3,2))*10+VALUE(MID(E360,2,1))<=242,"Pre",IF(VALUE(MID(D360,3,2))*10+VALUE(MID(E360,2,1))<=254,"Post","Later")) -> Pre | H360: 23-4/24-4/25-4/26-4 P&L + borrowing profile | I360: COMPUTED: annualised interest expended / avg borrowings; merged entity (STFC+SCUF) from FY23; FY23 Q1-Q2 restated; FY23Q1 uses closing borrowings
A361: Shriram Finance Ltd. | B361: SHRIRAMFIN | C361: Non-HFC NBFC | D361: FY24 | E361: Q3 | F361: 8.75 | G361: =IF(VALUE(MID(D361,3,2))*10+VALUE(MID(E361,2,1))<=242,"Pre",IF(VALUE(MID(D361,3,2))*10+VALUE(MID(E361,2,1))<=254,"Post","Later")) -> Post | H361: 23-4/24-4/25-4/26-4 P&L + borrowing profile | I361: COMPUTED: annualised interest expended / avg borrowings; merged entity (STFC+SCUF) from FY23; FY23 Q1-Q2 restated; FY23Q1 uses closing borrowings
A362: Shriram Finance Ltd. | B362: SHRIRAMFIN | C362: Non-HFC NBFC | D362: FY24 | E362: Q4 | F362: 8.89 | G362: =IF(VALUE(MID(D362,3,2))*10+VALUE(MID(E362,2,1))<=242,"Pre",IF(VALUE(MID(D362,3,2))*10+VALUE(MID(E362,2,1))<=254,"Post","Later")) -> Post | H362: 23-4/24-4/25-4/26-4 P&L + borrowing profile | I362: COMPUTED: annualised interest expended / avg borrowings; merged entity (STFC+SCUF) from FY23; FY23 Q1-Q2 restated; FY23Q1 uses closing borrowings
A363: Shriram Finance Ltd. | B363: SHRIRAMFIN | C363: Non-HFC NBFC | D363: FY25 | E363: Q1 | F363: 8.83 | G363: =IF(VALUE(MID(D363,3,2))*10+VALUE(MID(E363,2,1))<=242,"Pre",IF(VALUE(MID(D363,3,2))*10+VALUE(MID(E363,2,1))<=254,"Post","Later")) -> Post | H363: 23-4/24-4/25-4/26-4 P&L + borrowing profile | I363: COMPUTED: annualised interest expended / avg borrowings; merged entity (STFC+SCUF) from FY23; FY23 Q1-Q2 restated; FY23Q1 uses closing borrowings
A364: Shriram Finance Ltd. | B364: SHRIRAMFIN | C364: Non-HFC NBFC | D364: FY25 | E364: Q2 | F364: 8.81 | G364: =IF(VALUE(MID(D364,3,2))*10+VALUE(MID(E364,2,1))<=242,"Pre",IF(VALUE(MID(D364,3,2))*10+VALUE(MID(E364,2,1))<=254,"Post","Later")) -> Post | H364: 23-4/24-4/25-4/26-4 P&L + borrowing profile | I364: COMPUTED: annualised interest expended / avg borrowings; merged entity (STFC+SCUF) from FY23; FY23 Q1-Q2 restated; FY23Q1 uses closing borrowings
A365: Shriram Finance Ltd. | B365: SHRIRAMFIN | C365: Non-HFC NBFC | D365: FY25 | E365: Q3 | F365: 8.87 | G365: =IF(VALUE(MID(D365,3,2))*10+VALUE(MID(E365,2,1))<=242,"Pre",IF(VALUE(MID(D365,3,2))*10+VALUE(MID(E365,2,1))<=254,"Post","Later")) -> Post | H365: 23-4/24-4/25-4/26-4 P&L + borrowing profile | I365: COMPUTED: annualised interest expended / avg borrowings; merged entity (STFC+SCUF) from FY23; FY23 Q1-Q2 restated; FY23Q1 uses closing borrowings
A366: Shriram Finance Ltd. | B366: SHRIRAMFIN | C366: Non-HFC NBFC | D366: FY25 | E366: Q4 | F366: 9.22 | G366: =IF(VALUE(MID(D366,3,2))*10+VALUE(MID(E366,2,1))<=242,"Pre",IF(VALUE(MID(D366,3,2))*10+VALUE(MID(E366,2,1))<=254,"Post","Later")) -> Post | H366: 23-4/24-4/25-4/26-4 P&L + borrowing profile | I366: COMPUTED: annualised interest expended / avg borrowings; merged entity (STFC+SCUF) from FY23; FY23 Q1-Q2 restated; FY23Q1 uses closing borrowings
... A370: Shriram Finance Ltd. | B370: SHRIRAMFIN | C370: Non-HFC NBFC | D370: FY26 | E370: Q4 | F370: 8.59 | G370: =IF(VALUE(MID(D370,3,2))*10+VALUE(MID(E370,2,1))<=242,"Pre",IF(VALUE(MID(D370,3,2))*10+VALUE(MID(E370,2,1))<=254,"Post","Later")) -> Later | H370: 23-4/24-4/25-4/26-4 P&L + borrowing profile | I370: COMPUTED: annualised interest expended / avg borrowings; merged entity (STFC+SCUF) from FY23; FY23 Q1-Q2 restated; FY23Q1 uses closing borrowings

Sheet Firm_Bank_Share
A1: Bank share of borrowings by company and quarter (%)
A2: Source: company quarterly investor presentations. 'Source' gives the presentation (FY-quarter) and page. Period: Pre = up to Q2 FY2024; Post = Q3 FY2024 to Q4 FY2025 (before the rollback); Later = FY2026.
A4: Company | B4: NSE symbol | C4: Group | D4: Financial year | E4: Quarter | F4: Value (%) | G4: Period | H4: Source (presentation, page) | I4: Note / definition
A5: AAVAS Financiers Ltd. | B5: AAVAS | C5: HFC (exempt) | D5: FY21 | E5: Q2 | F5: 36.3 | G5: =IF(VALUE(MID(D5,3,2))*10+VALUE(MID(E5,2,1))<=242,"Pre",IF(VALUE(MID(D5,3,2))*10+VALUE(MID(E5,2,1))<=254,"Post","Later")) -> Pre | H5: 21-2 diversified funding mix pie | I5: Term loans % of funding mix (semi-annual; FY26 decks no longer show the mix)
A6: AAVAS Financiers Ltd. | B6: AAVAS | C6: HFC (exempt) | D6: FY21 | E6: Q4 | F6: 34.1 | G6: =IF(VALUE(MID(D6,3,2))*10+VALUE(MID(E6,2,1))<=242,"Pre",IF(VALUE(MID(D6,3,2))*10+VALUE(MID(E6,2,1))<=254,"Post","Later")) -> Pre | H6: 21-4 diversified funding mix pie | I6: Term loans % of funding mix (semi-annual; FY26 decks no longer show the mix)
A7: AAVAS Financiers Ltd. | B7: AAVAS | C7: HFC (exempt) | D7: FY22 | E7: Q2 | F7: 36.8 | G7: =IF(VALUE(MID(D7,3,2))*10+VALUE(MID(E7,2,1))<=242,"Pre",IF(VALUE(MID(D7,3,2))*10+VALUE(MID(E7,2,1))<=254,"Post","Later")) -> Pre | H7: 22-2 diversified funding mix pie | I7: Term loans % of funding mix (semi-annual; FY26 decks no longer show the mix)
A8: AAVAS Financiers Ltd. | B8: AAVAS | C8: HFC (exempt) | D8: FY22 | E8: Q4 | F8: 37.9 | G8: =IF(VALUE(MID(D8,3,2))*10+VALUE(MID(E8,2,1))<=242,"Pre",IF(VALUE(MID(D8,3,2))*10+VALUE(MID(E8,2,1))<=254,"Post","Later")) -> Pre | H8: 22-4 diversified funding mix pie | I8: Term loans % of funding mix (semi-annual; FY26 decks no longer show the mix)
A9: AAVAS Financiers Ltd. | B9: AAVAS | C9: HFC (exempt) | D9: FY23 | E9: Q2 | F9: 41.8 | G9: =IF(VALUE(MID(D9,3,2))*10+VALUE(MID(E9,2,1))<=242,"Pre",IF(VALUE(MID(D9,3,2))*10+VALUE(MID(E9,2,1))<=254,"Post","Later")) -> Pre | H9: 23-2 diversified funding mix pie | I9: Term loans % of funding mix (semi-annual; FY26 decks no longer show the mix)
A10: AAVAS Financiers Ltd. | B10: AAVAS | C10: HFC (exempt) | D10: FY23 | E10: Q4 | F10: 45 | G10: =IF(VALUE(MID(D10,3,2))*10+VALUE(MID(E10,2,1))<=242,"Pre",IF(VALUE(MID(D10,3,2))*10+VALUE(MID(E10,2,1))<=254,"Post","Later")) -> Pre | H10: 23-4 diversified funding mix pie | I10: Term loans % of funding mix (semi-annual; FY26 decks no longer show the mix)
A11: AAVAS Financiers Ltd. | B11: AAVAS | C11: HFC (exempt) | D11: FY24 | E11: Q2 | F11: 49.6 | G11: =IF(VALUE(MID(D11,3,2))*10+VALUE(MID(E11,2,1))<=242,"Pre",IF(VALUE(MID(D11,3,2))*10+VALUE(MID(E11,2,1))<=254,"Post","Later")) -> Pre | H11: 24-2 diversified funding mix pie | I11: Term loans % of funding mix (semi-annual; FY26 decks no longer show the mix)
A12: AAVAS Financiers Ltd. | B12: AAVAS | C12: HFC (exempt) | D12: FY24 | E12: Q4 | F12: 47.5 | G12: =IF(VALUE(MID(D12,3,2))*10+VALUE(MID(E12,2,1))<=242,"Pre",IF(VALUE(MID(D12,3,2))*10+VALUE(MID(E12,2,1))<=254,"Post","Later")) -> Post | H12: 24-4 diversified funding mix pie | I12: Term loans % of funding mix (semi-annual; FY26 decks no longer show the mix)
A13: AAVAS Financiers Ltd. | B13: AAVAS | C13: HFC (exempt) | D13: FY25 | E13: Q2 | F13: 50.8 | G13: =IF(VALUE(MID(D13,3,2))*10+VALUE(MID(E13,2,1))<=242,"Pre",IF(VALUE(MID(D13,3,2))*10+VALUE(MID(E13,2,1))<=254,"Post","Later")) -> Post | H13: 25-2 diversified funding mix pie | I13: Term loans % of funding mix (semi-annual; FY26 decks no longer show the mix)
A14: AAVAS Financiers Ltd. | B14: AAVAS | C14: HFC (exempt) | D14: FY25 | E14: Q4 | F14: 50.9 | G14: =IF(VALUE(MID(D14,3,2))*10+VALUE(MID(E14,2,1))<=242,"Pre",IF(VALUE(MID(D14,3,2))*10+VALUE(MID(E14,2,1))<=254,"Post","Later")) -> Post | H14: 25-4 diversified funding mix pie | I14: Term loans % of funding mix (semi-annual; FY26 decks no longer show the mix)
A15: Arman Financial Services Ltd. | B15: ARMANFIN | C15: Non-HFC NBFC | D15: FY21 | E15: Q2 | F15: 31 | G15: =IF(VALUE(MID(D15,3,2))*10+VALUE(MID(E15,2,1))<=242,"Pre",IF(VALUE(MID(D15,3,2))*10+VALUE(MID(E15,2,1))<=254,"Post","Later")) -> Pre | H15: 21-2/22-2 pies | I15: Banks & SFBs % of borrowings (ex CCD/OCRPS)
A16: Arman Financial Services Ltd. | B16: ARMANFIN | C16: Non-HFC NBFC | D16: FY21 | E16: Q4 | F16: 27 | G16: =IF(VALUE(MID(D16,3,2))*10+VALUE(MID(E16,2,1))<=242,"Pre",IF(VALUE(MID(D16,3,2))*10+VALUE(MID(E16,2,1))<=254,"Post","Later")) -> Pre | H16: 21-2/22-2 pies | I16: Banks & SFBs % of borrowings (ex CCD/OCRPS)
... A290: Shriram Finance Ltd. | B290: SHRIRAMFIN | C290: Non-HFC NBFC | D290: FY26 | E290: Q4 | F290: 20.42 | G290: =IF(VALUE(MID(D290,3,2))*10+VALUE(MID(E290,2,1))<=242,"Pre",IF(VALUE(MID(D290,3,2))*10+VALUE(MID(E290,2,1))<=254,"Post","Later")) -> Later | H290: 23-4/24-4/25-4/26-4 borrowing profile | I290: Term loans % of borrowings (merged entity from FY23)

Sheet Bajaj_Segments
A1: Bajaj Finance: assets under management by business segment (₹ crore)
A2: Source: Bajaj Finance quarterly investor presentations. Affected consumer segments: urban and rural sales finance and personal-loan (B2C) segments.
A4: Financial year | B4: Quarter | C4: Total AUM (₹ cr) | D4: Affected consumer segments (₹ cr) | E4: Share affected (formula) | F4: Source (presentation, page) | G4: Segment detail as reported
A5: FY21 | B5: Q1 | C5: 138055 | D5: 50820 | E5: =D5/C5 -> 0.36811416 | F5: 21-1 p.41 | G5: Auto Finance Business=12,802; Sales Finance Business=9,231; Consumer B2C Business=29,219; Rural Sales Finance Business=2,089; Rural B2C Business=10,281; SME Lending Business=18,277; Securities Lending Business=3,957; IPO financing=0; Commercial Lending Business=6,075; Mortgages=46,124
A6: FY21 | B6: Q2 | C6: 137090 | D6: 48279 | E6: =D6/C6 -> 0.35217011 | F6: 21-2 p.39 | G6: Auto Finance Business=12,687; Sales Finance Business=7,918; Consumer B2C Business=28,262; Rural Sales Finance Business=1,808; Rural B2C Business=10,291; SME Lending Business=18,253; Securities Lending Business=5,327; Commercial Lending Business=6,555; Mortgages=45,989
A7: FY21 | B7: Q3 | C7: 143550 | D7: 52620 | E7: =D7/C7 -> 0.36656217 | F7: 21-3 p.41 | G7: of 31 Dec 2020=31; Auto Finance Business=12,707; Sales Finance Business=10,186; Consumer B2C Business=29,042; Rural Sales Finance Business=2,438; Rural B2C Business=10,954; SME Lending Business=18,882; Securities Lending Business=5,074; Commercial Lending Business=7,510; Mortgages=46,758
A8: FY21 | B8: Q4 | C8: 152947 | D8: 56681 | E8: =D8/C8 -> 0.37059243 | F8: 21-4 p.43 | G8: Auto Finance Business=12,112; Sales Finance Business=11,526; Consumer B2C Business=30,450; Rural Sales Finance Business=2,883; Rural B2C Business=11,822; SME Lending Business=20,217; Securities Lending Business=6,054; Commercial Lending Business=8,293; Mortgages=49,592
A9: FY22 | B9: Q1 | C9: 159057 | D9: 58025 | E9: =D9/C9 -> 0.36480633 | F9: 22-1 p.40 | G9: Auto Finance Business=11,347; Sales Finance Business=11,175; Consumer B2C Business=31,399; Rural Sales Finance Business=2,914; Rural B2C Business=12,537; SME Lending Business=20,335; Securities Lending Business=6,290; IPO Financing=2,942; Commercial Lending Business=9,011; Mortgages=51,107
A10: FY22 | B10: Q2 | C10: 166937 | D10: 62868 | E10: =D10/C10 -> 0.37659716 | F10: 22-2 p.43 | G10: September 2020=2,020; Auto Finance Business=10,738; Sales Finance Business=12,555; Consumer B2C Business=33,679; Rural Sales Finance Business=3,258; Rural B2C Business=13,376; SME Lending Business=21,871; Securities Lending Business=7,293; IPO Financing=170; Commercial Lending Business=9,801; Mortgages=54,196
A11: FY22 | B11: Q3 | C11: 181250 | D11: 69568 | E11: =D11/C11 -> 0.38382345 | F11: 22-3 p.49 | G11: December 2020=2,021; Auto Finance Business=10,620; Sales Finance Business=14,920; Consumer B2C Business=36,344; Rural Sales Finance Business=3,993; Rural B2C Business=14,311; SME Lending Business=23,153; Securities Lending Business=9,127; IPO Financing=0; Commercial Lending Business=10,478; Mortgages=58,304
A12: FY22 | B12: Q4 | C12: 197452 | D12: 73179 | E12: =D12/C12 -> 0.37061666 | F12: 22-4 p.47 | G12: Auto Finance Business=10,194; Sales Finance Business=14,977; Consumer B2C Business=38,772; Rural Sales Finance Business=4,129; Rural B2C Business=15,301; SME Lending Business=24,979; Securities Lending Business=10,536; IPO Financing Business=5,365; Commercial Lending Business=11,498; Mortgages Business=61,701
A13: FY23 | B13: Q1 | C13: 204018 | D13: 78986 | E13: =D13/C13 -> 0.38715211 | F13: 23-1 p.46 | G13: Auto Finance Business=9,962; Urban Sales Finance Business=16,475; Urban B2C Business=41,207; Rural Sales Finance Business=4,564; Rural B2C Business=16,740; SME Lending Business=26,564; Securities Lending Business=10,801; IPO Financing Business=0; Commercial Lending Business=12,040; Mortgages Business=65,665
A14: FY23 | B14: Q2 | C14: 218366 | D14: 82568 | E14: =D14/C14 -> 0.37811747 | F14: 23-2 p.47 | G14: Two & Three wheeler Finance=10,160; Urban Sales Finance=16,259; Urban B2C=44,072; Rural Sales Finance=4,329; Rural B2C=17,908; SME Lending=28,881; Securities Lending=12,182; IPO Financing=105; Commercial Lending=13,378; Mortgages=71,092
A15: FY23 | B15: Q3 | C15: 230842 | D15: 86587 | E15: =D15/C15 -> 0.37509205 | F15: 23-3 p.59 | G15: Two & Three wheeler Finance=11,786; Urban Sales Finance=16,712; Urban B2C=46,733; Rural Sales Finance=4,684; Rural B2C=18,458; SME Lending=30,880; Securities Lending=13,257; Commercial Lending=14,848; Mortgages=73,484
A16: FY23 | B16: Q4 | C16: 247379 | D16: 91995 | E16: =D16/C16 -> 0.37187878 | F16: 23-4 p.52 | G16: Two & Three wheeler Finance=12,979; Urban Sales Finance=17,627; Urban B2C=50,108; Rural Sales Finance=4,803; Rural B2C=19,457; SME Lending=33,765; Loan Against Securities=15,093; IPO Financing=0; Commercial Lending=15,834; Mortgages=77,713
... A28: FY26 | B28: Q4 | C28: 509975 | D28: 195539 | E28: =D28/C28 -> 0.3834286 | F28: 26-4 p.63 | G28: Captive 2W & 3W Finance=4,288; Open Market 2W & 3W Finance=8,325; Urban Sales Finance=37,430; Urban B2C Loans=104,485; Rural Sales Finance=10,559; Rural B2C Loans=25,234; MFI Lending=2,198; Gold Loans=17,831; MSME Lending=51,570; CV & Tractor Finance=3,881; Car Loans=15,011; Commercial Lending=33,839; Loan Against Securities=33,247; Mortgages=162,077

Sheet Company_Disclosures
A1: Company statements on the effect of the November 2023 measures
A2: Verbatim quotes from investor presentations for the quarter ended 31 December 2023.
A4: Company | B4: Source | C4: Statement (verbatim) | D4: Implication
A5: Bajaj Finance Ltd. | B5: Q3 FY24 investor presentation | C5: RBI increased risk weights on consumer credit exposure from 100% to 125% which had an impact of 290 bps on the Company's CRAR. Adjusted for this change CRAR would have been 26.77%. | D5: Capital ratio cut by 2.9 pp
A6: Bajaj Finance Ltd. | B6: Q3 FY24 investor presentation | C6: Given the increase in risk weights and higher incremental cost of funds, the Company has increased rates across all portfolios by 20-30 bps. | D6: Lending rates raised 20-30 bps
A7: SBI Cards and Payment Services Ltd. | B7: Q3 FY24 investor presentation, capital adequacy slide | C7: CRAR impacted by ~400 bps due to increase in risk weight by RBI | D7: Capital ratio cut by about 4 pp

Sheet Event_Dates
A1: Policy events and the dates used in the analysis
A2: Release times are from the earliest dated news reports; NSE trading hours are 9:15 am to 3:30 pm IST.
A4: Event | B4: Date | C4: Time / note | D4: Source | E4: Used as
A5: RBI circular RBI/2023-24/85 (risk weights, exposure limits) | B5: 45246 | C5: First news report 5:26 pm IST, after market close | D5: RBI circular; Business Today, 16 Nov 2023 | E5: Policy date
A6: First trading day after the circular | B6: 45247 | C6: Day 0 of event 1 | D6: NSE trading calendar | E6: Event study day 0
A7: RBI embargo on Bajaj Finance eCOM and Insta EMI Card | B7: 45245 | C7: Lifted 2 May 2024 | D7: Company announcements | E7: Confounding event (Bajaj excluded in checks)
A8: Deadline for board-approved limits on unsecured consumer credit | B8: 45351 | D8: RBI circular RBI/2023-24/85 | E8: Context
A9: RBI embargo on IIFL Finance gold loans | B9: 45355 | C9: Lifted 19 Sep 2024 | D9: Company announcements | E9: Context
A10: RBI circulars RBI/2024-25/119 and /120 (rollback of bank-to-NBFC risk weight) | B10: 45713 | C10: First news report 9:31 pm IST, after market close | D10: RBI circulars; Business Standard, 25 Feb 2025 | E10: Rollback announcement
A11: Market holiday (Mahashivratri) | B11: 45714 | C11: NSE closed | D11: NSE holiday circular 170/2024
A12: First trading day after the rollback announcement | B12: 45715 | C12: Day 0 of event 2 | D12: NSE trading calendar | E12: Event study day 0
A13: Rollback effective | B13: 45748 | D13: RBI circular RBI/2024-25/120 | E13: Start of after-rollback period
A14: Bank credit tests: pre-policy period | B14: 44287 | C14: to 17-Nov-2023 (32 months) | D14: RBI DBIE Table 15 | E14: Before
A15: Bank credit tests: post-policy period | B15: 45289 | C15: to 31-Jan-2025 (14 months) | D15: RBI DBIE Table 15 | E15: After
A16: Event study estimation window, event 1 | B16: 44881 | C16: to 04-Oct-2023 (220 trading days) | D16: Share_Prices | E16: Market model
A17: Event study estimation window, event 2 | B17: 45349 | C17: to 15-Jan-2025 (220 trading days) | D17: Share_Prices | E17: Market model
