Workbook

Sheet README
A1: Capital Requirements and Credit Supply: statistical tests
A2: Workbook 2 of 2 accompanying the dissertation (Nityam Gupta, FMS Delhi, MBA 2025-27). The first workbook, Dissertation_Data_Compilation.xlsx, holds the full data set.
A4: Sheet | B4: Reproduces | C4: Tests | D4: How computed
A5: H1_Tests | B5: Tables 7.1 to 7.5 (H1) | C5: Welch t-test; regression on a Post dummy, without and with calendar-month dummies (model summary, ANOVA, coefficients); Durbin-Watson, Jarque-Bera, Breusch-Pagan and VIF; economic size | D5: Excel formulas
A6: H2_Tests | B6: Tables 7.1 to 7.5 (H2) | C6: Welch t-test; regression on a Post dummy, without and with calendar-month dummies (model summary, ANOVA, coefficients); Durbin-Watson, Jarque-Bera, Breusch-Pagan and VIF; economic size | D6: Excel formulas
A7: H2_Alt_Tests | B7: Table 7.1, third row; Section 7.2 | C7: Welch t-test; regression on a Post dummy, without and with calendar-month dummies (model summary, ANOVA, coefficients) | D7: Excel formulas
A8: H1_Placebo | B8: Table 7.6 | C8: Placebo Welch t-test and month-dummy regression at a fictitious date; linear pre-policy trend | D8: Excel formulas
A9: H2_Placebo | B9: Table 7.6 | C9: Placebo Welch t-test and month-dummy regression at a fictitious date; linear pre-policy trend | D9: Excel formulas
A10: H2_Rollback | B10: Table 7.6 | C10: Welch t-test of the H2 gap before and after the rollback | D10: Excel formulas
A11: H1_DropOne | B11: Table 7.7 | C11: Welch t-test and month-dummy regression with one H1 series dropped (summary at the top) | D11: Excel formulas
A12: NeweyWest_Output | B12: Table 7.4 (Newey-West columns) | C12: Newey-West standard errors, 3 lags | D12: Python output (not possible with Excel functions)
A13: ES_MarketModel | B13: Table 8.1 | C13: Market model (alpha, beta, R squared, residual standard deviation) for every stock and both events | D13: Excel formulas
A14: ES_E1 | B14: Tables 8.2 and 8.4 | C14: Abnormal and cumulative abnormal returns of portfolios and companies, t-tests, sign test, bank-share regression | D14: Excel formulas
A15: ES_E2 | B15: Tables 8.3 and 8.4 | C15: Abnormal and cumulative abnormal returns of portfolios and companies, t-tests, sign test, bank-share regression | D15: Excel formulas
... A20: Data_Monthly, Data_Prices, Data_Returns | B20: Inputs to Chapters 4, 7 and 8 | C20: Monthly credit growth and gaps; daily prices, returns and portfolio returns | D20: Data and formulas
A22: Colour code: blue = input data; black = Excel formula; green = link to another sheet; blue italics = value reported in the dissertation (for comparison).
A23: Excel functions used: T.TEST, LINEST, INDEX, SLOPE, INTERCEPT, RSQ, STEYX, CORREL, MINVERSE, SUMXMY2, SUMPRODUCT, T.DIST.2T, F.DIST.RT, CHISQ.DIST.RT, BINOM.DIST, AVERAGEIFS.
A24: LINEST returns the coefficients in reverse order of the X columns; the coefficient tables put them back in the order Post, M2 to M12, then the constant.
A25: The Welch p-value uses T.TEST (type 3), which keeps the fractional Welch degrees of freedom.
A26: Newey-West standard errors cannot be computed with standard Excel functions; NeweyWest_Output holds the Python (statsmodels) output.
A27: The analysis itself was run in Python (pandas, statsmodels, SciPy); every value in this workbook matches the value reported in the dissertation.

Sheet H1_Tests
A1: Gap1: bank credit to credit cards and other personal loans minus housing, vehicle and education loans: tests, April 2021 to January 2025
A2: Reproduces Tables 7.1 to 7.5 (H1). Data rows link to Data_Monthly; every result is an Excel formula. Months before the circular: April 2021 to 17 November 2023; after: 29 December 2023 to January 2025.
A4: Gap1 | T4: Test results
A5: Coefficients | B5: =Y19 -> 0.77455038 | C5: =Y7 -> -0.78280105 | D5: =Y8 -> -0.36801906 | E5: =Y9 -> 0.9306105 | F5: =Y10 -> -0.46244995 | G5: =Y11 -> -0.94696896 | H5: =Y12 -> -0.84753357 | I5: =Y13 -> 1.2849422 | J5: =Y14 -> -0.39042183 | K5: =Y15 -> -1.6018791 | L5: =Y16 -> 2.1376913 | M5: =Y17 -> -0.71586504 | N5: =Y18 -> -0.11090025 | T5: Post = 1 for months dated on or after | U5: 45260 | X5: Regression 2: all coefficients
A6: Date | B6: Gap (pp) | C6: Post | D6: M2 | E6: M3 | F6: M4 | G6: M5 | H6: M6 | I6: M7 | J6: M8 | K6: M9 | L6: M10 | M6: M11 | N6: M12 | O6: Fitted | P6: Residual | Q6: Residual squared | T6: Months before: rows 7 to 38; after: rows 39 to 52. | X6: Variable | Y6: B | Z6: Std. error | AA6: t | AB6: p-value | AC6: VIF
A7: =Data_Monthly!A5 -> 44309 | B7: =Data_Monthly!J5 -> -1.2000226 | C7: =IF($A7>=$U$5,1,0) -> 0 | D7: =IF(MONTH($A7)=2,1,0) -> 0 | E7: =IF(MONTH($A7)=3,1,0) -> 0 | F7: =IF(MONTH($A7)=4,1,0) -> 1 | G7: =IF(MONTH($A7)=5,1,0) -> 0 | H7: =IF(MONTH($A7)=6,1,0) -> 0 | I7: =IF(MONTH($A7)=7,1,0) -> 0 | J7: =IF(MONTH($A7)=8,1,0) -> 0 | K7: =IF(MONTH($A7)=9,1,0) -> 0 | L7: =IF(MONTH($A7)=10,1,0) -> 0 | M7: =IF(MONTH($A7)=11,1,0) -> 0 | N7: =IF(MONTH($A7)=12,1,0) -> 0 | O7: =$B$5+SUMPRODUCT(C7:N7,$C$5:$N$5) -> 0.31210044 | P7: =B7-O7 -> -1.512123 | Q7: =P7^2 -> 2.2865161 | T7: Welch two-sample t-test (unequal variances) | U7: Excel | V7: Dissertation | X7: Post | Y7: =INDEX(LINEST(B7:B52,C7:N52,TRUE(),TRUE()),1,12) -> -0.78280105 | Z7: =INDEX(LINEST(B7:B52,C7:N52,TRUE(),TRUE()),2,12) -> 0.41636117 | AA7: =Y7/Z7 -> -1.880101 | AB7: =_xlfn.T.DIST.2T(ABS(AA7),$U$35) -> 0.068946348 | AC7: =INDEX(MINVERSE($Y$23:$AJ$34),1,1) -> 1.0434783
A8: =Data_Monthly!A6 -> 44337 | B8: =Data_Monthly!J6 -> -3.0574799 | C8: =IF($A8>=$U$5,1,0) -> 0 | D8: =IF(MONTH($A8)=2,1,0) -> 0 | E8: =IF(MONTH($A8)=3,1,0) -> 0 | F8: =IF(MONTH($A8)=4,1,0) -> 0 | G8: =IF(MONTH($A8)=5,1,0) -> 1 | H8: =IF(MONTH($A8)=6,1,0) -> 0 | I8: =IF(MONTH($A8)=7,1,0) -> 0 | J8: =IF(MONTH($A8)=8,1,0) -> 0 | K8: =IF(MONTH($A8)=9,1,0) -> 0 | L8: =IF(MONTH($A8)=10,1,0) -> 0 | M8: =IF(MONTH($A8)=11,1,0) -> 0 | N8: =IF(MONTH($A8)=12,1,0) -> 0 | O8: =$B$5+SUMPRODUCT(C8:N8,$C$5:$N$5) -> -0.17241857 | P8: =B8-O8 -> -2.8850614 | Q8: =P8^2 -> 8.3235791 | T8: Months before (n1) | U8: =COUNT(B7:B38) -> 32 | V8: 32 | X8: M2 | Y8: =INDEX(LINEST(B7:B52,C7:N52,TRUE(),TRUE()),1,11) -> -0.36801906 | Z8: =INDEX(LINEST(B7:B52,C7:N52,TRUE(),TRUE()),2,11) -> 0.97398458 | AA8: =Y8/Z8 -> -0.37784896 | AB8: =_xlfn.T.DIST.2T(ABS(AA8),$U$35) -> 0.70796235 | AC8: =INDEX(MINVERSE($Y$23:$AJ$34),2,2) -> 1.6442158
A9: =Data_Monthly!A7 -> 44365 | B9: =Data_Monthly!J7 -> -0.91500129 | C9: =IF($A9>=$U$5,1,0) -> 0 | D9: =IF(MONTH($A9)=2,1,0) -> 0 | E9: =IF(MONTH($A9)=3,1,0) -> 0 | F9: =IF(MONTH($A9)=4,1,0) -> 0 | G9: =IF(MONTH($A9)=5,1,0) -> 0 | H9: =IF(MONTH($A9)=6,1,0) -> 1 | I9: =IF(MONTH($A9)=7,1,0) -> 0 | J9: =IF(MONTH($A9)=8,1,0) -> 0 | K9: =IF(MONTH($A9)=9,1,0) -> 0 | L9: =IF(MONTH($A9)=10,1,0) -> 0 | M9: =IF(MONTH($A9)=11,1,0) -> 0 | N9: =IF(MONTH($A9)=12,1,0) -> 0 | O9: =$B$5+SUMPRODUCT(C9:N9,$C$5:$N$5) -> -0.072983191 | P9: =B9-O9 -> -0.8420181 | Q9: =P9^2 -> 0.70899448 | T9: Months after (n2) | U9: =COUNT(B39:B52) -> 14 | V9: 14 | X9: M3 | Y9: =INDEX(LINEST(B7:B52,C7:N52,TRUE(),TRUE()),1,10) -> 0.9306105 | Z9: =INDEX(LINEST(B7:B52,C7:N52,TRUE(),TRUE()),2,10) -> 0.97398458 | AA9: =Y9/Z9 -> 0.95546738 | AB9: =_xlfn.T.DIST.2T(ABS(AA9),$U$35) -> 0.3462888 | AC9: =INDEX(MINVERSE($Y$23:$AJ$34),3,3) -> 1.6442158
A10: =Data_Monthly!A8 -> 44407 | B10: =Data_Monthly!J8 -> 4.8802768 | C10: =IF($A10>=$U$5,1,0) -> 0 | D10: =IF(MONTH($A10)=2,1,0) -> 0 | E10: =IF(MONTH($A10)=3,1,0) -> 0 | F10: =IF(MONTH($A10)=4,1,0) -> 0 | G10: =IF(MONTH($A10)=5,1,0) -> 0 | H10: =IF(MONTH($A10)=6,1,0) -> 0 | I10: =IF(MONTH($A10)=7,1,0) -> 1 | J10: =IF(MONTH($A10)=8,1,0) -> 0 | K10: =IF(MONTH($A10)=9,1,0) -> 0 | L10: =IF(MONTH($A10)=10,1,0) -> 0 | M10: =IF(MONTH($A10)=11,1,0) -> 0 | N10: =IF(MONTH($A10)=12,1,0) -> 0 | O10: =$B$5+SUMPRODUCT(C10:N10,$C$5:$N$5) -> 2.0594926 | P10: =B10-O10 -> 2.8207842 | Q10: =P10^2 -> 7.9568237 | T10: Mean gap before | U10: =AVERAGE(B7:B38) -> 0.65817312 | V10: 0.65817312 | X10: M4 | Y10: =INDEX(LINEST(B7:B52,C7:N52,TRUE(),TRUE()),1,9) -> -0.46244995 | Z10: =INDEX(LINEST(B7:B52,C7:N52,TRUE(),TRUE()),2,9) -> 0.90544595 | AA10: =Y10/Z10 -> -0.51074274 | AB10: =_xlfn.T.DIST.2T(ABS(AA10),$U$35) -> 0.61293121 | AC10: =INDEX(MINVERSE($Y$23:$AJ$34),4,4) -> 1.8505435
A11: =Data_Monthly!A9 -> 44435 | B11: =Data_Monthly!J9 -> 1.3340802 | C11: =IF($A11>=$U$5,1,0) -> 0 | D11: =IF(MONTH($A11)=2,1,0) -> 0 | E11: =IF(MONTH($A11)=3,1,0) -> 0 | F11: =IF(MONTH($A11)=4,1,0) -> 0 | G11: =IF(MONTH($A11)=5,1,0) -> 0 | H11: =IF(MONTH($A11)=6,1,0) -> 0 | I11: =IF(MONTH($A11)=7,1,0) -> 0 | J11: =IF(MONTH($A11)=8,1,0) -> 1 | K11: =IF(MONTH($A11)=9,1,0) -> 0 | L11: =IF(MONTH($A11)=10,1,0) -> 0 | M11: =IF(MONTH($A11)=11,1,0) -> 0 | N11: =IF(MONTH($A11)=12,1,0) -> 0 | O11: =$B$5+SUMPRODUCT(C11:N11,$C$5:$N$5) -> 0.38412855 | P11: =B11-O11 -> 0.94995165 | Q11: =P11^2 -> 0.90240813 | T11: Mean gap after | U11: =AVERAGE(B39:B52) -> -0.094085954 | V11: -0.094085954 | X11: M5 | Y11: =INDEX(LINEST(B7:B52,C7:N52,TRUE(),TRUE()),1,8) -> -0.94696896 | Z11: =INDEX(LINEST(B7:B52,C7:N52,TRUE(),TRUE()),2,8) -> 0.90544595 | AA11: =Y11/Z11 -> -1.0458592 | AB11: =_xlfn.T.DIST.2T(ABS(AA11),$U$35) -> 0.30322666 | AC11: =INDEX(MINVERSE($Y$23:$AJ$34),5,5) -> 1.8505435
A12: =Data_Monthly!A10 -> 44463 | B12: =Data_Monthly!J10 -> -0.88183491 | C12: =IF($A12>=$U$5,1,0) -> 0 | D12: =IF(MONTH($A12)=2,1,0) -> 0 | E12: =IF(MONTH($A12)=3,1,0) -> 0 | F12: =IF(MONTH($A12)=4,1,0) -> 0 | G12: =IF(MONTH($A12)=5,1,0) -> 0 | H12: =IF(MONTH($A12)=6,1,0) -> 0 | I12: =IF(MONTH($A12)=7,1,0) -> 0 | J12: =IF(MONTH($A12)=8,1,0) -> 0 | K12: =IF(MONTH($A12)=9,1,0) -> 1 | L12: =IF(MONTH($A12)=10,1,0) -> 0 | M12: =IF(MONTH($A12)=11,1,0) -> 0 | N12: =IF(MONTH($A12)=12,1,0) -> 0 | O12: =$B$5+SUMPRODUCT(C12:N12,$C$5:$N$5) -> -0.82732874 | P12: =B12-O12 -> -0.054506171 | Q12: =P12^2 -> 0.0029709227 | T12: Standard deviation before | U12: =_xlfn.STDEV.S(B7:B38) -> 1.7106114 | V12: 1.7106114 | X12: M6 | Y12: =INDEX(LINEST(B7:B52,C7:N52,TRUE(),TRUE()),1,7) -> -0.84753357 | Z12: =INDEX(LINEST(B7:B52,C7:N52,TRUE(),TRUE()),2,7) -> 0.90544595 | AA12: =Y12/Z12 -> -0.93603994 | AB12: =_xlfn.T.DIST.2T(ABS(AA12),$U$35) -> 0.35605255 | AC12: =INDEX(MINVERSE($Y$23:$AJ$34),6,6) -> 1.8505435
A13: =Data_Monthly!A11 -> 44491 | B13: =Data_Monthly!J11 -> 3.0475205 | C13: =IF($A13>=$U$5,1,0) -> 0 | D13: =IF(MONTH($A13)=2,1,0) -> 0 | E13: =IF(MONTH($A13)=3,1,0) -> 0 | F13: =IF(MONTH($A13)=4,1,0) -> 0 | G13: =IF(MONTH($A13)=5,1,0) -> 0 | H13: =IF(MONTH($A13)=6,1,0) -> 0 | I13: =IF(MONTH($A13)=7,1,0) -> 0 | J13: =IF(MONTH($A13)=8,1,0) -> 0 | K13: =IF(MONTH($A13)=9,1,0) -> 0 | L13: =IF(MONTH($A13)=10,1,0) -> 1 | M13: =IF(MONTH($A13)=11,1,0) -> 0 | N13: =IF(MONTH($A13)=12,1,0) -> 0 | O13: =$B$5+SUMPRODUCT(C13:N13,$C$5:$N$5) -> 2.9122417 | P13: =B13-O13 -> 0.13527877 | Q13: =P13^2 -> 0.018300347 | T13: Standard deviation after | U13: =_xlfn.STDEV.S(B39:B52) -> 0.89104569 | V13: 0.89104569 | X13: M7 | Y13: =INDEX(LINEST(B7:B52,C7:N52,TRUE(),TRUE()),1,6) -> 1.2849422 | Z13: =INDEX(LINEST(B7:B52,C7:N52,TRUE(),TRUE()),2,6) -> 0.90544595 | AA13: =Y13/Z13 -> 1.4191263 | AB13: =_xlfn.T.DIST.2T(ABS(AA13),$U$35) -> 0.16523922 | AC13: =INDEX(MINVERSE($Y$23:$AJ$34),7,7) -> 1.8505435
A14: =Data_Monthly!A12 -> 44519 | B14: =Data_Monthly!J12 -> 0.2231757 | C14: =IF($A14>=$U$5,1,0) -> 0 | D14: =IF(MONTH($A14)=2,1,0) -> 0 | E14: =IF(MONTH($A14)=3,1,0) -> 0 | F14: =IF(MONTH($A14)=4,1,0) -> 0 | G14: =IF(MONTH($A14)=5,1,0) -> 0 | H14: =IF(MONTH($A14)=6,1,0) -> 0 | I14: =IF(MONTH($A14)=7,1,0) -> 0 | J14: =IF(MONTH($A14)=8,1,0) -> 0 | K14: =IF(MONTH($A14)=9,1,0) -> 0 | L14: =IF(MONTH($A14)=10,1,0) -> 0 | M14: =IF(MONTH($A14)=11,1,0) -> 1 | N14: =IF(MONTH($A14)=12,1,0) -> 0 | O14: =$B$5+SUMPRODUCT(C14:N14,$C$5:$N$5) -> 0.058685338 | P14: =B14-O14 -> 0.16449036 | Q14: =P14^2 -> 0.027057078 | T14: Difference (after minus before) | U14: =$U$11-$U$10 -> -0.75225907 | V14: -0.75225907 | X14: M8 | Y14: =INDEX(LINEST(B7:B52,C7:N52,TRUE(),TRUE()),1,5) -> -0.39042183 | Z14: =INDEX(LINEST(B7:B52,C7:N52,TRUE(),TRUE()),2,5) -> 0.90544595 | AA14: =Y14/Z14 -> -0.43119286 | AB14: =_xlfn.T.DIST.2T(ABS(AA14),$U$35) -> 0.66913193 | AC14: =INDEX(MINVERSE($Y$23:$AJ$34),8,8) -> 1.8505435
A15: =Data_Monthly!A13 -> 44561 | B15: =Data_Monthly!J13 -> 0.55111209 | C15: =IF($A15>=$U$5,1,0) -> 0 | D15: =IF(MONTH($A15)=2,1,0) -> 0 | E15: =IF(MONTH($A15)=3,1,0) -> 0 | F15: =IF(MONTH($A15)=4,1,0) -> 0 | G15: =IF(MONTH($A15)=5,1,0) -> 0 | H15: =IF(MONTH($A15)=6,1,0) -> 0 | I15: =IF(MONTH($A15)=7,1,0) -> 0 | J15: =IF(MONTH($A15)=8,1,0) -> 0 | K15: =IF(MONTH($A15)=9,1,0) -> 0 | L15: =IF(MONTH($A15)=10,1,0) -> 0 | M15: =IF(MONTH($A15)=11,1,0) -> 0 | N15: =IF(MONTH($A15)=12,1,0) -> 1 | O15: =$B$5+SUMPRODUCT(C15:N15,$C$5:$N$5) -> 0.66365014 | P15: =B15-O15 -> -0.11253804 | Q15: =P15^2 -> 0.012664811 | T15: Difference per year (x 12) | U15: =12*$U$14 -> -9.0271089 | V15: -9.0271089 | X15: M9 | Y15: =INDEX(LINEST(B7:B52,C7:N52,TRUE(),TRUE()),1,4) -> -1.6018791 | Z15: =INDEX(LINEST(B7:B52,C7:N52,TRUE(),TRUE()),2,4) -> 0.90544595 | AA15: =Y15/Z15 -> -1.7691604 | AB15: =_xlfn.T.DIST.2T(ABS(AA15),$U$35) -> 0.086109293 | AC15: =INDEX(MINVERSE($Y$23:$AJ$34),9,9) -> 1.8505435
A16: =Data_Monthly!A14 -> 44589 | B16: =Data_Monthly!J14 -> -0.44045606 | C16: =IF($A16>=$U$5,1,0) -> 0 | D16: =IF(MONTH($A16)=2,1,0) -> 0 | E16: =IF(MONTH($A16)=3,1,0) -> 0 | F16: =IF(MONTH($A16)=4,1,0) -> 0 | G16: =IF(MONTH($A16)=5,1,0) -> 0 | H16: =IF(MONTH($A16)=6,1,0) -> 0 | I16: =IF(MONTH($A16)=7,1,0) -> 0 | J16: =IF(MONTH($A16)=8,1,0) -> 0 | K16: =IF(MONTH($A16)=9,1,0) -> 0 | L16: =IF(MONTH($A16)=10,1,0) -> 0 | M16: =IF(MONTH($A16)=11,1,0) -> 0 | N16: =IF(MONTH($A16)=12,1,0) -> 0 | O16: =$B$5+SUMPRODUCT(C16:N16,$C$5:$N$5) -> 0.77455038 | P16: =B16-O16 -> -1.2150064 | Q16: =P16^2 -> 1.4762407 | T16: Standard error of the difference | U16: =SQRT($U$13^2/$U$9+$U$12^2/$U$8) -> 0.38490919 | X16: M10 | Y16: =INDEX(LINEST(B7:B52,C7:N52,TRUE(),TRUE()),1,3) -> 2.1376913 | Z16: =INDEX(LINEST(B7:B52,C7:N52,TRUE(),TRUE()),2,3) -> 0.90544595 | AA16: =Y16/Z16 -> 2.3609265 | AB16: =_xlfn.T.DIST.2T(ABS(AA16),$U$35) -> 0.024288725 | AC16: =INDEX(MINVERSE($Y$23:$AJ$34),10,10) -> 1.8505435
A17: =Data_Monthly!A15 -> 44617 | B17: =Data_Monthly!J15 -> 0.44668201 | C17: =IF($A17>=$U$5,1,0) -> 0 | D17: =IF(MONTH($A17)=2,1,0) -> 1 | E17: =IF(MONTH($A17)=3,1,0) -> 0 | F17: =IF(MONTH($A17)=4,1,0) -> 0 | G17: =IF(MONTH($A17)=5,1,0) -> 0 | H17: =IF(MONTH($A17)=6,1,0) -> 0 | I17: =IF(MONTH($A17)=7,1,0) -> 0 | J17: =IF(MONTH($A17)=8,1,0) -> 0 | K17: =IF(MONTH($A17)=9,1,0) -> 0 | L17: =IF(MONTH($A17)=10,1,0) -> 0 | M17: =IF(MONTH($A17)=11,1,0) -> 0 | N17: =IF(MONTH($A17)=12,1,0) -> 0 | O17: =$B$5+SUMPRODUCT(C17:N17,$C$5:$N$5) -> 0.40653132 | P17: =B17-O17 -> 0.040150689 | Q17: =P17^2 -> 0.0016120778 | T17: t statistic | U17: =$U$14/$U$16 -> -1.9543807 | V17: -1.9543807 | X17: M11 | Y17: =INDEX(LINEST(B7:B52,C7:N52,TRUE(),TRUE()),1,2) -> -0.71586504 | Z17: =INDEX(LINEST(B7:B52,C7:N52,TRUE(),TRUE()),2,2) -> 0.90544595 | AA17: =Y17/Z17 -> -0.79062151 | AB17: =_xlfn.T.DIST.2T(ABS(AA17),$U$35) -> 0.43481025 | AC17: =INDEX(MINVERSE($Y$23:$AJ$34),11,11) -> 1.8505435
A18: =Data_Monthly!A16 -> 44645 | B18: =Data_Monthly!J16 -> 1.8446973 | C18: =IF($A18>=$U$5,1,0) -> 0 | D18: =IF(MONTH($A18)=2,1,0) -> 0 | E18: =IF(MONTH($A18)=3,1,0) -> 1 | F18: =IF(MONTH($A18)=4,1,0) -> 0 | G18: =IF(MONTH($A18)=5,1,0) -> 0 | H18: =IF(MONTH($A18)=6,1,0) -> 0 | I18: =IF(MONTH($A18)=7,1,0) -> 0 | J18: =IF(MONTH($A18)=8,1,0) -> 0 | K18: =IF(MONTH($A18)=9,1,0) -> 0 | L18: =IF(MONTH($A18)=10,1,0) -> 0 | M18: =IF(MONTH($A18)=11,1,0) -> 0 | N18: =IF(MONTH($A18)=12,1,0) -> 0 | O18: =$B$5+SUMPRODUCT(C18:N18,$C$5:$N$5) -> 1.7051609 | P18: =B18-O18 -> 0.13953642 | Q18: =P18^2 -> 0.019470413 | T18: Welch degrees of freedom | U18: =(($U$13^2/$U$9)+($U$12^2/$U$8))^2/(($U$13^2/$U$9)^2/($U$9-1)+($U$12^2/$U$8)^2/($U$8-1)) -> 42.44489 | V18: 42.44489 | X18: M12 | Y18: =INDEX(LINEST(B7:B52,C7:N52,TRUE(),TRUE()),1,1) -> -0.11090025 | Z18: =INDEX(LINEST(B7:B52,C7:N52,TRUE(),TRUE()),2,1) -> 0.89944292 | AA18: =Y18/Z18 -> -0.12329882 | AB18: =_xlfn.T.DIST.2T(ABS(AA18),$U$35) -> 0.90261839 | AC18: =INDEX(MINVERSE($Y$23:$AJ$34),12,12) -> 1.826087
A19: =Data_Monthly!A17 -> 44673 | B19: =Data_Monthly!J17 -> 2.2065841 | C19: =IF($A19>=$U$5,1,0) -> 0 | D19: =IF(MONTH($A19)=2,1,0) -> 0 | E19: =IF(MONTH($A19)=3,1,0) -> 0 | F19: =IF(MONTH($A19)=4,1,0) -> 1 | G19: =IF(MONTH($A19)=5,1,0) -> 0 | H19: =IF(MONTH($A19)=6,1,0) -> 0 | I19: =IF(MONTH($A19)=7,1,0) -> 0 | J19: =IF(MONTH($A19)=8,1,0) -> 0 | K19: =IF(MONTH($A19)=9,1,0) -> 0 | L19: =IF(MONTH($A19)=10,1,0) -> 0 | M19: =IF(MONTH($A19)=11,1,0) -> 0 | N19: =IF(MONTH($A19)=12,1,0) -> 0 | O19: =$B$5+SUMPRODUCT(C19:N19,$C$5:$N$5) -> 0.31210044 | P19: =B19-O19 -> 1.8944837 | Q19: =P19^2 -> 3.5890684 | T19: p-value, two-tailed (T.TEST type 3) | U19: =_xlfn.T.TEST(B39:B52,B7:B38,2,3) -> 0.057264702 | V19: 0.057264702 | X19: Constant | Y19: =INDEX(LINEST(B7:B52,C7:N52,TRUE(),TRUE()),1,13) -> 0.77455038 | Z19: =INDEX(LINEST(B7:B52,C7:N52,TRUE(),TRUE()),2,13) -> 0.66920695 | AA19: =Y19/Z19 -> 1.1574153 | AB19: =_xlfn.T.DIST.2T(ABS(AA19),$U$35) -> 0.25541183
A20: =Data_Monthly!A18 -> 44701 | B20: =Data_Monthly!J18 -> 0.36179199 | C20: =IF($A20>=$U$5,1,0) -> 0 | D20: =IF(MONTH($A20)=2,1,0) -> 0 | E20: =IF(MONTH($A20)=3,1,0) -> 0 | F20: =IF(MONTH($A20)=4,1,0) -> 0 | G20: =IF(MONTH($A20)=5,1,0) -> 1 | H20: =IF(MONTH($A20)=6,1,0) -> 0 | I20: =IF(MONTH($A20)=7,1,0) -> 0 | J20: =IF(MONTH($A20)=8,1,0) -> 0 | K20: =IF(MONTH($A20)=9,1,0) -> 0 | L20: =IF(MONTH($A20)=10,1,0) -> 0 | M20: =IF(MONTH($A20)=11,1,0) -> 0 | N20: =IF(MONTH($A20)=12,1,0) -> 0 | O20: =$B$5+SUMPRODUCT(C20:N20,$C$5:$N$5) -> -0.17241857 | P20: =B20-O20 -> 0.53421056 | Q20: =P20^2 -> 0.28538092 | X20: Row 5 repeats these coefficients above the data columns; Fitted = Constant + sum of coefficient x regressor.
A21: =Data_Monthly!A19 -> 44729 | B21: =Data_Monthly!J19 -> -1.2877125 | C21: =IF($A21>=$U$5,1,0) -> 0 | D21: =IF(MONTH($A21)=2,1,0) -> 0 | E21: =IF(MONTH($A21)=3,1,0) -> 0 | F21: =IF(MONTH($A21)=4,1,0) -> 0 | G21: =IF(MONTH($A21)=5,1,0) -> 0 | H21: =IF(MONTH($A21)=6,1,0) -> 1 | I21: =IF(MONTH($A21)=7,1,0) -> 0 | J21: =IF(MONTH($A21)=8,1,0) -> 0 | K21: =IF(MONTH($A21)=9,1,0) -> 0 | L21: =IF(MONTH($A21)=10,1,0) -> 0 | M21: =IF(MONTH($A21)=11,1,0) -> 0 | N21: =IF(MONTH($A21)=12,1,0) -> 0 | O21: =$B$5+SUMPRODUCT(C21:N21,$C$5:$N$5) -> -0.072983191 | P21: =B21-O21 -> -1.2147293 | Q21: =P21^2 -> 1.4755673 | T21: Regression 1 (Post dummy only) | U21: Excel | V21: Dissertation | X21: VIF = diagonal of the inverse of the correlation matrix of the regressors:
A22: =Data_Monthly!A20 -> 44771 | B22: =Data_Monthly!J20 -> 2.0687047 | C22: =IF($A22>=$U$5,1,0) -> 0 | D22: =IF(MONTH($A22)=2,1,0) -> 0 | E22: =IF(MONTH($A22)=3,1,0) -> 0 | F22: =IF(MONTH($A22)=4,1,0) -> 0 | G22: =IF(MONTH($A22)=5,1,0) -> 0 | H22: =IF(MONTH($A22)=6,1,0) -> 0 | I22: =IF(MONTH($A22)=7,1,0) -> 1 | J22: =IF(MONTH($A22)=8,1,0) -> 0 | K22: =IF(MONTH($A22)=9,1,0) -> 0 | L22: =IF(MONTH($A22)=10,1,0) -> 0 | M22: =IF(MONTH($A22)=11,1,0) -> 0 | N22: =IF(MONTH($A22)=12,1,0) -> 0 | O22: =$B$5+SUMPRODUCT(C22:N22,$C$5:$N$5) -> 2.0594926 | P22: =B22-O22 -> 0.009212164 | Q22: =P22^2 -> 8.4863966e-05 | T22: Constant | U22: =INDEX(LINEST(B7:B52,C7:C52,TRUE(),TRUE()),1,2) -> 0.65817312 | V22: 0.65817312 | Y22: Post | Z22: M2 | AA22: M3 | AB22: M4 | AC22: M5 | AD22: M6 | AE22: M7 | AF22: M8 | AG22: M9 | AH22: M10 | AI22: M11 | AJ22: M12
A23: =Data_Monthly!A21 -> 44799 | B23: =Data_Monthly!J21 -> 0.77630849 | C23: =IF($A23>=$U$5,1,0) -> 0 | D23: =IF(MONTH($A23)=2,1,0) -> 0 | E23: =IF(MONTH($A23)=3,1,0) -> 0 | F23: =IF(MONTH($A23)=4,1,0) -> 0 | G23: =IF(MONTH($A23)=5,1,0) -> 0 | H23: =IF(MONTH($A23)=6,1,0) -> 0 | I23: =IF(MONTH($A23)=7,1,0) -> 0 | J23: =IF(MONTH($A23)=8,1,0) -> 1 | K23: =IF(MONTH($A23)=9,1,0) -> 0 | L23: =IF(MONTH($A23)=10,1,0) -> 0 | M23: =IF(MONTH($A23)=11,1,0) -> 0 | N23: =IF(MONTH($A23)=12,1,0) -> 0 | O23: =$B$5+SUMPRODUCT(C23:N23,$C$5:$N$5) -> 0.38412855 | P23: =B23-O23 -> 0.39217994 | Q23: =P23^2 -> 0.1538051 | T23: Coefficient on Post | U23: =INDEX(LINEST(B7:B52,C7:C52,TRUE(),TRUE()),1,1) -> -0.75225907 | V23: -0.75225907 | X23: Post | Y23: =CORREL($C$7:$C$52,$C$7:$C$52) -> 1 | Z23: =CORREL($D$7:$D$52,$C$7:$C$52) -> 0.016638958 | AA23: =CORREL($E$7:$E$52,$C$7:$C$52) -> 0.016638958 | AB23: =CORREL($F$7:$F$52,$C$7:$C$52) -> -0.03645074 | AC23: =CORREL($G$7:$G$52,$C$7:$C$52) -> -0.03645074 | AD23: =CORREL($H$7:$H$52,$C$7:$C$52) -> -0.03645074 | AE23: =CORREL($I$7:$I$52,$C$7:$C$52) -> -0.03645074 | AF23: =CORREL($J$7:$J$52,$C$7:$C$52) -> -0.03645074 | AG23: =CORREL($K$7:$K$52,$C$7:$C$52) -> -0.03645074 | AH23: =CORREL($L$7:$L$52,$C$7:$C$52) -> -0.03645074 | AI23: =CORREL($M$7:$M$52,$C$7:$C$52) -> -0.03645074 | AJ23: =CORREL($N$7:$N$52,$C$7:$C$52) -> 0.13122266
A24: =Data_Monthly!A22 -> 44827 | B24: =Data_Monthly!J22 -> -0.49256519 | C24: =IF($A24>=$U$5,1,0) -> 0 | D24: =IF(MONTH($A24)=2,1,0) -> 0 | E24: =IF(MONTH($A24)=3,1,0) -> 0 | F24: =IF(MONTH($A24)=4,1,0) -> 0 | G24: =IF(MONTH($A24)=5,1,0) -> 0 | H24: =IF(MONTH($A24)=6,1,0) -> 0 | I24: =IF(MONTH($A24)=7,1,0) -> 0 | J24: =IF(MONTH($A24)=8,1,0) -> 0 | K24: =IF(MONTH($A24)=9,1,0) -> 1 | L24: =IF(MONTH($A24)=10,1,0) -> 0 | M24: =IF(MONTH($A24)=11,1,0) -> 0 | N24: =IF(MONTH($A24)=12,1,0) -> 0 | O24: =$B$5+SUMPRODUCT(C24:N24,$C$5:$N$5) -> -0.82732874 | P24: =B24-O24 -> 0.33476355 | Q24: =P24^2 -> 0.11206664 | T24: Standard error | U24: =INDEX(LINEST(B7:B52,C7:C52,TRUE(),TRUE()),2,1) -> 0.48556363 | V24: 0.48556363 | X24: M2 | Y24: =CORREL($C$7:$C$52,$D$7:$D$52) -> 0.016638958 | Z24: =CORREL($D$7:$D$52,$D$7:$D$52) -> 1 | AA24: =CORREL($E$7:$E$52,$D$7:$D$52) -> -0.069767442 | AB24: =CORREL($F$7:$F$52,$D$7:$D$52) -> -0.081513915 | AC24: =CORREL($G$7:$G$52,$D$7:$D$52) -> -0.081513915 | AD24: =CORREL($H$7:$H$52,$D$7:$D$52) -> -0.081513915 | AE24: =CORREL($I$7:$I$52,$D$7:$D$52) -> -0.081513915 | AF24: =CORREL($J$7:$J$52,$D$7:$D$52) -> -0.081513915 | AG24: =CORREL($K$7:$K$52,$D$7:$D$52) -> -0.081513915 | AH24: =CORREL($L$7:$L$52,$D$7:$D$52) -> -0.081513915 | AI24: =CORREL($M$7:$M$52,$D$7:$D$52) -> -0.081513915 | AJ24: =CORREL($N$7:$N$52,$D$7:$D$52) -> -0.081513915
A25: =Data_Monthly!A23 -> 44855 | B25: =Data_Monthly!J23 -> 2.8535303 | C25: =IF($A25>=$U$5,1,0) -> 0 | D25: =IF(MONTH($A25)=2,1,0) -> 0 | E25: =IF(MONTH($A25)=3,1,0) -> 0 | F25: =IF(MONTH($A25)=4,1,0) -> 0 | G25: =IF(MONTH($A25)=5,1,0) -> 0 | H25: =IF(MONTH($A25)=6,1,0) -> 0 | I25: =IF(MONTH($A25)=7,1,0) -> 0 | J25: =IF(MONTH($A25)=8,1,0) -> 0 | K25: =IF(MONTH($A25)=9,1,0) -> 0 | L25: =IF(MONTH($A25)=10,1,0) -> 1 | M25: =IF(MONTH($A25)=11,1,0) -> 0 | N25: =IF(MONTH($A25)=12,1,0) -> 0 | O25: =$B$5+SUMPRODUCT(C25:N25,$C$5:$N$5) -> 2.9122417 | P25: =B25-O25 -> -0.058711393 | Q25: =P25^2 -> 0.0034470276 | T25: t statistic | U25: =$U$23/$U$24 -> -1.5492492 | V25: -1.5492492 | X25: M3 | Y25: =CORREL($C$7:$C$52,$E$7:$E$52) -> 0.016638958 | Z25: =CORREL($D$7:$D$52,$E$7:$E$52) -> -0.069767442 | AA25: =CORREL($E$7:$E$52,$E$7:$E$52) -> 1 | AB25: =CORREL($F$7:$F$52,$E$7:$E$52) -> -0.081513915 | AC25: =CORREL($G$7:$G$52,$E$7:$E$52) -> -0.081513915 | AD25: =CORREL($H$7:$H$52,$E$7:$E$52) -> -0.081513915 | AE25: =CORREL($I$7:$I$52,$E$7:$E$52) -> -0.081513915 | AF25: =CORREL($J$7:$J$52,$E$7:$E$52) -> -0.081513915 | AG25: =CORREL($K$7:$K$52,$E$7:$E$52) -> -0.081513915 | AH25: =CORREL($L$7:$L$52,$E$7:$E$52) -> -0.081513915 | AI25: =CORREL($M$7:$M$52,$E$7:$E$52) -> -0.081513915 | AJ25: =CORREL($N$7:$N$52,$E$7:$E$52) -> -0.081513915
A26: =Data_Monthly!A24 -> 44883 | B26: =Data_Monthly!J24 -> -1.4761656 | C26: =IF($A26>=$U$5,1,0) -> 0 | D26: =IF(MONTH($A26)=2,1,0) -> 0 | E26: =IF(MONTH($A26)=3,1,0) -> 0 | F26: =IF(MONTH($A26)=4,1,0) -> 0 | G26: =IF(MONTH($A26)=5,1,0) -> 0 | H26: =IF(MONTH($A26)=6,1,0) -> 0 | I26: =IF(MONTH($A26)=7,1,0) -> 0 | J26: =IF(MONTH($A26)=8,1,0) -> 0 | K26: =IF(MONTH($A26)=9,1,0) -> 0 | L26: =IF(MONTH($A26)=10,1,0) -> 0 | M26: =IF(MONTH($A26)=11,1,0) -> 1 | N26: =IF(MONTH($A26)=12,1,0) -> 0 | O26: =$B$5+SUMPRODUCT(C26:N26,$C$5:$N$5) -> 0.058685338 | P26: =B26-O26 -> -1.5348509 | Q26: =P26^2 -> 2.3557674 | T26: Residual degrees of freedom | U26: =INDEX(LINEST(B7:B52,C7:C52,TRUE(),TRUE()),4,2) -> 44 | X26: M4 | Y26: =CORREL($C$7:$C$52,$F$7:$F$52) -> -0.03645074 | Z26: =CORREL($D$7:$D$52,$F$7:$F$52) -> -0.081513915 | AA26: =CORREL($E$7:$E$52,$F$7:$F$52) -> -0.081513915 | AB26: =CORREL($F$7:$F$52,$F$7:$F$52) -> 1 | AC26: =CORREL($G$7:$G$52,$F$7:$F$52) -> -0.095238095 | AD26: =CORREL($H$7:$H$52,$F$7:$F$52) -> -0.095238095 | AE26: =CORREL($I$7:$I$52,$F$7:$F$52) -> -0.095238095 | AF26: =CORREL($J$7:$J$52,$F$7:$F$52) -> -0.095238095 | AG26: =CORREL($K$7:$K$52,$F$7:$F$52) -> -0.095238095 | AH26: =CORREL($L$7:$L$52,$F$7:$F$52) -> -0.095238095 | AI26: =CORREL($M$7:$M$52,$F$7:$F$52) -> -0.095238095 | AJ26: =CORREL($N$7:$N$52,$F$7:$F$52) -> -0.095238095
A27: =Data_Monthly!A25 -> 44925 | B27: =Data_Monthly!J25 -> 0.89608742 | C27: =IF($A27>=$U$5,1,0) -> 0 | D27: =IF(MONTH($A27)=2,1,0) -> 0 | E27: =IF(MONTH($A27)=3,1,0) -> 0 | F27: =IF(MONTH($A27)=4,1,0) -> 0 | G27: =IF(MONTH($A27)=5,1,0) -> 0 | H27: =IF(MONTH($A27)=6,1,0) -> 0 | I27: =IF(MONTH($A27)=7,1,0) -> 0 | J27: =IF(MONTH($A27)=8,1,0) -> 0 | K27: =IF(MONTH($A27)=9,1,0) -> 0 | L27: =IF(MONTH($A27)=10,1,0) -> 0 | M27: =IF(MONTH($A27)=11,1,0) -> 0 | N27: =IF(MONTH($A27)=12,1,0) -> 1 | O27: =$B$5+SUMPRODUCT(C27:N27,$C$5:$N$5) -> 0.66365014 | P27: =B27-O27 -> 0.23243728 | Q27: =P27^2 -> 0.054027091 | T27: p-value | U27: =_xlfn.T.DIST.2T(ABS($U$25),$U$26) -> 0.12848536 | V27: 0.12848536 | X27: M5 | Y27: =CORREL($C$7:$C$52,$G$7:$G$52) -> -0.03645074 | Z27: =CORREL($D$7:$D$52,$G$7:$G$52) -> -0.081513915 | AA27: =CORREL($E$7:$E$52,$G$7:$G$52) -> -0.081513915 | AB27: =CORREL($F$7:$F$52,$G$7:$G$52) -> -0.095238095 | AC27: =CORREL($G$7:$G$52,$G$7:$G$52) -> 1 | AD27: =CORREL($H$7:$H$52,$G$7:$G$52) -> -0.095238095 | AE27: =CORREL($I$7:$I$52,$G$7:$G$52) -> -0.095238095 | AF27: =CORREL($J$7:$J$52,$G$7:$G$52) -> -0.095238095 | AG27: =CORREL($K$7:$K$52,$G$7:$G$52) -> -0.095238095 | AH27: =CORREL($L$7:$L$52,$G$7:$G$52) -> -0.095238095 | AI27: =CORREL($M$7:$M$52,$G$7:$G$52) -> -0.095238095 | AJ27: =CORREL($N$7:$N$52,$G$7:$G$52) -> -0.095238095
A28: =Data_Monthly!A26 -> 44953 | B28: =Data_Monthly!J26 -> 1.4747812 | C28: =IF($A28>=$U$5,1,0) -> 0 | D28: =IF(MONTH($A28)=2,1,0) -> 0 | E28: =IF(MONTH($A28)=3,1,0) -> 0 | F28: =IF(MONTH($A28)=4,1,0) -> 0 | G28: =IF(MONTH($A28)=5,1,0) -> 0 | H28: =IF(MONTH($A28)=6,1,0) -> 0 | I28: =IF(MONTH($A28)=7,1,0) -> 0 | J28: =IF(MONTH($A28)=8,1,0) -> 0 | K28: =IF(MONTH($A28)=9,1,0) -> 0 | L28: =IF(MONTH($A28)=10,1,0) -> 0 | M28: =IF(MONTH($A28)=11,1,0) -> 0 | N28: =IF(MONTH($A28)=12,1,0) -> 0 | O28: =$B$5+SUMPRODUCT(C28:N28,$C$5:$N$5) -> 0.77455038 | P28: =B28-O28 -> 0.70023086 | Q28: =P28^2 -> 0.49032326 | T28: R squared | U28: =INDEX(LINEST(B7:B52,C7:C52,TRUE(),TRUE()),3,1) -> 0.051727677 | V28: 0.051727677 | X28: M6 | Y28: =CORREL($C$7:$C$52,$H$7:$H$52) -> -0.03645074 | Z28: =CORREL($D$7:$D$52,$H$7:$H$52) -> -0.081513915 | AA28: =CORREL($E$7:$E$52,$H$7:$H$52) -> -0.081513915 | AB28: =CORREL($F$7:$F$52,$H$7:$H$52) -> -0.095238095 | AC28: =CORREL($G$7:$G$52,$H$7:$H$52) -> -0.095238095 | AD28: =CORREL($H$7:$H$52,$H$7:$H$52) -> 1 | AE28: =CORREL($I$7:$I$52,$H$7:$H$52) -> -0.095238095 | AF28: =CORREL($J$7:$J$52,$H$7:$H$52) -> -0.095238095 | AG28: =CORREL($K$7:$K$52,$H$7:$H$52) -> -0.095238095 | AH28: =CORREL($L$7:$L$52,$H$7:$H$52) -> -0.095238095 | AI28: =CORREL($M$7:$M$52,$H$7:$H$52) -> -0.095238095 | AJ28: =CORREL($N$7:$N$52,$H$7:$H$52) -> -0.095238095
A29: =Data_Monthly!A27 -> 44981 | B29: =Data_Monthly!J27 -> 0.55297879 | C29: =IF($A29>=$U$5,1,0) -> 0 | D29: =IF(MONTH($A29)=2,1,0) -> 1 | E29: =IF(MONTH($A29)=3,1,0) -> 0 | F29: =IF(MONTH($A29)=4,1,0) -> 0 | G29: =IF(MONTH($A29)=5,1,0) -> 0 | H29: =IF(MONTH($A29)=6,1,0) -> 0 | I29: =IF(MONTH($A29)=7,1,0) -> 0 | J29: =IF(MONTH($A29)=8,1,0) -> 0 | K29: =IF(MONTH($A29)=9,1,0) -> 0 | L29: =IF(MONTH($A29)=10,1,0) -> 0 | M29: =IF(MONTH($A29)=11,1,0) -> 0 | N29: =IF(MONTH($A29)=12,1,0) -> 0 | O29: =$B$5+SUMPRODUCT(C29:N29,$C$5:$N$5) -> 0.40653132 | P29: =B29-O29 -> 0.14644747 | Q29: =P29^2 -> 0.021446861 | T29: Residual sum of squares | U29: =INDEX(LINEST(B7:B52,C7:C52,TRUE(),TRUE()),5,2) -> 101.03344 | X29: M7 | Y29: =CORREL($C$7:$C$52,$I$7:$I$52) -> -0.03645074 | Z29: =CORREL($D$7:$D$52,$I$7:$I$52) -> -0.081513915 | AA29: =CORREL($E$7:$E$52,$I$7:$I$52) -> -0.081513915 | AB29: =CORREL($F$7:$F$52,$I$7:$I$52) -> -0.095238095 | AC29: =CORREL($G$7:$G$52,$I$7:$I$52) -> -0.095238095 | AD29: =CORREL($H$7:$H$52,$I$7:$I$52) -> -0.095238095 | AE29: =CORREL($I$7:$I$52,$I$7:$I$52) -> 1 | AF29: =CORREL($J$7:$J$52,$I$7:$I$52) -> -0.095238095 | AG29: =CORREL($K$7:$K$52,$I$7:$I$52) -> -0.095238095 | AH29: =CORREL($L$7:$L$52,$I$7:$I$52) -> -0.095238095 | AI29: =CORREL($M$7:$M$52,$I$7:$I$52) -> -0.095238095 | AJ29: =CORREL($N$7:$N$52,$I$7:$I$52) -> -0.095238095
A30: =Data_Monthly!A28 -> 45009 | B30: =Data_Monthly!J28 -> 3.3544495 | C30: =IF($A30>=$U$5,1,0) -> 0 | D30: =IF(MONTH($A30)=2,1,0) -> 0 | E30: =IF(MONTH($A30)=3,1,0) -> 1 | F30: =IF(MONTH($A30)=4,1,0) -> 0 | G30: =IF(MONTH($A30)=5,1,0) -> 0 | H30: =IF(MONTH($A30)=6,1,0) -> 0 | I30: =IF(MONTH($A30)=7,1,0) -> 0 | J30: =IF(MONTH($A30)=8,1,0) -> 0 | K30: =IF(MONTH($A30)=9,1,0) -> 0 | L30: =IF(MONTH($A30)=10,1,0) -> 0 | M30: =IF(MONTH($A30)=11,1,0) -> 0 | N30: =IF(MONTH($A30)=12,1,0) -> 0 | O30: =$B$5+SUMPRODUCT(C30:N30,$C$5:$N$5) -> 1.7051609 | P30: =B30-O30 -> 1.6492886 | Q30: =P30^2 -> 2.720153 | X30: M8 | Y30: =CORREL($C$7:$C$52,$J$7:$J$52) -> -0.03645074 | Z30: =CORREL($D$7:$D$52,$J$7:$J$52) -> -0.081513915 | AA30: =CORREL($E$7:$E$52,$J$7:$J$52) -> -0.081513915 | AB30: =CORREL($F$7:$F$52,$J$7:$J$52) -> -0.095238095 | AC30: =CORREL($G$7:$G$52,$J$7:$J$52) -> -0.095238095 | AD30: =CORREL($H$7:$H$52,$J$7:$J$52) -> -0.095238095 | AE30: =CORREL($I$7:$I$52,$J$7:$J$52) -> -0.095238095 | AF30: =CORREL($J$7:$J$52,$J$7:$J$52) -> 1 | AG30: =CORREL($K$7:$K$52,$J$7:$J$52) -> -0.095238095 | AH30: =CORREL($L$7:$L$52,$J$7:$J$52) -> -0.095238095 | AI30: =CORREL($M$7:$M$52,$J$7:$J$52) -> -0.095238095 | AJ30: =CORREL($N$7:$N$52,$J$7:$J$52) -> -0.095238095
A31: =Data_Monthly!A29 -> 45037 | B31: =Data_Monthly!J29 -> -0.069604258 | C31: =IF($A31>=$U$5,1,0) -> 0 | D31: =IF(MONTH($A31)=2,1,0) -> 0 | E31: =IF(MONTH($A31)=3,1,0) -> 0 | F31: =IF(MONTH($A31)=4,1,0) -> 1 | G31: =IF(MONTH($A31)=5,1,0) -> 0 | H31: =IF(MONTH($A31)=6,1,0) -> 0 | I31: =IF(MONTH($A31)=7,1,0) -> 0 | J31: =IF(MONTH($A31)=8,1,0) -> 0 | K31: =IF(MONTH($A31)=9,1,0) -> 0 | L31: =IF(MONTH($A31)=10,1,0) -> 0 | M31: =IF(MONTH($A31)=11,1,0) -> 0 | N31: =IF(MONTH($A31)=12,1,0) -> 0 | O31: =$B$5+SUMPRODUCT(C31:N31,$C$5:$N$5) -> 0.31210044 | P31: =B31-O31 -> -0.38170469 | Q31: =P31^2 -> 0.14569847 | T31: Regression 2 (Post and 11 month dummies): model summary | U31: Excel | V31: Dissertation | X31: M9 | Y31: =CORREL($C$7:$C$52,$K$7:$K$52) -> -0.03645074 | Z31: =CORREL($D$7:$D$52,$K$7:$K$52) -> -0.081513915 | AA31: =CORREL($E$7:$E$52,$K$7:$K$52) -> -0.081513915 | AB31: =CORREL($F$7:$F$52,$K$7:$K$52) -> -0.095238095 | AC31: =CORREL($G$7:$G$52,$K$7:$K$52) -> -0.095238095 | AD31: =CORREL($H$7:$H$52,$K$7:$K$52) -> -0.095238095 | AE31: =CORREL($I$7:$I$52,$K$7:$K$52) -> -0.095238095 | AF31: =CORREL($J$7:$J$52,$K$7:$K$52) -> -0.095238095 | AG31: =CORREL($K$7:$K$52,$K$7:$K$52) -> 1 | AH31: =CORREL($L$7:$L$52,$K$7:$K$52) -> -0.095238095 | AI31: =CORREL($M$7:$M$52,$K$7:$K$52) -> -0.095238095 | AJ31: =CORREL($N$7:$N$52,$K$7:$K$52) -> -0.095238095
A32: =Data_Monthly!A30 -> 45065 | B32: =Data_Monthly!J30 -> 0.35220475 | C32: =IF($A32>=$U$5,1,0) -> 0 | D32: =IF(MONTH($A32)=2,1,0) -> 0 | E32: =IF(MONTH($A32)=3,1,0) -> 0 | F32: =IF(MONTH($A32)=4,1,0) -> 0 | G32: =IF(MONTH($A32)=5,1,0) -> 1 | H32: =IF(MONTH($A32)=6,1,0) -> 0 | I32: =IF(MONTH($A32)=7,1,0) -> 0 | J32: =IF(MONTH($A32)=8,1,0) -> 0 | K32: =IF(MONTH($A32)=9,1,0) -> 0 | L32: =IF(MONTH($A32)=10,1,0) -> 0 | M32: =IF(MONTH($A32)=11,1,0) -> 0 | N32: =IF(MONTH($A32)=12,1,0) -> 0 | O32: =$B$5+SUMPRODUCT(C32:N32,$C$5:$N$5) -> -0.17241857 | P32: =B32-O32 -> 0.52462332 | Q32: =P32^2 -> 0.27522963 | T32: Observations | U32: =COUNT(B7:B52) -> 46 | V32: 46 | X32: M10 | Y32: =CORREL($C$7:$C$52,$L$7:$L$52) -> -0.03645074 | Z32: =CORREL($D$7:$D$52,$L$7:$L$52) -> -0.081513915 | AA32: =CORREL($E$7:$E$52,$L$7:$L$52) -> -0.081513915 | AB32: =CORREL($F$7:$F$52,$L$7:$L$52) -> -0.095238095 | AC32: =CORREL($G$7:$G$52,$L$7:$L$52) -> -0.095238095 | AD32: =CORREL($H$7:$H$52,$L$7:$L$52) -> -0.095238095 | AE32: =CORREL($I$7:$I$52,$L$7:$L$52) -> -0.095238095 | AF32: =CORREL($J$7:$J$52,$L$7:$L$52) -> -0.095238095 | AG32: =CORREL($K$7:$K$52,$L$7:$L$52) -> -0.095238095 | AH32: =CORREL($L$7:$L$52,$L$7:$L$52) -> 1 | AI32: =CORREL($M$7:$M$52,$L$7:$L$52) -> -0.095238095 | AJ32: =CORREL($N$7:$N$52,$L$7:$L$52) -> -0.095238095
A33: =Data_Monthly!A31 -> 45107 | B33: =Data_Monthly!J31 -> 0.77519798 | C33: =IF($A33>=$U$5,1,0) -> 0 | D33: =IF(MONTH($A33)=2,1,0) -> 0 | E33: =IF(MONTH($A33)=3,1,0) -> 0 | F33: =IF(MONTH($A33)=4,1,0) -> 0 | G33: =IF(MONTH($A33)=5,1,0) -> 0 | H33: =IF(MONTH($A33)=6,1,0) -> 1 | I33: =IF(MONTH($A33)=7,1,0) -> 0 | J33: =IF(MONTH($A33)=8,1,0) -> 0 | K33: =IF(MONTH($A33)=9,1,0) -> 0 | L33: =IF(MONTH($A33)=10,1,0) -> 0 | M33: =IF(MONTH($A33)=11,1,0) -> 0 | N33: =IF(MONTH($A33)=12,1,0) -> 0 | O33: =$B$5+SUMPRODUCT(C33:N33,$C$5:$N$5) -> -0.072983191 | P33: =B33-O33 -> 0.84818117 | Q33: =P33^2 -> 0.7194113 | T33: R squared | U33: =INDEX(LINEST(B7:B52,C7:N52,TRUE(),TRUE()),3,1) -> 0.49885999 | V33: 0.49885999 | X33: M11 | Y33: =CORREL($C$7:$C$52,$M$7:$M$52) -> -0.03645074 | Z33: =CORREL($D$7:$D$52,$M$7:$M$52) -> -0.081513915 | AA33: =CORREL($E$7:$E$52,$M$7:$M$52) -> -0.081513915 | AB33: =CORREL($F$7:$F$52,$M$7:$M$52) -> -0.095238095 | AC33: =CORREL($G$7:$G$52,$M$7:$M$52) -> -0.095238095 | AD33: =CORREL($H$7:$H$52,$M$7:$M$52) -> -0.095238095 | AE33: =CORREL($I$7:$I$52,$M$7:$M$52) -> -0.095238095 | AF33: =CORREL($J$7:$J$52,$M$7:$M$52) -> -0.095238095 | AG33: =CORREL($K$7:$K$52,$M$7:$M$52) -> -0.095238095 | AH33: =CORREL($L$7:$L$52,$M$7:$M$52) -> -0.095238095 | AI33: =CORREL($M$7:$M$52,$M$7:$M$52) -> 1 | AJ33: =CORREL($N$7:$N$52,$M$7:$M$52) -> -0.095238095
A34: =Data_Monthly!A32 -> 45135 | B34: =Data_Monthly!J32 -> 0.64475199 | C34: =IF($A34>=$U$5,1,0) -> 0 | D34: =IF(MONTH($A34)=2,1,0) -> 0 | E34: =IF(MONTH($A34)=3,1,0) -> 0 | F34: =IF(MONTH($A34)=4,1,0) -> 0 | G34: =IF(MONTH($A34)=5,1,0) -> 0 | H34: =IF(MONTH($A34)=6,1,0) -> 0 | I34: =IF(MONTH($A34)=7,1,0) -> 1 | J34: =IF(MONTH($A34)=8,1,0) -> 0 | K34: =IF(MONTH($A34)=9,1,0) -> 0 | L34: =IF(MONTH($A34)=10,1,0) -> 0 | M34: =IF(MONTH($A34)=11,1,0) -> 0 | N34: =IF(MONTH($A34)=12,1,0) -> 0 | O34: =$B$5+SUMPRODUCT(C34:N34,$C$5:$N$5) -> 2.0594926 | P34: =B34-O34 -> -1.4147406 | Q34: =P34^2 -> 2.0014909 | T34: R | U34: =SQRT($U$33) -> 0.70630021 | X34: M12 | Y34: =CORREL($C$7:$C$52,$N$7:$N$52) -> 0.13122266 | Z34: =CORREL($D$7:$D$52,$N$7:$N$52) -> -0.081513915 | AA34: =CORREL($E$7:$E$52,$N$7:$N$52) -> -0.081513915 | AB34: =CORREL($F$7:$F$52,$N$7:$N$52) -> -0.095238095 | AC34: =CORREL($G$7:$G$52,$N$7:$N$52) -> -0.095238095 | AD34: =CORREL($H$7:$H$52,$N$7:$N$52) -> -0.095238095 | AE34: =CORREL($I$7:$I$52,$N$7:$N$52) -> -0.095238095 | AF34: =CORREL($J$7:$J$52,$N$7:$N$52) -> -0.095238095 | AG34: =CORREL($K$7:$K$52,$N$7:$N$52) -> -0.095238095 | AH34: =CORREL($L$7:$L$52,$N$7:$N$52) -> -0.095238095 | AI34: =CORREL($M$7:$M$52,$N$7:$N$52) -> -0.095238095 | AJ34: =CORREL($N$7:$N$52,$N$7:$N$52) -> 1
A35: =Data_Monthly!A33 -> 45163 | B35: =Data_Monthly!J33 -> -0.28108759 | C35: =IF($A35>=$U$5,1,0) -> 0 | D35: =IF(MONTH($A35)=2,1,0) -> 0 | E35: =IF(MONTH($A35)=3,1,0) -> 0 | F35: =IF(MONTH($A35)=4,1,0) -> 0 | G35: =IF(MONTH($A35)=5,1,0) -> 0 | H35: =IF(MONTH($A35)=6,1,0) -> 0 | I35: =IF(MONTH($A35)=7,1,0) -> 0 | J35: =IF(MONTH($A35)=8,1,0) -> 1 | K35: =IF(MONTH($A35)=9,1,0) -> 0 | L35: =IF(MONTH($A35)=10,1,0) -> 0 | M35: =IF(MONTH($A35)=11,1,0) -> 0 | N35: =IF(MONTH($A35)=12,1,0) -> 0 | O35: =$B$5+SUMPRODUCT(C35:N35,$C$5:$N$5) -> 0.38412855 | P35: =B35-O35 -> -0.66521614 | Q35: =P35^2 -> 0.44251251 | T35: Residual degrees of freedom | U35: =INDEX(LINEST(B7:B52,C7:N52,TRUE(),TRUE()),4,2) -> 33
A36: =Data_Monthly!A34 -> 45191 | B36: =Data_Monthly!J34 -> -0.94315801 | C36: =IF($A36>=$U$5,1,0) -> 0 | D36: =IF(MONTH($A36)=2,1,0) -> 0 | E36: =IF(MONTH($A36)=3,1,0) -> 0 | F36: =IF(MONTH($A36)=4,1,0) -> 0 | G36: =IF(MONTH($A36)=5,1,0) -> 0 | H36: =IF(MONTH($A36)=6,1,0) -> 0 | I36: =IF(MONTH($A36)=7,1,0) -> 0 | J36: =IF(MONTH($A36)=8,1,0) -> 0 | K36: =IF(MONTH($A36)=9,1,0) -> 1 | L36: =IF(MONTH($A36)=10,1,0) -> 0 | M36: =IF(MONTH($A36)=11,1,0) -> 0 | N36: =IF(MONTH($A36)=12,1,0) -> 0 | O36: =$B$5+SUMPRODUCT(C36:N36,$C$5:$N$5) -> -0.82732874 | P36: =B36-O36 -> -0.11582927 | Q36: =P36^2 -> 0.013416419 | T36: Adjusted R squared | U36: =1-(1-$U$33)*($U$32-1)/$U$35 -> 0.31662726 | V36: 0.31662726
A37: =Data_Monthly!A35 -> 45219 | B37: =Data_Monthly!J35 -> 3.779056 | C37: =IF($A37>=$U$5,1,0) -> 0 | D37: =IF(MONTH($A37)=2,1,0) -> 0 | E37: =IF(MONTH($A37)=3,1,0) -> 0 | F37: =IF(MONTH($A37)=4,1,0) -> 0 | G37: =IF(MONTH($A37)=5,1,0) -> 0 | H37: =IF(MONTH($A37)=6,1,0) -> 0 | I37: =IF(MONTH($A37)=7,1,0) -> 0 | J37: =IF(MONTH($A37)=8,1,0) -> 0 | K37: =IF(MONTH($A37)=9,1,0) -> 0 | L37: =IF(MONTH($A37)=10,1,0) -> 1 | M37: =IF(MONTH($A37)=11,1,0) -> 0 | N37: =IF(MONTH($A37)=12,1,0) -> 0 | O37: =$B$5+SUMPRODUCT(C37:N37,$C$5:$N$5) -> 2.9122417 | P37: =B37-O37 -> 0.86681424 | Q37: =P37^2 -> 0.75136693 | T37: Standard error of the estimate | U37: =INDEX(LINEST(B7:B52,C7:N52,TRUE(),TRUE()),3,2) -> 1.2720044 | V37: 1.2720044
A38: =Data_Monthly!A36 -> 45247 | B38: =Data_Monthly!J36 -> -0.31734416 | C38: =IF($A38>=$U$5,1,0) -> 0 | D38: =IF(MONTH($A38)=2,1,0) -> 0 | E38: =IF(MONTH($A38)=3,1,0) -> 0 | F38: =IF(MONTH($A38)=4,1,0) -> 0 | G38: =IF(MONTH($A38)=5,1,0) -> 0 | H38: =IF(MONTH($A38)=6,1,0) -> 0 | I38: =IF(MONTH($A38)=7,1,0) -> 0 | J38: =IF(MONTH($A38)=8,1,0) -> 0 | K38: =IF(MONTH($A38)=9,1,0) -> 0 | L38: =IF(MONTH($A38)=10,1,0) -> 0 | M38: =IF(MONTH($A38)=11,1,0) -> 1 | N38: =IF(MONTH($A38)=12,1,0) -> 0 | O38: =$B$5+SUMPRODUCT(C38:N38,$C$5:$N$5) -> 0.058685338 | P38: =B38-O38 -> -0.3760295 | Q38: =P38^2 -> 0.14139818
A39: =Data_Monthly!A37 -> 45289 | B39: =Data_Monthly!J37 -> 0.2839432 | C39: =IF($A39>=$U$5,1,0) -> 1 | D39: =IF(MONTH($A39)=2,1,0) -> 0 | E39: =IF(MONTH($A39)=3,1,0) -> 0 | F39: =IF(MONTH($A39)=4,1,0) -> 0 | G39: =IF(MONTH($A39)=5,1,0) -> 0 | H39: =IF(MONTH($A39)=6,1,0) -> 0 | I39: =IF(MONTH($A39)=7,1,0) -> 0 | J39: =IF(MONTH($A39)=8,1,0) -> 0 | K39: =IF(MONTH($A39)=9,1,0) -> 0 | L39: =IF(MONTH($A39)=10,1,0) -> 0 | M39: =IF(MONTH($A39)=11,1,0) -> 0 | N39: =IF(MONTH($A39)=12,1,0) -> 1 | O39: =$B$5+SUMPRODUCT(C39:N39,$C$5:$N$5) -> -0.11915092 | P39: =B39-O39 -> 0.40309411 | Q39: =P39^2 -> 0.16248486 | T39: Regression 2 (Post and 11 month dummies): ANOVA | U39: Excel | V39: Dissertation
A40: =Data_Monthly!A38 -> 45317 | B40: =Data_Monthly!J38 -> 0.91190972 | C40: =IF($A40>=$U$5,1,0) -> 1 | D40: =IF(MONTH($A40)=2,1,0) -> 0 | E40: =IF(MONTH($A40)=3,1,0) -> 0 | F40: =IF(MONTH($A40)=4,1,0) -> 0 | G40: =IF(MONTH($A40)=5,1,0) -> 0 | H40: =IF(MONTH($A40)=6,1,0) -> 0 | I40: =IF(MONTH($A40)=7,1,0) -> 0 | J40: =IF(MONTH($A40)=8,1,0) -> 0 | K40: =IF(MONTH($A40)=9,1,0) -> 0 | L40: =IF(MONTH($A40)=10,1,0) -> 0 | M40: =IF(MONTH($A40)=11,1,0) -> 0 | N40: =IF(MONTH($A40)=12,1,0) -> 0 | O40: =$B$5+SUMPRODUCT(C40:N40,$C$5:$N$5) -> -0.0082506677 | P40: =B40-O40 -> 0.92016039 | Q40: =P40^2 -> 0.84669514 | T40: Regression sum of squares | U40: =INDEX(LINEST(B7:B52,C7:N52,TRUE(),TRUE()),5,1) -> 53.150916 | V40: 53.150916
A41: =Data_Monthly!A39 -> 45345 | B41: =Data_Monthly!J39 -> -0.56286789 | C41: =IF($A41>=$U$5,1,0) -> 1 | D41: =IF(MONTH($A41)=2,1,0) -> 1 | E41: =IF(MONTH($A41)=3,1,0) -> 0 | F41: =IF(MONTH($A41)=4,1,0) -> 0 | G41: =IF(MONTH($A41)=5,1,0) -> 0 | H41: =IF(MONTH($A41)=6,1,0) -> 0 | I41: =IF(MONTH($A41)=7,1,0) -> 0 | J41: =IF(MONTH($A41)=8,1,0) -> 0 | K41: =IF(MONTH($A41)=9,1,0) -> 0 | L41: =IF(MONTH($A41)=10,1,0) -> 0 | M41: =IF(MONTH($A41)=11,1,0) -> 0 | N41: =IF(MONTH($A41)=12,1,0) -> 0 | O41: =$B$5+SUMPRODUCT(C41:N41,$C$5:$N$5) -> -0.37626973 | P41: =B41-O41 -> -0.18659816 | Q41: =P41^2 -> 0.034818872 | T41: Residual sum of squares | U41: =INDEX(LINEST(B7:B52,C7:N52,TRUE(),TRUE()),5,2) -> 53.39384 | V41: 53.39384
A42: =Data_Monthly!A40 -> 45373 | B42: =Data_Monthly!J40 -> -0.86646523 | C42: =IF($A42>=$U$5,1,0) -> 1 | D42: =IF(MONTH($A42)=2,1,0) -> 0 | E42: =IF(MONTH($A42)=3,1,0) -> 1 | F42: =IF(MONTH($A42)=4,1,0) -> 0 | G42: =IF(MONTH($A42)=5,1,0) -> 0 | H42: =IF(MONTH($A42)=6,1,0) -> 0 | I42: =IF(MONTH($A42)=7,1,0) -> 0 | J42: =IF(MONTH($A42)=8,1,0) -> 0 | K42: =IF(MONTH($A42)=9,1,0) -> 0 | L42: =IF(MONTH($A42)=10,1,0) -> 0 | M42: =IF(MONTH($A42)=11,1,0) -> 0 | N42: =IF(MONTH($A42)=12,1,0) -> 0 | O42: =$B$5+SUMPRODUCT(C42:N42,$C$5:$N$5) -> 0.92235983 | P42: =B42-O42 -> -1.7888251 | Q42: =P42^2 -> 3.1998951 | T42: Regression degrees of freedom | U42: =COLUMNS(C7:N52) -> 12 | V42: 12
A43: =Data_Monthly!A41 -> 45401 | B43: =Data_Monthly!J41 -> -0.47135655 | C43: =IF($A43>=$U$5,1,0) -> 1 | D43: =IF(MONTH($A43)=2,1,0) -> 0 | E43: =IF(MONTH($A43)=3,1,0) -> 0 | F43: =IF(MONTH($A43)=4,1,0) -> 1 | G43: =IF(MONTH($A43)=5,1,0) -> 0 | H43: =IF(MONTH($A43)=6,1,0) -> 0 | I43: =IF(MONTH($A43)=7,1,0) -> 0 | J43: =IF(MONTH($A43)=8,1,0) -> 0 | K43: =IF(MONTH($A43)=9,1,0) -> 0 | L43: =IF(MONTH($A43)=10,1,0) -> 0 | M43: =IF(MONTH($A43)=11,1,0) -> 0 | N43: =IF(MONTH($A43)=12,1,0) -> 0 | O43: =$B$5+SUMPRODUCT(C43:N43,$C$5:$N$5) -> -0.47070062 | P43: =B43-O43 -> -0.00065593451 | Q43: =P43^2 -> 4.3025009e-07 | T43: Residual degrees of freedom | U43: =$U$35 -> 33 | V43: 33
A44: =Data_Monthly!A42 -> 45443 | B44: =Data_Monthly!J42 -> 0.87100787 | C44: =IF($A44>=$U$5,1,0) -> 1 | D44: =IF(MONTH($A44)=2,1,0) -> 0 | E44: =IF(MONTH($A44)=3,1,0) -> 0 | F44: =IF(MONTH($A44)=4,1,0) -> 0 | G44: =IF(MONTH($A44)=5,1,0) -> 1 | H44: =IF(MONTH($A44)=6,1,0) -> 0 | I44: =IF(MONTH($A44)=7,1,0) -> 0 | J44: =IF(MONTH($A44)=8,1,0) -> 0 | K44: =IF(MONTH($A44)=9,1,0) -> 0 | L44: =IF(MONTH($A44)=10,1,0) -> 0 | M44: =IF(MONTH($A44)=11,1,0) -> 0 | N44: =IF(MONTH($A44)=12,1,0) -> 0 | O44: =$B$5+SUMPRODUCT(C44:N44,$C$5:$N$5) -> -0.95521962 | P44: =B44-O44 -> 1.8262275 | Q44: =P44^2 -> 3.3351069 | T44: Regression mean square | U44: =$U$40/$U$42 -> 4.429243
A45: =Data_Monthly!A43 -> 45471 | B45: =Data_Monthly!J43 -> 0.352782 | C45: =IF($A45>=$U$5,1,0) -> 1 | D45: =IF(MONTH($A45)=2,1,0) -> 0 | E45: =IF(MONTH($A45)=3,1,0) -> 0 | F45: =IF(MONTH($A45)=4,1,0) -> 0 | G45: =IF(MONTH($A45)=5,1,0) -> 0 | H45: =IF(MONTH($A45)=6,1,0) -> 1 | I45: =IF(MONTH($A45)=7,1,0) -> 0 | J45: =IF(MONTH($A45)=8,1,0) -> 0 | K45: =IF(MONTH($A45)=9,1,0) -> 0 | L45: =IF(MONTH($A45)=10,1,0) -> 0 | M45: =IF(MONTH($A45)=11,1,0) -> 0 | N45: =IF(MONTH($A45)=12,1,0) -> 0 | O45: =$B$5+SUMPRODUCT(C45:N45,$C$5:$N$5) -> -0.85578424 | P45: =B45-O45 -> 1.2085662 | Q45: =P45^2 -> 1.4606324 | T45: Residual mean square | U45: =$U$41/$U$43 -> 1.6179951
A46: =Data_Monthly!A44 -> 45499 | B46: =Data_Monthly!J44 -> -0.1385643 | C46: =IF($A46>=$U$5,1,0) -> 1 | D46: =IF(MONTH($A46)=2,1,0) -> 0 | E46: =IF(MONTH($A46)=3,1,0) -> 0 | F46: =IF(MONTH($A46)=4,1,0) -> 0 | G46: =IF(MONTH($A46)=5,1,0) -> 0 | H46: =IF(MONTH($A46)=6,1,0) -> 0 | I46: =IF(MONTH($A46)=7,1,0) -> 1 | J46: =IF(MONTH($A46)=8,1,0) -> 0 | K46: =IF(MONTH($A46)=9,1,0) -> 0 | L46: =IF(MONTH($A46)=10,1,0) -> 0 | M46: =IF(MONTH($A46)=11,1,0) -> 0 | N46: =IF(MONTH($A46)=12,1,0) -> 0 | O46: =$B$5+SUMPRODUCT(C46:N46,$C$5:$N$5) -> 1.2766915 | P46: =B46-O46 -> -1.4152558 | Q46: =P46^2 -> 2.002949 | T46: F statistic | U46: =INDEX(LINEST(B7:B52,C7:N52,TRUE(),TRUE()),4,1) -> 2.7374884 | V46: 2.7374884
A47: =Data_Monthly!A45 -> 45527 | B47: =Data_Monthly!J45 -> -1.0755879 | C47: =IF($A47>=$U$5,1,0) -> 1 | D47: =IF(MONTH($A47)=2,1,0) -> 0 | E47: =IF(MONTH($A47)=3,1,0) -> 0 | F47: =IF(MONTH($A47)=4,1,0) -> 0 | G47: =IF(MONTH($A47)=5,1,0) -> 0 | H47: =IF(MONTH($A47)=6,1,0) -> 0 | I47: =IF(MONTH($A47)=7,1,0) -> 0 | J47: =IF(MONTH($A47)=8,1,0) -> 1 | K47: =IF(MONTH($A47)=9,1,0) -> 0 | L47: =IF(MONTH($A47)=10,1,0) -> 0 | M47: =IF(MONTH($A47)=11,1,0) -> 0 | N47: =IF(MONTH($A47)=12,1,0) -> 0 | O47: =$B$5+SUMPRODUCT(C47:N47,$C$5:$N$5) -> -0.3986725 | P47: =B47-O47 -> -0.67691544 | Q47: =P47^2 -> 0.45821452 | T47: Significance of F | U47: =_xlfn.F.DIST.RT($U$46,$U$42,$U$43) -> 0.010914602 | V47: 0.010914602
A48: =Data_Monthly!A46 -> 45555 | B48: =Data_Monthly!J46 -> -1.7745579 | C48: =IF($A48>=$U$5,1,0) -> 1 | D48: =IF(MONTH($A48)=2,1,0) -> 0 | E48: =IF(MONTH($A48)=3,1,0) -> 0 | F48: =IF(MONTH($A48)=4,1,0) -> 0 | G48: =IF(MONTH($A48)=5,1,0) -> 0 | H48: =IF(MONTH($A48)=6,1,0) -> 0 | I48: =IF(MONTH($A48)=7,1,0) -> 0 | J48: =IF(MONTH($A48)=8,1,0) -> 0 | K48: =IF(MONTH($A48)=9,1,0) -> 1 | L48: =IF(MONTH($A48)=10,1,0) -> 0 | M48: =IF(MONTH($A48)=11,1,0) -> 0 | N48: =IF(MONTH($A48)=12,1,0) -> 0 | O48: =$B$5+SUMPRODUCT(C48:N48,$C$5:$N$5) -> -1.6101298 | P48: =B48-O48 -> -0.16442811 | Q48: =P48^2 -> 0.027036605
A49: =Data_Monthly!A47 -> 45583 | B49: =Data_Monthly!J47 -> 1.186059 | C49: =IF($A49>=$U$5,1,0) -> 1 | D49: =IF(MONTH($A49)=2,1,0) -> 0 | E49: =IF(MONTH($A49)=3,1,0) -> 0 | F49: =IF(MONTH($A49)=4,1,0) -> 0 | G49: =IF(MONTH($A49)=5,1,0) -> 0 | H49: =IF(MONTH($A49)=6,1,0) -> 0 | I49: =IF(MONTH($A49)=7,1,0) -> 0 | J49: =IF(MONTH($A49)=8,1,0) -> 0 | K49: =IF(MONTH($A49)=9,1,0) -> 0 | L49: =IF(MONTH($A49)=10,1,0) -> 1 | M49: =IF(MONTH($A49)=11,1,0) -> 0 | N49: =IF(MONTH($A49)=12,1,0) -> 0 | O49: =$B$5+SUMPRODUCT(C49:N49,$C$5:$N$5) -> 2.1294407 | P49: =B49-O49 -> -0.94338162 | Q49: =P49^2 -> 0.88996889 | T49: Regression 2 (Post and 11 month dummies): Post | U49: Excel | V49: Dissertation
A50: =Data_Monthly!A48 -> 45625 | B50: =Data_Monthly!J48 -> 1.0222744 | C50: =IF($A50>=$U$5,1,0) -> 1 | D50: =IF(MONTH($A50)=2,1,0) -> 0 | E50: =IF(MONTH($A50)=3,1,0) -> 0 | F50: =IF(MONTH($A50)=4,1,0) -> 0 | G50: =IF(MONTH($A50)=5,1,0) -> 0 | H50: =IF(MONTH($A50)=6,1,0) -> 0 | I50: =IF(MONTH($A50)=7,1,0) -> 0 | J50: =IF(MONTH($A50)=8,1,0) -> 0 | K50: =IF(MONTH($A50)=9,1,0) -> 0 | L50: =IF(MONTH($A50)=10,1,0) -> 0 | M50: =IF(MONTH($A50)=11,1,0) -> 1 | N50: =IF(MONTH($A50)=12,1,0) -> 0 | O50: =$B$5+SUMPRODUCT(C50:N50,$C$5:$N$5) -> -0.72411571 | P50: =B50-O50 -> 1.7463901 | Q50: =P50^2 -> 3.0498783 | T50: Coefficient on Post | U50: =Y7 -> -0.78280105 | V50: -0.78280105
A51: =Data_Monthly!A49 -> 45653 | B51: =Data_Monthly!J49 -> -0.64214427 | C51: =IF($A51>=$U$5,1,0) -> 1 | D51: =IF(MONTH($A51)=2,1,0) -> 0 | E51: =IF(MONTH($A51)=3,1,0) -> 0 | F51: =IF(MONTH($A51)=4,1,0) -> 0 | G51: =IF(MONTH($A51)=5,1,0) -> 0 | H51: =IF(MONTH($A51)=6,1,0) -> 0 | I51: =IF(MONTH($A51)=7,1,0) -> 0 | J51: =IF(MONTH($A51)=8,1,0) -> 0 | K51: =IF(MONTH($A51)=9,1,0) -> 0 | L51: =IF(MONTH($A51)=10,1,0) -> 0 | M51: =IF(MONTH($A51)=11,1,0) -> 0 | N51: =IF(MONTH($A51)=12,1,0) -> 1 | O51: =$B$5+SUMPRODUCT(C51:N51,$C$5:$N$5) -> -0.11915092 | P51: =B51-O51 -> -0.52299335 | Q51: =P51^2 -> 0.27352205 | T51: Standard error | U51: =Z7 -> 0.41636117 | V51: 0.41636117
A52: =Data_Monthly!A50 -> 45681 | B52: =Data_Monthly!J50 -> -0.41363547 | C52: =IF($A52>=$U$5,1,0) -> 1 | D52: =IF(MONTH($A52)=2,1,0) -> 0 | E52: =IF(MONTH($A52)=3,1,0) -> 0 | F52: =IF(MONTH($A52)=4,1,0) -> 0 | G52: =IF(MONTH($A52)=5,1,0) -> 0 | H52: =IF(MONTH($A52)=6,1,0) -> 0 | I52: =IF(MONTH($A52)=7,1,0) -> 0 | J52: =IF(MONTH($A52)=8,1,0) -> 0 | K52: =IF(MONTH($A52)=9,1,0) -> 0 | L52: =IF(MONTH($A52)=10,1,0) -> 0 | M52: =IF(MONTH($A52)=11,1,0) -> 0 | N52: =IF(MONTH($A52)=12,1,0) -> 0 | O52: =$B$5+SUMPRODUCT(C52:N52,$C$5:$N$5) -> -0.0082506677 | P52: =B52-O52 -> -0.4053848 | Q52: =P52^2 -> 0.16433684 | T52: t statistic | U52: =AA7 -> -1.880101 | V52: -1.880101
T53: p-value | U53: =AB7 -> 0.068946348 | V53: 0.068946348
T54: Month dummies jointly zero: F-test p-value | U54: =_xlfn.F.DIST.RT((($U$29-$U$41)/11)/($U$41/$U$43),11,$U$43) -> 0.014147977 | V54: 0.014147977
T56: Diagnostic tests on the residuals of Regression 2 | U56: Excel | V56: Dissertation
T57: Durbin-Watson | U57: =SUMXMY2(P8:P52,P7:P51)/SUMSQ(P7:P52) -> 1.6968823 | V57: 1.6968823
T58: Second moment of residuals | U58: =SUMSQ(P7:P52)/$U$32 -> 1.1607356
T59: Skewness | U59: =(SUMPRODUCT(P7:P52^3)/$U$32)/$U$58^1.5 -> 0.038273367
T60: Kurtosis | U60: =(SUMPRODUCT(P7:P52^4)/$U$32)/$U$58^2 -> 3.4488682
T61: Jarque-Bera statistic | U61: =$U$32/6*($U$59^2+($U$60-3)^2/4) -> 0.3974056 | V61: 0.3974056
T62: Jarque-Bera p-value (chi-squared, 2 df) | U62: =_xlfn.CHISQ.DIST.RT($U$61,2) -> 0.8197935 | V62: 0.8197935
T63: Breusch-Pagan: R squared, squared residuals on regressors | U63: =INDEX(LINEST(Q7:Q52,C7:N52,TRUE(),TRUE()),3,1) -> 0.3199564
T64: Breusch-Pagan statistic (n x R squared) | U64: =$U$32*$U$63 -> 14.717995 | V64: 14.717995
T65: Breusch-Pagan p-value (chi-squared, 12 df) | U65: =_xlfn.CHISQ.DIST.RT($U$64,$U$42) -> 0.25722199 | V65: 0.25722199
T66: Largest variance inflation factor | U66: =MAX(AC7:AC18) -> 1.8505435 | V66: 1.8505435
T68: Economic size over the post-policy months | U68: Excel | V68: Dissertation
T69: Credit to cards and other PL, 24-Jan-2025 (₹ crore) | U69: 1802669.7 | V69: 1802669.7
T70: Post-policy months | U70: =$U$9 -> 14 | V70: 14
T71: Cumulative shortfall in growth (per cent) | U71: =100*(EXP(-$U$14*$U$70/100)-1) -> 11.106195 | V71: 11.106195
T72: Implied shortfall (₹ crore) | U72: =$U$69*(EXP(-$U$14*$U$70/100)-1) -> 200208.02 | V72: 200208.02
T73: Implied shortfall (₹ lakh crore) | U73: =$U$72/100000 -> 2.0020802 | V73: 2.0020802

Sheet H2_Tests
A1: Gap2: bank credit to NBFCs (excl. HFCs) minus total non-food credit: tests, April 2021 to January 2025
A2: Reproduces Tables 7.1 to 7.5 (H2). Data rows link to Data_Monthly; every result is an Excel formula. Months before the circular: April 2021 to 17 November 2023; after: 29 December 2023 to January 2025.
A4: Gap2 | T4: Test results
A5: Coefficients | B5: =Y19 -> -0.79938413 | C5: =Y7 -> -1.2638864 | D5: =Y8 -> 1.0296852 | E5: =Y9 -> 2.0044225 | F5: =Y10 -> 0.52597583 | G5: =Y11 -> 0.043742646 | H5: =Y12 -> 1.5232828 | I5: =Y13 -> 2.7184279 | J5: =Y14 -> 0.030874037 | K5: =Y15 -> 1.5888357 | L5: =Y16 -> 3.1316577 | M5: =Y17 -> 3.1659501 | N5: =Y18 -> 5.2136553 | T5: Post = 1 for months dated on or after | U5: 45260 | X5: Regression 2: all coefficients
A6: Date | B6: Gap (pp) | C6: Post | D6: M2 | E6: M3 | F6: M4 | G6: M5 | H6: M6 | I6: M7 | J6: M8 | K6: M9 | L6: M10 | M6: M11 | N6: M12 | O6: Fitted | P6: Residual | Q6: Residual squared | T6: Months before: rows 7 to 37; after: rows 38 to 51. | X6: Variable | Y6: B | Z6: Std. error | AA6: t | AB6: p-value | AC6: VIF
A7: =Data_Monthly!A5 -> 44309 | B7: =Data_Monthly!K5 -> -3.5853842 | C7: =IF($A7>=$U$5,1,0) -> 0 | D7: =IF(MONTH($A7)=2,1,0) -> 0 | E7: =IF(MONTH($A7)=3,1,0) -> 0 | F7: =IF(MONTH($A7)=4,1,0) -> 1 | G7: =IF(MONTH($A7)=5,1,0) -> 0 | H7: =IF(MONTH($A7)=6,1,0) -> 0 | I7: =IF(MONTH($A7)=7,1,0) -> 0 | J7: =IF(MONTH($A7)=8,1,0) -> 0 | K7: =IF(MONTH($A7)=9,1,0) -> 0 | L7: =IF(MONTH($A7)=10,1,0) -> 0 | M7: =IF(MONTH($A7)=11,1,0) -> 0 | N7: =IF(MONTH($A7)=12,1,0) -> 0 | O7: =$B$5+SUMPRODUCT(C7:N7,$C$5:$N$5) -> -0.2734083 | P7: =B7-O7 -> -3.3119759 | Q7: =P7^2 -> 10.969185 | T7: Welch two-sample t-test (unequal variances) | U7: Excel | V7: Dissertation | X7: Post | Y7: =INDEX(LINEST(B7:B51,C7:N51,TRUE(),TRUE()),1,12) -> -1.2638864 | Z7: =INDEX(LINEST(B7:B51,C7:N51,TRUE(),TRUE()),2,12) -> 0.61316228 | AA7: =Y7/Z7 -> -2.0612592 | AB7: =_xlfn.T.DIST.2T(ABS(AA7),$U$35) -> 0.047481353 | AC7: =INDEX(MINVERSE($Y$23:$AJ$34),1,1) -> 1.0426426
A8: =Data_Monthly!A6 -> 44337 | B8: =Data_Monthly!K6 -> -1.0344892 | C8: =IF($A8>=$U$5,1,0) -> 0 | D8: =IF(MONTH($A8)=2,1,0) -> 0 | E8: =IF(MONTH($A8)=3,1,0) -> 0 | F8: =IF(MONTH($A8)=4,1,0) -> 0 | G8: =IF(MONTH($A8)=5,1,0) -> 1 | H8: =IF(MONTH($A8)=6,1,0) -> 0 | I8: =IF(MONTH($A8)=7,1,0) -> 0 | J8: =IF(MONTH($A8)=8,1,0) -> 0 | K8: =IF(MONTH($A8)=9,1,0) -> 0 | L8: =IF(MONTH($A8)=10,1,0) -> 0 | M8: =IF(MONTH($A8)=11,1,0) -> 0 | N8: =IF(MONTH($A8)=12,1,0) -> 0 | O8: =$B$5+SUMPRODUCT(C8:N8,$C$5:$N$5) -> -0.75564148 | P8: =B8-O8 -> -0.27884769 | Q8: =P8^2 -> 0.077756034 | T8: Months before (n1) | U8: =COUNT(B7:B37) -> 31 | V8: 31 | X8: M2 | Y8: =INDEX(LINEST(B7:B51,C7:N51,TRUE(),TRUE()),1,11) -> 1.0296852 | Z8: =INDEX(LINEST(B7:B51,C7:N51,TRUE(),TRUE()),2,11) -> 1.427972 | AA8: =Y8/Z8 -> 0.72108221 | AB8: =_xlfn.T.DIST.2T(ABS(AA8),$U$35) -> 0.47609447 | AC8: =INDEX(MINVERSE($Y$23:$AJ$34),2,2) -> 1.6417417
A9: =Data_Monthly!A7 -> 44365 | B9: =Data_Monthly!K7 -> -0.36946528 | C9: =IF($A9>=$U$5,1,0) -> 0 | D9: =IF(MONTH($A9)=2,1,0) -> 0 | E9: =IF(MONTH($A9)=3,1,0) -> 0 | F9: =IF(MONTH($A9)=4,1,0) -> 0 | G9: =IF(MONTH($A9)=5,1,0) -> 0 | H9: =IF(MONTH($A9)=6,1,0) -> 1 | I9: =IF(MONTH($A9)=7,1,0) -> 0 | J9: =IF(MONTH($A9)=8,1,0) -> 0 | K9: =IF(MONTH($A9)=9,1,0) -> 0 | L9: =IF(MONTH($A9)=10,1,0) -> 0 | M9: =IF(MONTH($A9)=11,1,0) -> 0 | N9: =IF(MONTH($A9)=12,1,0) -> 0 | O9: =$B$5+SUMPRODUCT(C9:N9,$C$5:$N$5) -> 0.72389868 | P9: =B9-O9 -> -1.093364 | Q9: =P9^2 -> 1.1954448 | T9: Months after (n2) | U9: =COUNT(B38:B51) -> 14 | V9: 14 | X9: M3 | Y9: =INDEX(LINEST(B7:B51,C7:N51,TRUE(),TRUE()),1,10) -> 2.0044225 | Z9: =INDEX(LINEST(B7:B51,C7:N51,TRUE(),TRUE()),2,10) -> 1.427972 | AA9: =Y9/Z9 -> 1.4036847 | AB9: =_xlfn.T.DIST.2T(ABS(AA9),$U$35) -> 0.17004329 | AC9: =INDEX(MINVERSE($Y$23:$AJ$34),3,3) -> 1.6417417
A10: =Data_Monthly!A8 -> 44407 | B10: =Data_Monthly!K8 -> 0.010605503 | C10: =IF($A10>=$U$5,1,0) -> 0 | D10: =IF(MONTH($A10)=2,1,0) -> 0 | E10: =IF(MONTH($A10)=3,1,0) -> 0 | F10: =IF(MONTH($A10)=4,1,0) -> 0 | G10: =IF(MONTH($A10)=5,1,0) -> 0 | H10: =IF(MONTH($A10)=6,1,0) -> 0 | I10: =IF(MONTH($A10)=7,1,0) -> 1 | J10: =IF(MONTH($A10)=8,1,0) -> 0 | K10: =IF(MONTH($A10)=9,1,0) -> 0 | L10: =IF(MONTH($A10)=10,1,0) -> 0 | M10: =IF(MONTH($A10)=11,1,0) -> 0 | N10: =IF(MONTH($A10)=12,1,0) -> 0 | O10: =$B$5+SUMPRODUCT(C10:N10,$C$5:$N$5) -> 1.9190437 | P10: =B10-O10 -> -1.9084382 | Q10: =P10^2 -> 3.6421365 | T10: Mean gap before | U10: =AVERAGE(B7:B37) -> 0.87685259 | V10: 0.87685259 | X10: M4 | Y10: =INDEX(LINEST(B7:B51,C7:N51,TRUE(),TRUE()),1,9) -> 0.52597583 | Z10: =INDEX(LINEST(B7:B51,C7:N51,TRUE(),TRUE()),2,9) -> 1.3275353 | AA10: =Y10/Z10 -> 0.39620479 | AB10: =_xlfn.T.DIST.2T(ABS(AA10),$U$35) -> 0.6945836 | AC10: =INDEX(MINVERSE($Y$23:$AJ$34),4,4) -> 1.8468468
A11: =Data_Monthly!A9 -> 44435 | B11: =Data_Monthly!K9 -> -2.2963644 | C11: =IF($A11>=$U$5,1,0) -> 0 | D11: =IF(MONTH($A11)=2,1,0) -> 0 | E11: =IF(MONTH($A11)=3,1,0) -> 0 | F11: =IF(MONTH($A11)=4,1,0) -> 0 | G11: =IF(MONTH($A11)=5,1,0) -> 0 | H11: =IF(MONTH($A11)=6,1,0) -> 0 | I11: =IF(MONTH($A11)=7,1,0) -> 0 | J11: =IF(MONTH($A11)=8,1,0) -> 1 | K11: =IF(MONTH($A11)=9,1,0) -> 0 | L11: =IF(MONTH($A11)=10,1,0) -> 0 | M11: =IF(MONTH($A11)=11,1,0) -> 0 | N11: =IF(MONTH($A11)=12,1,0) -> 0 | O11: =$B$5+SUMPRODUCT(C11:N11,$C$5:$N$5) -> -0.76851009 | P11: =B11-O11 -> -1.5278543 | Q11: =P11^2 -> 2.3343388 | T11: Mean gap after | U11: =AVERAGE(B38:B51) -> -0.19254444 | V11: -0.19254444 | X11: M5 | Y11: =INDEX(LINEST(B7:B51,C7:N51,TRUE(),TRUE()),1,8) -> 0.043742646 | Z11: =INDEX(LINEST(B7:B51,C7:N51,TRUE(),TRUE()),2,8) -> 1.3275353 | AA11: =Y11/Z11 -> 0.03295027 | AB11: =_xlfn.T.DIST.2T(ABS(AA11),$U$35) -> 0.97391892 | AC11: =INDEX(MINVERSE($Y$23:$AJ$34),5,5) -> 1.8468468
A12: =Data_Monthly!A10 -> 44463 | B12: =Data_Monthly!K10 -> -0.33197555 | C12: =IF($A12>=$U$5,1,0) -> 0 | D12: =IF(MONTH($A12)=2,1,0) -> 0 | E12: =IF(MONTH($A12)=3,1,0) -> 0 | F12: =IF(MONTH($A12)=4,1,0) -> 0 | G12: =IF(MONTH($A12)=5,1,0) -> 0 | H12: =IF(MONTH($A12)=6,1,0) -> 0 | I12: =IF(MONTH($A12)=7,1,0) -> 0 | J12: =IF(MONTH($A12)=8,1,0) -> 0 | K12: =IF(MONTH($A12)=9,1,0) -> 1 | L12: =IF(MONTH($A12)=10,1,0) -> 0 | M12: =IF(MONTH($A12)=11,1,0) -> 0 | N12: =IF(MONTH($A12)=12,1,0) -> 0 | O12: =$B$5+SUMPRODUCT(C12:N12,$C$5:$N$5) -> 0.78945162 | P12: =B12-O12 -> -1.1214272 | Q12: =P12^2 -> 1.2575989 | T12: Standard deviation before | U12: =_xlfn.STDEV.S(B7:B37) -> 2.4480817 | V12: 2.4480817 | X12: M6 | Y12: =INDEX(LINEST(B7:B51,C7:N51,TRUE(),TRUE()),1,7) -> 1.5232828 | Z12: =INDEX(LINEST(B7:B51,C7:N51,TRUE(),TRUE()),2,7) -> 1.3275353 | AA12: =Y12/Z12 -> 1.1474519 | AB12: =_xlfn.T.DIST.2T(ABS(AA12),$U$35) -> 0.25970164 | AC12: =INDEX(MINVERSE($Y$23:$AJ$34),6,6) -> 1.8468468
A13: =Data_Monthly!A11 -> 44491 | B13: =Data_Monthly!K11 -> 2.4520809 | C13: =IF($A13>=$U$5,1,0) -> 0 | D13: =IF(MONTH($A13)=2,1,0) -> 0 | E13: =IF(MONTH($A13)=3,1,0) -> 0 | F13: =IF(MONTH($A13)=4,1,0) -> 0 | G13: =IF(MONTH($A13)=5,1,0) -> 0 | H13: =IF(MONTH($A13)=6,1,0) -> 0 | I13: =IF(MONTH($A13)=7,1,0) -> 0 | J13: =IF(MONTH($A13)=8,1,0) -> 0 | K13: =IF(MONTH($A13)=9,1,0) -> 0 | L13: =IF(MONTH($A13)=10,1,0) -> 1 | M13: =IF(MONTH($A13)=11,1,0) -> 0 | N13: =IF(MONTH($A13)=12,1,0) -> 0 | O13: =$B$5+SUMPRODUCT(C13:N13,$C$5:$N$5) -> 2.3322735 | P13: =B13-O13 -> 0.11980739 | Q13: =P13^2 -> 0.01435381 | T13: Standard deviation after | U13: =_xlfn.STDEV.S(B38:B51) -> 1.7834166 | V13: 1.7834166 | X13: M7 | Y13: =INDEX(LINEST(B7:B51,C7:N51,TRUE(),TRUE()),1,6) -> 2.7184279 | Z13: =INDEX(LINEST(B7:B51,C7:N51,TRUE(),TRUE()),2,6) -> 1.427972 | AA13: =Y13/Z13 -> 1.9036983 | AB13: =_xlfn.T.DIST.2T(ABS(AA13),$U$35) -> 0.065976062 | AC13: =INDEX(MINVERSE($Y$23:$AJ$34),7,7) -> 1.6417417
A14: =Data_Monthly!A12 -> 44519 | B14: =Data_Monthly!K12 -> 2.6574207 | C14: =IF($A14>=$U$5,1,0) -> 0 | D14: =IF(MONTH($A14)=2,1,0) -> 0 | E14: =IF(MONTH($A14)=3,1,0) -> 0 | F14: =IF(MONTH($A14)=4,1,0) -> 0 | G14: =IF(MONTH($A14)=5,1,0) -> 0 | H14: =IF(MONTH($A14)=6,1,0) -> 0 | I14: =IF(MONTH($A14)=7,1,0) -> 0 | J14: =IF(MONTH($A14)=8,1,0) -> 0 | K14: =IF(MONTH($A14)=9,1,0) -> 0 | L14: =IF(MONTH($A14)=10,1,0) -> 0 | M14: =IF(MONTH($A14)=11,1,0) -> 1 | N14: =IF(MONTH($A14)=12,1,0) -> 0 | O14: =$B$5+SUMPRODUCT(C14:N14,$C$5:$N$5) -> 2.366566 | P14: =B14-O14 -> 0.29085469 | Q14: =P14^2 -> 0.084596449 | T14: Difference (after minus before) | U14: =$U$11-$U$10 -> -1.069397 | V14: -1.069397 | X14: M8 | Y14: =INDEX(LINEST(B7:B51,C7:N51,TRUE(),TRUE()),1,5) -> 0.030874037 | Z14: =INDEX(LINEST(B7:B51,C7:N51,TRUE(),TRUE()),2,5) -> 1.3275353 | AA14: =Y14/Z14 -> 0.02325666 | AB14: =_xlfn.T.DIST.2T(ABS(AA14),$U$35) -> 0.98158996 | AC14: =INDEX(MINVERSE($Y$23:$AJ$34),8,8) -> 1.8468468
A15: =Data_Monthly!A13 -> 44561 | B15: =Data_Monthly!K13 -> 4.3183459 | C15: =IF($A15>=$U$5,1,0) -> 0 | D15: =IF(MONTH($A15)=2,1,0) -> 0 | E15: =IF(MONTH($A15)=3,1,0) -> 0 | F15: =IF(MONTH($A15)=4,1,0) -> 0 | G15: =IF(MONTH($A15)=5,1,0) -> 0 | H15: =IF(MONTH($A15)=6,1,0) -> 0 | I15: =IF(MONTH($A15)=7,1,0) -> 0 | J15: =IF(MONTH($A15)=8,1,0) -> 0 | K15: =IF(MONTH($A15)=9,1,0) -> 0 | L15: =IF(MONTH($A15)=10,1,0) -> 0 | M15: =IF(MONTH($A15)=11,1,0) -> 0 | N15: =IF(MONTH($A15)=12,1,0) -> 1 | O15: =$B$5+SUMPRODUCT(C15:N15,$C$5:$N$5) -> 4.4142711 | P15: =B15-O15 -> -0.095925192 | Q15: =P15^2 -> 0.0092016424 | T15: Difference per year (x 12) | U15: =12*$U$14 -> -12.832764 | V15: -12.832764 | X15: M9 | Y15: =INDEX(LINEST(B7:B51,C7:N51,TRUE(),TRUE()),1,4) -> 1.5888357 | Z15: =INDEX(LINEST(B7:B51,C7:N51,TRUE(),TRUE()),2,4) -> 1.3275353 | AA15: =Y15/Z15 -> 1.1968313 | AB15: =_xlfn.T.DIST.2T(ABS(AA15),$U$35) -> 0.24016413 | AC15: =INDEX(MINVERSE($Y$23:$AJ$34),9,9) -> 1.8468468
A16: =Data_Monthly!A14 -> 44589 | B16: =Data_Monthly!K14 -> 1.5133246 | C16: =IF($A16>=$U$5,1,0) -> 0 | D16: =IF(MONTH($A16)=2,1,0) -> 0 | E16: =IF(MONTH($A16)=3,1,0) -> 0 | F16: =IF(MONTH($A16)=4,1,0) -> 0 | G16: =IF(MONTH($A16)=5,1,0) -> 0 | H16: =IF(MONTH($A16)=6,1,0) -> 0 | I16: =IF(MONTH($A16)=7,1,0) -> 0 | J16: =IF(MONTH($A16)=8,1,0) -> 0 | K16: =IF(MONTH($A16)=9,1,0) -> 0 | L16: =IF(MONTH($A16)=10,1,0) -> 0 | M16: =IF(MONTH($A16)=11,1,0) -> 0 | N16: =IF(MONTH($A16)=12,1,0) -> 0 | O16: =$B$5+SUMPRODUCT(C16:N16,$C$5:$N$5) -> -0.79938413 | P16: =B16-O16 -> 2.3127088 | Q16: =P16^2 -> 5.3486218 | T16: Standard error of the difference | U16: =SQRT($U$13^2/$U$9+$U$12^2/$U$8) -> 0.64846731 | X16: M10 | Y16: =INDEX(LINEST(B7:B51,C7:N51,TRUE(),TRUE()),1,3) -> 3.1316577 | Z16: =INDEX(LINEST(B7:B51,C7:N51,TRUE(),TRUE()),2,3) -> 1.3275353 | AA16: =Y16/Z16 -> 2.3590015 | AB16: =_xlfn.T.DIST.2T(ABS(AA16),$U$35) -> 0.024594363 | AC16: =INDEX(MINVERSE($Y$23:$AJ$34),10,10) -> 1.8468468
A17: =Data_Monthly!A15 -> 44617 | B17: =Data_Monthly!K15 -> -0.94064234 | C17: =IF($A17>=$U$5,1,0) -> 0 | D17: =IF(MONTH($A17)=2,1,0) -> 1 | E17: =IF(MONTH($A17)=3,1,0) -> 0 | F17: =IF(MONTH($A17)=4,1,0) -> 0 | G17: =IF(MONTH($A17)=5,1,0) -> 0 | H17: =IF(MONTH($A17)=6,1,0) -> 0 | I17: =IF(MONTH($A17)=7,1,0) -> 0 | J17: =IF(MONTH($A17)=8,1,0) -> 0 | K17: =IF(MONTH($A17)=9,1,0) -> 0 | L17: =IF(MONTH($A17)=10,1,0) -> 0 | M17: =IF(MONTH($A17)=11,1,0) -> 0 | N17: =IF(MONTH($A17)=12,1,0) -> 0 | O17: =$B$5+SUMPRODUCT(C17:N17,$C$5:$N$5) -> 0.2303011 | P17: =B17-O17 -> -1.1709434 | Q17: =P17^2 -> 1.3711085 | T17: t statistic | U17: =$U$14/$U$16 -> -1.6491148 | V17: -1.6491148 | X17: M11 | Y17: =INDEX(LINEST(B7:B51,C7:N51,TRUE(),TRUE()),1,2) -> 3.1659501 | Z17: =INDEX(LINEST(B7:B51,C7:N51,TRUE(),TRUE()),2,2) -> 1.3275353 | AA17: =Y17/Z17 -> 2.3848331 | AB17: =_xlfn.T.DIST.2T(ABS(AA17),$U$35) -> 0.023181277 | AC17: =INDEX(MINVERSE($Y$23:$AJ$34),11,11) -> 1.8468468
A18: =Data_Monthly!A16 -> 44645 | B18: =Data_Monthly!K16 -> 1.0403223 | C18: =IF($A18>=$U$5,1,0) -> 0 | D18: =IF(MONTH($A18)=2,1,0) -> 0 | E18: =IF(MONTH($A18)=3,1,0) -> 1 | F18: =IF(MONTH($A18)=4,1,0) -> 0 | G18: =IF(MONTH($A18)=5,1,0) -> 0 | H18: =IF(MONTH($A18)=6,1,0) -> 0 | I18: =IF(MONTH($A18)=7,1,0) -> 0 | J18: =IF(MONTH($A18)=8,1,0) -> 0 | K18: =IF(MONTH($A18)=9,1,0) -> 0 | L18: =IF(MONTH($A18)=10,1,0) -> 0 | M18: =IF(MONTH($A18)=11,1,0) -> 0 | N18: =IF(MONTH($A18)=12,1,0) -> 0 | O18: =$B$5+SUMPRODUCT(C18:N18,$C$5:$N$5) -> 1.2050384 | P18: =B18-O18 -> -0.16471605 | Q18: =P18^2 -> 0.027131378 | T18: Welch degrees of freedom | U18: =(($U$13^2/$U$9)+($U$12^2/$U$8))^2/(($U$13^2/$U$9)^2/($U$9-1)+($U$12^2/$U$8)^2/($U$8-1)) -> 33.901011 | V18: 33.901011 | X18: M12 | Y18: =INDEX(LINEST(B7:B51,C7:N51,TRUE(),TRUE()),1,1) -> 5.2136553 | Z18: =INDEX(LINEST(B7:B51,C7:N51,TRUE(),TRUE()),2,1) -> 1.3186553 | AA18: =Y18/Z18 -> 3.9537665 | AB18: =_xlfn.T.DIST.2T(ABS(AA18),$U$35) -> 0.00039874771 | AC18: =INDEX(MINVERSE($Y$23:$AJ$34),12,12) -> 1.8222222
A19: =Data_Monthly!A17 -> 44673 | B19: =Data_Monthly!K17 -> 0.34182661 | C19: =IF($A19>=$U$5,1,0) -> 0 | D19: =IF(MONTH($A19)=2,1,0) -> 0 | E19: =IF(MONTH($A19)=3,1,0) -> 0 | F19: =IF(MONTH($A19)=4,1,0) -> 1 | G19: =IF(MONTH($A19)=5,1,0) -> 0 | H19: =IF(MONTH($A19)=6,1,0) -> 0 | I19: =IF(MONTH($A19)=7,1,0) -> 0 | J19: =IF(MONTH($A19)=8,1,0) -> 0 | K19: =IF(MONTH($A19)=9,1,0) -> 0 | L19: =IF(MONTH($A19)=10,1,0) -> 0 | M19: =IF(MONTH($A19)=11,1,0) -> 0 | N19: =IF(MONTH($A19)=12,1,0) -> 0 | O19: =$B$5+SUMPRODUCT(C19:N19,$C$5:$N$5) -> -0.2734083 | P19: =B19-O19 -> 0.61523491 | Q19: =P19^2 -> 0.37851399 | T19: p-value, two-tailed (T.TEST type 3) | U19: =_xlfn.T.TEST(B38:B51,B7:B37,2,3) -> 0.10836169 | V19: 0.10836169 | X19: Constant | Y19: =INDEX(LINEST(B7:B51,C7:N51,TRUE(),TRUE()),1,13) -> -0.79938413 | Z19: =INDEX(LINEST(B7:B51,C7:N51,TRUE(),TRUE()),2,13) -> 0.98153856 | AA19: =Y19/Z19 -> -0.81441948 | AB19: =_xlfn.T.DIST.2T(ABS(AA19),$U$35) -> 0.42142439
A20: =Data_Monthly!A18 -> 44701 | B20: =Data_Monthly!K18 -> -0.33879971 | C20: =IF($A20>=$U$5,1,0) -> 0 | D20: =IF(MONTH($A20)=2,1,0) -> 0 | E20: =IF(MONTH($A20)=3,1,0) -> 0 | F20: =IF(MONTH($A20)=4,1,0) -> 0 | G20: =IF(MONTH($A20)=5,1,0) -> 1 | H20: =IF(MONTH($A20)=6,1,0) -> 0 | I20: =IF(MONTH($A20)=7,1,0) -> 0 | J20: =IF(MONTH($A20)=8,1,0) -> 0 | K20: =IF(MONTH($A20)=9,1,0) -> 0 | L20: =IF(MONTH($A20)=10,1,0) -> 0 | M20: =IF(MONTH($A20)=11,1,0) -> 0 | N20: =IF(MONTH($A20)=12,1,0) -> 0 | O20: =$B$5+SUMPRODUCT(C20:N20,$C$5:$N$5) -> -0.75564148 | P20: =B20-O20 -> 0.41684177 | Q20: =P20^2 -> 0.17375706 | X20: Row 5 repeats these coefficients above the data columns; Fitted = Constant + sum of coefficient x regressor.
A21: =Data_Monthly!A19 -> 44729 | B21: =Data_Monthly!K19 -> -1.1596309 | C21: =IF($A21>=$U$5,1,0) -> 0 | D21: =IF(MONTH($A21)=2,1,0) -> 0 | E21: =IF(MONTH($A21)=3,1,0) -> 0 | F21: =IF(MONTH($A21)=4,1,0) -> 0 | G21: =IF(MONTH($A21)=5,1,0) -> 0 | H21: =IF(MONTH($A21)=6,1,0) -> 1 | I21: =IF(MONTH($A21)=7,1,0) -> 0 | J21: =IF(MONTH($A21)=8,1,0) -> 0 | K21: =IF(MONTH($A21)=9,1,0) -> 0 | L21: =IF(MONTH($A21)=10,1,0) -> 0 | M21: =IF(MONTH($A21)=11,1,0) -> 0 | N21: =IF(MONTH($A21)=12,1,0) -> 0 | O21: =$B$5+SUMPRODUCT(C21:N21,$C$5:$N$5) -> 0.72389868 | P21: =B21-O21 -> -1.8835296 | Q21: =P21^2 -> 3.5476837 | T21: Regression 1 (Post dummy only) | U21: Excel | V21: Dissertation | X21: VIF = diagonal of the inverse of the correlation matrix of the regressors:
A22: =Data_Monthly!A20 -> 44771 | B22: =Data_Monthly!K20 -> 5.6377211 | C22: =IF($A22>=$U$5,1,0) -> 0 | D22: =IF(MONTH($A22)=2,1,0) -> 0 | E22: =IF(MONTH($A22)=3,1,0) -> 0 | F22: =IF(MONTH($A22)=4,1,0) -> 0 | G22: =IF(MONTH($A22)=5,1,0) -> 0 | H22: =IF(MONTH($A22)=6,1,0) -> 0 | I22: =IF(MONTH($A22)=7,1,0) -> 1 | J22: =IF(MONTH($A22)=8,1,0) -> 0 | K22: =IF(MONTH($A22)=9,1,0) -> 0 | L22: =IF(MONTH($A22)=10,1,0) -> 0 | M22: =IF(MONTH($A22)=11,1,0) -> 0 | N22: =IF(MONTH($A22)=12,1,0) -> 0 | O22: =$B$5+SUMPRODUCT(C22:N22,$C$5:$N$5) -> 1.9190437 | P22: =B22-O22 -> 3.7186773 | Q22: =P22^2 -> 13.828561 | T22: Constant | U22: =INDEX(LINEST(B7:B51,C7:C51,TRUE(),TRUE()),1,2) -> 0.87685259 | V22: 0.87685259 | Y22: Post | Z22: M2 | AA22: M3 | AB22: M4 | AC22: M5 | AD22: M6 | AE22: M7 | AF22: M8 | AG22: M9 | AH22: M10 | AI22: M11 | AJ22: M12
A23: =Data_Monthly!A21 -> 44799 | B23: =Data_Monthly!K21 -> -0.55502341 | C23: =IF($A23>=$U$5,1,0) -> 0 | D23: =IF(MONTH($A23)=2,1,0) -> 0 | E23: =IF(MONTH($A23)=3,1,0) -> 0 | F23: =IF(MONTH($A23)=4,1,0) -> 0 | G23: =IF(MONTH($A23)=5,1,0) -> 0 | H23: =IF(MONTH($A23)=6,1,0) -> 0 | I23: =IF(MONTH($A23)=7,1,0) -> 0 | J23: =IF(MONTH($A23)=8,1,0) -> 1 | K23: =IF(MONTH($A23)=9,1,0) -> 0 | L23: =IF(MONTH($A23)=10,1,0) -> 0 | M23: =IF(MONTH($A23)=11,1,0) -> 0 | N23: =IF(MONTH($A23)=12,1,0) -> 0 | O23: =$B$5+SUMPRODUCT(C23:N23,$C$5:$N$5) -> -0.76851009 | P23: =B23-O23 -> 0.21348668 | Q23: =P23^2 -> 0.045576564 | T23: Coefficient on Post | U23: =INDEX(LINEST(B7:B51,C7:C51,TRUE(),TRUE()),1,1) -> -1.069397 | V23: -1.069397 | X23: Post | Y23: =CORREL($C$7:$C$51,$C$7:$C$51) -> 1 | Z23: =CORREL($D$7:$D$51,$C$7:$C$51) -> 0.01282895 | AA23: =CORREL($E$7:$E$51,$C$7:$C$51) -> 0.01282895 | AB23: =CORREL($F$7:$F$51,$C$7:$C$51) -> -0.041231193 | AC23: =CORREL($G$7:$G$51,$C$7:$C$51) -> -0.041231193 | AD23: =CORREL($H$7:$H$51,$C$7:$C$51) -> -0.041231193 | AE23: =CORREL($I$7:$I$51,$C$7:$C$51) -> 0.01282895 | AF23: =CORREL($J$7:$J$51,$C$7:$C$51) -> -0.041231193 | AG23: =CORREL($K$7:$K$51,$C$7:$C$51) -> -0.041231193 | AH23: =CORREL($L$7:$L$51,$C$7:$C$51) -> -0.041231193 | AI23: =CORREL($M$7:$M$51,$C$7:$C$51) -> -0.041231193 | AJ23: =CORREL($N$7:$N$51,$C$7:$C$51) -> 0.12744187
A24: =Data_Monthly!A22 -> 44827 | B24: =Data_Monthly!K22 -> 0.68514286 | C24: =IF($A24>=$U$5,1,0) -> 0 | D24: =IF(MONTH($A24)=2,1,0) -> 0 | E24: =IF(MONTH($A24)=3,1,0) -> 0 | F24: =IF(MONTH($A24)=4,1,0) -> 0 | G24: =IF(MONTH($A24)=5,1,0) -> 0 | H24: =IF(MONTH($A24)=6,1,0) -> 0 | I24: =IF(MONTH($A24)=7,1,0) -> 0 | J24: =IF(MONTH($A24)=8,1,0) -> 0 | K24: =IF(MONTH($A24)=9,1,0) -> 1 | L24: =IF(MONTH($A24)=10,1,0) -> 0 | M24: =IF(MONTH($A24)=11,1,0) -> 0 | N24: =IF(MONTH($A24)=12,1,0) -> 0 | O24: =$B$5+SUMPRODUCT(C24:N24,$C$5:$N$5) -> 0.78945162 | P24: =B24-O24 -> -0.10430875 | Q24: =P24^2 -> 0.010880316 | T24: Standard error | U24: =INDEX(LINEST(B7:B51,C7:C51,TRUE(),TRUE()),2,1) -> 0.7302329 | V24: 0.7302329 | X24: M2 | Y24: =CORREL($C$7:$C$51,$D$7:$D$51) -> 0.01282895 | Z24: =CORREL($D$7:$D$51,$D$7:$D$51) -> 1 | AA24: =CORREL($E$7:$E$51,$D$7:$D$51) -> -0.071428571 | AB24: =CORREL($F$7:$F$51,$D$7:$D$51) -> -0.083478387 | AC24: =CORREL($G$7:$G$51,$D$7:$D$51) -> -0.083478387 | AD24: =CORREL($H$7:$H$51,$D$7:$D$51) -> -0.083478387 | AE24: =CORREL($I$7:$I$51,$D$7:$D$51) -> -0.071428571 | AF24: =CORREL($J$7:$J$51,$D$7:$D$51) -> -0.083478387 | AG24: =CORREL($K$7:$K$51,$D$7:$D$51) -> -0.083478387 | AH24: =CORREL($L$7:$L$51,$D$7:$D$51) -> -0.083478387 | AI24: =CORREL($M$7:$M$51,$D$7:$D$51) -> -0.083478387 | AJ24: =CORREL($N$7:$N$51,$D$7:$D$51) -> -0.083478387
A25: =Data_Monthly!A23 -> 44855 | B25: =Data_Monthly!K23 -> 6.2526135 | C25: =IF($A25>=$U$5,1,0) -> 0 | D25: =IF(MONTH($A25)=2,1,0) -> 0 | E25: =IF(MONTH($A25)=3,1,0) -> 0 | F25: =IF(MONTH($A25)=4,1,0) -> 0 | G25: =IF(MONTH($A25)=5,1,0) -> 0 | H25: =IF(MONTH($A25)=6,1,0) -> 0 | I25: =IF(MONTH($A25)=7,1,0) -> 0 | J25: =IF(MONTH($A25)=8,1,0) -> 0 | K25: =IF(MONTH($A25)=9,1,0) -> 0 | L25: =IF(MONTH($A25)=10,1,0) -> 1 | M25: =IF(MONTH($A25)=11,1,0) -> 0 | N25: =IF(MONTH($A25)=12,1,0) -> 0 | O25: =$B$5+SUMPRODUCT(C25:N25,$C$5:$N$5) -> 2.3322735 | P25: =B25-O25 -> 3.92034 | Q25: =P25^2 -> 15.369065 | T25: t statistic | U25: =$U$23/$U$24 -> -1.4644602 | V25: -1.4644602 | X25: M3 | Y25: =CORREL($C$7:$C$51,$E$7:$E$51) -> 0.01282895 | Z25: =CORREL($D$7:$D$51,$E$7:$E$51) -> -0.071428571 | AA25: =CORREL($E$7:$E$51,$E$7:$E$51) -> 1 | AB25: =CORREL($F$7:$F$51,$E$7:$E$51) -> -0.083478387 | AC25: =CORREL($G$7:$G$51,$E$7:$E$51) -> -0.083478387 | AD25: =CORREL($H$7:$H$51,$E$7:$E$51) -> -0.083478387 | AE25: =CORREL($I$7:$I$51,$E$7:$E$51) -> -0.071428571 | AF25: =CORREL($J$7:$J$51,$E$7:$E$51) -> -0.083478387 | AG25: =CORREL($K$7:$K$51,$E$7:$E$51) -> -0.083478387 | AH25: =CORREL($L$7:$L$51,$E$7:$E$51) -> -0.083478387 | AI25: =CORREL($M$7:$M$51,$E$7:$E$51) -> -0.083478387 | AJ25: =CORREL($N$7:$N$51,$E$7:$E$51) -> -0.083478387
A26: =Data_Monthly!A24 -> 44883 | B26: =Data_Monthly!K24 -> 1.0884583 | C26: =IF($A26>=$U$5,1,0) -> 0 | D26: =IF(MONTH($A26)=2,1,0) -> 0 | E26: =IF(MONTH($A26)=3,1,0) -> 0 | F26: =IF(MONTH($A26)=4,1,0) -> 0 | G26: =IF(MONTH($A26)=5,1,0) -> 0 | H26: =IF(MONTH($A26)=6,1,0) -> 0 | I26: =IF(MONTH($A26)=7,1,0) -> 0 | J26: =IF(MONTH($A26)=8,1,0) -> 0 | K26: =IF(MONTH($A26)=9,1,0) -> 0 | L26: =IF(MONTH($A26)=10,1,0) -> 0 | M26: =IF(MONTH($A26)=11,1,0) -> 1 | N26: =IF(MONTH($A26)=12,1,0) -> 0 | O26: =$B$5+SUMPRODUCT(C26:N26,$C$5:$N$5) -> 2.366566 | P26: =B26-O26 -> -1.2781077 | Q26: =P26^2 -> 1.6335592 | T26: Residual degrees of freedom | U26: =INDEX(LINEST(B7:B51,C7:C51,TRUE(),TRUE()),4,2) -> 43 | X26: M4 | Y26: =CORREL($C$7:$C$51,$F$7:$F$51) -> -0.041231193 | Z26: =CORREL($D$7:$D$51,$F$7:$F$51) -> -0.083478387 | AA26: =CORREL($E$7:$E$51,$F$7:$F$51) -> -0.083478387 | AB26: =CORREL($F$7:$F$51,$F$7:$F$51) -> 1 | AC26: =CORREL($G$7:$G$51,$F$7:$F$51) -> -0.097560976 | AD26: =CORREL($H$7:$H$51,$F$7:$F$51) -> -0.097560976 | AE26: =CORREL($I$7:$I$51,$F$7:$F$51) -> -0.083478387 | AF26: =CORREL($J$7:$J$51,$F$7:$F$51) -> -0.097560976 | AG26: =CORREL($K$7:$K$51,$F$7:$F$51) -> -0.097560976 | AH26: =CORREL($L$7:$L$51,$F$7:$F$51) -> -0.097560976 | AI26: =CORREL($M$7:$M$51,$F$7:$F$51) -> -0.097560976 | AJ26: =CORREL($N$7:$N$51,$F$7:$F$51) -> -0.097560976
A27: =Data_Monthly!A25 -> 44925 | B27: =Data_Monthly!K25 -> 6.5472353 | C27: =IF($A27>=$U$5,1,0) -> 0 | D27: =IF(MONTH($A27)=2,1,0) -> 0 | E27: =IF(MONTH($A27)=3,1,0) -> 0 | F27: =IF(MONTH($A27)=4,1,0) -> 0 | G27: =IF(MONTH($A27)=5,1,0) -> 0 | H27: =IF(MONTH($A27)=6,1,0) -> 0 | I27: =IF(MONTH($A27)=7,1,0) -> 0 | J27: =IF(MONTH($A27)=8,1,0) -> 0 | K27: =IF(MONTH($A27)=9,1,0) -> 0 | L27: =IF(MONTH($A27)=10,1,0) -> 0 | M27: =IF(MONTH($A27)=11,1,0) -> 0 | N27: =IF(MONTH($A27)=12,1,0) -> 1 | O27: =$B$5+SUMPRODUCT(C27:N27,$C$5:$N$5) -> 4.4142711 | P27: =B27-O27 -> 2.1329642 | Q27: =P27^2 -> 4.5495362 | T27: p-value | U27: =_xlfn.T.DIST.2T(ABS($U$25),$U$26) -> 0.15034159 | V27: 0.15034159 | X27: M5 | Y27: =CORREL($C$7:$C$51,$G$7:$G$51) -> -0.041231193 | Z27: =CORREL($D$7:$D$51,$G$7:$G$51) -> -0.083478387 | AA27: =CORREL($E$7:$E$51,$G$7:$G$51) -> -0.083478387 | AB27: =CORREL($F$7:$F$51,$G$7:$G$51) -> -0.097560976 | AC27: =CORREL($G$7:$G$51,$G$7:$G$51) -> 1 | AD27: =CORREL($H$7:$H$51,$G$7:$G$51) -> -0.097560976 | AE27: =CORREL($I$7:$I$51,$G$7:$G$51) -> -0.083478387 | AF27: =CORREL($J$7:$J$51,$G$7:$G$51) -> -0.097560976 | AG27: =CORREL($K$7:$K$51,$G$7:$G$51) -> -0.097560976 | AH27: =CORREL($L$7:$L$51,$G$7:$G$51) -> -0.097560976 | AI27: =CORREL($M$7:$M$51,$G$7:$G$51) -> -0.097560976 | AJ27: =CORREL($N$7:$N$51,$G$7:$G$51) -> -0.097560976
A28: =Data_Monthly!A26 -> 44953 | B28: =Data_Monthly!K26 -> -2.2944451 | C28: =IF($A28>=$U$5,1,0) -> 0 | D28: =IF(MONTH($A28)=2,1,0) -> 0 | E28: =IF(MONTH($A28)=3,1,0) -> 0 | F28: =IF(MONTH($A28)=4,1,0) -> 0 | G28: =IF(MONTH($A28)=5,1,0) -> 0 | H28: =IF(MONTH($A28)=6,1,0) -> 0 | I28: =IF(MONTH($A28)=7,1,0) -> 0 | J28: =IF(MONTH($A28)=8,1,0) -> 0 | K28: =IF(MONTH($A28)=9,1,0) -> 0 | L28: =IF(MONTH($A28)=10,1,0) -> 0 | M28: =IF(MONTH($A28)=11,1,0) -> 0 | N28: =IF(MONTH($A28)=12,1,0) -> 0 | O28: =$B$5+SUMPRODUCT(C28:N28,$C$5:$N$5) -> -0.79938413 | P28: =B28-O28 -> -1.4950609 | Q28: =P28^2 -> 2.2352072 | T28: R squared | U28: =INDEX(LINEST(B7:B51,C7:C51,TRUE(),TRUE()),3,1) -> 0.047506051 | V28: 0.047506051 | X28: M6 | Y28: =CORREL($C$7:$C$51,$H$7:$H$51) -> -0.041231193 | Z28: =CORREL($D$7:$D$51,$H$7:$H$51) -> -0.083478387 | AA28: =CORREL($E$7:$E$51,$H$7:$H$51) -> -0.083478387 | AB28: =CORREL($F$7:$F$51,$H$7:$H$51) -> -0.097560976 | AC28: =CORREL($G$7:$G$51,$H$7:$H$51) -> -0.097560976 | AD28: =CORREL($H$7:$H$51,$H$7:$H$51) -> 1 | AE28: =CORREL($I$7:$I$51,$H$7:$H$51) -> -0.083478387 | AF28: =CORREL($J$7:$J$51,$H$7:$H$51) -> -0.097560976 | AG28: =CORREL($K$7:$K$51,$H$7:$H$51) -> -0.097560976 | AH28: =CORREL($L$7:$L$51,$H$7:$H$51) -> -0.097560976 | AI28: =CORREL($M$7:$M$51,$H$7:$H$51) -> -0.097560976 | AJ28: =CORREL($N$7:$N$51,$H$7:$H$51) -> -0.097560976
A29: =Data_Monthly!A27 -> 44981 | B29: =Data_Monthly!K27 -> 1.2779078 | C29: =IF($A29>=$U$5,1,0) -> 0 | D29: =IF(MONTH($A29)=2,1,0) -> 1 | E29: =IF(MONTH($A29)=3,1,0) -> 0 | F29: =IF(MONTH($A29)=4,1,0) -> 0 | G29: =IF(MONTH($A29)=5,1,0) -> 0 | H29: =IF(MONTH($A29)=6,1,0) -> 0 | I29: =IF(MONTH($A29)=7,1,0) -> 0 | J29: =IF(MONTH($A29)=8,1,0) -> 0 | K29: =IF(MONTH($A29)=9,1,0) -> 0 | L29: =IF(MONTH($A29)=10,1,0) -> 0 | M29: =IF(MONTH($A29)=11,1,0) -> 0 | N29: =IF(MONTH($A29)=12,1,0) -> 0 | O29: =$B$5+SUMPRODUCT(C29:N29,$C$5:$N$5) -> 0.2303011 | P29: =B29-O29 -> 1.0476067 | Q29: =P29^2 -> 1.0974798 | T29: Residual sum of squares | U29: =INDEX(LINEST(B7:B51,C7:C51,TRUE(),TRUE()),5,2) -> 221.14059 | X29: M7 | Y29: =CORREL($C$7:$C$51,$I$7:$I$51) -> 0.01282895 | Z29: =CORREL($D$7:$D$51,$I$7:$I$51) -> -0.071428571 | AA29: =CORREL($E$7:$E$51,$I$7:$I$51) -> -0.071428571 | AB29: =CORREL($F$7:$F$51,$I$7:$I$51) -> -0.083478387 | AC29: =CORREL($G$7:$G$51,$I$7:$I$51) -> -0.083478387 | AD29: =CORREL($H$7:$H$51,$I$7:$I$51) -> -0.083478387 | AE29: =CORREL($I$7:$I$51,$I$7:$I$51) -> 1 | AF29: =CORREL($J$7:$J$51,$I$7:$I$51) -> -0.083478387 | AG29: =CORREL($K$7:$K$51,$I$7:$I$51) -> -0.083478387 | AH29: =CORREL($L$7:$L$51,$I$7:$I$51) -> -0.083478387 | AI29: =CORREL($M$7:$M$51,$I$7:$I$51) -> -0.083478387 | AJ29: =CORREL($N$7:$N$51,$I$7:$I$51) -> -0.083478387
A30: =Data_Monthly!A28 -> 45009 | B30: =Data_Monthly!K28 -> -0.2597696 | C30: =IF($A30>=$U$5,1,0) -> 0 | D30: =IF(MONTH($A30)=2,1,0) -> 0 | E30: =IF(MONTH($A30)=3,1,0) -> 1 | F30: =IF(MONTH($A30)=4,1,0) -> 0 | G30: =IF(MONTH($A30)=5,1,0) -> 0 | H30: =IF(MONTH($A30)=6,1,0) -> 0 | I30: =IF(MONTH($A30)=7,1,0) -> 0 | J30: =IF(MONTH($A30)=8,1,0) -> 0 | K30: =IF(MONTH($A30)=9,1,0) -> 0 | L30: =IF(MONTH($A30)=10,1,0) -> 0 | M30: =IF(MONTH($A30)=11,1,0) -> 0 | N30: =IF(MONTH($A30)=12,1,0) -> 0 | O30: =$B$5+SUMPRODUCT(C30:N30,$C$5:$N$5) -> 1.2050384 | P30: =B30-O30 -> -1.464808 | Q30: =P30^2 -> 2.1456625 | X30: M8 | Y30: =CORREL($C$7:$C$51,$J$7:$J$51) -> -0.041231193 | Z30: =CORREL($D$7:$D$51,$J$7:$J$51) -> -0.083478387 | AA30: =CORREL($E$7:$E$51,$J$7:$J$51) -> -0.083478387 | AB30: =CORREL($F$7:$F$51,$J$7:$J$51) -> -0.097560976 | AC30: =CORREL($G$7:$G$51,$J$7:$J$51) -> -0.097560976 | AD30: =CORREL($H$7:$H$51,$J$7:$J$51) -> -0.097560976 | AE30: =CORREL($I$7:$I$51,$J$7:$J$51) -> -0.083478387 | AF30: =CORREL($J$7:$J$51,$J$7:$J$51) -> 1 | AG30: =CORREL($K$7:$K$51,$J$7:$J$51) -> -0.097560976 | AH30: =CORREL($L$7:$L$51,$J$7:$J$51) -> -0.097560976 | AI30: =CORREL($M$7:$M$51,$J$7:$J$51) -> -0.097560976 | AJ30: =CORREL($N$7:$N$51,$J$7:$J$51) -> -0.097560976
A31: =Data_Monthly!A29 -> 45037 | B31: =Data_Monthly!K29 -> 0.1415809 | C31: =IF($A31>=$U$5,1,0) -> 0 | D31: =IF(MONTH($A31)=2,1,0) -> 0 | E31: =IF(MONTH($A31)=3,1,0) -> 0 | F31: =IF(MONTH($A31)=4,1,0) -> 1 | G31: =IF(MONTH($A31)=5,1,0) -> 0 | H31: =IF(MONTH($A31)=6,1,0) -> 0 | I31: =IF(MONTH($A31)=7,1,0) -> 0 | J31: =IF(MONTH($A31)=8,1,0) -> 0 | K31: =IF(MONTH($A31)=9,1,0) -> 0 | L31: =IF(MONTH($A31)=10,1,0) -> 0 | M31: =IF(MONTH($A31)=11,1,0) -> 0 | N31: =IF(MONTH($A31)=12,1,0) -> 0 | O31: =$B$5+SUMPRODUCT(C31:N31,$C$5:$N$5) -> -0.2734083 | P31: =B31-O31 -> 0.4149892 | Q31: =P31^2 -> 0.17221603 | T31: Regression 2 (Post and 11 month dummies): model summary | U31: Excel | V31: Dissertation | X31: M9 | Y31: =CORREL($C$7:$C$51,$K$7:$K$51) -> -0.041231193 | Z31: =CORREL($D$7:$D$51,$K$7:$K$51) -> -0.083478387 | AA31: =CORREL($E$7:$E$51,$K$7:$K$51) -> -0.083478387 | AB31: =CORREL($F$7:$F$51,$K$7:$K$51) -> -0.097560976 | AC31: =CORREL($G$7:$G$51,$K$7:$K$51) -> -0.097560976 | AD31: =CORREL($H$7:$H$51,$K$7:$K$51) -> -0.097560976 | AE31: =CORREL($I$7:$I$51,$K$7:$K$51) -> -0.083478387 | AF31: =CORREL($J$7:$J$51,$K$7:$K$51) -> -0.097560976 | AG31: =CORREL($K$7:$K$51,$K$7:$K$51) -> 1 | AH31: =CORREL($L$7:$L$51,$K$7:$K$51) -> -0.097560976 | AI31: =CORREL($M$7:$M$51,$K$7:$K$51) -> -0.097560976 | AJ31: =CORREL($N$7:$N$51,$K$7:$K$51) -> -0.097560976
A32: =Data_Monthly!A30 -> 45065 | B32: =Data_Monthly!K30 -> -1.6479854 | C32: =IF($A32>=$U$5,1,0) -> 0 | D32: =IF(MONTH($A32)=2,1,0) -> 0 | E32: =IF(MONTH($A32)=3,1,0) -> 0 | F32: =IF(MONTH($A32)=4,1,0) -> 0 | G32: =IF(MONTH($A32)=5,1,0) -> 1 | H32: =IF(MONTH($A32)=6,1,0) -> 0 | I32: =IF(MONTH($A32)=7,1,0) -> 0 | J32: =IF(MONTH($A32)=8,1,0) -> 0 | K32: =IF(MONTH($A32)=9,1,0) -> 0 | L32: =IF(MONTH($A32)=10,1,0) -> 0 | M32: =IF(MONTH($A32)=11,1,0) -> 0 | N32: =IF(MONTH($A32)=12,1,0) -> 0 | O32: =$B$5+SUMPRODUCT(C32:N32,$C$5:$N$5) -> -0.75564148 | P32: =B32-O32 -> -0.89234389 | Q32: =P32^2 -> 0.79627762 | T32: Observations | U32: =COUNT(B7:B51) -> 45 | V32: 45 | X32: M10 | Y32: =CORREL($C$7:$C$51,$L$7:$L$51) -> -0.041231193 | Z32: =CORREL($D$7:$D$51,$L$7:$L$51) -> -0.083478387 | AA32: =CORREL($E$7:$E$51,$L$7:$L$51) -> -0.083478387 | AB32: =CORREL($F$7:$F$51,$L$7:$L$51) -> -0.097560976 | AC32: =CORREL($G$7:$G$51,$L$7:$L$51) -> -0.097560976 | AD32: =CORREL($H$7:$H$51,$L$7:$L$51) -> -0.097560976 | AE32: =CORREL($I$7:$I$51,$L$7:$L$51) -> -0.083478387 | AF32: =CORREL($J$7:$J$51,$L$7:$L$51) -> -0.097560976 | AG32: =CORREL($K$7:$K$51,$L$7:$L$51) -> -0.097560976 | AH32: =CORREL($L$7:$L$51,$L$7:$L$51) -> 1 | AI32: =CORREL($M$7:$M$51,$L$7:$L$51) -> -0.097560976 | AJ32: =CORREL($N$7:$N$51,$L$7:$L$51) -> -0.097560976
A33: =Data_Monthly!A31 -> 45107 | B33: =Data_Monthly!K31 -> 3.735506 | C33: =IF($A33>=$U$5,1,0) -> 0 | D33: =IF(MONTH($A33)=2,1,0) -> 0 | E33: =IF(MONTH($A33)=3,1,0) -> 0 | F33: =IF(MONTH($A33)=4,1,0) -> 0 | G33: =IF(MONTH($A33)=5,1,0) -> 0 | H33: =IF(MONTH($A33)=6,1,0) -> 1 | I33: =IF(MONTH($A33)=7,1,0) -> 0 | J33: =IF(MONTH($A33)=8,1,0) -> 0 | K33: =IF(MONTH($A33)=9,1,0) -> 0 | L33: =IF(MONTH($A33)=10,1,0) -> 0 | M33: =IF(MONTH($A33)=11,1,0) -> 0 | N33: =IF(MONTH($A33)=12,1,0) -> 0 | O33: =$B$5+SUMPRODUCT(C33:N33,$C$5:$N$5) -> 0.72389868 | P33: =B33-O33 -> 3.0116073 | Q33: =P33^2 -> 9.0697786 | T33: R squared | U33: =INDEX(LINEST(B7:B51,C7:N51,TRUE(),TRUE()),3,1) -> 0.52066809 | V33: 0.52066809 | X33: M11 | Y33: =CORREL($C$7:$C$51,$M$7:$M$51) -> -0.041231193 | Z33: =CORREL($D$7:$D$51,$M$7:$M$51) -> -0.083478387 | AA33: =CORREL($E$7:$E$51,$M$7:$M$51) -> -0.083478387 | AB33: =CORREL($F$7:$F$51,$M$7:$M$51) -> -0.097560976 | AC33: =CORREL($G$7:$G$51,$M$7:$M$51) -> -0.097560976 | AD33: =CORREL($H$7:$H$51,$M$7:$M$51) -> -0.097560976 | AE33: =CORREL($I$7:$I$51,$M$7:$M$51) -> -0.083478387 | AF33: =CORREL($J$7:$J$51,$M$7:$M$51) -> -0.097560976 | AG33: =CORREL($K$7:$K$51,$M$7:$M$51) -> -0.097560976 | AH33: =CORREL($L$7:$L$51,$M$7:$M$51) -> -0.097560976 | AI33: =CORREL($M$7:$M$51,$M$7:$M$51) -> 1 | AJ33: =CORREL($N$7:$N$51,$M$7:$M$51) -> -0.097560976
A34: =Data_Monthly!A33 -> 45163 | B34: =Data_Monthly!K33 -> 0.23794724 | C34: =IF($A34>=$U$5,1,0) -> 0 | D34: =IF(MONTH($A34)=2,1,0) -> 0 | E34: =IF(MONTH($A34)=3,1,0) -> 0 | F34: =IF(MONTH($A34)=4,1,0) -> 0 | G34: =IF(MONTH($A34)=5,1,0) -> 0 | H34: =IF(MONTH($A34)=6,1,0) -> 0 | I34: =IF(MONTH($A34)=7,1,0) -> 0 | J34: =IF(MONTH($A34)=8,1,0) -> 1 | K34: =IF(MONTH($A34)=9,1,0) -> 0 | L34: =IF(MONTH($A34)=10,1,0) -> 0 | M34: =IF(MONTH($A34)=11,1,0) -> 0 | N34: =IF(MONTH($A34)=12,1,0) -> 0 | O34: =$B$5+SUMPRODUCT(C34:N34,$C$5:$N$5) -> -0.76851009 | P34: =B34-O34 -> 1.0064573 | Q34: =P34^2 -> 1.0129564 | T34: R | U34: =SQRT($U$33) -> 0.72157335 | X34: M12 | Y34: =CORREL($C$7:$C$51,$N$7:$N$51) -> 0.12744187 | Z34: =CORREL($D$7:$D$51,$N$7:$N$51) -> -0.083478387 | AA34: =CORREL($E$7:$E$51,$N$7:$N$51) -> -0.083478387 | AB34: =CORREL($F$7:$F$51,$N$7:$N$51) -> -0.097560976 | AC34: =CORREL($G$7:$G$51,$N$7:$N$51) -> -0.097560976 | AD34: =CORREL($H$7:$H$51,$N$7:$N$51) -> -0.097560976 | AE34: =CORREL($I$7:$I$51,$N$7:$N$51) -> -0.083478387 | AF34: =CORREL($J$7:$J$51,$N$7:$N$51) -> -0.097560976 | AG34: =CORREL($K$7:$K$51,$N$7:$N$51) -> -0.097560976 | AH34: =CORREL($L$7:$L$51,$N$7:$N$51) -> -0.097560976 | AI34: =CORREL($M$7:$M$51,$N$7:$N$51) -> -0.097560976 | AJ34: =CORREL($N$7:$N$51,$N$7:$N$51) -> 1
A35: =Data_Monthly!A34 -> 45191 | B35: =Data_Monthly!K34 -> 1.9824059 | C35: =IF($A35>=$U$5,1,0) -> 0 | D35: =IF(MONTH($A35)=2,1,0) -> 0 | E35: =IF(MONTH($A35)=3,1,0) -> 0 | F35: =IF(MONTH($A35)=4,1,0) -> 0 | G35: =IF(MONTH($A35)=5,1,0) -> 0 | H35: =IF(MONTH($A35)=6,1,0) -> 0 | I35: =IF(MONTH($A35)=7,1,0) -> 0 | J35: =IF(MONTH($A35)=8,1,0) -> 0 | K35: =IF(MONTH($A35)=9,1,0) -> 1 | L35: =IF(MONTH($A35)=10,1,0) -> 0 | M35: =IF(MONTH($A35)=11,1,0) -> 0 | N35: =IF(MONTH($A35)=12,1,0) -> 0 | O35: =$B$5+SUMPRODUCT(C35:N35,$C$5:$N$5) -> 0.78945162 | P35: =B35-O35 -> 1.1929543 | Q35: =P35^2 -> 1.42314 | T35: Residual degrees of freedom | U35: =INDEX(LINEST(B7:B51,C7:N51,TRUE(),TRUE()),4,2) -> 32
A36: =Data_Monthly!A35 -> 45219 | B36: =Data_Monthly!K35 -> 0.28875143 | C36: =IF($A36>=$U$5,1,0) -> 0 | D36: =IF(MONTH($A36)=2,1,0) -> 0 | E36: =IF(MONTH($A36)=3,1,0) -> 0 | F36: =IF(MONTH($A36)=4,1,0) -> 0 | G36: =IF(MONTH($A36)=5,1,0) -> 0 | H36: =IF(MONTH($A36)=6,1,0) -> 0 | I36: =IF(MONTH($A36)=7,1,0) -> 0 | J36: =IF(MONTH($A36)=8,1,0) -> 0 | K36: =IF(MONTH($A36)=9,1,0) -> 0 | L36: =IF(MONTH($A36)=10,1,0) -> 1 | M36: =IF(MONTH($A36)=11,1,0) -> 0 | N36: =IF(MONTH($A36)=12,1,0) -> 0 | O36: =$B$5+SUMPRODUCT(C36:N36,$C$5:$N$5) -> 2.3322735 | P36: =B36-O36 -> -2.0435221 | Q36: =P36^2 -> 4.1759826 | T36: Adjusted R squared | U36: =1-(1-$U$33)*($U$32-1)/$U$35 -> 0.34091863 | V36: 0.34091863
A37: =Data_Monthly!A36 -> 45247 | B37: =Data_Monthly!K36 -> 1.7872083 | C37: =IF($A37>=$U$5,1,0) -> 0 | D37: =IF(MONTH($A37)=2,1,0) -> 0 | E37: =IF(MONTH($A37)=3,1,0) -> 0 | F37: =IF(MONTH($A37)=4,1,0) -> 0 | G37: =IF(MONTH($A37)=5,1,0) -> 0 | H37: =IF(MONTH($A37)=6,1,0) -> 0 | I37: =IF(MONTH($A37)=7,1,0) -> 0 | J37: =IF(MONTH($A37)=8,1,0) -> 0 | K37: =IF(MONTH($A37)=9,1,0) -> 0 | L37: =IF(MONTH($A37)=10,1,0) -> 0 | M37: =IF(MONTH($A37)=11,1,0) -> 1 | N37: =IF(MONTH($A37)=12,1,0) -> 0 | O37: =$B$5+SUMPRODUCT(C37:N37,$C$5:$N$5) -> 2.366566 | P37: =B37-O37 -> -0.57935764 | Q37: =P37^2 -> 0.33565528 | T37: Standard error of the estimate | U37: =INDEX(LINEST(B7:B51,C7:N51,TRUE(),TRUE()),3,2) -> 1.8648603 | V37: 1.8648603
A38: =Data_Monthly!A37 -> 45289 | B38: =Data_Monthly!K37 -> 1.9189598 | C38: =IF($A38>=$U$5,1,0) -> 1 | D38: =IF(MONTH($A38)=2,1,0) -> 0 | E38: =IF(MONTH($A38)=3,1,0) -> 0 | F38: =IF(MONTH($A38)=4,1,0) -> 0 | G38: =IF(MONTH($A38)=5,1,0) -> 0 | H38: =IF(MONTH($A38)=6,1,0) -> 0 | I38: =IF(MONTH($A38)=7,1,0) -> 0 | J38: =IF(MONTH($A38)=8,1,0) -> 0 | K38: =IF(MONTH($A38)=9,1,0) -> 0 | L38: =IF(MONTH($A38)=10,1,0) -> 0 | M38: =IF(MONTH($A38)=11,1,0) -> 0 | N38: =IF(MONTH($A38)=12,1,0) -> 1 | O38: =$B$5+SUMPRODUCT(C38:N38,$C$5:$N$5) -> 3.1503847 | P38: =B38-O38 -> -1.2314249 | Q38: =P38^2 -> 1.5164074
A39: =Data_Monthly!A38 -> 45317 | B39: =Data_Monthly!K38 -> -3.5192413 | C39: =IF($A39>=$U$5,1,0) -> 1 | D39: =IF(MONTH($A39)=2,1,0) -> 0 | E39: =IF(MONTH($A39)=3,1,0) -> 0 | F39: =IF(MONTH($A39)=4,1,0) -> 0 | G39: =IF(MONTH($A39)=5,1,0) -> 0 | H39: =IF(MONTH($A39)=6,1,0) -> 0 | I39: =IF(MONTH($A39)=7,1,0) -> 0 | J39: =IF(MONTH($A39)=8,1,0) -> 0 | K39: =IF(MONTH($A39)=9,1,0) -> 0 | L39: =IF(MONTH($A39)=10,1,0) -> 0 | M39: =IF(MONTH($A39)=11,1,0) -> 0 | N39: =IF(MONTH($A39)=12,1,0) -> 0 | O39: =$B$5+SUMPRODUCT(C39:N39,$C$5:$N$5) -> -2.0632705 | P39: =B39-O39 -> -1.4559708 | Q39: =P39^2 -> 2.119851 | T39: Regression 2 (Post and 11 month dummies): ANOVA | U39: Excel | V39: Dissertation
A40: =Data_Monthly!A39 -> 45345 | B40: =Data_Monthly!K39 -> -0.91024854 | C40: =IF($A40>=$U$5,1,0) -> 1 | D40: =IF(MONTH($A40)=2,1,0) -> 1 | E40: =IF(MONTH($A40)=3,1,0) -> 0 | F40: =IF(MONTH($A40)=4,1,0) -> 0 | G40: =IF(MONTH($A40)=5,1,0) -> 0 | H40: =IF(MONTH($A40)=6,1,0) -> 0 | I40: =IF(MONTH($A40)=7,1,0) -> 0 | J40: =IF(MONTH($A40)=8,1,0) -> 0 | K40: =IF(MONTH($A40)=9,1,0) -> 0 | L40: =IF(MONTH($A40)=10,1,0) -> 0 | M40: =IF(MONTH($A40)=11,1,0) -> 0 | N40: =IF(MONTH($A40)=12,1,0) -> 0 | O40: =$B$5+SUMPRODUCT(C40:N40,$C$5:$N$5) -> -1.0335853 | P40: =B40-O40 -> 0.12333675 | Q40: =P40^2 -> 0.015211953 | T40: Regression sum of squares | U40: =INDEX(LINEST(B7:B51,C7:N51,TRUE(),TRUE()),5,1) -> 120.88355 | V40: 120.88355
A41: =Data_Monthly!A40 -> 45373 | B41: =Data_Monthly!K40 -> 1.5706761 | C41: =IF($A41>=$U$5,1,0) -> 1 | D41: =IF(MONTH($A41)=2,1,0) -> 0 | E41: =IF(MONTH($A41)=3,1,0) -> 1 | F41: =IF(MONTH($A41)=4,1,0) -> 0 | G41: =IF(MONTH($A41)=5,1,0) -> 0 | H41: =IF(MONTH($A41)=6,1,0) -> 0 | I41: =IF(MONTH($A41)=7,1,0) -> 0 | J41: =IF(MONTH($A41)=8,1,0) -> 0 | K41: =IF(MONTH($A41)=9,1,0) -> 0 | L41: =IF(MONTH($A41)=10,1,0) -> 0 | M41: =IF(MONTH($A41)=11,1,0) -> 0 | N41: =IF(MONTH($A41)=12,1,0) -> 0 | O41: =$B$5+SUMPRODUCT(C41:N41,$C$5:$N$5) -> -0.058847994 | P41: =B41-O41 -> 1.629524 | Q41: =P41^2 -> 2.6553486 | T41: Residual sum of squares | U41: =INDEX(LINEST(B7:B51,C7:N51,TRUE(),TRUE()),5,2) -> 111.28652 | V41: 111.28652
A42: =Data_Monthly!A41 -> 45401 | B42: =Data_Monthly!K41 -> 0.74445714 | C42: =IF($A42>=$U$5,1,0) -> 1 | D42: =IF(MONTH($A42)=2,1,0) -> 0 | E42: =IF(MONTH($A42)=3,1,0) -> 0 | F42: =IF(MONTH($A42)=4,1,0) -> 1 | G42: =IF(MONTH($A42)=5,1,0) -> 0 | H42: =IF(MONTH($A42)=6,1,0) -> 0 | I42: =IF(MONTH($A42)=7,1,0) -> 0 | J42: =IF(MONTH($A42)=8,1,0) -> 0 | K42: =IF(MONTH($A42)=9,1,0) -> 0 | L42: =IF(MONTH($A42)=10,1,0) -> 0 | M42: =IF(MONTH($A42)=11,1,0) -> 0 | N42: =IF(MONTH($A42)=12,1,0) -> 0 | O42: =$B$5+SUMPRODUCT(C42:N42,$C$5:$N$5) -> -1.5372947 | P42: =B42-O42 -> 2.2817518 | Q42: =P42^2 -> 5.2063914 | T42: Regression degrees of freedom | U42: =COLUMNS(C7:N51) -> 12 | V42: 12
A43: =Data_Monthly!A42 -> 45443 | B43: =Data_Monthly!K42 -> -1.2651781 | C43: =IF($A43>=$U$5,1,0) -> 1 | D43: =IF(MONTH($A43)=2,1,0) -> 0 | E43: =IF(MONTH($A43)=3,1,0) -> 0 | F43: =IF(MONTH($A43)=4,1,0) -> 0 | G43: =IF(MONTH($A43)=5,1,0) -> 1 | H43: =IF(MONTH($A43)=6,1,0) -> 0 | I43: =IF(MONTH($A43)=7,1,0) -> 0 | J43: =IF(MONTH($A43)=8,1,0) -> 0 | K43: =IF(MONTH($A43)=9,1,0) -> 0 | L43: =IF(MONTH($A43)=10,1,0) -> 0 | M43: =IF(MONTH($A43)=11,1,0) -> 0 | N43: =IF(MONTH($A43)=12,1,0) -> 0 | O43: =$B$5+SUMPRODUCT(C43:N43,$C$5:$N$5) -> -2.0195279 | P43: =B43-O43 -> 0.75434981 | Q43: =P43^2 -> 0.56904364 | T43: Residual degrees of freedom | U43: =$U$35 -> 32 | V43: 32
A44: =Data_Monthly!A43 -> 45471 | B44: =Data_Monthly!K43 -> -0.57470146 | C44: =IF($A44>=$U$5,1,0) -> 1 | D44: =IF(MONTH($A44)=2,1,0) -> 0 | E44: =IF(MONTH($A44)=3,1,0) -> 0 | F44: =IF(MONTH($A44)=4,1,0) -> 0 | G44: =IF(MONTH($A44)=5,1,0) -> 0 | H44: =IF(MONTH($A44)=6,1,0) -> 1 | I44: =IF(MONTH($A44)=7,1,0) -> 0 | J44: =IF(MONTH($A44)=8,1,0) -> 0 | K44: =IF(MONTH($A44)=9,1,0) -> 0 | L44: =IF(MONTH($A44)=10,1,0) -> 0 | M44: =IF(MONTH($A44)=11,1,0) -> 0 | N44: =IF(MONTH($A44)=12,1,0) -> 0 | O44: =$B$5+SUMPRODUCT(C44:N44,$C$5:$N$5) -> -0.5399877 | P44: =B44-O44 -> -0.034713753 | Q44: =P44^2 -> 0.0012050446 | T44: Regression mean square | U44: =$U$40/$U$42 -> 10.073629
A45: =Data_Monthly!A44 -> 45499 | B45: =Data_Monthly!K44 -> -1.1550818 | C45: =IF($A45>=$U$5,1,0) -> 1 | D45: =IF(MONTH($A45)=2,1,0) -> 0 | E45: =IF(MONTH($A45)=3,1,0) -> 0 | F45: =IF(MONTH($A45)=4,1,0) -> 0 | G45: =IF(MONTH($A45)=5,1,0) -> 0 | H45: =IF(MONTH($A45)=6,1,0) -> 0 | I45: =IF(MONTH($A45)=7,1,0) -> 1 | J45: =IF(MONTH($A45)=8,1,0) -> 0 | K45: =IF(MONTH($A45)=9,1,0) -> 0 | L45: =IF(MONTH($A45)=10,1,0) -> 0 | M45: =IF(MONTH($A45)=11,1,0) -> 0 | N45: =IF(MONTH($A45)=12,1,0) -> 0 | O45: =$B$5+SUMPRODUCT(C45:N45,$C$5:$N$5) -> 0.65515735 | P45: =B45-O45 -> -1.8102391 | Q45: =P45^2 -> 3.2769657 | T45: Residual mean square | U45: =$U$41/$U$43 -> 3.4777038
A46: =Data_Monthly!A45 -> 45527 | B46: =Data_Monthly!K45 -> -1.7244862 | C46: =IF($A46>=$U$5,1,0) -> 1 | D46: =IF(MONTH($A46)=2,1,0) -> 0 | E46: =IF(MONTH($A46)=3,1,0) -> 0 | F46: =IF(MONTH($A46)=4,1,0) -> 0 | G46: =IF(MONTH($A46)=5,1,0) -> 0 | H46: =IF(MONTH($A46)=6,1,0) -> 0 | I46: =IF(MONTH($A46)=7,1,0) -> 0 | J46: =IF(MONTH($A46)=8,1,0) -> 1 | K46: =IF(MONTH($A46)=9,1,0) -> 0 | L46: =IF(MONTH($A46)=10,1,0) -> 0 | M46: =IF(MONTH($A46)=11,1,0) -> 0 | N46: =IF(MONTH($A46)=12,1,0) -> 0 | O46: =$B$5+SUMPRODUCT(C46:N46,$C$5:$N$5) -> -2.0323965 | P46: =B46-O46 -> 0.3079103 | Q46: =P46^2 -> 0.094808753 | T46: F statistic | U46: =INDEX(LINEST(B7:B51,C7:N51,TRUE(),TRUE()),4,1) -> 2.8966322 | V46: 2.8966322
A47: =Data_Monthly!A46 -> 45555 | B47: =Data_Monthly!K46 -> -0.44165316 | C47: =IF($A47>=$U$5,1,0) -> 1 | D47: =IF(MONTH($A47)=2,1,0) -> 0 | E47: =IF(MONTH($A47)=3,1,0) -> 0 | F47: =IF(MONTH($A47)=4,1,0) -> 0 | G47: =IF(MONTH($A47)=5,1,0) -> 0 | H47: =IF(MONTH($A47)=6,1,0) -> 0 | I47: =IF(MONTH($A47)=7,1,0) -> 0 | J47: =IF(MONTH($A47)=8,1,0) -> 0 | K47: =IF(MONTH($A47)=9,1,0) -> 1 | L47: =IF(MONTH($A47)=10,1,0) -> 0 | M47: =IF(MONTH($A47)=11,1,0) -> 0 | N47: =IF(MONTH($A47)=12,1,0) -> 0 | O47: =$B$5+SUMPRODUCT(C47:N47,$C$5:$N$5) -> -0.47443477 | P47: =B47-O47 -> 0.032781605 | Q47: =P47^2 -> 0.0010746336 | T47: Significance of F | U47: =_xlfn.F.DIST.RT($U$46,$U$42,$U$43) -> 0.0080724667 | V47: 0.0080724667
A48: =Data_Monthly!A47 -> 45583 | B48: =Data_Monthly!K47 -> -0.92823811 | C48: =IF($A48>=$U$5,1,0) -> 1 | D48: =IF(MONTH($A48)=2,1,0) -> 0 | E48: =IF(MONTH($A48)=3,1,0) -> 0 | F48: =IF(MONTH($A48)=4,1,0) -> 0 | G48: =IF(MONTH($A48)=5,1,0) -> 0 | H48: =IF(MONTH($A48)=6,1,0) -> 0 | I48: =IF(MONTH($A48)=7,1,0) -> 0 | J48: =IF(MONTH($A48)=8,1,0) -> 0 | K48: =IF(MONTH($A48)=9,1,0) -> 0 | L48: =IF(MONTH($A48)=10,1,0) -> 1 | M48: =IF(MONTH($A48)=11,1,0) -> 0 | N48: =IF(MONTH($A48)=12,1,0) -> 0 | O48: =$B$5+SUMPRODUCT(C48:N48,$C$5:$N$5) -> 1.0683871 | P48: =B48-O48 -> -1.9966252 | Q48: =P48^2 -> 3.9865124
A49: =Data_Monthly!A48 -> 45625 | B49: =Data_Monthly!K48 -> 2.6692902 | C49: =IF($A49>=$U$5,1,0) -> 1 | D49: =IF(MONTH($A49)=2,1,0) -> 0 | E49: =IF(MONTH($A49)=3,1,0) -> 0 | F49: =IF(MONTH($A49)=4,1,0) -> 0 | G49: =IF(MONTH($A49)=5,1,0) -> 0 | H49: =IF(MONTH($A49)=6,1,0) -> 0 | I49: =IF(MONTH($A49)=7,1,0) -> 0 | J49: =IF(MONTH($A49)=8,1,0) -> 0 | K49: =IF(MONTH($A49)=9,1,0) -> 0 | L49: =IF(MONTH($A49)=10,1,0) -> 0 | M49: =IF(MONTH($A49)=11,1,0) -> 1 | N49: =IF(MONTH($A49)=12,1,0) -> 0 | O49: =$B$5+SUMPRODUCT(C49:N49,$C$5:$N$5) -> 1.1026796 | P49: =B49-O49 -> 1.5666106 | Q49: =P49^2 -> 2.4542688 | T49: Regression 2 (Post and 11 month dummies): Post | U49: Excel | V49: Dissertation
A50: =Data_Monthly!A49 -> 45653 | B50: =Data_Monthly!K49 -> 2.3447707 | C50: =IF($A50>=$U$5,1,0) -> 1 | D50: =IF(MONTH($A50)=2,1,0) -> 0 | E50: =IF(MONTH($A50)=3,1,0) -> 0 | F50: =IF(MONTH($A50)=4,1,0) -> 0 | G50: =IF(MONTH($A50)=5,1,0) -> 0 | H50: =IF(MONTH($A50)=6,1,0) -> 0 | I50: =IF(MONTH($A50)=7,1,0) -> 0 | J50: =IF(MONTH($A50)=8,1,0) -> 0 | K50: =IF(MONTH($A50)=9,1,0) -> 0 | L50: =IF(MONTH($A50)=10,1,0) -> 0 | M50: =IF(MONTH($A50)=11,1,0) -> 0 | N50: =IF(MONTH($A50)=12,1,0) -> 1 | O50: =$B$5+SUMPRODUCT(C50:N50,$C$5:$N$5) -> 3.1503847 | P50: =B50-O50 -> -0.80561405 | Q50: =P50^2 -> 0.64901399 | T50: Coefficient on Post | U50: =Y7 -> -1.2638864 | V50: -1.2638864
A51: =Data_Monthly!A50 -> 45681 | B51: =Data_Monthly!K50 -> -1.4249475 | C51: =IF($A51>=$U$5,1,0) -> 1 | D51: =IF(MONTH($A51)=2,1,0) -> 0 | E51: =IF(MONTH($A51)=3,1,0) -> 0 | F51: =IF(MONTH($A51)=4,1,0) -> 0 | G51: =IF(MONTH($A51)=5,1,0) -> 0 | H51: =IF(MONTH($A51)=6,1,0) -> 0 | I51: =IF(MONTH($A51)=7,1,0) -> 0 | J51: =IF(MONTH($A51)=8,1,0) -> 0 | K51: =IF(MONTH($A51)=9,1,0) -> 0 | L51: =IF(MONTH($A51)=10,1,0) -> 0 | M51: =IF(MONTH($A51)=11,1,0) -> 0 | N51: =IF(MONTH($A51)=12,1,0) -> 0 | O51: =$B$5+SUMPRODUCT(C51:N51,$C$5:$N$5) -> -2.0632705 | P51: =B51-O51 -> 0.63832297 | Q51: =P51^2 -> 0.40745621 | T51: Standard error | U51: =Z7 -> 0.61316228 | V51: 0.61316228
T52: t statistic | U52: =AA7 -> -2.0612592 | V52: -2.0612592
T53: p-value | U53: =AB7 -> 0.047481353 | V53: 0.047481353
T54: Month dummies jointly zero: F-test p-value | U54: =_xlfn.F.DIST.RT((($U$29-$U$41)/11)/($U$41/$U$43),11,$U$43) -> 0.0097635342 | V54: 0.0097635342
T56: Diagnostic tests on the residuals of Regression 2 | U56: Excel | V56: Dissertation
T57: Durbin-Watson | U57: =SUMXMY2(P8:P51,P7:P50)/SUMSQ(P7:P51) -> 2.1569079 | V57: 2.1569079
T58: Second moment of residuals | U58: =SUMSQ(P7:P51)/$U$32 -> 2.4730338
T59: Skewness | U59: =(SUMPRODUCT(P7:P51^3)/$U$32)/$U$58^1.5 -> 0.51915508
T60: Kurtosis | U60: =(SUMPRODUCT(P7:P51^4)/$U$32)/$U$58^2 -> 2.9975539
T61: Jarque-Bera statistic | U61: =$U$32/6*($U$59^2+($U$60-3)^2/4) -> 2.0214262 | V61: 2.0214262
T62: Jarque-Bera p-value (chi-squared, 2 df) | U62: =_xlfn.CHISQ.DIST.RT($U$61,2) -> 0.36395935 | V62: 0.36395935
T63: Breusch-Pagan: R squared, squared residuals on regressors | U63: =INDEX(LINEST(Q7:Q51,C7:N51,TRUE(),TRUE()),3,1) -> 0.35632006
T64: Breusch-Pagan statistic (n x R squared) | U64: =$U$32*$U$63 -> 16.034403 | V64: 16.034403
T65: Breusch-Pagan p-value (chi-squared, 12 df) | U65: =_xlfn.CHISQ.DIST.RT($U$64,$U$42) -> 0.18966543 | V65: 0.18966543
T66: Largest variance inflation factor | U66: =MAX(AC7:AC18) -> 1.8468468 | V66: 1.8468468
T68: Economic size over the post-policy months | U68: Excel | V68: Dissertation
T69: Credit to NBFCs excl. HFCs, 24-Jan-2025 (₹ crore) | U69: 1292215.9 | V69: 1292215.9
T70: Post-policy months | U70: =$U$9 -> 14 | V70: 14
T71: Cumulative shortfall in growth (per cent) | U71: =100*(EXP(-$U$14*$U$70/100)-1) -> 16.150385 | V71: 16.150385
T72: Implied shortfall (₹ crore) | U72: =$U$69*(EXP(-$U$14*$U$70/100)-1) -> 208697.84 | V72: 208697.84
T73: Implied shortfall (₹ lakh crore) | U73: =$U$72/100000 -> 2.0869784 | V73: 2.0869784

Sheet H2_Alt_Tests
A1: Gap2 alternative: NBFCs (excl. HFCs) minus non-food credit excl. NBFCs, cards and other PL: tests, April 2021 to January 2025
A2: Reproduces Table 7.1, third row; Section 7.2. Data rows link to Data_Monthly; every result is an Excel formula. Months before the circular: April 2021 to 17 November 2023; after: 29 December 2023 to January 2025.
A4: Gap2 alternative | T4: Test results
A5: Coefficients | B5: =Y19 -> -0.71642136 | C5: =Y7 -> -1.4581352 | D5: =Y8 -> 0.98564143 | E5: =Y9 -> 2.0758357 | F5: =Y10 -> 0.51940892 | G5: =Y11 -> -0.12164585 | H5: =Y12 -> 1.4347225 | I5: =Y13 -> 3.1488279 | J5: =Y14 -> -0.078973877 | K5: =Y15 -> 1.5544838 | L5: =Y16 -> 3.3080385 | M5: =Y17 -> 3.2985261 | N5: =Y18 -> 5.6004499 | T5: Post = 1 for months dated on or after | U5: 45260 | X5: Regression 2: all coefficients
A6: Date | B6: Gap (pp) | C6: Post | D6: M2 | E6: M3 | F6: M4 | G6: M5 | H6: M6 | I6: M7 | J6: M8 | K6: M9 | L6: M10 | M6: M11 | N6: M12 | O6: Fitted | P6: Residual | Q6: Residual squared | T6: Months before: rows 7 to 37; after: rows 38 to 51. | X6: Variable | Y6: B | Z6: Std. error | AA6: t | AB6: p-value | AC6: VIF
A7: =Data_Monthly!A5 -> 44309 | B7: =Data_Monthly!L5 -> -3.6851223 | C7: =IF($A7>=$U$5,1,0) -> 0 | D7: =IF(MONTH($A7)=2,1,0) -> 0 | E7: =IF(MONTH($A7)=3,1,0) -> 0 | F7: =IF(MONTH($A7)=4,1,0) -> 1 | G7: =IF(MONTH($A7)=5,1,0) -> 0 | H7: =IF(MONTH($A7)=6,1,0) -> 0 | I7: =IF(MONTH($A7)=7,1,0) -> 0 | J7: =IF(MONTH($A7)=8,1,0) -> 0 | K7: =IF(MONTH($A7)=9,1,0) -> 0 | L7: =IF(MONTH($A7)=10,1,0) -> 0 | M7: =IF(MONTH($A7)=11,1,0) -> 0 | N7: =IF(MONTH($A7)=12,1,0) -> 0 | O7: =$B$5+SUMPRODUCT(C7:N7,$C$5:$N$5) -> -0.19701244 | P7: =B7-O7 -> -3.4881098 | Q7: =P7^2 -> 12.16691 | T7: Welch two-sample t-test (unequal variances) | U7: Excel | V7: Dissertation | X7: Post | Y7: =INDEX(LINEST(B7:B51,C7:N51,TRUE(),TRUE()),1,12) -> -1.4581352 | Z7: =INDEX(LINEST(B7:B51,C7:N51,TRUE(),TRUE()),2,12) -> 0.67492872 | AA7: =Y7/Z7 -> -2.1604284 | AB7: =_xlfn.T.DIST.2T(ABS(AA7),$U$35) -> 0.038333807 | AC7: =INDEX(MINVERSE($Y$23:$AJ$34),1,1) -> 1.0426426
A8: =Data_Monthly!A6 -> 44337 | B8: =Data_Monthly!L6 -> -1.2191905 | C8: =IF($A8>=$U$5,1,0) -> 0 | D8: =IF(MONTH($A8)=2,1,0) -> 0 | E8: =IF(MONTH($A8)=3,1,0) -> 0 | F8: =IF(MONTH($A8)=4,1,0) -> 0 | G8: =IF(MONTH($A8)=5,1,0) -> 1 | H8: =IF(MONTH($A8)=6,1,0) -> 0 | I8: =IF(MONTH($A8)=7,1,0) -> 0 | J8: =IF(MONTH($A8)=8,1,0) -> 0 | K8: =IF(MONTH($A8)=9,1,0) -> 0 | L8: =IF(MONTH($A8)=10,1,0) -> 0 | M8: =IF(MONTH($A8)=11,1,0) -> 0 | N8: =IF(MONTH($A8)=12,1,0) -> 0 | O8: =$B$5+SUMPRODUCT(C8:N8,$C$5:$N$5) -> -0.83806722 | P8: =B8-O8 -> -0.38112328 | Q8: =P8^2 -> 0.14525496 | T8: Months before (n1) | U8: =COUNT(B7:B37) -> 31 | V8: 31 | X8: M2 | Y8: =INDEX(LINEST(B7:B51,C7:N51,TRUE(),TRUE()),1,11) -> 0.98564143 | Z8: =INDEX(LINEST(B7:B51,C7:N51,TRUE(),TRUE()),2,11) -> 1.5718177 | AA8: =Y8/Z8 -> 0.62707108 | AB8: =_xlfn.T.DIST.2T(ABS(AA8),$U$35) -> 0.53506148 | AC8: =INDEX(MINVERSE($Y$23:$AJ$34),2,2) -> 1.6417417
A9: =Data_Monthly!A7 -> 44365 | B9: =Data_Monthly!L7 -> -0.63511631 | C9: =IF($A9>=$U$5,1,0) -> 0 | D9: =IF(MONTH($A9)=2,1,0) -> 0 | E9: =IF(MONTH($A9)=3,1,0) -> 0 | F9: =IF(MONTH($A9)=4,1,0) -> 0 | G9: =IF(MONTH($A9)=5,1,0) -> 0 | H9: =IF(MONTH($A9)=6,1,0) -> 1 | I9: =IF(MONTH($A9)=7,1,0) -> 0 | J9: =IF(MONTH($A9)=8,1,0) -> 0 | K9: =IF(MONTH($A9)=9,1,0) -> 0 | L9: =IF(MONTH($A9)=10,1,0) -> 0 | M9: =IF(MONTH($A9)=11,1,0) -> 0 | N9: =IF(MONTH($A9)=12,1,0) -> 0 | O9: =$B$5+SUMPRODUCT(C9:N9,$C$5:$N$5) -> 0.71830111 | P9: =B9-O9 -> -1.3534174 | Q9: =P9^2 -> 1.8317387 | T9: Months after (n2) | U9: =COUNT(B38:B51) -> 14 | V9: 14 | X9: M3 | Y9: =INDEX(LINEST(B7:B51,C7:N51,TRUE(),TRUE()),1,10) -> 2.0758357 | Z9: =INDEX(LINEST(B7:B51,C7:N51,TRUE(),TRUE()),2,10) -> 1.5718177 | AA9: =Y9/Z9 -> 1.3206593 | AB9: =_xlfn.T.DIST.2T(ABS(AA9),$U$35) -> 0.19598269 | AC9: =INDEX(MINVERSE($Y$23:$AJ$34),3,3) -> 1.6417417
A10: =Data_Monthly!A8 -> 44407 | B10: =Data_Monthly!L8 -> 0.44082364 | C10: =IF($A10>=$U$5,1,0) -> 0 | D10: =IF(MONTH($A10)=2,1,0) -> 0 | E10: =IF(MONTH($A10)=3,1,0) -> 0 | F10: =IF(MONTH($A10)=4,1,0) -> 0 | G10: =IF(MONTH($A10)=5,1,0) -> 0 | H10: =IF(MONTH($A10)=6,1,0) -> 0 | I10: =IF(MONTH($A10)=7,1,0) -> 1 | J10: =IF(MONTH($A10)=8,1,0) -> 0 | K10: =IF(MONTH($A10)=9,1,0) -> 0 | L10: =IF(MONTH($A10)=10,1,0) -> 0 | M10: =IF(MONTH($A10)=11,1,0) -> 0 | N10: =IF(MONTH($A10)=12,1,0) -> 0 | O10: =$B$5+SUMPRODUCT(C10:N10,$C$5:$N$5) -> 2.4324065 | P10: =B10-O10 -> -1.9915829 | Q10: =P10^2 -> 3.9664025 | T10: Mean gap before | U10: =AVERAGE(B7:B37) -> 1.0050364 | V10: 1.0050364 | X10: M4 | Y10: =INDEX(LINEST(B7:B51,C7:N51,TRUE(),TRUE()),1,9) -> 0.51940892 | Z10: =INDEX(LINEST(B7:B51,C7:N51,TRUE(),TRUE()),2,9) -> 1.4612635 | AA10: =Y10/Z10 -> 0.35545191 | AB10: =_xlfn.T.DIST.2T(ABS(AA10),$U$35) -> 0.72458349 | AC10: =INDEX(MINVERSE($Y$23:$AJ$34),4,4) -> 1.8468468
A11: =Data_Monthly!A9 -> 44435 | B11: =Data_Monthly!L9 -> -2.3161924 | C11: =IF($A11>=$U$5,1,0) -> 0 | D11: =IF(MONTH($A11)=2,1,0) -> 0 | E11: =IF(MONTH($A11)=3,1,0) -> 0 | F11: =IF(MONTH($A11)=4,1,0) -> 0 | G11: =IF(MONTH($A11)=5,1,0) -> 0 | H11: =IF(MONTH($A11)=6,1,0) -> 0 | I11: =IF(MONTH($A11)=7,1,0) -> 0 | J11: =IF(MONTH($A11)=8,1,0) -> 1 | K11: =IF(MONTH($A11)=9,1,0) -> 0 | L11: =IF(MONTH($A11)=10,1,0) -> 0 | M11: =IF(MONTH($A11)=11,1,0) -> 0 | N11: =IF(MONTH($A11)=12,1,0) -> 0 | O11: =$B$5+SUMPRODUCT(C11:N11,$C$5:$N$5) -> -0.79539524 | P11: =B11-O11 -> -1.5207971 | Q11: =P11^2 -> 2.3128239 | T11: Mean gap after | U11: =AVERAGE(B38:B51) -> -0.22271619 | V11: -0.22271619 | X11: M5 | Y11: =INDEX(LINEST(B7:B51,C7:N51,TRUE(),TRUE()),1,8) -> -0.12164585 | Z11: =INDEX(LINEST(B7:B51,C7:N51,TRUE(),TRUE()),2,8) -> 1.4612635 | AA11: =Y11/Z11 -> -0.083247033 | AB11: =_xlfn.T.DIST.2T(ABS(AA11),$U$35) -> 0.9341737 | AC11: =INDEX(MINVERSE($Y$23:$AJ$34),5,5) -> 1.8468468
A12: =Data_Monthly!A10 -> 44463 | B12: =Data_Monthly!L10 -> -0.44595242 | C12: =IF($A12>=$U$5,1,0) -> 0 | D12: =IF(MONTH($A12)=2,1,0) -> 0 | E12: =IF(MONTH($A12)=3,1,0) -> 0 | F12: =IF(MONTH($A12)=4,1,0) -> 0 | G12: =IF(MONTH($A12)=5,1,0) -> 0 | H12: =IF(MONTH($A12)=6,1,0) -> 0 | I12: =IF(MONTH($A12)=7,1,0) -> 0 | J12: =IF(MONTH($A12)=8,1,0) -> 0 | K12: =IF(MONTH($A12)=9,1,0) -> 1 | L12: =IF(MONTH($A12)=10,1,0) -> 0 | M12: =IF(MONTH($A12)=11,1,0) -> 0 | N12: =IF(MONTH($A12)=12,1,0) -> 0 | O12: =$B$5+SUMPRODUCT(C12:N12,$C$5:$N$5) -> 0.83806245 | P12: =B12-O12 -> -1.2840149 | Q12: =P12^2 -> 1.6486942 | T12: Standard deviation before | U12: =_xlfn.STDEV.S(B7:B37) -> 2.6871908 | V12: 2.6871908 | X12: M6 | Y12: =INDEX(LINEST(B7:B51,C7:N51,TRUE(),TRUE()),1,7) -> 1.4347225 | Z12: =INDEX(LINEST(B7:B51,C7:N51,TRUE(),TRUE()),2,7) -> 1.4612635 | AA12: =Y12/Z12 -> 0.9818369 | AB12: =_xlfn.T.DIST.2T(ABS(AA12),$U$35) -> 0.33354564 | AC12: =INDEX(MINVERSE($Y$23:$AJ$34),6,6) -> 1.8468468
A13: =Data_Monthly!A11 -> 44491 | B13: =Data_Monthly!L11 -> 2.7736313 | C13: =IF($A13>=$U$5,1,0) -> 0 | D13: =IF(MONTH($A13)=2,1,0) -> 0 | E13: =IF(MONTH($A13)=3,1,0) -> 0 | F13: =IF(MONTH($A13)=4,1,0) -> 0 | G13: =IF(MONTH($A13)=5,1,0) -> 0 | H13: =IF(MONTH($A13)=6,1,0) -> 0 | I13: =IF(MONTH($A13)=7,1,0) -> 0 | J13: =IF(MONTH($A13)=8,1,0) -> 0 | K13: =IF(MONTH($A13)=9,1,0) -> 0 | L13: =IF(MONTH($A13)=10,1,0) -> 1 | M13: =IF(MONTH($A13)=11,1,0) -> 0 | N13: =IF(MONTH($A13)=12,1,0) -> 0 | O13: =$B$5+SUMPRODUCT(C13:N13,$C$5:$N$5) -> 2.5916171 | P13: =B13-O13 -> 0.18201416 | Q13: =P13^2 -> 0.033129154 | T13: Standard deviation after | U13: =_xlfn.STDEV.S(B38:B51) -> 1.969161 | V13: 1.969161 | X13: M7 | Y13: =INDEX(LINEST(B7:B51,C7:N51,TRUE(),TRUE()),1,6) -> 3.1488279 | Z13: =INDEX(LINEST(B7:B51,C7:N51,TRUE(),TRUE()),2,6) -> 1.5718177 | AA13: =Y13/Z13 -> 2.0033035 | AB13: =_xlfn.T.DIST.2T(ABS(AA13),$U$35) -> 0.053674774 | AC13: =INDEX(MINVERSE($Y$23:$AJ$34),7,7) -> 1.6417417
A14: =Data_Monthly!A12 -> 44519 | B14: =Data_Monthly!L12 -> 2.951105 | C14: =IF($A14>=$U$5,1,0) -> 0 | D14: =IF(MONTH($A14)=2,1,0) -> 0 | E14: =IF(MONTH($A14)=3,1,0) -> 0 | F14: =IF(MONTH($A14)=4,1,0) -> 0 | G14: =IF(MONTH($A14)=5,1,0) -> 0 | H14: =IF(MONTH($A14)=6,1,0) -> 0 | I14: =IF(MONTH($A14)=7,1,0) -> 0 | J14: =IF(MONTH($A14)=8,1,0) -> 0 | K14: =IF(MONTH($A14)=9,1,0) -> 0 | L14: =IF(MONTH($A14)=10,1,0) -> 0 | M14: =IF(MONTH($A14)=11,1,0) -> 1 | N14: =IF(MONTH($A14)=12,1,0) -> 0 | O14: =$B$5+SUMPRODUCT(C14:N14,$C$5:$N$5) -> 2.5821047 | P14: =B14-O14 -> 0.36900028 | Q14: =P14^2 -> 0.13616121 | T14: Difference (after minus before) | U14: =$U$11-$U$10 -> -1.2277526 | V14: -1.2277526 | X14: M8 | Y14: =INDEX(LINEST(B7:B51,C7:N51,TRUE(),TRUE()),1,5) -> -0.078973877 | Z14: =INDEX(LINEST(B7:B51,C7:N51,TRUE(),TRUE()),2,5) -> 1.4612635 | AA14: =Y14/Z14 -> -0.054044924 | AB14: =_xlfn.T.DIST.2T(ABS(AA14),$U$35) -> 0.95723538 | AC14: =INDEX(MINVERSE($Y$23:$AJ$34),8,8) -> 1.8468468
A15: =Data_Monthly!A13 -> 44561 | B15: =Data_Monthly!L13 -> 4.4787814 | C15: =IF($A15>=$U$5,1,0) -> 0 | D15: =IF(MONTH($A15)=2,1,0) -> 0 | E15: =IF(MONTH($A15)=3,1,0) -> 0 | F15: =IF(MONTH($A15)=4,1,0) -> 0 | G15: =IF(MONTH($A15)=5,1,0) -> 0 | H15: =IF(MONTH($A15)=6,1,0) -> 0 | I15: =IF(MONTH($A15)=7,1,0) -> 0 | J15: =IF(MONTH($A15)=8,1,0) -> 0 | K15: =IF(MONTH($A15)=9,1,0) -> 0 | L15: =IF(MONTH($A15)=10,1,0) -> 0 | M15: =IF(MONTH($A15)=11,1,0) -> 0 | N15: =IF(MONTH($A15)=12,1,0) -> 1 | O15: =$B$5+SUMPRODUCT(C15:N15,$C$5:$N$5) -> 4.8840286 | P15: =B15-O15 -> -0.40524714 | Q15: =P15^2 -> 0.16422524 | T15: Difference per year (x 12) | U15: =12*$U$14 -> -14.733031 | V15: -14.733031 | X15: M9 | Y15: =INDEX(LINEST(B7:B51,C7:N51,TRUE(),TRUE()),1,4) -> 1.5544838 | Z15: =INDEX(LINEST(B7:B51,C7:N51,TRUE(),TRUE()),2,4) -> 1.4612635 | AA15: =Y15/Z15 -> 1.0637943 | AB15: =_xlfn.T.DIST.2T(ABS(AA15),$U$35) -> 0.29538384 | AC15: =INDEX(MINVERSE($Y$23:$AJ$34),9,9) -> 1.8468468
A16: =Data_Monthly!A14 -> 44589 | B16: =Data_Monthly!L14 -> 1.8286024 | C16: =IF($A16>=$U$5,1,0) -> 0 | D16: =IF(MONTH($A16)=2,1,0) -> 0 | E16: =IF(MONTH($A16)=3,1,0) -> 0 | F16: =IF(MONTH($A16)=4,1,0) -> 0 | G16: =IF(MONTH($A16)=5,1,0) -> 0 | H16: =IF(MONTH($A16)=6,1,0) -> 0 | I16: =IF(MONTH($A16)=7,1,0) -> 0 | J16: =IF(MONTH($A16)=8,1,0) -> 0 | K16: =IF(MONTH($A16)=9,1,0) -> 0 | L16: =IF(MONTH($A16)=10,1,0) -> 0 | M16: =IF(MONTH($A16)=11,1,0) -> 0 | N16: =IF(MONTH($A16)=12,1,0) -> 0 | O16: =$B$5+SUMPRODUCT(C16:N16,$C$5:$N$5) -> -0.71642136 | P16: =B16-O16 -> 2.5450238 | Q16: =P16^2 -> 6.477146 | T16: Standard error of the difference | U16: =SQRT($U$13^2/$U$9+$U$12^2/$U$8) -> 0.7140773 | X16: M10 | Y16: =INDEX(LINEST(B7:B51,C7:N51,TRUE(),TRUE()),1,3) -> 3.3080385 | Z16: =INDEX(LINEST(B7:B51,C7:N51,TRUE(),TRUE()),2,3) -> 1.4612635 | AA16: =Y16/Z16 -> 2.2638206 | AB16: =_xlfn.T.DIST.2T(ABS(AA16),$U$35) -> 0.030500086 | AC16: =INDEX(MINVERSE($Y$23:$AJ$34),10,10) -> 1.8468468
A17: =Data_Monthly!A15 -> 44617 | B17: =Data_Monthly!L15 -> -0.99598019 | C17: =IF($A17>=$U$5,1,0) -> 0 | D17: =IF(MONTH($A17)=2,1,0) -> 1 | E17: =IF(MONTH($A17)=3,1,0) -> 0 | F17: =IF(MONTH($A17)=4,1,0) -> 0 | G17: =IF(MONTH($A17)=5,1,0) -> 0 | H17: =IF(MONTH($A17)=6,1,0) -> 0 | I17: =IF(MONTH($A17)=7,1,0) -> 0 | J17: =IF(MONTH($A17)=8,1,0) -> 0 | K17: =IF(MONTH($A17)=9,1,0) -> 0 | L17: =IF(MONTH($A17)=10,1,0) -> 0 | M17: =IF(MONTH($A17)=11,1,0) -> 0 | N17: =IF(MONTH($A17)=12,1,0) -> 0 | O17: =$B$5+SUMPRODUCT(C17:N17,$C$5:$N$5) -> 0.26922007 | P17: =B17-O17 -> -1.2652003 | Q17: =P17^2 -> 1.6007317 | T17: t statistic | U17: =$U$14/$U$16 -> -1.7193553 | V17: -1.7193553 | X17: M11 | Y17: =INDEX(LINEST(B7:B51,C7:N51,TRUE(),TRUE()),1,2) -> 3.2985261 | Z17: =INDEX(LINEST(B7:B51,C7:N51,TRUE(),TRUE()),2,2) -> 1.4612635 | AA17: =Y17/Z17 -> 2.2573109 | AB17: =_xlfn.T.DIST.2T(ABS(AA17),$U$35) -> 0.030947239 | AC17: =INDEX(MINVERSE($Y$23:$AJ$34),11,11) -> 1.8468468
A18: =Data_Monthly!A16 -> 44645 | B18: =Data_Monthly!L16 -> 1.1371694 | C18: =IF($A18>=$U$5,1,0) -> 0 | D18: =IF(MONTH($A18)=2,1,0) -> 0 | E18: =IF(MONTH($A18)=3,1,0) -> 1 | F18: =IF(MONTH($A18)=4,1,0) -> 0 | G18: =IF(MONTH($A18)=5,1,0) -> 0 | H18: =IF(MONTH($A18)=6,1,0) -> 0 | I18: =IF(MONTH($A18)=7,1,0) -> 0 | J18: =IF(MONTH($A18)=8,1,0) -> 0 | K18: =IF(MONTH($A18)=9,1,0) -> 0 | L18: =IF(MONTH($A18)=10,1,0) -> 0 | M18: =IF(MONTH($A18)=11,1,0) -> 0 | N18: =IF(MONTH($A18)=12,1,0) -> 0 | O18: =$B$5+SUMPRODUCT(C18:N18,$C$5:$N$5) -> 1.3594144 | P18: =B18-O18 -> -0.22224493 | Q18: =P18^2 -> 0.049392808 | T18: Welch degrees of freedom | U18: =(($U$13^2/$U$9)+($U$12^2/$U$8))^2/(($U$13^2/$U$9)^2/($U$9-1)+($U$12^2/$U$8)^2/($U$8-1)) -> 33.724657 | V18: 33.724657 | X18: M12 | Y18: =INDEX(LINEST(B7:B51,C7:N51,TRUE(),TRUE()),1,1) -> 5.6004499 | Z18: =INDEX(LINEST(B7:B51,C7:N51,TRUE(),TRUE()),2,1) -> 1.4514891 | AA18: =Y18/Z18 -> 3.8584168 | AB18: =_xlfn.T.DIST.2T(ABS(AA18),$U$35) -> 0.00052043601 | AC18: =INDEX(MINVERSE($Y$23:$AJ$34),12,12) -> 1.8222222
A19: =Data_Monthly!A17 -> 44673 | B19: =Data_Monthly!L17 -> 0.70529904 | C19: =IF($A19>=$U$5,1,0) -> 0 | D19: =IF(MONTH($A19)=2,1,0) -> 0 | E19: =IF(MONTH($A19)=3,1,0) -> 0 | F19: =IF(MONTH($A19)=4,1,0) -> 1 | G19: =IF(MONTH($A19)=5,1,0) -> 0 | H19: =IF(MONTH($A19)=6,1,0) -> 0 | I19: =IF(MONTH($A19)=7,1,0) -> 0 | J19: =IF(MONTH($A19)=8,1,0) -> 0 | K19: =IF(MONTH($A19)=9,1,0) -> 0 | L19: =IF(MONTH($A19)=10,1,0) -> 0 | M19: =IF(MONTH($A19)=11,1,0) -> 0 | N19: =IF(MONTH($A19)=12,1,0) -> 0 | O19: =$B$5+SUMPRODUCT(C19:N19,$C$5:$N$5) -> -0.19701244 | P19: =B19-O19 -> 0.90231148 | Q19: =P19^2 -> 0.814166 | T19: p-value, two-tailed (T.TEST type 3) | U19: =_xlfn.T.TEST(B38:B51,B7:B37,2,3) -> 0.094716898 | V19: 0.094716898 | X19: Constant | Y19: =INDEX(LINEST(B7:B51,C7:N51,TRUE(),TRUE()),1,13) -> -0.71642136 | Z19: =INDEX(LINEST(B7:B51,C7:N51,TRUE(),TRUE()),2,13) -> 1.0804131 | AA19: =Y19/Z19 -> -0.66309947 | AB19: =_xlfn.T.DIST.2T(ABS(AA19),$U$35) -> 0.51201558
A20: =Data_Monthly!A18 -> 44701 | B20: =Data_Monthly!L18 -> -0.41366093 | C20: =IF($A20>=$U$5,1,0) -> 0 | D20: =IF(MONTH($A20)=2,1,0) -> 0 | E20: =IF(MONTH($A20)=3,1,0) -> 0 | F20: =IF(MONTH($A20)=4,1,0) -> 0 | G20: =IF(MONTH($A20)=5,1,0) -> 1 | H20: =IF(MONTH($A20)=6,1,0) -> 0 | I20: =IF(MONTH($A20)=7,1,0) -> 0 | J20: =IF(MONTH($A20)=8,1,0) -> 0 | K20: =IF(MONTH($A20)=9,1,0) -> 0 | L20: =IF(MONTH($A20)=10,1,0) -> 0 | M20: =IF(MONTH($A20)=11,1,0) -> 0 | N20: =IF(MONTH($A20)=12,1,0) -> 0 | O20: =$B$5+SUMPRODUCT(C20:N20,$C$5:$N$5) -> -0.83806722 | P20: =B20-O20 -> 0.42440628 | Q20: =P20^2 -> 0.18012069 | X20: Row 5 repeats these coefficients above the data columns; Fitted = Constant + sum of coefficient x regressor.
A21: =Data_Monthly!A19 -> 44729 | B21: =Data_Monthly!L19 -> -1.4883748 | C21: =IF($A21>=$U$5,1,0) -> 0 | D21: =IF(MONTH($A21)=2,1,0) -> 0 | E21: =IF(MONTH($A21)=3,1,0) -> 0 | F21: =IF(MONTH($A21)=4,1,0) -> 0 | G21: =IF(MONTH($A21)=5,1,0) -> 0 | H21: =IF(MONTH($A21)=6,1,0) -> 1 | I21: =IF(MONTH($A21)=7,1,0) -> 0 | J21: =IF(MONTH($A21)=8,1,0) -> 0 | K21: =IF(MONTH($A21)=9,1,0) -> 0 | L21: =IF(MONTH($A21)=10,1,0) -> 0 | M21: =IF(MONTH($A21)=11,1,0) -> 0 | N21: =IF(MONTH($A21)=12,1,0) -> 0 | O21: =$B$5+SUMPRODUCT(C21:N21,$C$5:$N$5) -> 0.71830111 | P21: =B21-O21 -> -2.2066759 | Q21: =P21^2 -> 4.8694187 | T21: Regression 1 (Post dummy only) | U21: Excel | V21: Dissertation | X21: VIF = diagonal of the inverse of the correlation matrix of the regressors:
A22: =Data_Monthly!A20 -> 44771 | B22: =Data_Monthly!L20 -> 6.6290497 | C22: =IF($A22>=$U$5,1,0) -> 0 | D22: =IF(MONTH($A22)=2,1,0) -> 0 | E22: =IF(MONTH($A22)=3,1,0) -> 0 | F22: =IF(MONTH($A22)=4,1,0) -> 0 | G22: =IF(MONTH($A22)=5,1,0) -> 0 | H22: =IF(MONTH($A22)=6,1,0) -> 0 | I22: =IF(MONTH($A22)=7,1,0) -> 1 | J22: =IF(MONTH($A22)=8,1,0) -> 0 | K22: =IF(MONTH($A22)=9,1,0) -> 0 | L22: =IF(MONTH($A22)=10,1,0) -> 0 | M22: =IF(MONTH($A22)=11,1,0) -> 0 | N22: =IF(MONTH($A22)=12,1,0) -> 0 | O22: =$B$5+SUMPRODUCT(C22:N22,$C$5:$N$5) -> 2.4324065 | P22: =B22-O22 -> 4.1966432 | Q22: =P22^2 -> 17.611814 | T22: Constant | U22: =INDEX(LINEST(B7:B51,C7:C51,TRUE(),TRUE()),1,2) -> 1.0050364 | V22: 1.0050364 | Y22: Post | Z22: M2 | AA22: M3 | AB22: M4 | AC22: M5 | AD22: M6 | AE22: M7 | AF22: M8 | AG22: M9 | AH22: M10 | AI22: M11 | AJ22: M12
A23: =Data_Monthly!A21 -> 44799 | B23: =Data_Monthly!L21 -> -0.57440229 | C23: =IF($A23>=$U$5,1,0) -> 0 | D23: =IF(MONTH($A23)=2,1,0) -> 0 | E23: =IF(MONTH($A23)=3,1,0) -> 0 | F23: =IF(MONTH($A23)=4,1,0) -> 0 | G23: =IF(MONTH($A23)=5,1,0) -> 0 | H23: =IF(MONTH($A23)=6,1,0) -> 0 | I23: =IF(MONTH($A23)=7,1,0) -> 0 | J23: =IF(MONTH($A23)=8,1,0) -> 1 | K23: =IF(MONTH($A23)=9,1,0) -> 0 | L23: =IF(MONTH($A23)=10,1,0) -> 0 | M23: =IF(MONTH($A23)=11,1,0) -> 0 | N23: =IF(MONTH($A23)=12,1,0) -> 0 | O23: =$B$5+SUMPRODUCT(C23:N23,$C$5:$N$5) -> -0.79539524 | P23: =B23-O23 -> 0.22099295 | Q23: =P23^2 -> 0.048837885 | T23: Coefficient on Post | U23: =INDEX(LINEST(B7:B51,C7:C51,TRUE(),TRUE()),1,1) -> -1.2277526 | V23: -1.2277526 | X23: Post | Y23: =CORREL($C$7:$C$51,$C$7:$C$51) -> 1 | Z23: =CORREL($D$7:$D$51,$C$7:$C$51) -> 0.01282895 | AA23: =CORREL($E$7:$E$51,$C$7:$C$51) -> 0.01282895 | AB23: =CORREL($F$7:$F$51,$C$7:$C$51) -> -0.041231193 | AC23: =CORREL($G$7:$G$51,$C$7:$C$51) -> -0.041231193 | AD23: =CORREL($H$7:$H$51,$C$7:$C$51) -> -0.041231193 | AE23: =CORREL($I$7:$I$51,$C$7:$C$51) -> 0.01282895 | AF23: =CORREL($J$7:$J$51,$C$7:$C$51) -> -0.041231193 | AG23: =CORREL($K$7:$K$51,$C$7:$C$51) -> -0.041231193 | AH23: =CORREL($L$7:$L$51,$C$7:$C$51) -> -0.041231193 | AI23: =CORREL($M$7:$M$51,$C$7:$C$51) -> -0.041231193 | AJ23: =CORREL($N$7:$N$51,$C$7:$C$51) -> 0.12744187
A24: =Data_Monthly!A22 -> 44827 | B24: =Data_Monthly!L22 -> 0.81122485 | C24: =IF($A24>=$U$5,1,0) -> 0 | D24: =IF(MONTH($A24)=2,1,0) -> 0 | E24: =IF(MONTH($A24)=3,1,0) -> 0 | F24: =IF(MONTH($A24)=4,1,0) -> 0 | G24: =IF(MONTH($A24)=5,1,0) -> 0 | H24: =IF(MONTH($A24)=6,1,0) -> 0 | I24: =IF(MONTH($A24)=7,1,0) -> 0 | J24: =IF(MONTH($A24)=8,1,0) -> 0 | K24: =IF(MONTH($A24)=9,1,0) -> 1 | L24: =IF(MONTH($A24)=10,1,0) -> 0 | M24: =IF(MONTH($A24)=11,1,0) -> 0 | N24: =IF(MONTH($A24)=12,1,0) -> 0 | O24: =$B$5+SUMPRODUCT(C24:N24,$C$5:$N$5) -> 0.83806245 | P24: =B24-O24 -> -0.0268376 | Q24: =P24^2 -> 0.00072025679 | T24: Standard error | U24: =INDEX(LINEST(B7:B51,C7:C51,TRUE(),TRUE()),2,1) -> 0.80244294 | V24: 0.80244294 | X24: M2 | Y24: =CORREL($C$7:$C$51,$D$7:$D$51) -> 0.01282895 | Z24: =CORREL($D$7:$D$51,$D$7:$D$51) -> 1 | AA24: =CORREL($E$7:$E$51,$D$7:$D$51) -> -0.071428571 | AB24: =CORREL($F$7:$F$51,$D$7:$D$51) -> -0.083478387 | AC24: =CORREL($G$7:$G$51,$D$7:$D$51) -> -0.083478387 | AD24: =CORREL($H$7:$H$51,$D$7:$D$51) -> -0.083478387 | AE24: =CORREL($I$7:$I$51,$D$7:$D$51) -> -0.071428571 | AF24: =CORREL($J$7:$J$51,$D$7:$D$51) -> -0.083478387 | AG24: =CORREL($K$7:$K$51,$D$7:$D$51) -> -0.083478387 | AH24: =CORREL($L$7:$L$51,$D$7:$D$51) -> -0.083478387 | AI24: =CORREL($M$7:$M$51,$D$7:$D$51) -> -0.083478387 | AJ24: =CORREL($N$7:$N$51,$D$7:$D$51) -> -0.083478387
A25: =Data_Monthly!A23 -> 44855 | B25: =Data_Monthly!L23 -> 6.7999935 | C25: =IF($A25>=$U$5,1,0) -> 0 | D25: =IF(MONTH($A25)=2,1,0) -> 0 | E25: =IF(MONTH($A25)=3,1,0) -> 0 | F25: =IF(MONTH($A25)=4,1,0) -> 0 | G25: =IF(MONTH($A25)=5,1,0) -> 0 | H25: =IF(MONTH($A25)=6,1,0) -> 0 | I25: =IF(MONTH($A25)=7,1,0) -> 0 | J25: =IF(MONTH($A25)=8,1,0) -> 0 | K25: =IF(MONTH($A25)=9,1,0) -> 0 | L25: =IF(MONTH($A25)=10,1,0) -> 1 | M25: =IF(MONTH($A25)=11,1,0) -> 0 | N25: =IF(MONTH($A25)=12,1,0) -> 0 | O25: =$B$5+SUMPRODUCT(C25:N25,$C$5:$N$5) -> 2.5916171 | P25: =B25-O25 -> 4.2083763 | Q25: =P25^2 -> 17.710431 | T25: t statistic | U25: =$U$23/$U$24 -> -1.5300185 | V25: -1.5300185 | X25: M3 | Y25: =CORREL($C$7:$C$51,$E$7:$E$51) -> 0.01282895 | Z25: =CORREL($D$7:$D$51,$E$7:$E$51) -> -0.071428571 | AA25: =CORREL($E$7:$E$51,$E$7:$E$51) -> 1 | AB25: =CORREL($F$7:$F$51,$E$7:$E$51) -> -0.083478387 | AC25: =CORREL($G$7:$G$51,$E$7:$E$51) -> -0.083478387 | AD25: =CORREL($H$7:$H$51,$E$7:$E$51) -> -0.083478387 | AE25: =CORREL($I$7:$I$51,$E$7:$E$51) -> -0.071428571 | AF25: =CORREL($J$7:$J$51,$E$7:$E$51) -> -0.083478387 | AG25: =CORREL($K$7:$K$51,$E$7:$E$51) -> -0.083478387 | AH25: =CORREL($L$7:$L$51,$E$7:$E$51) -> -0.083478387 | AI25: =CORREL($M$7:$M$51,$E$7:$E$51) -> -0.083478387 | AJ25: =CORREL($N$7:$N$51,$E$7:$E$51) -> -0.083478387
A26: =Data_Monthly!A24 -> 44883 | B26: =Data_Monthly!L24 -> 1.1710702 | C26: =IF($A26>=$U$5,1,0) -> 0 | D26: =IF(MONTH($A26)=2,1,0) -> 0 | E26: =IF(MONTH($A26)=3,1,0) -> 0 | F26: =IF(MONTH($A26)=4,1,0) -> 0 | G26: =IF(MONTH($A26)=5,1,0) -> 0 | H26: =IF(MONTH($A26)=6,1,0) -> 0 | I26: =IF(MONTH($A26)=7,1,0) -> 0 | J26: =IF(MONTH($A26)=8,1,0) -> 0 | K26: =IF(MONTH($A26)=9,1,0) -> 0 | L26: =IF(MONTH($A26)=10,1,0) -> 0 | M26: =IF(MONTH($A26)=11,1,0) -> 1 | N26: =IF(MONTH($A26)=12,1,0) -> 0 | O26: =$B$5+SUMPRODUCT(C26:N26,$C$5:$N$5) -> 2.5821047 | P26: =B26-O26 -> -1.4110345 | Q26: =P26^2 -> 1.9910183 | T26: Residual degrees of freedom | U26: =INDEX(LINEST(B7:B51,C7:C51,TRUE(),TRUE()),4,2) -> 43 | X26: M4 | Y26: =CORREL($C$7:$C$51,$F$7:$F$51) -> -0.041231193 | Z26: =CORREL($D$7:$D$51,$F$7:$F$51) -> -0.083478387 | AA26: =CORREL($E$7:$E$51,$F$7:$F$51) -> -0.083478387 | AB26: =CORREL($F$7:$F$51,$F$7:$F$51) -> 1 | AC26: =CORREL($G$7:$G$51,$F$7:$F$51) -> -0.097560976 | AD26: =CORREL($H$7:$H$51,$F$7:$F$51) -> -0.097560976 | AE26: =CORREL($I$7:$I$51,$F$7:$F$51) -> -0.083478387 | AF26: =CORREL($J$7:$J$51,$F$7:$F$51) -> -0.097560976 | AG26: =CORREL($K$7:$K$51,$F$7:$F$51) -> -0.097560976 | AH26: =CORREL($L$7:$L$51,$F$7:$F$51) -> -0.097560976 | AI26: =CORREL($M$7:$M$51,$F$7:$F$51) -> -0.097560976 | AJ26: =CORREL($N$7:$N$51,$F$7:$F$51) -> -0.097560976
A27: =Data_Monthly!A25 -> 44925 | B27: =Data_Monthly!L25 -> 7.2488306 | C27: =IF($A27>=$U$5,1,0) -> 0 | D27: =IF(MONTH($A27)=2,1,0) -> 0 | E27: =IF(MONTH($A27)=3,1,0) -> 0 | F27: =IF(MONTH($A27)=4,1,0) -> 0 | G27: =IF(MONTH($A27)=5,1,0) -> 0 | H27: =IF(MONTH($A27)=6,1,0) -> 0 | I27: =IF(MONTH($A27)=7,1,0) -> 0 | J27: =IF(MONTH($A27)=8,1,0) -> 0 | K27: =IF(MONTH($A27)=9,1,0) -> 0 | L27: =IF(MONTH($A27)=10,1,0) -> 0 | M27: =IF(MONTH($A27)=11,1,0) -> 0 | N27: =IF(MONTH($A27)=12,1,0) -> 1 | O27: =$B$5+SUMPRODUCT(C27:N27,$C$5:$N$5) -> 4.8840286 | P27: =B27-O27 -> 2.3648021 | Q27: =P27^2 -> 5.5922889 | T27: p-value | U27: =_xlfn.T.DIST.2T(ABS($U$25),$U$26) -> 0.13333629 | V27: 0.13333629 | X27: M5 | Y27: =CORREL($C$7:$C$51,$G$7:$G$51) -> -0.041231193 | Z27: =CORREL($D$7:$D$51,$G$7:$G$51) -> -0.083478387 | AA27: =CORREL($E$7:$E$51,$G$7:$G$51) -> -0.083478387 | AB27: =CORREL($F$7:$F$51,$G$7:$G$51) -> -0.097560976 | AC27: =CORREL($G$7:$G$51,$G$7:$G$51) -> 1 | AD27: =CORREL($H$7:$H$51,$G$7:$G$51) -> -0.097560976 | AE27: =CORREL($I$7:$I$51,$G$7:$G$51) -> -0.083478387 | AF27: =CORREL($J$7:$J$51,$G$7:$G$51) -> -0.097560976 | AG27: =CORREL($K$7:$K$51,$G$7:$G$51) -> -0.097560976 | AH27: =CORREL($L$7:$L$51,$G$7:$G$51) -> -0.097560976 | AI27: =CORREL($M$7:$M$51,$G$7:$G$51) -> -0.097560976 | AJ27: =CORREL($N$7:$N$51,$G$7:$G$51) -> -0.097560976
A28: =Data_Monthly!A26 -> 44953 | B28: =Data_Monthly!L26 -> -2.3643405 | C28: =IF($A28>=$U$5,1,0) -> 0 | D28: =IF(MONTH($A28)=2,1,0) -> 0 | E28: =IF(MONTH($A28)=3,1,0) -> 0 | F28: =IF(MONTH($A28)=4,1,0) -> 0 | G28: =IF(MONTH($A28)=5,1,0) -> 0 | H28: =IF(MONTH($A28)=6,1,0) -> 0 | I28: =IF(MONTH($A28)=7,1,0) -> 0 | J28: =IF(MONTH($A28)=8,1,0) -> 0 | K28: =IF(MONTH($A28)=9,1,0) -> 0 | L28: =IF(MONTH($A28)=10,1,0) -> 0 | M28: =IF(MONTH($A28)=11,1,0) -> 0 | N28: =IF(MONTH($A28)=12,1,0) -> 0 | O28: =$B$5+SUMPRODUCT(C28:N28,$C$5:$N$5) -> -0.71642136 | P28: =B28-O28 -> -1.6479191 | Q28: =P28^2 -> 2.7156374 | T28: R squared | U28: =INDEX(LINEST(B7:B51,C7:C51,TRUE(),TRUE()),3,1) -> 0.051630068 | V28: 0.051630068 | X28: M6 | Y28: =CORREL($C$7:$C$51,$H$7:$H$51) -> -0.041231193 | Z28: =CORREL($D$7:$D$51,$H$7:$H$51) -> -0.083478387 | AA28: =CORREL($E$7:$E$51,$H$7:$H$51) -> -0.083478387 | AB28: =CORREL($F$7:$F$51,$H$7:$H$51) -> -0.097560976 | AC28: =CORREL($G$7:$G$51,$H$7:$H$51) -> -0.097560976 | AD28: =CORREL($H$7:$H$51,$H$7:$H$51) -> 1 | AE28: =CORREL($I$7:$I$51,$H$7:$H$51) -> -0.083478387 | AF28: =CORREL($J$7:$J$51,$H$7:$H$51) -> -0.097560976 | AG28: =CORREL($K$7:$K$51,$H$7:$H$51) -> -0.097560976 | AH28: =CORREL($L$7:$L$51,$H$7:$H$51) -> -0.097560976 | AI28: =CORREL($M$7:$M$51,$H$7:$H$51) -> -0.097560976 | AJ28: =CORREL($N$7:$N$51,$H$7:$H$51) -> -0.097560976
A29: =Data_Monthly!A27 -> 44981 | B29: =Data_Monthly!L27 -> 1.4743867 | C29: =IF($A29>=$U$5,1,0) -> 0 | D29: =IF(MONTH($A29)=2,1,0) -> 1 | E29: =IF(MONTH($A29)=3,1,0) -> 0 | F29: =IF(MONTH($A29)=4,1,0) -> 0 | G29: =IF(MONTH($A29)=5,1,0) -> 0 | H29: =IF(MONTH($A29)=6,1,0) -> 0 | I29: =IF(MONTH($A29)=7,1,0) -> 0 | J29: =IF(MONTH($A29)=8,1,0) -> 0 | K29: =IF(MONTH($A29)=9,1,0) -> 0 | L29: =IF(MONTH($A29)=10,1,0) -> 0 | M29: =IF(MONTH($A29)=11,1,0) -> 0 | N29: =IF(MONTH($A29)=12,1,0) -> 0 | O29: =$B$5+SUMPRODUCT(C29:N29,$C$5:$N$5) -> 0.26922007 | P29: =B29-O29 -> 1.2051667 | Q29: =P29^2 -> 1.4524267 | T29: Residual sum of squares | U29: =INDEX(LINEST(B7:B51,C7:C51,TRUE(),TRUE()),5,2) -> 267.03857 | X29: M7 | Y29: =CORREL($C$7:$C$51,$I$7:$I$51) -> 0.01282895 | Z29: =CORREL($D$7:$D$51,$I$7:$I$51) -> -0.071428571 | AA29: =CORREL($E$7:$E$51,$I$7:$I$51) -> -0.071428571 | AB29: =CORREL($F$7:$F$51,$I$7:$I$51) -> -0.083478387 | AC29: =CORREL($G$7:$G$51,$I$7:$I$51) -> -0.083478387 | AD29: =CORREL($H$7:$H$51,$I$7:$I$51) -> -0.083478387 | AE29: =CORREL($I$7:$I$51,$I$7:$I$51) -> 1 | AF29: =CORREL($J$7:$J$51,$I$7:$I$51) -> -0.083478387 | AG29: =CORREL($K$7:$K$51,$I$7:$I$51) -> -0.083478387 | AH29: =CORREL($L$7:$L$51,$I$7:$I$51) -> -0.083478387 | AI29: =CORREL($M$7:$M$51,$I$7:$I$51) -> -0.083478387 | AJ29: =CORREL($N$7:$N$51,$I$7:$I$51) -> -0.083478387
A30: =Data_Monthly!A28 -> 45009 | B30: =Data_Monthly!L28 -> -0.08210092 | C30: =IF($A30>=$U$5,1,0) -> 0 | D30: =IF(MONTH($A30)=2,1,0) -> 0 | E30: =IF(MONTH($A30)=3,1,0) -> 1 | F30: =IF(MONTH($A30)=4,1,0) -> 0 | G30: =IF(MONTH($A30)=5,1,0) -> 0 | H30: =IF(MONTH($A30)=6,1,0) -> 0 | I30: =IF(MONTH($A30)=7,1,0) -> 0 | J30: =IF(MONTH($A30)=8,1,0) -> 0 | K30: =IF(MONTH($A30)=9,1,0) -> 0 | L30: =IF(MONTH($A30)=10,1,0) -> 0 | M30: =IF(MONTH($A30)=11,1,0) -> 0 | N30: =IF(MONTH($A30)=12,1,0) -> 0 | O30: =$B$5+SUMPRODUCT(C30:N30,$C$5:$N$5) -> 1.3594144 | P30: =B30-O30 -> -1.4415153 | Q30: =P30^2 -> 2.0779663 | X30: M8 | Y30: =CORREL($C$7:$C$51,$J$7:$J$51) -> -0.041231193 | Z30: =CORREL($D$7:$D$51,$J$7:$J$51) -> -0.083478387 | AA30: =CORREL($E$7:$E$51,$J$7:$J$51) -> -0.083478387 | AB30: =CORREL($F$7:$F$51,$J$7:$J$51) -> -0.097560976 | AC30: =CORREL($G$7:$G$51,$J$7:$J$51) -> -0.097560976 | AD30: =CORREL($H$7:$H$51,$J$7:$J$51) -> -0.097560976 | AE30: =CORREL($I$7:$I$51,$J$7:$J$51) -> -0.083478387 | AF30: =CORREL($J$7:$J$51,$J$7:$J$51) -> 1 | AG30: =CORREL($K$7:$K$51,$J$7:$J$51) -> -0.097560976 | AH30: =CORREL($L$7:$L$51,$J$7:$J$51) -> -0.097560976 | AI30: =CORREL($M$7:$M$51,$J$7:$J$51) -> -0.097560976 | AJ30: =CORREL($N$7:$N$51,$J$7:$J$51) -> -0.097560976
A31: =Data_Monthly!A29 -> 45037 | B31: =Data_Monthly!L29 -> 0.035717328 | C31: =IF($A31>=$U$5,1,0) -> 0 | D31: =IF(MONTH($A31)=2,1,0) -> 0 | E31: =IF(MONTH($A31)=3,1,0) -> 0 | F31: =IF(MONTH($A31)=4,1,0) -> 1 | G31: =IF(MONTH($A31)=5,1,0) -> 0 | H31: =IF(MONTH($A31)=6,1,0) -> 0 | I31: =IF(MONTH($A31)=7,1,0) -> 0 | J31: =IF(MONTH($A31)=8,1,0) -> 0 | K31: =IF(MONTH($A31)=9,1,0) -> 0 | L31: =IF(MONTH($A31)=10,1,0) -> 0 | M31: =IF(MONTH($A31)=11,1,0) -> 0 | N31: =IF(MONTH($A31)=12,1,0) -> 0 | O31: =$B$5+SUMPRODUCT(C31:N31,$C$5:$N$5) -> -0.19701244 | P31: =B31-O31 -> 0.23272977 | Q31: =P31^2 -> 0.054163146 | T31: Regression 2 (Post and 11 month dummies): model summary | U31: Excel | V31: Dissertation | X31: M9 | Y31: =CORREL($C$7:$C$51,$K$7:$K$51) -> -0.041231193 | Z31: =CORREL($D$7:$D$51,$K$7:$K$51) -> -0.083478387 | AA31: =CORREL($E$7:$E$51,$K$7:$K$51) -> -0.083478387 | AB31: =CORREL($F$7:$F$51,$K$7:$K$51) -> -0.097560976 | AC31: =CORREL($G$7:$G$51,$K$7:$K$51) -> -0.097560976 | AD31: =CORREL($H$7:$H$51,$K$7:$K$51) -> -0.097560976 | AE31: =CORREL($I$7:$I$51,$K$7:$K$51) -> -0.083478387 | AF31: =CORREL($J$7:$J$51,$K$7:$K$51) -> -0.097560976 | AG31: =CORREL($K$7:$K$51,$K$7:$K$51) -> 1 | AH31: =CORREL($L$7:$L$51,$K$7:$K$51) -> -0.097560976 | AI31: =CORREL($M$7:$M$51,$K$7:$K$51) -> -0.097560976 | AJ31: =CORREL($N$7:$N$51,$K$7:$K$51) -> -0.097560976
A32: =Data_Monthly!A30 -> 45065 | B32: =Data_Monthly!L30 -> -1.8235369 | C32: =IF($A32>=$U$5,1,0) -> 0 | D32: =IF(MONTH($A32)=2,1,0) -> 0 | E32: =IF(MONTH($A32)=3,1,0) -> 0 | F32: =IF(MONTH($A32)=4,1,0) -> 0 | G32: =IF(MONTH($A32)=5,1,0) -> 1 | H32: =IF(MONTH($A32)=6,1,0) -> 0 | I32: =IF(MONTH($A32)=7,1,0) -> 0 | J32: =IF(MONTH($A32)=8,1,0) -> 0 | K32: =IF(MONTH($A32)=9,1,0) -> 0 | L32: =IF(MONTH($A32)=10,1,0) -> 0 | M32: =IF(MONTH($A32)=11,1,0) -> 0 | N32: =IF(MONTH($A32)=12,1,0) -> 0 | O32: =$B$5+SUMPRODUCT(C32:N32,$C$5:$N$5) -> -0.83806722 | P32: =B32-O32 -> -0.98546973 | Q32: =P32^2 -> 0.97115058 | T32: Observations | U32: =COUNT(B7:B51) -> 45 | V32: 45 | X32: M10 | Y32: =CORREL($C$7:$C$51,$L$7:$L$51) -> -0.041231193 | Z32: =CORREL($D$7:$D$51,$L$7:$L$51) -> -0.083478387 | AA32: =CORREL($E$7:$E$51,$L$7:$L$51) -> -0.083478387 | AB32: =CORREL($F$7:$F$51,$L$7:$L$51) -> -0.097560976 | AC32: =CORREL($G$7:$G$51,$L$7:$L$51) -> -0.097560976 | AD32: =CORREL($H$7:$H$51,$L$7:$L$51) -> -0.097560976 | AE32: =CORREL($I$7:$I$51,$L$7:$L$51) -> -0.083478387 | AF32: =CORREL($J$7:$J$51,$L$7:$L$51) -> -0.097560976 | AG32: =CORREL($K$7:$K$51,$L$7:$L$51) -> -0.097560976 | AH32: =CORREL($L$7:$L$51,$L$7:$L$51) -> 1 | AI32: =CORREL($M$7:$M$51,$L$7:$L$51) -> -0.097560976 | AJ32: =CORREL($N$7:$N$51,$L$7:$L$51) -> -0.097560976
A33: =Data_Monthly!A31 -> 45107 | B33: =Data_Monthly!L31 -> 4.2506941 | C33: =IF($A33>=$U$5,1,0) -> 0 | D33: =IF(MONTH($A33)=2,1,0) -> 0 | E33: =IF(MONTH($A33)=3,1,0) -> 0 | F33: =IF(MONTH($A33)=4,1,0) -> 0 | G33: =IF(MONTH($A33)=5,1,0) -> 0 | H33: =IF(MONTH($A33)=6,1,0) -> 1 | I33: =IF(MONTH($A33)=7,1,0) -> 0 | J33: =IF(MONTH($A33)=8,1,0) -> 0 | K33: =IF(MONTH($A33)=9,1,0) -> 0 | L33: =IF(MONTH($A33)=10,1,0) -> 0 | M33: =IF(MONTH($A33)=11,1,0) -> 0 | N33: =IF(MONTH($A33)=12,1,0) -> 0 | O33: =$B$5+SUMPRODUCT(C33:N33,$C$5:$N$5) -> 0.71830111 | P33: =B33-O33 -> 3.532393 | Q33: =P33^2 -> 12.4778 | T33: R squared | U33: =INDEX(LINEST(B7:B51,C7:N51,TRUE(),TRUE()),3,1) -> 0.52113697 | V33: 0.52113697 | X33: M11 | Y33: =CORREL($C$7:$C$51,$M$7:$M$51) -> -0.041231193 | Z33: =CORREL($D$7:$D$51,$M$7:$M$51) -> -0.083478387 | AA33: =CORREL($E$7:$E$51,$M$7:$M$51) -> -0.083478387 | AB33: =CORREL($F$7:$F$51,$M$7:$M$51) -> -0.097560976 | AC33: =CORREL($G$7:$G$51,$M$7:$M$51) -> -0.097560976 | AD33: =CORREL($H$7:$H$51,$M$7:$M$51) -> -0.097560976 | AE33: =CORREL($I$7:$I$51,$M$7:$M$51) -> -0.083478387 | AF33: =CORREL($J$7:$J$51,$M$7:$M$51) -> -0.097560976 | AG33: =CORREL($K$7:$K$51,$M$7:$M$51) -> -0.097560976 | AH33: =CORREL($L$7:$L$51,$M$7:$M$51) -> -0.097560976 | AI33: =CORREL($M$7:$M$51,$M$7:$M$51) -> 1 | AJ33: =CORREL($N$7:$N$51,$M$7:$M$51) -> -0.097560976
A34: =Data_Monthly!A33 -> 45163 | B34: =Data_Monthly!L33 -> 0.16994222 | C34: =IF($A34>=$U$5,1,0) -> 0 | D34: =IF(MONTH($A34)=2,1,0) -> 0 | E34: =IF(MONTH($A34)=3,1,0) -> 0 | F34: =IF(MONTH($A34)=4,1,0) -> 0 | G34: =IF(MONTH($A34)=5,1,0) -> 0 | H34: =IF(MONTH($A34)=6,1,0) -> 0 | I34: =IF(MONTH($A34)=7,1,0) -> 0 | J34: =IF(MONTH($A34)=8,1,0) -> 1 | K34: =IF(MONTH($A34)=9,1,0) -> 0 | L34: =IF(MONTH($A34)=10,1,0) -> 0 | M34: =IF(MONTH($A34)=11,1,0) -> 0 | N34: =IF(MONTH($A34)=12,1,0) -> 0 | O34: =$B$5+SUMPRODUCT(C34:N34,$C$5:$N$5) -> -0.79539524 | P34: =B34-O34 -> 0.96533746 | Q34: =P34^2 -> 0.9318764 | T34: R | U34: =SQRT($U$33) -> 0.72189817 | X34: M12 | Y34: =CORREL($C$7:$C$51,$N$7:$N$51) -> 0.12744187 | Z34: =CORREL($D$7:$D$51,$N$7:$N$51) -> -0.083478387 | AA34: =CORREL($E$7:$E$51,$N$7:$N$51) -> -0.083478387 | AB34: =CORREL($F$7:$F$51,$N$7:$N$51) -> -0.097560976 | AC34: =CORREL($G$7:$G$51,$N$7:$N$51) -> -0.097560976 | AD34: =CORREL($H$7:$H$51,$N$7:$N$51) -> -0.097560976 | AE34: =CORREL($I$7:$I$51,$N$7:$N$51) -> -0.083478387 | AF34: =CORREL($J$7:$J$51,$N$7:$N$51) -> -0.097560976 | AG34: =CORREL($K$7:$K$51,$N$7:$N$51) -> -0.097560976 | AH34: =CORREL($L$7:$L$51,$N$7:$N$51) -> -0.097560976 | AI34: =CORREL($M$7:$M$51,$N$7:$N$51) -> -0.097560976 | AJ34: =CORREL($N$7:$N$51,$N$7:$N$51) -> 1
A35: =Data_Monthly!A34 -> 45191 | B35: =Data_Monthly!L34 -> 2.101205 | C35: =IF($A35>=$U$5,1,0) -> 0 | D35: =IF(MONTH($A35)=2,1,0) -> 0 | E35: =IF(MONTH($A35)=3,1,0) -> 0 | F35: =IF(MONTH($A35)=4,1,0) -> 0 | G35: =IF(MONTH($A35)=5,1,0) -> 0 | H35: =IF(MONTH($A35)=6,1,0) -> 0 | I35: =IF(MONTH($A35)=7,1,0) -> 0 | J35: =IF(MONTH($A35)=8,1,0) -> 0 | K35: =IF(MONTH($A35)=9,1,0) -> 1 | L35: =IF(MONTH($A35)=10,1,0) -> 0 | M35: =IF(MONTH($A35)=11,1,0) -> 0 | N35: =IF(MONTH($A35)=12,1,0) -> 0 | O35: =$B$5+SUMPRODUCT(C35:N35,$C$5:$N$5) -> 0.83806245 | P35: =B35-O35 -> 1.2631425 | Q35: =P35^2 -> 1.595529 | T35: Residual degrees of freedom | U35: =INDEX(LINEST(B7:B51,C7:N51,TRUE(),TRUE()),4,2) -> 32
A36: =Data_Monthly!A35 -> 45219 | B36: =Data_Monthly!L35 -> 0.53135552 | C36: =IF($A36>=$U$5,1,0) -> 0 | D36: =IF(MONTH($A36)=2,1,0) -> 0 | E36: =IF(MONTH($A36)=3,1,0) -> 0 | F36: =IF(MONTH($A36)=4,1,0) -> 0 | G36: =IF(MONTH($A36)=5,1,0) -> 0 | H36: =IF(MONTH($A36)=6,1,0) -> 0 | I36: =IF(MONTH($A36)=7,1,0) -> 0 | J36: =IF(MONTH($A36)=8,1,0) -> 0 | K36: =IF(MONTH($A36)=9,1,0) -> 0 | L36: =IF(MONTH($A36)=10,1,0) -> 1 | M36: =IF(MONTH($A36)=11,1,0) -> 0 | N36: =IF(MONTH($A36)=12,1,0) -> 0 | O36: =$B$5+SUMPRODUCT(C36:N36,$C$5:$N$5) -> 2.5916171 | P36: =B36-O36 -> -2.0602616 | Q36: =P36^2 -> 4.2446779 | T36: Adjusted R squared | U36: =1-(1-$U$33)*($U$32-1)/$U$35 -> 0.34156333 | V36: 0.34156333
A37: =Data_Monthly!A36 -> 45247 | B37: =Data_Monthly!L36 -> 1.6612162 | C37: =IF($A37>=$U$5,1,0) -> 0 | D37: =IF(MONTH($A37)=2,1,0) -> 0 | E37: =IF(MONTH($A37)=3,1,0) -> 0 | F37: =IF(MONTH($A37)=4,1,0) -> 0 | G37: =IF(MONTH($A37)=5,1,0) -> 0 | H37: =IF(MONTH($A37)=6,1,0) -> 0 | I37: =IF(MONTH($A37)=7,1,0) -> 0 | J37: =IF(MONTH($A37)=8,1,0) -> 0 | K37: =IF(MONTH($A37)=9,1,0) -> 0 | L37: =IF(MONTH($A37)=10,1,0) -> 0 | M37: =IF(MONTH($A37)=11,1,0) -> 1 | N37: =IF(MONTH($A37)=12,1,0) -> 0 | O37: =$B$5+SUMPRODUCT(C37:N37,$C$5:$N$5) -> 2.5821047 | P37: =B37-O37 -> -0.92088849 | Q37: =P37^2 -> 0.8480356 | T37: Standard error of the estimate | U37: =INDEX(LINEST(B7:B51,C7:N51,TRUE(),TRUE()),3,2) -> 2.0527156 | V37: 2.0527156
A38: =Data_Monthly!A37 -> 45289 | B38: =Data_Monthly!L37 -> 2.5067313 | C38: =IF($A38>=$U$5,1,0) -> 1 | D38: =IF(MONTH($A38)=2,1,0) -> 0 | E38: =IF(MONTH($A38)=3,1,0) -> 0 | F38: =IF(MONTH($A38)=4,1,0) -> 0 | G38: =IF(MONTH($A38)=5,1,0) -> 0 | H38: =IF(MONTH($A38)=6,1,0) -> 0 | I38: =IF(MONTH($A38)=7,1,0) -> 0 | J38: =IF(MONTH($A38)=8,1,0) -> 0 | K38: =IF(MONTH($A38)=9,1,0) -> 0 | L38: =IF(MONTH($A38)=10,1,0) -> 0 | M38: =IF(MONTH($A38)=11,1,0) -> 0 | N38: =IF(MONTH($A38)=12,1,0) -> 1 | O38: =$B$5+SUMPRODUCT(C38:N38,$C$5:$N$5) -> 3.4258934 | P38: =B38-O38 -> -0.91916206 | Q38: =P38^2 -> 0.84485889
A39: =Data_Monthly!A38 -> 45317 | B39: =Data_Monthly!L38 -> -3.7024687 | C39: =IF($A39>=$U$5,1,0) -> 1 | D39: =IF(MONTH($A39)=2,1,0) -> 0 | E39: =IF(MONTH($A39)=3,1,0) -> 0 | F39: =IF(MONTH($A39)=4,1,0) -> 0 | G39: =IF(MONTH($A39)=5,1,0) -> 0 | H39: =IF(MONTH($A39)=6,1,0) -> 0 | I39: =IF(MONTH($A39)=7,1,0) -> 0 | J39: =IF(MONTH($A39)=8,1,0) -> 0 | K39: =IF(MONTH($A39)=9,1,0) -> 0 | L39: =IF(MONTH($A39)=10,1,0) -> 0 | M39: =IF(MONTH($A39)=11,1,0) -> 0 | N39: =IF(MONTH($A39)=12,1,0) -> 0 | O39: =$B$5+SUMPRODUCT(C39:N39,$C$5:$N$5) -> -2.1745565 | P39: =B39-O39 -> -1.5279122 | Q39: =P39^2 -> 2.3345157 | T39: Regression 2 (Post and 11 month dummies): ANOVA | U39: Excel | V39: Dissertation
A40: =Data_Monthly!A39 -> 45345 | B40: =Data_Monthly!L39 -> -1.1288815 | C40: =IF($A40>=$U$5,1,0) -> 1 | D40: =IF(MONTH($A40)=2,1,0) -> 1 | E40: =IF(MONTH($A40)=3,1,0) -> 0 | F40: =IF(MONTH($A40)=4,1,0) -> 0 | G40: =IF(MONTH($A40)=5,1,0) -> 0 | H40: =IF(MONTH($A40)=6,1,0) -> 0 | I40: =IF(MONTH($A40)=7,1,0) -> 0 | J40: =IF(MONTH($A40)=8,1,0) -> 0 | K40: =IF(MONTH($A40)=9,1,0) -> 0 | L40: =IF(MONTH($A40)=10,1,0) -> 0 | M40: =IF(MONTH($A40)=11,1,0) -> 0 | N40: =IF(MONTH($A40)=12,1,0) -> 0 | O40: =$B$5+SUMPRODUCT(C40:N40,$C$5:$N$5) -> -1.1889151 | P40: =B40-O40 -> 0.060033592 | Q40: =P40^2 -> 0.0036040322 | T40: Regression sum of squares | U40: =INDEX(LINEST(B7:B51,C7:N51,TRUE(),TRUE()),5,1) -> 146.73986 | V40: 146.73986
A41: =Data_Monthly!A40 -> 45373 | B41: =Data_Monthly!L40 -> 1.5650394 | C41: =IF($A41>=$U$5,1,0) -> 1 | D41: =IF(MONTH($A41)=2,1,0) -> 0 | E41: =IF(MONTH($A41)=3,1,0) -> 1 | F41: =IF(MONTH($A41)=4,1,0) -> 0 | G41: =IF(MONTH($A41)=5,1,0) -> 0 | H41: =IF(MONTH($A41)=6,1,0) -> 0 | I41: =IF(MONTH($A41)=7,1,0) -> 0 | J41: =IF(MONTH($A41)=8,1,0) -> 0 | K41: =IF(MONTH($A41)=9,1,0) -> 0 | L41: =IF(MONTH($A41)=10,1,0) -> 0 | M41: =IF(MONTH($A41)=11,1,0) -> 0 | N41: =IF(MONTH($A41)=12,1,0) -> 0 | O41: =$B$5+SUMPRODUCT(C41:N41,$C$5:$N$5) -> -0.098720815 | P41: =B41-O41 -> 1.6637602 | Q41: =P41^2 -> 2.768098 | T41: Residual sum of squares | U41: =INDEX(LINEST(B7:B51,C7:N51,TRUE(),TRUE()),5,2) -> 134.83652 | V41: 134.83652
A42: =Data_Monthly!A41 -> 45401 | B42: =Data_Monthly!L41 -> 0.69792095 | C42: =IF($A42>=$U$5,1,0) -> 1 | D42: =IF(MONTH($A42)=2,1,0) -> 0 | E42: =IF(MONTH($A42)=3,1,0) -> 0 | F42: =IF(MONTH($A42)=4,1,0) -> 1 | G42: =IF(MONTH($A42)=5,1,0) -> 0 | H42: =IF(MONTH($A42)=6,1,0) -> 0 | I42: =IF(MONTH($A42)=7,1,0) -> 0 | J42: =IF(MONTH($A42)=8,1,0) -> 0 | K42: =IF(MONTH($A42)=9,1,0) -> 0 | L42: =IF(MONTH($A42)=10,1,0) -> 0 | M42: =IF(MONTH($A42)=11,1,0) -> 0 | N42: =IF(MONTH($A42)=12,1,0) -> 0 | O42: =$B$5+SUMPRODUCT(C42:N42,$C$5:$N$5) -> -1.6551476 | P42: =B42-O42 -> 2.3530686 | Q42: =P42^2 -> 5.5369317 | T42: Regression degrees of freedom | U42: =COLUMNS(C7:N51) -> 12 | V42: 12
A43: =Data_Monthly!A42 -> 45443 | B43: =Data_Monthly!L42 -> -1.3540157 | C43: =IF($A43>=$U$5,1,0) -> 1 | D43: =IF(MONTH($A43)=2,1,0) -> 0 | E43: =IF(MONTH($A43)=3,1,0) -> 0 | F43: =IF(MONTH($A43)=4,1,0) -> 0 | G43: =IF(MONTH($A43)=5,1,0) -> 1 | H43: =IF(MONTH($A43)=6,1,0) -> 0 | I43: =IF(MONTH($A43)=7,1,0) -> 0 | J43: =IF(MONTH($A43)=8,1,0) -> 0 | K43: =IF(MONTH($A43)=9,1,0) -> 0 | L43: =IF(MONTH($A43)=10,1,0) -> 0 | M43: =IF(MONTH($A43)=11,1,0) -> 0 | N43: =IF(MONTH($A43)=12,1,0) -> 0 | O43: =$B$5+SUMPRODUCT(C43:N43,$C$5:$N$5) -> -2.2962024 | P43: =B43-O43 -> 0.94218672 | Q43: =P43^2 -> 0.88771582 | T43: Residual degrees of freedom | U43: =$U$35 -> 32 | V43: 32
A44: =Data_Monthly!A43 -> 45471 | B44: =Data_Monthly!L43 -> -0.71213371 | C44: =IF($A44>=$U$5,1,0) -> 1 | D44: =IF(MONTH($A44)=2,1,0) -> 0 | E44: =IF(MONTH($A44)=3,1,0) -> 0 | F44: =IF(MONTH($A44)=4,1,0) -> 0 | G44: =IF(MONTH($A44)=5,1,0) -> 0 | H44: =IF(MONTH($A44)=6,1,0) -> 1 | I44: =IF(MONTH($A44)=7,1,0) -> 0 | J44: =IF(MONTH($A44)=8,1,0) -> 0 | K44: =IF(MONTH($A44)=9,1,0) -> 0 | L44: =IF(MONTH($A44)=10,1,0) -> 0 | M44: =IF(MONTH($A44)=11,1,0) -> 0 | N44: =IF(MONTH($A44)=12,1,0) -> 0 | O44: =$B$5+SUMPRODUCT(C44:N44,$C$5:$N$5) -> -0.73983407 | P44: =B44-O44 -> 0.027700364 | Q44: =P44^2 -> 0.00076731014 | T44: Regression mean square | U44: =$U$40/$U$42 -> 12.228322
A45: =Data_Monthly!A44 -> 45499 | B45: =Data_Monthly!L44 -> -1.2307889 | C45: =IF($A45>=$U$5,1,0) -> 1 | D45: =IF(MONTH($A45)=2,1,0) -> 0 | E45: =IF(MONTH($A45)=3,1,0) -> 0 | F45: =IF(MONTH($A45)=4,1,0) -> 0 | G45: =IF(MONTH($A45)=5,1,0) -> 0 | H45: =IF(MONTH($A45)=6,1,0) -> 0 | I45: =IF(MONTH($A45)=7,1,0) -> 1 | J45: =IF(MONTH($A45)=8,1,0) -> 0 | K45: =IF(MONTH($A45)=9,1,0) -> 0 | L45: =IF(MONTH($A45)=10,1,0) -> 0 | M45: =IF(MONTH($A45)=11,1,0) -> 0 | N45: =IF(MONTH($A45)=12,1,0) -> 0 | O45: =$B$5+SUMPRODUCT(C45:N45,$C$5:$N$5) -> 0.97427137 | P45: =B45-O45 -> -2.2050603 | Q45: =P45^2 -> 4.8622909 | T45: Residual mean square | U45: =$U$41/$U$43 -> 4.2136412
A46: =Data_Monthly!A45 -> 45527 | B46: =Data_Monthly!L45 -> -1.9190637 | C46: =IF($A46>=$U$5,1,0) -> 1 | D46: =IF(MONTH($A46)=2,1,0) -> 0 | E46: =IF(MONTH($A46)=3,1,0) -> 0 | F46: =IF(MONTH($A46)=4,1,0) -> 0 | G46: =IF(MONTH($A46)=5,1,0) -> 0 | H46: =IF(MONTH($A46)=6,1,0) -> 0 | I46: =IF(MONTH($A46)=7,1,0) -> 0 | J46: =IF(MONTH($A46)=8,1,0) -> 1 | K46: =IF(MONTH($A46)=9,1,0) -> 0 | L46: =IF(MONTH($A46)=10,1,0) -> 0 | M46: =IF(MONTH($A46)=11,1,0) -> 0 | N46: =IF(MONTH($A46)=12,1,0) -> 0 | O46: =$B$5+SUMPRODUCT(C46:N46,$C$5:$N$5) -> -2.2535304 | P46: =B46-O46 -> 0.33446672 | Q46: =P46^2 -> 0.11186799 | T46: F statistic | U46: =INDEX(LINEST(B7:B51,C7:N51,TRUE(),TRUE()),4,1) -> 2.9020795 | V46: 2.9020795
A47: =Data_Monthly!A46 -> 45555 | B47: =Data_Monthly!L46 -> -0.57236277 | C47: =IF($A47>=$U$5,1,0) -> 1 | D47: =IF(MONTH($A47)=2,1,0) -> 0 | E47: =IF(MONTH($A47)=3,1,0) -> 0 | F47: =IF(MONTH($A47)=4,1,0) -> 0 | G47: =IF(MONTH($A47)=5,1,0) -> 0 | H47: =IF(MONTH($A47)=6,1,0) -> 0 | I47: =IF(MONTH($A47)=7,1,0) -> 0 | J47: =IF(MONTH($A47)=8,1,0) -> 0 | K47: =IF(MONTH($A47)=9,1,0) -> 1 | L47: =IF(MONTH($A47)=10,1,0) -> 0 | M47: =IF(MONTH($A47)=11,1,0) -> 0 | N47: =IF(MONTH($A47)=12,1,0) -> 0 | O47: =$B$5+SUMPRODUCT(C47:N47,$C$5:$N$5) -> -0.62007272 | P47: =B47-O47 -> 0.047709949 | Q47: =P47^2 -> 0.0022762393 | T47: Significance of F | U47: =_xlfn.F.DIST.RT($U$46,$U$42,$U$43) -> 0.0079783075 | V47: 0.0079783075
A48: =Data_Monthly!A47 -> 45583 | B48: =Data_Monthly!L47 -> -1.1966469 | C48: =IF($A48>=$U$5,1,0) -> 1 | D48: =IF(MONTH($A48)=2,1,0) -> 0 | E48: =IF(MONTH($A48)=3,1,0) -> 0 | F48: =IF(MONTH($A48)=4,1,0) -> 0 | G48: =IF(MONTH($A48)=5,1,0) -> 0 | H48: =IF(MONTH($A48)=6,1,0) -> 0 | I48: =IF(MONTH($A48)=7,1,0) -> 0 | J48: =IF(MONTH($A48)=8,1,0) -> 0 | K48: =IF(MONTH($A48)=9,1,0) -> 0 | L48: =IF(MONTH($A48)=10,1,0) -> 1 | M48: =IF(MONTH($A48)=11,1,0) -> 0 | N48: =IF(MONTH($A48)=12,1,0) -> 0 | O48: =$B$5+SUMPRODUCT(C48:N48,$C$5:$N$5) -> 1.1334819 | P48: =B48-O48 -> -2.3301289 | Q48: =P48^2 -> 5.4295006
A49: =Data_Monthly!A48 -> 45625 | B49: =Data_Monthly!L48 -> 3.0868922 | C49: =IF($A49>=$U$5,1,0) -> 1 | D49: =IF(MONTH($A49)=2,1,0) -> 0 | E49: =IF(MONTH($A49)=3,1,0) -> 0 | F49: =IF(MONTH($A49)=4,1,0) -> 0 | G49: =IF(MONTH($A49)=5,1,0) -> 0 | H49: =IF(MONTH($A49)=6,1,0) -> 0 | I49: =IF(MONTH($A49)=7,1,0) -> 0 | J49: =IF(MONTH($A49)=8,1,0) -> 0 | K49: =IF(MONTH($A49)=9,1,0) -> 0 | L49: =IF(MONTH($A49)=10,1,0) -> 0 | M49: =IF(MONTH($A49)=11,1,0) -> 1 | N49: =IF(MONTH($A49)=12,1,0) -> 0 | O49: =$B$5+SUMPRODUCT(C49:N49,$C$5:$N$5) -> 1.1239695 | P49: =B49-O49 -> 1.9629227 | Q49: =P49^2 -> 3.8530654 | T49: Regression 2 (Post and 11 month dummies): Post | U49: Excel | V49: Dissertation
A50: =Data_Monthly!A49 -> 45653 | B50: =Data_Monthly!L49 -> 2.3855005 | C50: =IF($A50>=$U$5,1,0) -> 1 | D50: =IF(MONTH($A50)=2,1,0) -> 0 | E50: =IF(MONTH($A50)=3,1,0) -> 0 | F50: =IF(MONTH($A50)=4,1,0) -> 0 | G50: =IF(MONTH($A50)=5,1,0) -> 0 | H50: =IF(MONTH($A50)=6,1,0) -> 0 | I50: =IF(MONTH($A50)=7,1,0) -> 0 | J50: =IF(MONTH($A50)=8,1,0) -> 0 | K50: =IF(MONTH($A50)=9,1,0) -> 0 | L50: =IF(MONTH($A50)=10,1,0) -> 0 | M50: =IF(MONTH($A50)=11,1,0) -> 0 | N50: =IF(MONTH($A50)=12,1,0) -> 1 | O50: =$B$5+SUMPRODUCT(C50:N50,$C$5:$N$5) -> 3.4258934 | P50: =B50-O50 -> -1.0403929 | Q50: =P50^2 -> 1.0824174 | T50: Coefficient on Post | U50: =Y7 -> -1.4581352 | V50: -1.4581352
A51: =Data_Monthly!A50 -> 45681 | B51: =Data_Monthly!L50 -> -1.543749 | C51: =IF($A51>=$U$5,1,0) -> 1 | D51: =IF(MONTH($A51)=2,1,0) -> 0 | E51: =IF(MONTH($A51)=3,1,0) -> 0 | F51: =IF(MONTH($A51)=4,1,0) -> 0 | G51: =IF(MONTH($A51)=5,1,0) -> 0 | H51: =IF(MONTH($A51)=6,1,0) -> 0 | I51: =IF(MONTH($A51)=7,1,0) -> 0 | J51: =IF(MONTH($A51)=8,1,0) -> 0 | K51: =IF(MONTH($A51)=9,1,0) -> 0 | L51: =IF(MONTH($A51)=10,1,0) -> 0 | M51: =IF(MONTH($A51)=11,1,0) -> 0 | N51: =IF(MONTH($A51)=12,1,0) -> 0 | O51: =$B$5+SUMPRODUCT(C51:N51,$C$5:$N$5) -> -2.1745565 | P51: =B51-O51 -> 0.63080752 | Q51: =P51^2 -> 0.39791813 | T51: Standard error | U51: =Z7 -> 0.67492872 | V51: 0.67492872
T52: t statistic | U52: =AA7 -> -2.1604284 | V52: -2.1604284
T53: p-value | U53: =AB7 -> 0.038333807 | V53: 0.038333807
T54: Month dummies jointly zero: F-test p-value | U54: =_xlfn.F.DIST.RT((($U$29-$U$41)/11)/($U$41/$U$43),11,$U$43) -> 0.010166351 | V54: 0.010166351

Sheet H1_Placebo
A1: H1: placebo test with a fictitious policy date (November 2022) and pre-policy trend
A2: Reproduces Table 7.6. Pre-policy data only: July 2021 to 17 November 2023. 'Post' switches on at the fictitious date. The trend regression uses the same months, with time measured in years from July 2021.
A4: H1 gap, July 2021 to November 2023 | T4: Test results
A5: Coefficients | B5: =Y19 -> 0.54371137 | C5: =Y7 -> -0.053097556 | D5: =Y8 -> -0.017332193 | E5: =Y9 -> 2.0824108 | F5: =Y10 -> 0.55132733 | G5: =Y11 -> -0.16016422 | H5: =Y12 -> -0.77341985 | I5: =Y13 -> 2.0052323 | J5: =Y14 -> 0.083754852 | K5: =Y15 -> -1.2985316 | L5: =Y16 -> 2.7006901 | M5: =Y17 -> -1.0494569 | N5: =Y18 -> 0.20643717 | T5: Post = 1 for months dated on or after | U5: 44895 | X5: Regression 2: all coefficients
A6: Date | B6: Gap (pp) | C6: Post | D6: M2 | E6: M3 | F6: M4 | G6: M5 | H6: M6 | I6: M7 | J6: M8 | K6: M9 | L6: M10 | M6: M11 | N6: M12 | O6: Fitted | P6: Residual | Q6: Residual squared | R6: Time (years from start) | T6: Months before: rows 7 to 23; after: rows 24 to 35. | X6: Variable | Y6: B | Z6: Std. error | AA6: t | AB6: p-value | AC6: VIF
A7: =Data_Monthly!A8 -> 44407 | B7: =Data_Monthly!J8 -> 4.8802768 | C7: =IF($A7>=$U$5,1,0) -> 0 | D7: =IF(MONTH($A7)=2,1,0) -> 0 | E7: =IF(MONTH($A7)=3,1,0) -> 0 | F7: =IF(MONTH($A7)=4,1,0) -> 0 | G7: =IF(MONTH($A7)=5,1,0) -> 0 | H7: =IF(MONTH($A7)=6,1,0) -> 0 | I7: =IF(MONTH($A7)=7,1,0) -> 1 | J7: =IF(MONTH($A7)=8,1,0) -> 0 | K7: =IF(MONTH($A7)=9,1,0) -> 0 | L7: =IF(MONTH($A7)=10,1,0) -> 0 | M7: =IF(MONTH($A7)=11,1,0) -> 0 | N7: =IF(MONTH($A7)=12,1,0) -> 0 | O7: =$B$5+SUMPRODUCT(C7:N7,$C$5:$N$5) -> 2.5489437 | P7: =B7-O7 -> 2.3313331 | Q7: =P7^2 -> 5.4351141 | R7: =(ROW()-ROW($A$7))/12 -> 0 | T7: Welch two-sample t-test (unequal variances) | U7: Excel | V7: Dissertation | X7: Post | Y7: =INDEX(LINEST(B7:B35,C7:N35,TRUE(),TRUE()),1,12) -> -0.053097556 | Z7: =INDEX(LINEST(B7:B35,C7:N35,TRUE(),TRUE()),2,12) -> 0.43278269 | AA7: =Y7/Z7 -> -0.12268872 | AB7: =_xlfn.T.DIST.2T(ABS(AA7),$U$25) -> 0.90388146 | AC7: =INDEX(MINVERSE($Y$23:$AJ$34),1,1) -> 1.0294365
A8: =Data_Monthly!A9 -> 44435 | B8: =Data_Monthly!J9 -> 1.3340802 | C8: =IF($A8>=$U$5,1,0) -> 0 | D8: =IF(MONTH($A8)=2,1,0) -> 0 | E8: =IF(MONTH($A8)=3,1,0) -> 0 | F8: =IF(MONTH($A8)=4,1,0) -> 0 | G8: =IF(MONTH($A8)=5,1,0) -> 0 | H8: =IF(MONTH($A8)=6,1,0) -> 0 | I8: =IF(MONTH($A8)=7,1,0) -> 0 | J8: =IF(MONTH($A8)=8,1,0) -> 1 | K8: =IF(MONTH($A8)=9,1,0) -> 0 | L8: =IF(MONTH($A8)=10,1,0) -> 0 | M8: =IF(MONTH($A8)=11,1,0) -> 0 | N8: =IF(MONTH($A8)=12,1,0) -> 0 | O8: =$B$5+SUMPRODUCT(C8:N8,$C$5:$N$5) -> 0.62746622 | P8: =B8-O8 -> 0.70661398 | Q8: =P8^2 -> 0.49930332 | R8: =(ROW()-ROW($A$7))/12 -> 0.083333333 | T8: Months before (n1) | U8: =COUNT(B7:B23) -> 17 | V8: 17 | X8: M2 | Y8: =INDEX(LINEST(B7:B35,C7:N35,TRUE(),TRUE()),1,11) -> -0.017332193 | Z8: =INDEX(LINEST(B7:B35,C7:N35,TRUE(),TRUE()),2,11) -> 1.1313219 | AA8: =Y8/Z8 -> -0.015320303 | AB8: =_xlfn.T.DIST.2T(ABS(AA8),$U$25) -> 0.98796606 | AC8: =INDEX(MINVERSE($Y$23:$AJ$34),2,2) -> 1.862069
A9: =Data_Monthly!A10 -> 44463 | B9: =Data_Monthly!J10 -> -0.88183491 | C9: =IF($A9>=$U$5,1,0) -> 0 | D9: =IF(MONTH($A9)=2,1,0) -> 0 | E9: =IF(MONTH($A9)=3,1,0) -> 0 | F9: =IF(MONTH($A9)=4,1,0) -> 0 | G9: =IF(MONTH($A9)=5,1,0) -> 0 | H9: =IF(MONTH($A9)=6,1,0) -> 0 | I9: =IF(MONTH($A9)=7,1,0) -> 0 | J9: =IF(MONTH($A9)=8,1,0) -> 0 | K9: =IF(MONTH($A9)=9,1,0) -> 1 | L9: =IF(MONTH($A9)=10,1,0) -> 0 | M9: =IF(MONTH($A9)=11,1,0) -> 0 | N9: =IF(MONTH($A9)=12,1,0) -> 0 | O9: =$B$5+SUMPRODUCT(C9:N9,$C$5:$N$5) -> -0.75482018 | P9: =B9-O9 -> -0.12701473 | Q9: =P9^2 -> 0.016132741 | R9: =(ROW()-ROW($A$7))/12 -> 0.16666667 | T9: Months after (n2) | U9: =COUNT(B24:B35) -> 12 | V9: 12 | X9: M3 | Y9: =INDEX(LINEST(B7:B35,C7:N35,TRUE(),TRUE()),1,10) -> 2.0824108 | Z9: =INDEX(LINEST(B7:B35,C7:N35,TRUE(),TRUE()),2,10) -> 1.1313219 | AA9: =Y9/Z9 -> 1.8406882 | AB9: =_xlfn.T.DIST.2T(ABS(AA9),$U$25) -> 0.08428879 | AC9: =INDEX(MINVERSE($Y$23:$AJ$34),3,3) -> 1.862069
A10: =Data_Monthly!A11 -> 44491 | B10: =Data_Monthly!J11 -> 3.0475205 | C10: =IF($A10>=$U$5,1,0) -> 0 | D10: =IF(MONTH($A10)=2,1,0) -> 0 | E10: =IF(MONTH($A10)=3,1,0) -> 0 | F10: =IF(MONTH($A10)=4,1,0) -> 0 | G10: =IF(MONTH($A10)=5,1,0) -> 0 | H10: =IF(MONTH($A10)=6,1,0) -> 0 | I10: =IF(MONTH($A10)=7,1,0) -> 0 | J10: =IF(MONTH($A10)=8,1,0) -> 0 | K10: =IF(MONTH($A10)=9,1,0) -> 0 | L10: =IF(MONTH($A10)=10,1,0) -> 1 | M10: =IF(MONTH($A10)=11,1,0) -> 0 | N10: =IF(MONTH($A10)=12,1,0) -> 0 | O10: =$B$5+SUMPRODUCT(C10:N10,$C$5:$N$5) -> 3.2444014 | P10: =B10-O10 -> -0.19688095 | Q10: =P10^2 -> 0.038762109 | R10: =(ROW()-ROW($A$7))/12 -> 0.25 | T10: Mean gap before | U10: =AVERAGE(B7:B23) -> 0.94210176 | V10: 0.94210176 | X10: M4 | Y10: =INDEX(LINEST(B7:B35,C7:N35,TRUE(),TRUE()),1,9) -> 0.55132733 | Z10: =INDEX(LINEST(B7:B35,C7:N35,TRUE(),TRUE()),2,9) -> 1.1313219 | AA10: =Y10/Z10 -> 0.48733021 | AB10: =_xlfn.T.DIST.2T(ABS(AA10),$U$25) -> 0.63263386 | AC10: =INDEX(MINVERSE($Y$23:$AJ$34),4,4) -> 1.862069
A11: =Data_Monthly!A12 -> 44519 | B11: =Data_Monthly!J12 -> 0.2231757 | C11: =IF($A11>=$U$5,1,0) -> 0 | D11: =IF(MONTH($A11)=2,1,0) -> 0 | E11: =IF(MONTH($A11)=3,1,0) -> 0 | F11: =IF(MONTH($A11)=4,1,0) -> 0 | G11: =IF(MONTH($A11)=5,1,0) -> 0 | H11: =IF(MONTH($A11)=6,1,0) -> 0 | I11: =IF(MONTH($A11)=7,1,0) -> 0 | J11: =IF(MONTH($A11)=8,1,0) -> 0 | K11: =IF(MONTH($A11)=9,1,0) -> 0 | L11: =IF(MONTH($A11)=10,1,0) -> 0 | M11: =IF(MONTH($A11)=11,1,0) -> 1 | N11: =IF(MONTH($A11)=12,1,0) -> 0 | O11: =$B$5+SUMPRODUCT(C11:N11,$C$5:$N$5) -> -0.5057455 | P11: =B11-O11 -> 0.7289212 | Q11: =P11^2 -> 0.53132611 | R11: =(ROW()-ROW($A$7))/12 -> 0.33333333 | T11: Mean gap after | U11: =AVERAGE(B24:B35) -> 0.85152614 | V11: 0.85152614 | X11: M5 | Y11: =INDEX(LINEST(B7:B35,C7:N35,TRUE(),TRUE()),1,8) -> -0.16016422 | Z11: =INDEX(LINEST(B7:B35,C7:N35,TRUE(),TRUE()),2,8) -> 1.1313219 | AA11: =Y11/Z11 -> -0.14157264 | AB11: =_xlfn.T.DIST.2T(ABS(AA11),$U$25) -> 0.88918481 | AC11: =INDEX(MINVERSE($Y$23:$AJ$34),5,5) -> 1.862069
A12: =Data_Monthly!A13 -> 44561 | B12: =Data_Monthly!J13 -> 0.55111209 | C12: =IF($A12>=$U$5,1,0) -> 0 | D12: =IF(MONTH($A12)=2,1,0) -> 0 | E12: =IF(MONTH($A12)=3,1,0) -> 0 | F12: =IF(MONTH($A12)=4,1,0) -> 0 | G12: =IF(MONTH($A12)=5,1,0) -> 0 | H12: =IF(MONTH($A12)=6,1,0) -> 0 | I12: =IF(MONTH($A12)=7,1,0) -> 0 | J12: =IF(MONTH($A12)=8,1,0) -> 0 | K12: =IF(MONTH($A12)=9,1,0) -> 0 | L12: =IF(MONTH($A12)=10,1,0) -> 0 | M12: =IF(MONTH($A12)=11,1,0) -> 0 | N12: =IF(MONTH($A12)=12,1,0) -> 1 | O12: =$B$5+SUMPRODUCT(C12:N12,$C$5:$N$5) -> 0.75014853 | P12: =B12-O12 -> -0.19903644 | Q12: =P12^2 -> 0.039615505 | R12: =(ROW()-ROW($A$7))/12 -> 0.41666667 | T12: Standard deviation before | U12: =_xlfn.STDEV.S(B7:B23) -> 1.7107752 | V12: 1.7107752 | X12: M6 | Y12: =INDEX(LINEST(B7:B35,C7:N35,TRUE(),TRUE()),1,7) -> -0.77341985 | Z12: =INDEX(LINEST(B7:B35,C7:N35,TRUE(),TRUE()),2,7) -> 1.1313219 | AA12: =Y12/Z12 -> -0.68364262 | AB12: =_xlfn.T.DIST.2T(ABS(AA12),$U$25) -> 0.50398195 | AC12: =INDEX(MINVERSE($Y$23:$AJ$34),6,6) -> 1.862069
A13: =Data_Monthly!A14 -> 44589 | B13: =Data_Monthly!J14 -> -0.44045606 | C13: =IF($A13>=$U$5,1,0) -> 0 | D13: =IF(MONTH($A13)=2,1,0) -> 0 | E13: =IF(MONTH($A13)=3,1,0) -> 0 | F13: =IF(MONTH($A13)=4,1,0) -> 0 | G13: =IF(MONTH($A13)=5,1,0) -> 0 | H13: =IF(MONTH($A13)=6,1,0) -> 0 | I13: =IF(MONTH($A13)=7,1,0) -> 0 | J13: =IF(MONTH($A13)=8,1,0) -> 0 | K13: =IF(MONTH($A13)=9,1,0) -> 0 | L13: =IF(MONTH($A13)=10,1,0) -> 0 | M13: =IF(MONTH($A13)=11,1,0) -> 0 | N13: =IF(MONTH($A13)=12,1,0) -> 0 | O13: =$B$5+SUMPRODUCT(C13:N13,$C$5:$N$5) -> 0.54371137 | P13: =B13-O13 -> -0.98416743 | Q13: =P13^2 -> 0.96858553 | R13: =(ROW()-ROW($A$7))/12 -> 0.5 | T13: Standard deviation after | U13: =_xlfn.STDEV.S(B24:B35) -> 1.4248115 | V13: 1.4248115 | X13: M7 | Y13: =INDEX(LINEST(B7:B35,C7:N35,TRUE(),TRUE()),1,6) -> 2.0052323 | Z13: =INDEX(LINEST(B7:B35,C7:N35,TRUE(),TRUE()),2,6) -> 1.0352667 | AA13: =Y13/Z13 -> 1.9369234 | AB13: =_xlfn.T.DIST.2T(ABS(AA13),$U$25) -> 0.070617663 | AC13: =INDEX(MINVERSE($Y$23:$AJ$34),7,7) -> 2.2523129
A14: =Data_Monthly!A15 -> 44617 | B14: =Data_Monthly!J15 -> 0.44668201 | C14: =IF($A14>=$U$5,1,0) -> 0 | D14: =IF(MONTH($A14)=2,1,0) -> 1 | E14: =IF(MONTH($A14)=3,1,0) -> 0 | F14: =IF(MONTH($A14)=4,1,0) -> 0 | G14: =IF(MONTH($A14)=5,1,0) -> 0 | H14: =IF(MONTH($A14)=6,1,0) -> 0 | I14: =IF(MONTH($A14)=7,1,0) -> 0 | J14: =IF(MONTH($A14)=8,1,0) -> 0 | K14: =IF(MONTH($A14)=9,1,0) -> 0 | L14: =IF(MONTH($A14)=10,1,0) -> 0 | M14: =IF(MONTH($A14)=11,1,0) -> 0 | N14: =IF(MONTH($A14)=12,1,0) -> 0 | O14: =$B$5+SUMPRODUCT(C14:N14,$C$5:$N$5) -> 0.52637917 | P14: =B14-O14 -> -0.079697167 | Q14: =P14^2 -> 0.0063516384 | R14: =(ROW()-ROW($A$7))/12 -> 0.58333333 | T14: Difference (after minus before) | U14: =$U$11-$U$10 -> -0.090575628 | V14: -0.090575628 | X14: M8 | Y14: =INDEX(LINEST(B7:B35,C7:N35,TRUE(),TRUE()),1,5) -> 0.083754852 | Z14: =INDEX(LINEST(B7:B35,C7:N35,TRUE(),TRUE()),2,5) -> 1.0352667 | AA14: =Y14/Z14 -> 0.080901716 | AB14: =_xlfn.T.DIST.2T(ABS(AA14),$U$25) -> 0.93652346 | AC14: =INDEX(MINVERSE($Y$23:$AJ$34),8,8) -> 2.2523129
A15: =Data_Monthly!A16 -> 44645 | B15: =Data_Monthly!J16 -> 1.8446973 | C15: =IF($A15>=$U$5,1,0) -> 0 | D15: =IF(MONTH($A15)=2,1,0) -> 0 | E15: =IF(MONTH($A15)=3,1,0) -> 1 | F15: =IF(MONTH($A15)=4,1,0) -> 0 | G15: =IF(MONTH($A15)=5,1,0) -> 0 | H15: =IF(MONTH($A15)=6,1,0) -> 0 | I15: =IF(MONTH($A15)=7,1,0) -> 0 | J15: =IF(MONTH($A15)=8,1,0) -> 0 | K15: =IF(MONTH($A15)=9,1,0) -> 0 | L15: =IF(MONTH($A15)=10,1,0) -> 0 | M15: =IF(MONTH($A15)=11,1,0) -> 0 | N15: =IF(MONTH($A15)=12,1,0) -> 0 | O15: =$B$5+SUMPRODUCT(C15:N15,$C$5:$N$5) -> 2.6261222 | P15: =B15-O15 -> -0.78142489 | Q15: =P15^2 -> 0.61062485 | R15: =(ROW()-ROW($A$7))/12 -> 0.66666667 | T15: Difference per year (x 12) | U15: =12*$U$14 -> -1.0869075 | V15: -1.0869075 | X15: M9 | Y15: =INDEX(LINEST(B7:B35,C7:N35,TRUE(),TRUE()),1,4) -> -1.2985316 | Z15: =INDEX(LINEST(B7:B35,C7:N35,TRUE(),TRUE()),2,4) -> 1.0352667 | AA15: =Y15/Z15 -> -1.2542967 | AB15: =_xlfn.T.DIST.2T(ABS(AA15),$U$25) -> 0.22774959 | AC15: =INDEX(MINVERSE($Y$23:$AJ$34),9,9) -> 2.2523129
A16: =Data_Monthly!A17 -> 44673 | B16: =Data_Monthly!J17 -> 2.2065841 | C16: =IF($A16>=$U$5,1,0) -> 0 | D16: =IF(MONTH($A16)=2,1,0) -> 0 | E16: =IF(MONTH($A16)=3,1,0) -> 0 | F16: =IF(MONTH($A16)=4,1,0) -> 1 | G16: =IF(MONTH($A16)=5,1,0) -> 0 | H16: =IF(MONTH($A16)=6,1,0) -> 0 | I16: =IF(MONTH($A16)=7,1,0) -> 0 | J16: =IF(MONTH($A16)=8,1,0) -> 0 | K16: =IF(MONTH($A16)=9,1,0) -> 0 | L16: =IF(MONTH($A16)=10,1,0) -> 0 | M16: =IF(MONTH($A16)=11,1,0) -> 0 | N16: =IF(MONTH($A16)=12,1,0) -> 0 | O16: =$B$5+SUMPRODUCT(C16:N16,$C$5:$N$5) -> 1.0950387 | P16: =B16-O16 -> 1.1115454 | Q16: =P16^2 -> 1.2355332 | R16: =(ROW()-ROW($A$7))/12 -> 0.75 | T16: Standard error of the difference | U16: =SQRT($U$13^2/$U$9+$U$12^2/$U$8) -> 0.58423956 | X16: M10 | Y16: =INDEX(LINEST(B7:B35,C7:N35,TRUE(),TRUE()),1,3) -> 2.7006901 | Z16: =INDEX(LINEST(B7:B35,C7:N35,TRUE(),TRUE()),2,3) -> 1.0352667 | AA16: =Y16/Z16 -> 2.6086902 | AB16: =_xlfn.T.DIST.2T(ABS(AA16),$U$25) -> 0.01900229 | AC16: =INDEX(MINVERSE($Y$23:$AJ$34),10,10) -> 2.2523129
A17: =Data_Monthly!A18 -> 44701 | B17: =Data_Monthly!J18 -> 0.36179199 | C17: =IF($A17>=$U$5,1,0) -> 0 | D17: =IF(MONTH($A17)=2,1,0) -> 0 | E17: =IF(MONTH($A17)=3,1,0) -> 0 | F17: =IF(MONTH($A17)=4,1,0) -> 0 | G17: =IF(MONTH($A17)=5,1,0) -> 1 | H17: =IF(MONTH($A17)=6,1,0) -> 0 | I17: =IF(MONTH($A17)=7,1,0) -> 0 | J17: =IF(MONTH($A17)=8,1,0) -> 0 | K17: =IF(MONTH($A17)=9,1,0) -> 0 | L17: =IF(MONTH($A17)=10,1,0) -> 0 | M17: =IF(MONTH($A17)=11,1,0) -> 0 | N17: =IF(MONTH($A17)=12,1,0) -> 0 | O17: =$B$5+SUMPRODUCT(C17:N17,$C$5:$N$5) -> 0.38354714 | P17: =B17-O17 -> -0.021755158 | Q17: =P17^2 -> 0.00047328689 | R17: =(ROW()-ROW($A$7))/12 -> 0.83333333 | T17: t statistic | U17: =$U$14/$U$16 -> -0.15503166 | V17: -0.15503166 | X17: M11 | Y17: =INDEX(LINEST(B7:B35,C7:N35,TRUE(),TRUE()),1,2) -> -1.0494569 | Z17: =INDEX(LINEST(B7:B35,C7:N35,TRUE(),TRUE()),2,2) -> 1.0352667 | AA17: =Y17/Z17 -> -1.0137068 | AB17: =_xlfn.T.DIST.2T(ABS(AA17),$U$25) -> 0.32580775 | AC17: =INDEX(MINVERSE($Y$23:$AJ$34),11,11) -> 2.2523129
A18: =Data_Monthly!A19 -> 44729 | B18: =Data_Monthly!J19 -> -1.2877125 | C18: =IF($A18>=$U$5,1,0) -> 0 | D18: =IF(MONTH($A18)=2,1,0) -> 0 | E18: =IF(MONTH($A18)=3,1,0) -> 0 | F18: =IF(MONTH($A18)=4,1,0) -> 0 | G18: =IF(MONTH($A18)=5,1,0) -> 0 | H18: =IF(MONTH($A18)=6,1,0) -> 1 | I18: =IF(MONTH($A18)=7,1,0) -> 0 | J18: =IF(MONTH($A18)=8,1,0) -> 0 | K18: =IF(MONTH($A18)=9,1,0) -> 0 | L18: =IF(MONTH($A18)=10,1,0) -> 0 | M18: =IF(MONTH($A18)=11,1,0) -> 0 | N18: =IF(MONTH($A18)=12,1,0) -> 0 | O18: =$B$5+SUMPRODUCT(C18:N18,$C$5:$N$5) -> -0.22970848 | P18: =B18-O18 -> -1.058004 | Q18: =P18^2 -> 1.1193725 | R18: =(ROW()-ROW($A$7))/12 -> 0.91666667 | T18: Welch degrees of freedom | U18: =(($U$13^2/$U$9)+($U$12^2/$U$8))^2/(($U$13^2/$U$9)^2/($U$9-1)+($U$12^2/$U$8)^2/($U$8-1)) -> 26.156871 | V18: 26.156871 | X18: M12 | Y18: =INDEX(LINEST(B7:B35,C7:N35,TRUE(),TRUE()),1,1) -> 0.20643717 | Z18: =INDEX(LINEST(B7:B35,C7:N35,TRUE(),TRUE()),2,1) -> 1.1313219 | AA18: =Y18/Z18 -> 0.1824743 | AB18: =_xlfn.T.DIST.2T(ABS(AA18),$U$25) -> 0.85750252 | AC18: =INDEX(MINVERSE($Y$23:$AJ$34),12,12) -> 1.862069
A19: =Data_Monthly!A20 -> 44771 | B19: =Data_Monthly!J20 -> 2.0687047 | C19: =IF($A19>=$U$5,1,0) -> 0 | D19: =IF(MONTH($A19)=2,1,0) -> 0 | E19: =IF(MONTH($A19)=3,1,0) -> 0 | F19: =IF(MONTH($A19)=4,1,0) -> 0 | G19: =IF(MONTH($A19)=5,1,0) -> 0 | H19: =IF(MONTH($A19)=6,1,0) -> 0 | I19: =IF(MONTH($A19)=7,1,0) -> 1 | J19: =IF(MONTH($A19)=8,1,0) -> 0 | K19: =IF(MONTH($A19)=9,1,0) -> 0 | L19: =IF(MONTH($A19)=10,1,0) -> 0 | M19: =IF(MONTH($A19)=11,1,0) -> 0 | N19: =IF(MONTH($A19)=12,1,0) -> 0 | O19: =$B$5+SUMPRODUCT(C19:N19,$C$5:$N$5) -> 2.5489437 | P19: =B19-O19 -> -0.48023896 | Q19: =P19^2 -> 0.23062946 | R19: =(ROW()-ROW($A$7))/12 -> 1 | T19: p-value, two-tailed (T.TEST type 3) | U19: =_xlfn.T.TEST(B24:B35,B7:B23,2,3) -> 0.8779865 | V19: 0.8779865 | X19: Constant | Y19: =INDEX(LINEST(B7:B35,C7:N35,TRUE(),TRUE()),1,13) -> 0.54371137 | Z19: =INDEX(LINEST(B7:B35,C7:N35,TRUE(),TRUE()),2,13) -> 0.82871576 | AA19: =Y19/Z19 -> 0.65608909 | AB19: =_xlfn.T.DIST.2T(ABS(AA19),$U$25) -> 0.521091
A20: =Data_Monthly!A21 -> 44799 | B20: =Data_Monthly!J21 -> 0.77630849 | C20: =IF($A20>=$U$5,1,0) -> 0 | D20: =IF(MONTH($A20)=2,1,0) -> 0 | E20: =IF(MONTH($A20)=3,1,0) -> 0 | F20: =IF(MONTH($A20)=4,1,0) -> 0 | G20: =IF(MONTH($A20)=5,1,0) -> 0 | H20: =IF(MONTH($A20)=6,1,0) -> 0 | I20: =IF(MONTH($A20)=7,1,0) -> 0 | J20: =IF(MONTH($A20)=8,1,0) -> 1 | K20: =IF(MONTH($A20)=9,1,0) -> 0 | L20: =IF(MONTH($A20)=10,1,0) -> 0 | M20: =IF(MONTH($A20)=11,1,0) -> 0 | N20: =IF(MONTH($A20)=12,1,0) -> 0 | O20: =$B$5+SUMPRODUCT(C20:N20,$C$5:$N$5) -> 0.62746622 | P20: =B20-O20 -> 0.14884227 | Q20: =P20^2 -> 0.022154021 | R20: =(ROW()-ROW($A$7))/12 -> 1.0833333 | X20: Row 5 repeats these coefficients above the data columns; Fitted = Constant + sum of coefficient x regressor.
A21: =Data_Monthly!A22 -> 44827 | B21: =Data_Monthly!J22 -> -0.49256519 | C21: =IF($A21>=$U$5,1,0) -> 0 | D21: =IF(MONTH($A21)=2,1,0) -> 0 | E21: =IF(MONTH($A21)=3,1,0) -> 0 | F21: =IF(MONTH($A21)=4,1,0) -> 0 | G21: =IF(MONTH($A21)=5,1,0) -> 0 | H21: =IF(MONTH($A21)=6,1,0) -> 0 | I21: =IF(MONTH($A21)=7,1,0) -> 0 | J21: =IF(MONTH($A21)=8,1,0) -> 0 | K21: =IF(MONTH($A21)=9,1,0) -> 1 | L21: =IF(MONTH($A21)=10,1,0) -> 0 | M21: =IF(MONTH($A21)=11,1,0) -> 0 | N21: =IF(MONTH($A21)=12,1,0) -> 0 | O21: =$B$5+SUMPRODUCT(C21:N21,$C$5:$N$5) -> -0.75482018 | P21: =B21-O21 -> 0.262255 | Q21: =P21^2 -> 0.068777683 | R21: =(ROW()-ROW($A$7))/12 -> 1.1666667 | T21: Regression 2 (Post and 11 month dummies): model summary | U21: Excel | V21: Dissertation | X21: VIF = diagonal of the inverse of the correlation matrix of the regressors:
A22: =Data_Monthly!A23 -> 44855 | B22: =Data_Monthly!J23 -> 2.8535303 | C22: =IF($A22>=$U$5,1,0) -> 0 | D22: =IF(MONTH($A22)=2,1,0) -> 0 | E22: =IF(MONTH($A22)=3,1,0) -> 0 | F22: =IF(MONTH($A22)=4,1,0) -> 0 | G22: =IF(MONTH($A22)=5,1,0) -> 0 | H22: =IF(MONTH($A22)=6,1,0) -> 0 | I22: =IF(MONTH($A22)=7,1,0) -> 0 | J22: =IF(MONTH($A22)=8,1,0) -> 0 | K22: =IF(MONTH($A22)=9,1,0) -> 0 | L22: =IF(MONTH($A22)=10,1,0) -> 1 | M22: =IF(MONTH($A22)=11,1,0) -> 0 | N22: =IF(MONTH($A22)=12,1,0) -> 0 | O22: =$B$5+SUMPRODUCT(C22:N22,$C$5:$N$5) -> 3.2444014 | P22: =B22-O22 -> -0.39087112 | Q22: =P22^2 -> 0.15278023 | R22: =(ROW()-ROW($A$7))/12 -> 1.25 | T22: Observations | U22: =COUNT(B7:B35) -> 29 | V22: 29 | Y22: Post | Z22: M2 | AA22: M3 | AB22: M4 | AC22: M5 | AD22: M6 | AE22: M7 | AF22: M8 | AG22: M9 | AH22: M10 | AI22: M11 | AJ22: M12
A23: =Data_Monthly!A24 -> 44883 | B23: =Data_Monthly!J24 -> -1.4761656 | C23: =IF($A23>=$U$5,1,0) -> 0 | D23: =IF(MONTH($A23)=2,1,0) -> 0 | E23: =IF(MONTH($A23)=3,1,0) -> 0 | F23: =IF(MONTH($A23)=4,1,0) -> 0 | G23: =IF(MONTH($A23)=5,1,0) -> 0 | H23: =IF(MONTH($A23)=6,1,0) -> 0 | I23: =IF(MONTH($A23)=7,1,0) -> 0 | J23: =IF(MONTH($A23)=8,1,0) -> 0 | K23: =IF(MONTH($A23)=9,1,0) -> 0 | L23: =IF(MONTH($A23)=10,1,0) -> 0 | M23: =IF(MONTH($A23)=11,1,0) -> 1 | N23: =IF(MONTH($A23)=12,1,0) -> 0 | O23: =$B$5+SUMPRODUCT(C23:N23,$C$5:$N$5) -> -0.5057455 | P23: =B23-O23 -> -0.97042009 | Q23: =P23^2 -> 0.94171515 | R23: =(ROW()-ROW($A$7))/12 -> 1.3333333 | T23: R squared | U23: =INDEX(LINEST(B7:B35,C7:N35,TRUE(),TRUE()),3,1) -> 0.70414329 | V23: 0.70414329 | X23: Post | Y23: =CORREL($C$7:$C$35,$C$7:$C$35) -> 1 | Z23: =CORREL($D$7:$D$35,$C$7:$C$35) -> 0.047638496 | AA23: =CORREL($E$7:$E$35,$C$7:$C$35) -> 0.047638496 | AB23: =CORREL($F$7:$F$35,$C$7:$C$35) -> 0.047638496 | AC23: =CORREL($G$7:$G$35,$C$7:$C$35) -> 0.047638496 | AD23: =CORREL($H$7:$H$35,$C$7:$C$35) -> 0.047638496 | AE23: =CORREL($I$7:$I$35,$C$7:$C$35) -> -0.055492674 | AF23: =CORREL($J$7:$J$35,$C$7:$C$35) -> -0.055492674 | AG23: =CORREL($K$7:$K$35,$C$7:$C$35) -> -0.055492674 | AH23: =CORREL($L$7:$L$35,$C$7:$C$35) -> -0.055492674 | AI23: =CORREL($M$7:$M$35,$C$7:$C$35) -> -0.055492674 | AJ23: =CORREL($N$7:$N$35,$C$7:$C$35) -> 0.047638496
A24: =Data_Monthly!A25 -> 44925 | B24: =Data_Monthly!J25 -> 0.89608742 | C24: =IF($A24>=$U$5,1,0) -> 1 | D24: =IF(MONTH($A24)=2,1,0) -> 0 | E24: =IF(MONTH($A24)=3,1,0) -> 0 | F24: =IF(MONTH($A24)=4,1,0) -> 0 | G24: =IF(MONTH($A24)=5,1,0) -> 0 | H24: =IF(MONTH($A24)=6,1,0) -> 0 | I24: =IF(MONTH($A24)=7,1,0) -> 0 | J24: =IF(MONTH($A24)=8,1,0) -> 0 | K24: =IF(MONTH($A24)=9,1,0) -> 0 | L24: =IF(MONTH($A24)=10,1,0) -> 0 | M24: =IF(MONTH($A24)=11,1,0) -> 0 | N24: =IF(MONTH($A24)=12,1,0) -> 1 | O24: =$B$5+SUMPRODUCT(C24:N24,$C$5:$N$5) -> 0.69705098 | P24: =B24-O24 -> 0.19903644 | Q24: =P24^2 -> 0.039615505 | R24: =(ROW()-ROW($A$7))/12 -> 1.4166667 | T24: R | U24: =SQRT($U$23) -> 0.83913246 | X24: M2 | Y24: =CORREL($C$7:$C$35,$D$7:$D$35) -> 0.047638496 | Z24: =CORREL($D$7:$D$35,$D$7:$D$35) -> 1 | AA24: =CORREL($E$7:$E$35,$D$7:$D$35) -> -0.074074074 | AB24: =CORREL($F$7:$F$35,$D$7:$D$35) -> -0.074074074 | AC24: =CORREL($G$7:$G$35,$D$7:$D$35) -> -0.074074074 | AD24: =CORREL($H$7:$H$35,$D$7:$D$35) -> -0.074074074 | AE24: =CORREL($I$7:$I$35,$D$7:$D$35) -> -0.092450033 | AF24: =CORREL($J$7:$J$35,$D$7:$D$35) -> -0.092450033 | AG24: =CORREL($K$7:$K$35,$D$7:$D$35) -> -0.092450033 | AH24: =CORREL($L$7:$L$35,$D$7:$D$35) -> -0.092450033 | AI24: =CORREL($M$7:$M$35,$D$7:$D$35) -> -0.092450033 | AJ24: =CORREL($N$7:$N$35,$D$7:$D$35) -> -0.074074074
A25: =Data_Monthly!A26 -> 44953 | B25: =Data_Monthly!J26 -> 1.4747812 | C25: =IF($A25>=$U$5,1,0) -> 1 | D25: =IF(MONTH($A25)=2,1,0) -> 0 | E25: =IF(MONTH($A25)=3,1,0) -> 0 | F25: =IF(MONTH($A25)=4,1,0) -> 0 | G25: =IF(MONTH($A25)=5,1,0) -> 0 | H25: =IF(MONTH($A25)=6,1,0) -> 0 | I25: =IF(MONTH($A25)=7,1,0) -> 0 | J25: =IF(MONTH($A25)=8,1,0) -> 0 | K25: =IF(MONTH($A25)=9,1,0) -> 0 | L25: =IF(MONTH($A25)=10,1,0) -> 0 | M25: =IF(MONTH($A25)=11,1,0) -> 0 | N25: =IF(MONTH($A25)=12,1,0) -> 0 | O25: =$B$5+SUMPRODUCT(C25:N25,$C$5:$N$5) -> 0.49061381 | P25: =B25-O25 -> 0.98416743 | Q25: =P25^2 -> 0.96858553 | R25: =(ROW()-ROW($A$7))/12 -> 1.5 | T25: Residual degrees of freedom | U25: =INDEX(LINEST(B7:B35,C7:N35,TRUE(),TRUE()),4,2) -> 16 | X25: M3 | Y25: =CORREL($C$7:$C$35,$E$7:$E$35) -> 0.047638496 | Z25: =CORREL($D$7:$D$35,$E$7:$E$35) -> -0.074074074 | AA25: =CORREL($E$7:$E$35,$E$7:$E$35) -> 1 | AB25: =CORREL($F$7:$F$35,$E$7:$E$35) -> -0.074074074 | AC25: =CORREL($G$7:$G$35,$E$7:$E$35) -> -0.074074074 | AD25: =CORREL($H$7:$H$35,$E$7:$E$35) -> -0.074074074 | AE25: =CORREL($I$7:$I$35,$E$7:$E$35) -> -0.092450033 | AF25: =CORREL($J$7:$J$35,$E$7:$E$35) -> -0.092450033 | AG25: =CORREL($K$7:$K$35,$E$7:$E$35) -> -0.092450033 | AH25: =CORREL($L$7:$L$35,$E$7:$E$35) -> -0.092450033 | AI25: =CORREL($M$7:$M$35,$E$7:$E$35) -> -0.092450033 | AJ25: =CORREL($N$7:$N$35,$E$7:$E$35) -> -0.074074074
A26: =Data_Monthly!A27 -> 44981 | B26: =Data_Monthly!J27 -> 0.55297879 | C26: =IF($A26>=$U$5,1,0) -> 1 | D26: =IF(MONTH($A26)=2,1,0) -> 1 | E26: =IF(MONTH($A26)=3,1,0) -> 0 | F26: =IF(MONTH($A26)=4,1,0) -> 0 | G26: =IF(MONTH($A26)=5,1,0) -> 0 | H26: =IF(MONTH($A26)=6,1,0) -> 0 | I26: =IF(MONTH($A26)=7,1,0) -> 0 | J26: =IF(MONTH($A26)=8,1,0) -> 0 | K26: =IF(MONTH($A26)=9,1,0) -> 0 | L26: =IF(MONTH($A26)=10,1,0) -> 0 | M26: =IF(MONTH($A26)=11,1,0) -> 0 | N26: =IF(MONTH($A26)=12,1,0) -> 0 | O26: =$B$5+SUMPRODUCT(C26:N26,$C$5:$N$5) -> 0.47328162 | P26: =B26-O26 -> 0.079697167 | Q26: =P26^2 -> 0.0063516384 | R26: =(ROW()-ROW($A$7))/12 -> 1.5833333 | T26: Adjusted R squared | U26: =1-(1-$U$23)*($U$22-1)/$U$25 -> 0.48225076 | V26: 0.48225076 | X26: M4 | Y26: =CORREL($C$7:$C$35,$F$7:$F$35) -> 0.047638496 | Z26: =CORREL($D$7:$D$35,$F$7:$F$35) -> -0.074074074 | AA26: =CORREL($E$7:$E$35,$F$7:$F$35) -> -0.074074074 | AB26: =CORREL($F$7:$F$35,$F$7:$F$35) -> 1 | AC26: =CORREL($G$7:$G$35,$F$7:$F$35) -> -0.074074074 | AD26: =CORREL($H$7:$H$35,$F$7:$F$35) -> -0.074074074 | AE26: =CORREL($I$7:$I$35,$F$7:$F$35) -> -0.092450033 | AF26: =CORREL($J$7:$J$35,$F$7:$F$35) -> -0.092450033 | AG26: =CORREL($K$7:$K$35,$F$7:$F$35) -> -0.092450033 | AH26: =CORREL($L$7:$L$35,$F$7:$F$35) -> -0.092450033 | AI26: =CORREL($M$7:$M$35,$F$7:$F$35) -> -0.092450033 | AJ26: =CORREL($N$7:$N$35,$F$7:$F$35) -> -0.074074074
A27: =Data_Monthly!A28 -> 45009 | B27: =Data_Monthly!J28 -> 3.3544495 | C27: =IF($A27>=$U$5,1,0) -> 1 | D27: =IF(MONTH($A27)=2,1,0) -> 0 | E27: =IF(MONTH($A27)=3,1,0) -> 1 | F27: =IF(MONTH($A27)=4,1,0) -> 0 | G27: =IF(MONTH($A27)=5,1,0) -> 0 | H27: =IF(MONTH($A27)=6,1,0) -> 0 | I27: =IF(MONTH($A27)=7,1,0) -> 0 | J27: =IF(MONTH($A27)=8,1,0) -> 0 | K27: =IF(MONTH($A27)=9,1,0) -> 0 | L27: =IF(MONTH($A27)=10,1,0) -> 0 | M27: =IF(MONTH($A27)=11,1,0) -> 0 | N27: =IF(MONTH($A27)=12,1,0) -> 0 | O27: =$B$5+SUMPRODUCT(C27:N27,$C$5:$N$5) -> 2.5730246 | P27: =B27-O27 -> 0.78142489 | Q27: =P27^2 -> 0.61062485 | R27: =(ROW()-ROW($A$7))/12 -> 1.6666667 | T27: Standard error of the estimate | U27: =INDEX(LINEST(B7:B35,C7:N35,TRUE(),TRUE()),3,2) -> 1.1313219 | V27: 1.1313219 | X27: M5 | Y27: =CORREL($C$7:$C$35,$G$7:$G$35) -> 0.047638496 | Z27: =CORREL($D$7:$D$35,$G$7:$G$35) -> -0.074074074 | AA27: =CORREL($E$7:$E$35,$G$7:$G$35) -> -0.074074074 | AB27: =CORREL($F$7:$F$35,$G$7:$G$35) -> -0.074074074 | AC27: =CORREL($G$7:$G$35,$G$7:$G$35) -> 1 | AD27: =CORREL($H$7:$H$35,$G$7:$G$35) -> -0.074074074 | AE27: =CORREL($I$7:$I$35,$G$7:$G$35) -> -0.092450033 | AF27: =CORREL($J$7:$J$35,$G$7:$G$35) -> -0.092450033 | AG27: =CORREL($K$7:$K$35,$G$7:$G$35) -> -0.092450033 | AH27: =CORREL($L$7:$L$35,$G$7:$G$35) -> -0.092450033 | AI27: =CORREL($M$7:$M$35,$G$7:$G$35) -> -0.092450033 | AJ27: =CORREL($N$7:$N$35,$G$7:$G$35) -> -0.074074074
A28: =Data_Monthly!A29 -> 45037 | B28: =Data_Monthly!J29 -> -0.069604258 | C28: =IF($A28>=$U$5,1,0) -> 1 | D28: =IF(MONTH($A28)=2,1,0) -> 0 | E28: =IF(MONTH($A28)=3,1,0) -> 0 | F28: =IF(MONTH($A28)=4,1,0) -> 1 | G28: =IF(MONTH($A28)=5,1,0) -> 0 | H28: =IF(MONTH($A28)=6,1,0) -> 0 | I28: =IF(MONTH($A28)=7,1,0) -> 0 | J28: =IF(MONTH($A28)=8,1,0) -> 0 | K28: =IF(MONTH($A28)=9,1,0) -> 0 | L28: =IF(MONTH($A28)=10,1,0) -> 0 | M28: =IF(MONTH($A28)=11,1,0) -> 0 | N28: =IF(MONTH($A28)=12,1,0) -> 0 | O28: =$B$5+SUMPRODUCT(C28:N28,$C$5:$N$5) -> 1.0419411 | P28: =B28-O28 -> -1.1115454 | Q28: =P28^2 -> 1.2355332 | R28: =(ROW()-ROW($A$7))/12 -> 1.75 | X28: M6 | Y28: =CORREL($C$7:$C$35,$H$7:$H$35) -> 0.047638496 | Z28: =CORREL($D$7:$D$35,$H$7:$H$35) -> -0.074074074 | AA28: =CORREL($E$7:$E$35,$H$7:$H$35) -> -0.074074074 | AB28: =CORREL($F$7:$F$35,$H$7:$H$35) -> -0.074074074 | AC28: =CORREL($G$7:$G$35,$H$7:$H$35) -> -0.074074074 | AD28: =CORREL($H$7:$H$35,$H$7:$H$35) -> 1 | AE28: =CORREL($I$7:$I$35,$H$7:$H$35) -> -0.092450033 | AF28: =CORREL($J$7:$J$35,$H$7:$H$35) -> -0.092450033 | AG28: =CORREL($K$7:$K$35,$H$7:$H$35) -> -0.092450033 | AH28: =CORREL($L$7:$L$35,$H$7:$H$35) -> -0.092450033 | AI28: =CORREL($M$7:$M$35,$H$7:$H$35) -> -0.092450033 | AJ28: =CORREL($N$7:$N$35,$H$7:$H$35) -> -0.074074074
A29: =Data_Monthly!A30 -> 45065 | B29: =Data_Monthly!J30 -> 0.35220475 | C29: =IF($A29>=$U$5,1,0) -> 1 | D29: =IF(MONTH($A29)=2,1,0) -> 0 | E29: =IF(MONTH($A29)=3,1,0) -> 0 | F29: =IF(MONTH($A29)=4,1,0) -> 0 | G29: =IF(MONTH($A29)=5,1,0) -> 1 | H29: =IF(MONTH($A29)=6,1,0) -> 0 | I29: =IF(MONTH($A29)=7,1,0) -> 0 | J29: =IF(MONTH($A29)=8,1,0) -> 0 | K29: =IF(MONTH($A29)=9,1,0) -> 0 | L29: =IF(MONTH($A29)=10,1,0) -> 0 | M29: =IF(MONTH($A29)=11,1,0) -> 0 | N29: =IF(MONTH($A29)=12,1,0) -> 0 | O29: =$B$5+SUMPRODUCT(C29:N29,$C$5:$N$5) -> 0.33044959 | P29: =B29-O29 -> 0.021755158 | Q29: =P29^2 -> 0.00047328689 | R29: =(ROW()-ROW($A$7))/12 -> 1.8333333 | T29: Regression 2 (Post and 11 month dummies): ANOVA | U29: Excel | V29: Dissertation | X29: M7 | Y29: =CORREL($C$7:$C$35,$I$7:$I$35) -> -0.055492674 | Z29: =CORREL($D$7:$D$35,$I$7:$I$35) -> -0.092450033 | AA29: =CORREL($E$7:$E$35,$I$7:$I$35) -> -0.092450033 | AB29: =CORREL($F$7:$F$35,$I$7:$I$35) -> -0.092450033 | AC29: =CORREL($G$7:$G$35,$I$7:$I$35) -> -0.092450033 | AD29: =CORREL($H$7:$H$35,$I$7:$I$35) -> -0.092450033 | AE29: =CORREL($I$7:$I$35,$I$7:$I$35) -> 1 | AF29: =CORREL($J$7:$J$35,$I$7:$I$35) -> -0.11538462 | AG29: =CORREL($K$7:$K$35,$I$7:$I$35) -> -0.11538462 | AH29: =CORREL($L$7:$L$35,$I$7:$I$35) -> -0.11538462 | AI29: =CORREL($M$7:$M$35,$I$7:$I$35) -> -0.11538462 | AJ29: =CORREL($N$7:$N$35,$I$7:$I$35) -> -0.092450033
A30: =Data_Monthly!A31 -> 45107 | B30: =Data_Monthly!J31 -> 0.77519798 | C30: =IF($A30>=$U$5,1,0) -> 1 | D30: =IF(MONTH($A30)=2,1,0) -> 0 | E30: =IF(MONTH($A30)=3,1,0) -> 0 | F30: =IF(MONTH($A30)=4,1,0) -> 0 | G30: =IF(MONTH($A30)=5,1,0) -> 0 | H30: =IF(MONTH($A30)=6,1,0) -> 1 | I30: =IF(MONTH($A30)=7,1,0) -> 0 | J30: =IF(MONTH($A30)=8,1,0) -> 0 | K30: =IF(MONTH($A30)=9,1,0) -> 0 | L30: =IF(MONTH($A30)=10,1,0) -> 0 | M30: =IF(MONTH($A30)=11,1,0) -> 0 | N30: =IF(MONTH($A30)=12,1,0) -> 0 | O30: =$B$5+SUMPRODUCT(C30:N30,$C$5:$N$5) -> -0.28280604 | P30: =B30-O30 -> 1.058004 | Q30: =P30^2 -> 1.1193725 | R30: =(ROW()-ROW($A$7))/12 -> 1.9166667 | T30: Regression sum of squares | U30: =INDEX(LINEST(B7:B35,C7:N35,TRUE(),TRUE()),5,1) -> 48.73848 | V30: 48.73848 | X30: M8 | Y30: =CORREL($C$7:$C$35,$J$7:$J$35) -> -0.055492674 | Z30: =CORREL($D$7:$D$35,$J$7:$J$35) -> -0.092450033 | AA30: =CORREL($E$7:$E$35,$J$7:$J$35) -> -0.092450033 | AB30: =CORREL($F$7:$F$35,$J$7:$J$35) -> -0.092450033 | AC30: =CORREL($G$7:$G$35,$J$7:$J$35) -> -0.092450033 | AD30: =CORREL($H$7:$H$35,$J$7:$J$35) -> -0.092450033 | AE30: =CORREL($I$7:$I$35,$J$7:$J$35) -> -0.11538462 | AF30: =CORREL($J$7:$J$35,$J$7:$J$35) -> 1 | AG30: =CORREL($K$7:$K$35,$J$7:$J$35) -> -0.11538462 | AH30: =CORREL($L$7:$L$35,$J$7:$J$35) -> -0.11538462 | AI30: =CORREL($M$7:$M$35,$J$7:$J$35) -> -0.11538462 | AJ30: =CORREL($N$7:$N$35,$J$7:$J$35) -> -0.092450033
A31: =Data_Monthly!A32 -> 45135 | B31: =Data_Monthly!J32 -> 0.64475199 | C31: =IF($A31>=$U$5,1,0) -> 1 | D31: =IF(MONTH($A31)=2,1,0) -> 0 | E31: =IF(MONTH($A31)=3,1,0) -> 0 | F31: =IF(MONTH($A31)=4,1,0) -> 0 | G31: =IF(MONTH($A31)=5,1,0) -> 0 | H31: =IF(MONTH($A31)=6,1,0) -> 0 | I31: =IF(MONTH($A31)=7,1,0) -> 1 | J31: =IF(MONTH($A31)=8,1,0) -> 0 | K31: =IF(MONTH($A31)=9,1,0) -> 0 | L31: =IF(MONTH($A31)=10,1,0) -> 0 | M31: =IF(MONTH($A31)=11,1,0) -> 0 | N31: =IF(MONTH($A31)=12,1,0) -> 0 | O31: =$B$5+SUMPRODUCT(C31:N31,$C$5:$N$5) -> 2.4958461 | P31: =B31-O31 -> -1.8510942 | Q31: =P31^2 -> 3.4265496 | R31: =(ROW()-ROW($A$7))/12 -> 2 | T31: Residual sum of squares | U31: =INDEX(LINEST(B7:B35,C7:N35,TRUE(),TRUE()),5,2) -> 20.478227 | V31: 20.478227 | X31: M9 | Y31: =CORREL($C$7:$C$35,$K$7:$K$35) -> -0.055492674 | Z31: =CORREL($D$7:$D$35,$K$7:$K$35) -> -0.092450033 | AA31: =CORREL($E$7:$E$35,$K$7:$K$35) -> -0.092450033 | AB31: =CORREL($F$7:$F$35,$K$7:$K$35) -> -0.092450033 | AC31: =CORREL($G$7:$G$35,$K$7:$K$35) -> -0.092450033 | AD31: =CORREL($H$7:$H$35,$K$7:$K$35) -> -0.092450033 | AE31: =CORREL($I$7:$I$35,$K$7:$K$35) -> -0.11538462 | AF31: =CORREL($J$7:$J$35,$K$7:$K$35) -> -0.11538462 | AG31: =CORREL($K$7:$K$35,$K$7:$K$35) -> 1 | AH31: =CORREL($L$7:$L$35,$K$7:$K$35) -> -0.11538462 | AI31: =CORREL($M$7:$M$35,$K$7:$K$35) -> -0.11538462 | AJ31: =CORREL($N$7:$N$35,$K$7:$K$35) -> -0.092450033
A32: =Data_Monthly!A33 -> 45163 | B32: =Data_Monthly!J33 -> -0.28108759 | C32: =IF($A32>=$U$5,1,0) -> 1 | D32: =IF(MONTH($A32)=2,1,0) -> 0 | E32: =IF(MONTH($A32)=3,1,0) -> 0 | F32: =IF(MONTH($A32)=4,1,0) -> 0 | G32: =IF(MONTH($A32)=5,1,0) -> 0 | H32: =IF(MONTH($A32)=6,1,0) -> 0 | I32: =IF(MONTH($A32)=7,1,0) -> 0 | J32: =IF(MONTH($A32)=8,1,0) -> 1 | K32: =IF(MONTH($A32)=9,1,0) -> 0 | L32: =IF(MONTH($A32)=10,1,0) -> 0 | M32: =IF(MONTH($A32)=11,1,0) -> 0 | N32: =IF(MONTH($A32)=12,1,0) -> 0 | O32: =$B$5+SUMPRODUCT(C32:N32,$C$5:$N$5) -> 0.57436866 | P32: =B32-O32 -> -0.85545625 | Q32: =P32^2 -> 0.7318054 | R32: =(ROW()-ROW($A$7))/12 -> 2.0833333 | T32: Regression degrees of freedom | U32: =COLUMNS(C7:N35) -> 12 | V32: 12 | X32: M10 | Y32: =CORREL($C$7:$C$35,$L$7:$L$35) -> -0.055492674 | Z32: =CORREL($D$7:$D$35,$L$7:$L$35) -> -0.092450033 | AA32: =CORREL($E$7:$E$35,$L$7:$L$35) -> -0.092450033 | AB32: =CORREL($F$7:$F$35,$L$7:$L$35) -> -0.092450033 | AC32: =CORREL($G$7:$G$35,$L$7:$L$35) -> -0.092450033 | AD32: =CORREL($H$7:$H$35,$L$7:$L$35) -> -0.092450033 | AE32: =CORREL($I$7:$I$35,$L$7:$L$35) -> -0.11538462 | AF32: =CORREL($J$7:$J$35,$L$7:$L$35) -> -0.11538462 | AG32: =CORREL($K$7:$K$35,$L$7:$L$35) -> -0.11538462 | AH32: =CORREL($L$7:$L$35,$L$7:$L$35) -> 1 | AI32: =CORREL($M$7:$M$35,$L$7:$L$35) -> -0.11538462 | AJ32: =CORREL($N$7:$N$35,$L$7:$L$35) -> -0.092450033
A33: =Data_Monthly!A34 -> 45191 | B33: =Data_Monthly!J34 -> -0.94315801 | C33: =IF($A33>=$U$5,1,0) -> 1 | D33: =IF(MONTH($A33)=2,1,0) -> 0 | E33: =IF(MONTH($A33)=3,1,0) -> 0 | F33: =IF(MONTH($A33)=4,1,0) -> 0 | G33: =IF(MONTH($A33)=5,1,0) -> 0 | H33: =IF(MONTH($A33)=6,1,0) -> 0 | I33: =IF(MONTH($A33)=7,1,0) -> 0 | J33: =IF(MONTH($A33)=8,1,0) -> 0 | K33: =IF(MONTH($A33)=9,1,0) -> 1 | L33: =IF(MONTH($A33)=10,1,0) -> 0 | M33: =IF(MONTH($A33)=11,1,0) -> 0 | N33: =IF(MONTH($A33)=12,1,0) -> 0 | O33: =$B$5+SUMPRODUCT(C33:N33,$C$5:$N$5) -> -0.80791774 | P33: =B33-O33 -> -0.13524027 | Q33: =P33^2 -> 0.01828993 | R33: =(ROW()-ROW($A$7))/12 -> 2.1666667 | T33: Residual degrees of freedom | U33: =$U$25 -> 16 | V33: 16 | X33: M11 | Y33: =CORREL($C$7:$C$35,$M$7:$M$35) -> -0.055492674 | Z33: =CORREL($D$7:$D$35,$M$7:$M$35) -> -0.092450033 | AA33: =CORREL($E$7:$E$35,$M$7:$M$35) -> -0.092450033 | AB33: =CORREL($F$7:$F$35,$M$7:$M$35) -> -0.092450033 | AC33: =CORREL($G$7:$G$35,$M$7:$M$35) -> -0.092450033 | AD33: =CORREL($H$7:$H$35,$M$7:$M$35) -> -0.092450033 | AE33: =CORREL($I$7:$I$35,$M$7:$M$35) -> -0.11538462 | AF33: =CORREL($J$7:$J$35,$M$7:$M$35) -> -0.11538462 | AG33: =CORREL($K$7:$K$35,$M$7:$M$35) -> -0.11538462 | AH33: =CORREL($L$7:$L$35,$M$7:$M$35) -> -0.11538462 | AI33: =CORREL($M$7:$M$35,$M$7:$M$35) -> 1 | AJ33: =CORREL($N$7:$N$35,$M$7:$M$35) -> -0.092450033
A34: =Data_Monthly!A35 -> 45219 | B34: =Data_Monthly!J35 -> 3.779056 | C34: =IF($A34>=$U$5,1,0) -> 1 | D34: =IF(MONTH($A34)=2,1,0) -> 0 | E34: =IF(MONTH($A34)=3,1,0) -> 0 | F34: =IF(MONTH($A34)=4,1,0) -> 0 | G34: =IF(MONTH($A34)=5,1,0) -> 0 | H34: =IF(MONTH($A34)=6,1,0) -> 0 | I34: =IF(MONTH($A34)=7,1,0) -> 0 | J34: =IF(MONTH($A34)=8,1,0) -> 0 | K34: =IF(MONTH($A34)=9,1,0) -> 0 | L34: =IF(MONTH($A34)=10,1,0) -> 1 | M34: =IF(MONTH($A34)=11,1,0) -> 0 | N34: =IF(MONTH($A34)=12,1,0) -> 0 | O34: =$B$5+SUMPRODUCT(C34:N34,$C$5:$N$5) -> 3.1913039 | P34: =B34-O34 -> 0.58775207 | Q34: =P34^2 -> 0.3454525 | R34: =(ROW()-ROW($A$7))/12 -> 2.25 | T34: Regression mean square | U34: =$U$30/$U$32 -> 4.06154 | X34: M12 | Y34: =CORREL($C$7:$C$35,$N$7:$N$35) -> 0.047638496 | Z34: =CORREL($D$7:$D$35,$N$7:$N$35) -> -0.074074074 | AA34: =CORREL($E$7:$E$35,$N$7:$N$35) -> -0.074074074 | AB34: =CORREL($F$7:$F$35,$N$7:$N$35) -> -0.074074074 | AC34: =CORREL($G$7:$G$35,$N$7:$N$35) -> -0.074074074 | AD34: =CORREL($H$7:$H$35,$N$7:$N$35) -> -0.074074074 | AE34: =CORREL($I$7:$I$35,$N$7:$N$35) -> -0.092450033 | AF34: =CORREL($J$7:$J$35,$N$7:$N$35) -> -0.092450033 | AG34: =CORREL($K$7:$K$35,$N$7:$N$35) -> -0.092450033 | AH34: =CORREL($L$7:$L$35,$N$7:$N$35) -> -0.092450033 | AI34: =CORREL($M$7:$M$35,$N$7:$N$35) -> -0.092450033 | AJ34: =CORREL($N$7:$N$35,$N$7:$N$35) -> 1
A35: =Data_Monthly!A36 -> 45247 | B35: =Data_Monthly!J36 -> -0.31734416 | C35: =IF($A35>=$U$5,1,0) -> 1 | D35: =IF(MONTH($A35)=2,1,0) -> 0 | E35: =IF(MONTH($A35)=3,1,0) -> 0 | F35: =IF(MONTH($A35)=4,1,0) -> 0 | G35: =IF(MONTH($A35)=5,1,0) -> 0 | H35: =IF(MONTH($A35)=6,1,0) -> 0 | I35: =IF(MONTH($A35)=7,1,0) -> 0 | J35: =IF(MONTH($A35)=8,1,0) -> 0 | K35: =IF(MONTH($A35)=9,1,0) -> 0 | L35: =IF(MONTH($A35)=10,1,0) -> 0 | M35: =IF(MONTH($A35)=11,1,0) -> 1 | N35: =IF(MONTH($A35)=12,1,0) -> 0 | O35: =$B$5+SUMPRODUCT(C35:N35,$C$5:$N$5) -> -0.55884306 | P35: =B35-O35 -> 0.24149889 | Q35: =P35^2 -> 0.058321716 | R35: =(ROW()-ROW($A$7))/12 -> 2.3333333 | T35: Residual mean square | U35: =$U$31/$U$33 -> 1.2798892
T36: F statistic | U36: =INDEX(LINEST(B7:B35,C7:N35,TRUE(),TRUE()),4,1) -> 3.1733529 | V36: 3.1733529
T37: Significance of F | U37: =_xlfn.F.DIST.RT($U$36,$U$32,$U$33) -> 0.016706601 | V37: 0.016706601
T39: Regression 2 (Post and 11 month dummies): Post | U39: Excel | V39: Dissertation
T40: Coefficient on Post | U40: =Y7 -> -0.053097556 | V40: -0.053097556
T41: Standard error | U41: =Z7 -> 0.43278269 | V41: 0.43278269
T42: t statistic | U42: =AA7 -> -0.12268872 | V42: -0.12268872
T43: p-value | U43: =AB7 -> 0.90388146 | V43: 0.90388146
T46: Pre-policy trend: gap on time in years (LINEST) | U46: Excel | V46: Dissertation
T47: Slope (pp per year) | U47: =INDEX(LINEST(B7:B35,R7:R35,TRUE(),TRUE()),1,1) -> -0.36999861 | V47: -0.36999861
T48: Standard error | U48: =INDEX(LINEST(B7:B35,R7:R35,TRUE(),TRUE()),2,1) -> 0.4204519 | V48: 0.4204519
T49: t statistic | U49: =$U$47/$U$48 -> -0.88000223
T50: p-value | U50: =_xlfn.T.DIST.2T(ABS($U$49),INDEX(LINEST(B7:B35,R7:R35,TRUE(),TRUE()),4,2)) -> 0.38662387 | V50: 0.38662387
T51: Observations | U51: =COUNT(B7:B35) -> 29 | V51: 29

Sheet H2_Placebo
A1: H2: placebo test with a fictitious policy date (November 2022) and pre-policy trend
A2: Reproduces Table 7.6. Pre-policy data only: July 2021 to 17 November 2023. 'Post' switches on at the fictitious date. The trend regression uses the same months, with time measured in years from July 2021.
A4: H2 gap, July 2021 to November 2023 | T4: Test results
A5: Coefficients | B5: =Y19 -> -0.46429529 | C5: =Y7 -> 0.14747017 | D5: =Y8 -> 0.55919293 | E5: =Y9 -> 0.78083658 | F5: =Y10 -> 0.63226397 | G5: =Y11 -> -0.60283233 | H5: =Y12 -> 1.6784977 | I5: =Y13 -> 3.2884586 | J5: =Y14 -> -0.45600829 | K5: =Y15 -> 1.193663 | L5: =Y16 -> 3.4129538 | M5: =Y17 -> 2.259501 | N5: =Y18 -> 5.8233508 | T5: Post = 1 for months dated on or after | U5: 44895 | X5: Regression 2: all coefficients
A6: Date | B6: Gap (pp) | C6: Post | D6: M2 | E6: M3 | F6: M4 | G6: M5 | H6: M6 | I6: M7 | J6: M8 | K6: M9 | L6: M10 | M6: M11 | N6: M12 | O6: Fitted | P6: Residual | Q6: Residual squared | R6: Time (years from start) | T6: Months before: rows 7 to 23; after: rows 24 to 34. | X6: Variable | Y6: B | Z6: Std. error | AA6: t | AB6: p-value | AC6: VIF
A7: =Data_Monthly!A8 -> 44407 | B7: =Data_Monthly!K8 -> 0.010605503 | C7: =IF($A7>=$U$5,1,0) -> 0 | D7: =IF(MONTH($A7)=2,1,0) -> 0 | E7: =IF(MONTH($A7)=3,1,0) -> 0 | F7: =IF(MONTH($A7)=4,1,0) -> 0 | G7: =IF(MONTH($A7)=5,1,0) -> 0 | H7: =IF(MONTH($A7)=6,1,0) -> 0 | I7: =IF(MONTH($A7)=7,1,0) -> 1 | J7: =IF(MONTH($A7)=8,1,0) -> 0 | K7: =IF(MONTH($A7)=9,1,0) -> 0 | L7: =IF(MONTH($A7)=10,1,0) -> 0 | M7: =IF(MONTH($A7)=11,1,0) -> 0 | N7: =IF(MONTH($A7)=12,1,0) -> 0 | O7: =$B$5+SUMPRODUCT(C7:N7,$C$5:$N$5) -> 2.8241633 | P7: =B7-O7 -> -2.8135578 | Q7: =P7^2 -> 7.9161074 | R7: =(ROW()-ROW($A$7))/12 -> 0 | T7: Welch two-sample t-test (unequal variances) | U7: Excel | V7: Dissertation | X7: Post | Y7: =INDEX(LINEST(B7:B34,C7:N34,TRUE(),TRUE()),1,12) -> 0.14747017 | Z7: =INDEX(LINEST(B7:B34,C7:N34,TRUE(),TRUE()),2,12) -> 0.85180106 | AA7: =Y7/Z7 -> 0.17312748 | AB7: =_xlfn.T.DIST.2T(ABS(AA7),$U$25) -> 0.86486579 | AC7: =INDEX(MINVERSE($Y$23:$AJ$34),1,1) -> 1.0830116
A8: =Data_Monthly!A9 -> 44435 | B8: =Data_Monthly!K9 -> -2.2963644 | C8: =IF($A8>=$U$5,1,0) -> 0 | D8: =IF(MONTH($A8)=2,1,0) -> 0 | E8: =IF(MONTH($A8)=3,1,0) -> 0 | F8: =IF(MONTH($A8)=4,1,0) -> 0 | G8: =IF(MONTH($A8)=5,1,0) -> 0 | H8: =IF(MONTH($A8)=6,1,0) -> 0 | I8: =IF(MONTH($A8)=7,1,0) -> 0 | J8: =IF(MONTH($A8)=8,1,0) -> 1 | K8: =IF(MONTH($A8)=9,1,0) -> 0 | L8: =IF(MONTH($A8)=10,1,0) -> 0 | M8: =IF(MONTH($A8)=11,1,0) -> 0 | N8: =IF(MONTH($A8)=12,1,0) -> 0 | O8: =$B$5+SUMPRODUCT(C8:N8,$C$5:$N$5) -> -0.92030358 | P8: =B8-O8 -> -1.3760608 | Q8: =P8^2 -> 1.8935434 | R8: =(ROW()-ROW($A$7))/12 -> 0.083333333 | T8: Months before (n1) | U8: =COUNT(B7:B23) -> 17 | V8: 17 | X8: M2 | Y8: =INDEX(LINEST(B7:B34,C7:N34,TRUE(),TRUE()),1,11) -> 0.55919293 | Z8: =INDEX(LINEST(B7:B34,C7:N34,TRUE(),TRUE()),2,11) -> 2.1152583 | AA8: =Y8/Z8 -> 0.26436153 | AB8: =_xlfn.T.DIST.2T(ABS(AA8),$U$25) -> 0.79509915 | AC8: =INDEX(MINVERSE($Y$23:$AJ$34),2,2) -> 1.8571429
A9: =Data_Monthly!A10 -> 44463 | B9: =Data_Monthly!K10 -> -0.33197555 | C9: =IF($A9>=$U$5,1,0) -> 0 | D9: =IF(MONTH($A9)=2,1,0) -> 0 | E9: =IF(MONTH($A9)=3,1,0) -> 0 | F9: =IF(MONTH($A9)=4,1,0) -> 0 | G9: =IF(MONTH($A9)=5,1,0) -> 0 | H9: =IF(MONTH($A9)=6,1,0) -> 0 | I9: =IF(MONTH($A9)=7,1,0) -> 0 | J9: =IF(MONTH($A9)=8,1,0) -> 0 | K9: =IF(MONTH($A9)=9,1,0) -> 1 | L9: =IF(MONTH($A9)=10,1,0) -> 0 | M9: =IF(MONTH($A9)=11,1,0) -> 0 | N9: =IF(MONTH($A9)=12,1,0) -> 0 | O9: =$B$5+SUMPRODUCT(C9:N9,$C$5:$N$5) -> 0.72936769 | P9: =B9-O9 -> -1.0613432 | Q9: =P9^2 -> 1.1264495 | R9: =(ROW()-ROW($A$7))/12 -> 0.16666667 | T9: Months after (n2) | U9: =COUNT(B24:B34) -> 11 | V9: 11 | X9: M3 | Y9: =INDEX(LINEST(B7:B34,C7:N34,TRUE(),TRUE()),1,10) -> 0.78083658 | Z9: =INDEX(LINEST(B7:B34,C7:N34,TRUE(),TRUE()),2,10) -> 2.1152583 | AA9: =Y9/Z9 -> 0.36914478 | AB9: =_xlfn.T.DIST.2T(ABS(AA9),$U$25) -> 0.71717866 | AC9: =INDEX(MINVERSE($Y$23:$AJ$34),3,3) -> 1.8571429
A10: =Data_Monthly!A11 -> 44491 | B10: =Data_Monthly!K11 -> 2.4520809 | C10: =IF($A10>=$U$5,1,0) -> 0 | D10: =IF(MONTH($A10)=2,1,0) -> 0 | E10: =IF(MONTH($A10)=3,1,0) -> 0 | F10: =IF(MONTH($A10)=4,1,0) -> 0 | G10: =IF(MONTH($A10)=5,1,0) -> 0 | H10: =IF(MONTH($A10)=6,1,0) -> 0 | I10: =IF(MONTH($A10)=7,1,0) -> 0 | J10: =IF(MONTH($A10)=8,1,0) -> 0 | K10: =IF(MONTH($A10)=9,1,0) -> 0 | L10: =IF(MONTH($A10)=10,1,0) -> 1 | M10: =IF(MONTH($A10)=11,1,0) -> 0 | N10: =IF(MONTH($A10)=12,1,0) -> 0 | O10: =$B$5+SUMPRODUCT(C10:N10,$C$5:$N$5) -> 2.9486586 | P10: =B10-O10 -> -0.49657764 | Q10: =P10^2 -> 0.24658935 | R10: =(ROW()-ROW($A$7))/12 -> 0.25 | T10: Mean gap before | U10: =AVERAGE(B7:B23) -> 1.1985545 | V10: 1.1985545 | X10: M4 | Y10: =INDEX(LINEST(B7:B34,C7:N34,TRUE(),TRUE()),1,9) -> 0.63226397 | Z10: =INDEX(LINEST(B7:B34,C7:N34,TRUE(),TRUE()),2,9) -> 2.1152583 | AA10: =Y10/Z10 -> 0.29890627 | AB10: =_xlfn.T.DIST.2T(ABS(AA10),$U$25) -> 0.76911283 | AC10: =INDEX(MINVERSE($Y$23:$AJ$34),4,4) -> 1.8571429
A11: =Data_Monthly!A12 -> 44519 | B11: =Data_Monthly!K12 -> 2.6574207 | C11: =IF($A11>=$U$5,1,0) -> 0 | D11: =IF(MONTH($A11)=2,1,0) -> 0 | E11: =IF(MONTH($A11)=3,1,0) -> 0 | F11: =IF(MONTH($A11)=4,1,0) -> 0 | G11: =IF(MONTH($A11)=5,1,0) -> 0 | H11: =IF(MONTH($A11)=6,1,0) -> 0 | I11: =IF(MONTH($A11)=7,1,0) -> 0 | J11: =IF(MONTH($A11)=8,1,0) -> 0 | K11: =IF(MONTH($A11)=9,1,0) -> 0 | L11: =IF(MONTH($A11)=10,1,0) -> 0 | M11: =IF(MONTH($A11)=11,1,0) -> 1 | N11: =IF(MONTH($A11)=12,1,0) -> 0 | O11: =$B$5+SUMPRODUCT(C11:N11,$C$5:$N$5) -> 1.7952057 | P11: =B11-O11 -> 0.86221495 | Q11: =P11^2 -> 0.74341462 | R11: =(ROW()-ROW($A$7))/12 -> 0.33333333 | T11: Mean gap after | U11: =AVERAGE(B24:B34) -> 1.0723948 | V11: 1.0723948 | X11: M5 | Y11: =INDEX(LINEST(B7:B34,C7:N34,TRUE(),TRUE()),1,8) -> -0.60283233 | Z11: =INDEX(LINEST(B7:B34,C7:N34,TRUE(),TRUE()),2,8) -> 2.1152583 | AA11: =Y11/Z11 -> -0.2849923 | AB11: =_xlfn.T.DIST.2T(ABS(AA11),$U$25) -> 0.77954725 | AC11: =INDEX(MINVERSE($Y$23:$AJ$34),5,5) -> 1.8571429
A12: =Data_Monthly!A13 -> 44561 | B12: =Data_Monthly!K13 -> 4.3183459 | C12: =IF($A12>=$U$5,1,0) -> 0 | D12: =IF(MONTH($A12)=2,1,0) -> 0 | E12: =IF(MONTH($A12)=3,1,0) -> 0 | F12: =IF(MONTH($A12)=4,1,0) -> 0 | G12: =IF(MONTH($A12)=5,1,0) -> 0 | H12: =IF(MONTH($A12)=6,1,0) -> 0 | I12: =IF(MONTH($A12)=7,1,0) -> 0 | J12: =IF(MONTH($A12)=8,1,0) -> 0 | K12: =IF(MONTH($A12)=9,1,0) -> 0 | L12: =IF(MONTH($A12)=10,1,0) -> 0 | M12: =IF(MONTH($A12)=11,1,0) -> 0 | N12: =IF(MONTH($A12)=12,1,0) -> 1 | O12: =$B$5+SUMPRODUCT(C12:N12,$C$5:$N$5) -> 5.3590555 | P12: =B12-O12 -> -1.0407096 | Q12: =P12^2 -> 1.0830765 | R12: =(ROW()-ROW($A$7))/12 -> 0.41666667 | T12: Standard deviation before | U12: =_xlfn.STDEV.S(B7:B23) -> 2.3895625 | V12: 2.3895625 | X12: M6 | Y12: =INDEX(LINEST(B7:B34,C7:N34,TRUE(),TRUE()),1,7) -> 1.6784977 | Z12: =INDEX(LINEST(B7:B34,C7:N34,TRUE(),TRUE()),2,7) -> 2.1152583 | AA12: =Y12/Z12 -> 0.79351903 | AB12: =_xlfn.T.DIST.2T(ABS(AA12),$U$25) -> 0.43984827 | AC12: =INDEX(MINVERSE($Y$23:$AJ$34),6,6) -> 1.8571429
A13: =Data_Monthly!A14 -> 44589 | B13: =Data_Monthly!K14 -> 1.5133246 | C13: =IF($A13>=$U$5,1,0) -> 0 | D13: =IF(MONTH($A13)=2,1,0) -> 0 | E13: =IF(MONTH($A13)=3,1,0) -> 0 | F13: =IF(MONTH($A13)=4,1,0) -> 0 | G13: =IF(MONTH($A13)=5,1,0) -> 0 | H13: =IF(MONTH($A13)=6,1,0) -> 0 | I13: =IF(MONTH($A13)=7,1,0) -> 0 | J13: =IF(MONTH($A13)=8,1,0) -> 0 | K13: =IF(MONTH($A13)=9,1,0) -> 0 | L13: =IF(MONTH($A13)=10,1,0) -> 0 | M13: =IF(MONTH($A13)=11,1,0) -> 0 | N13: =IF(MONTH($A13)=12,1,0) -> 0 | O13: =$B$5+SUMPRODUCT(C13:N13,$C$5:$N$5) -> -0.46429529 | P13: =B13-O13 -> 1.9776199 | Q13: =P13^2 -> 3.9109806 | R13: =(ROW()-ROW($A$7))/12 -> 0.5 | T13: Standard deviation after | U13: =_xlfn.STDEV.S(B24:B34) -> 2.4725475 | V13: 2.4725475 | X13: M7 | Y13: =INDEX(LINEST(B7:B34,C7:N34,TRUE(),TRUE()),1,6) -> 3.2884586 | Z13: =INDEX(LINEST(B7:B34,C7:N34,TRUE(),TRUE()),2,6) -> 2.1577092 | AA13: =Y13/Z13 -> 1.5240509 | AB13: =_xlfn.T.DIST.2T(ABS(AA13),$U$25) -> 0.14829957 | AC13: =INDEX(MINVERSE($Y$23:$AJ$34),7,7) -> 1.9324324
A14: =Data_Monthly!A15 -> 44617 | B14: =Data_Monthly!K15 -> -0.94064234 | C14: =IF($A14>=$U$5,1,0) -> 0 | D14: =IF(MONTH($A14)=2,1,0) -> 1 | E14: =IF(MONTH($A14)=3,1,0) -> 0 | F14: =IF(MONTH($A14)=4,1,0) -> 0 | G14: =IF(MONTH($A14)=5,1,0) -> 0 | H14: =IF(MONTH($A14)=6,1,0) -> 0 | I14: =IF(MONTH($A14)=7,1,0) -> 0 | J14: =IF(MONTH($A14)=8,1,0) -> 0 | K14: =IF(MONTH($A14)=9,1,0) -> 0 | L14: =IF(MONTH($A14)=10,1,0) -> 0 | M14: =IF(MONTH($A14)=11,1,0) -> 0 | N14: =IF(MONTH($A14)=12,1,0) -> 0 | O14: =$B$5+SUMPRODUCT(C14:N14,$C$5:$N$5) -> 0.09489764 | P14: =B14-O14 -> -1.03554 | Q14: =P14^2 -> 1.0723431 | R14: =(ROW()-ROW($A$7))/12 -> 0.58333333 | T14: Difference (after minus before) | U14: =$U$11-$U$10 -> -0.12615966 | V14: -0.12615966 | X14: M8 | Y14: =INDEX(LINEST(B7:B34,C7:N34,TRUE(),TRUE()),1,5) -> -0.45600829 | Z14: =INDEX(LINEST(B7:B34,C7:N34,TRUE(),TRUE()),2,5) -> 1.9361696 | AA14: =Y14/Z14 -> -0.23552084 | AB14: =_xlfn.T.DIST.2T(ABS(AA14),$U$25) -> 0.81698979 | AC14: =INDEX(MINVERSE($Y$23:$AJ$34),8,8) -> 2.2442085
A15: =Data_Monthly!A16 -> 44645 | B15: =Data_Monthly!K16 -> 1.0403223 | C15: =IF($A15>=$U$5,1,0) -> 0 | D15: =IF(MONTH($A15)=2,1,0) -> 0 | E15: =IF(MONTH($A15)=3,1,0) -> 1 | F15: =IF(MONTH($A15)=4,1,0) -> 0 | G15: =IF(MONTH($A15)=5,1,0) -> 0 | H15: =IF(MONTH($A15)=6,1,0) -> 0 | I15: =IF(MONTH($A15)=7,1,0) -> 0 | J15: =IF(MONTH($A15)=8,1,0) -> 0 | K15: =IF(MONTH($A15)=9,1,0) -> 0 | L15: =IF(MONTH($A15)=10,1,0) -> 0 | M15: =IF(MONTH($A15)=11,1,0) -> 0 | N15: =IF(MONTH($A15)=12,1,0) -> 0 | O15: =$B$5+SUMPRODUCT(C15:N15,$C$5:$N$5) -> 0.31654128 | P15: =B15-O15 -> 0.72378105 | Q15: =P15^2 -> 0.52385901 | R15: =(ROW()-ROW($A$7))/12 -> 0.66666667 | T15: Difference per year (x 12) | U15: =12*$U$14 -> -1.513916 | V15: -1.513916 | X15: M9 | Y15: =INDEX(LINEST(B7:B34,C7:N34,TRUE(),TRUE()),1,4) -> 1.193663 | Z15: =INDEX(LINEST(B7:B34,C7:N34,TRUE(),TRUE()),2,4) -> 1.9361696 | AA15: =Y15/Z15 -> 0.61650745 | AB15: =_xlfn.T.DIST.2T(ABS(AA15),$U$25) -> 0.54680311 | AC15: =INDEX(MINVERSE($Y$23:$AJ$34),9,9) -> 2.2442085
A16: =Data_Monthly!A17 -> 44673 | B16: =Data_Monthly!K17 -> 0.34182661 | C16: =IF($A16>=$U$5,1,0) -> 0 | D16: =IF(MONTH($A16)=2,1,0) -> 0 | E16: =IF(MONTH($A16)=3,1,0) -> 0 | F16: =IF(MONTH($A16)=4,1,0) -> 1 | G16: =IF(MONTH($A16)=5,1,0) -> 0 | H16: =IF(MONTH($A16)=6,1,0) -> 0 | I16: =IF(MONTH($A16)=7,1,0) -> 0 | J16: =IF(MONTH($A16)=8,1,0) -> 0 | K16: =IF(MONTH($A16)=9,1,0) -> 0 | L16: =IF(MONTH($A16)=10,1,0) -> 0 | M16: =IF(MONTH($A16)=11,1,0) -> 0 | N16: =IF(MONTH($A16)=12,1,0) -> 0 | O16: =$B$5+SUMPRODUCT(C16:N16,$C$5:$N$5) -> 0.16796867 | P16: =B16-O16 -> 0.17385794 | Q16: =P16^2 -> 0.030226583 | R16: =(ROW()-ROW($A$7))/12 -> 0.75 | T16: Standard error of the difference | U16: =SQRT($U$13^2/$U$9+$U$12^2/$U$8) -> 0.94427473 | X16: M10 | Y16: =INDEX(LINEST(B7:B34,C7:N34,TRUE(),TRUE()),1,3) -> 3.4129538 | Z16: =INDEX(LINEST(B7:B34,C7:N34,TRUE(),TRUE()),2,3) -> 1.9361696 | AA16: =Y16/Z16 -> 1.762735 | AB16: =_xlfn.T.DIST.2T(ABS(AA16),$U$25) -> 0.098301844 | AC16: =INDEX(MINVERSE($Y$23:$AJ$34),10,10) -> 2.2442085
A17: =Data_Monthly!A18 -> 44701 | B17: =Data_Monthly!K18 -> -0.33879971 | C17: =IF($A17>=$U$5,1,0) -> 0 | D17: =IF(MONTH($A17)=2,1,0) -> 0 | E17: =IF(MONTH($A17)=3,1,0) -> 0 | F17: =IF(MONTH($A17)=4,1,0) -> 0 | G17: =IF(MONTH($A17)=5,1,0) -> 1 | H17: =IF(MONTH($A17)=6,1,0) -> 0 | I17: =IF(MONTH($A17)=7,1,0) -> 0 | J17: =IF(MONTH($A17)=8,1,0) -> 0 | K17: =IF(MONTH($A17)=9,1,0) -> 0 | L17: =IF(MONTH($A17)=10,1,0) -> 0 | M17: =IF(MONTH($A17)=11,1,0) -> 0 | N17: =IF(MONTH($A17)=12,1,0) -> 0 | O17: =$B$5+SUMPRODUCT(C17:N17,$C$5:$N$5) -> -1.0671276 | P17: =B17-O17 -> 0.72832791 | Q17: =P17^2 -> 0.53046155 | R17: =(ROW()-ROW($A$7))/12 -> 0.83333333 | T17: t statistic | U17: =$U$14/$U$16 -> -0.13360483 | V17: -0.13360483 | X17: M11 | Y17: =INDEX(LINEST(B7:B34,C7:N34,TRUE(),TRUE()),1,2) -> 2.259501 | Z17: =INDEX(LINEST(B7:B34,C7:N34,TRUE(),TRUE()),2,2) -> 1.9361696 | AA17: =Y17/Z17 -> 1.1669954 | AB17: =_xlfn.T.DIST.2T(ABS(AA17),$U$25) -> 0.2614301 | AC17: =INDEX(MINVERSE($Y$23:$AJ$34),11,11) -> 2.2442085
A18: =Data_Monthly!A19 -> 44729 | B18: =Data_Monthly!K19 -> -1.1596309 | C18: =IF($A18>=$U$5,1,0) -> 0 | D18: =IF(MONTH($A18)=2,1,0) -> 0 | E18: =IF(MONTH($A18)=3,1,0) -> 0 | F18: =IF(MONTH($A18)=4,1,0) -> 0 | G18: =IF(MONTH($A18)=5,1,0) -> 0 | H18: =IF(MONTH($A18)=6,1,0) -> 1 | I18: =IF(MONTH($A18)=7,1,0) -> 0 | J18: =IF(MONTH($A18)=8,1,0) -> 0 | K18: =IF(MONTH($A18)=9,1,0) -> 0 | L18: =IF(MONTH($A18)=10,1,0) -> 0 | M18: =IF(MONTH($A18)=11,1,0) -> 0 | N18: =IF(MONTH($A18)=12,1,0) -> 0 | O18: =$B$5+SUMPRODUCT(C18:N18,$C$5:$N$5) -> 1.2142025 | P18: =B18-O18 -> -2.3738334 | Q18: =P18^2 -> 5.6350848 | R18: =(ROW()-ROW($A$7))/12 -> 0.91666667 | T18: Welch degrees of freedom | U18: =(($U$13^2/$U$9)+($U$12^2/$U$8))^2/(($U$13^2/$U$9)^2/($U$9-1)+($U$12^2/$U$8)^2/($U$8-1)) -> 20.955784 | V18: 20.955784 | X18: M12 | Y18: =INDEX(LINEST(B7:B34,C7:N34,TRUE(),TRUE()),1,1) -> 5.8233508 | Z18: =INDEX(LINEST(B7:B34,C7:N34,TRUE(),TRUE()),2,1) -> 2.1152583 | AA18: =Y18/Z18 -> 2.7530211 | AB18: =_xlfn.T.DIST.2T(ABS(AA18),$U$25) -> 0.014796008 | AC18: =INDEX(MINVERSE($Y$23:$AJ$34),12,12) -> 1.8571429
A19: =Data_Monthly!A20 -> 44771 | B19: =Data_Monthly!K20 -> 5.6377211 | C19: =IF($A19>=$U$5,1,0) -> 0 | D19: =IF(MONTH($A19)=2,1,0) -> 0 | E19: =IF(MONTH($A19)=3,1,0) -> 0 | F19: =IF(MONTH($A19)=4,1,0) -> 0 | G19: =IF(MONTH($A19)=5,1,0) -> 0 | H19: =IF(MONTH($A19)=6,1,0) -> 0 | I19: =IF(MONTH($A19)=7,1,0) -> 1 | J19: =IF(MONTH($A19)=8,1,0) -> 0 | K19: =IF(MONTH($A19)=9,1,0) -> 0 | L19: =IF(MONTH($A19)=10,1,0) -> 0 | M19: =IF(MONTH($A19)=11,1,0) -> 0 | N19: =IF(MONTH($A19)=12,1,0) -> 0 | O19: =$B$5+SUMPRODUCT(C19:N19,$C$5:$N$5) -> 2.8241633 | P19: =B19-O19 -> 2.8135578 | Q19: =P19^2 -> 7.9161074 | R19: =(ROW()-ROW($A$7))/12 -> 1 | T19: p-value, two-tailed (T.TEST type 3) | U19: =_xlfn.T.TEST(B24:B34,B7:B23,2,3) -> 0.89498982 | V19: 0.89498982 | X19: Constant | Y19: =INDEX(LINEST(B7:B34,C7:N34,TRUE(),TRUE()),1,13) -> -0.46429529 | Z19: =INDEX(LINEST(B7:B34,C7:N34,TRUE(),TRUE()),2,13) -> 1.5551689 | AA19: =Y19/Z19 -> -0.29854976 | AB19: =_xlfn.T.DIST.2T(ABS(AA19),$U$25) -> 0.76937962
A20: =Data_Monthly!A21 -> 44799 | B20: =Data_Monthly!K21 -> -0.55502341 | C20: =IF($A20>=$U$5,1,0) -> 0 | D20: =IF(MONTH($A20)=2,1,0) -> 0 | E20: =IF(MONTH($A20)=3,1,0) -> 0 | F20: =IF(MONTH($A20)=4,1,0) -> 0 | G20: =IF(MONTH($A20)=5,1,0) -> 0 | H20: =IF(MONTH($A20)=6,1,0) -> 0 | I20: =IF(MONTH($A20)=7,1,0) -> 0 | J20: =IF(MONTH($A20)=8,1,0) -> 1 | K20: =IF(MONTH($A20)=9,1,0) -> 0 | L20: =IF(MONTH($A20)=10,1,0) -> 0 | M20: =IF(MONTH($A20)=11,1,0) -> 0 | N20: =IF(MONTH($A20)=12,1,0) -> 0 | O20: =$B$5+SUMPRODUCT(C20:N20,$C$5:$N$5) -> -0.92030358 | P20: =B20-O20 -> 0.36528017 | Q20: =P20^2 -> 0.1334296 | R20: =(ROW()-ROW($A$7))/12 -> 1.0833333 | X20: Row 5 repeats these coefficients above the data columns; Fitted = Constant + sum of coefficient x regressor.
A21: =Data_Monthly!A22 -> 44827 | B21: =Data_Monthly!K22 -> 0.68514286 | C21: =IF($A21>=$U$5,1,0) -> 0 | D21: =IF(MONTH($A21)=2,1,0) -> 0 | E21: =IF(MONTH($A21)=3,1,0) -> 0 | F21: =IF(MONTH($A21)=4,1,0) -> 0 | G21: =IF(MONTH($A21)=5,1,0) -> 0 | H21: =IF(MONTH($A21)=6,1,0) -> 0 | I21: =IF(MONTH($A21)=7,1,0) -> 0 | J21: =IF(MONTH($A21)=8,1,0) -> 0 | K21: =IF(MONTH($A21)=9,1,0) -> 1 | L21: =IF(MONTH($A21)=10,1,0) -> 0 | M21: =IF(MONTH($A21)=11,1,0) -> 0 | N21: =IF(MONTH($A21)=12,1,0) -> 0 | O21: =$B$5+SUMPRODUCT(C21:N21,$C$5:$N$5) -> 0.72936769 | P21: =B21-O21 -> -0.04422483 | Q21: =P21^2 -> 0.0019558356 | R21: =(ROW()-ROW($A$7))/12 -> 1.1666667 | T21: Regression 2 (Post and 11 month dummies): model summary | U21: Excel | V21: Dissertation | X21: VIF = diagonal of the inverse of the correlation matrix of the regressors:
A22: =Data_Monthly!A23 -> 44855 | B22: =Data_Monthly!K23 -> 6.2526135 | C22: =IF($A22>=$U$5,1,0) -> 0 | D22: =IF(MONTH($A22)=2,1,0) -> 0 | E22: =IF(MONTH($A22)=3,1,0) -> 0 | F22: =IF(MONTH($A22)=4,1,0) -> 0 | G22: =IF(MONTH($A22)=5,1,0) -> 0 | H22: =IF(MONTH($A22)=6,1,0) -> 0 | I22: =IF(MONTH($A22)=7,1,0) -> 0 | J22: =IF(MONTH($A22)=8,1,0) -> 0 | K22: =IF(MONTH($A22)=9,1,0) -> 0 | L22: =IF(MONTH($A22)=10,1,0) -> 1 | M22: =IF(MONTH($A22)=11,1,0) -> 0 | N22: =IF(MONTH($A22)=12,1,0) -> 0 | O22: =$B$5+SUMPRODUCT(C22:N22,$C$5:$N$5) -> 2.9486586 | P22: =B22-O22 -> 3.3039549 | Q22: =P22^2 -> 10.916118 | R22: =(ROW()-ROW($A$7))/12 -> 1.25 | T22: Observations | U22: =COUNT(B7:B34) -> 28 | V22: 28 | Y22: Post | Z22: M2 | AA22: M3 | AB22: M4 | AC22: M5 | AD22: M6 | AE22: M7 | AF22: M8 | AG22: M9 | AH22: M10 | AI22: M11 | AJ22: M12
A23: =Data_Monthly!A24 -> 44883 | B23: =Data_Monthly!K24 -> 1.0884583 | C23: =IF($A23>=$U$5,1,0) -> 0 | D23: =IF(MONTH($A23)=2,1,0) -> 0 | E23: =IF(MONTH($A23)=3,1,0) -> 0 | F23: =IF(MONTH($A23)=4,1,0) -> 0 | G23: =IF(MONTH($A23)=5,1,0) -> 0 | H23: =IF(MONTH($A23)=6,1,0) -> 0 | I23: =IF(MONTH($A23)=7,1,0) -> 0 | J23: =IF(MONTH($A23)=8,1,0) -> 0 | K23: =IF(MONTH($A23)=9,1,0) -> 0 | L23: =IF(MONTH($A23)=10,1,0) -> 0 | M23: =IF(MONTH($A23)=11,1,0) -> 1 | N23: =IF(MONTH($A23)=12,1,0) -> 0 | O23: =$B$5+SUMPRODUCT(C23:N23,$C$5:$N$5) -> 1.7952057 | P23: =B23-O23 -> -0.7067474 | Q23: =P23^2 -> 0.49949189 | R23: =(ROW()-ROW($A$7))/12 -> 1.3333333 | T23: R squared | U23: =INDEX(LINEST(B7:B34,C7:N34,TRUE(),TRUE()),3,1) -> 0.56019545 | V23: 0.56019545 | X23: Post | Y23: =CORREL($C$7:$C$34,$C$7:$C$34) -> 1 | Z23: =CORREL($D$7:$D$34,$C$7:$C$34) -> 0.060845544 | AA23: =CORREL($E$7:$E$34,$C$7:$C$34) -> 0.060845544 | AB23: =CORREL($F$7:$F$34,$C$7:$C$34) -> 0.060845544 | AC23: =CORREL($G$7:$G$34,$C$7:$C$34) -> 0.060845544 | AD23: =CORREL($H$7:$H$34,$C$7:$C$34) -> 0.060845544 | AE23: =CORREL($I$7:$I$34,$C$7:$C$34) -> -0.22310033 | AF23: =CORREL($J$7:$J$34,$C$7:$C$34) -> -0.042220033 | AG23: =CORREL($K$7:$K$34,$C$7:$C$34) -> -0.042220033 | AH23: =CORREL($L$7:$L$34,$C$7:$C$34) -> -0.042220033 | AI23: =CORREL($M$7:$M$34,$C$7:$C$34) -> -0.042220033 | AJ23: =CORREL($N$7:$N$34,$C$7:$C$34) -> 0.060845544
A24: =Data_Monthly!A25 -> 44925 | B24: =Data_Monthly!K25 -> 6.5472353 | C24: =IF($A24>=$U$5,1,0) -> 1 | D24: =IF(MONTH($A24)=2,1,0) -> 0 | E24: =IF(MONTH($A24)=3,1,0) -> 0 | F24: =IF(MONTH($A24)=4,1,0) -> 0 | G24: =IF(MONTH($A24)=5,1,0) -> 0 | H24: =IF(MONTH($A24)=6,1,0) -> 0 | I24: =IF(MONTH($A24)=7,1,0) -> 0 | J24: =IF(MONTH($A24)=8,1,0) -> 0 | K24: =IF(MONTH($A24)=9,1,0) -> 0 | L24: =IF(MONTH($A24)=10,1,0) -> 0 | M24: =IF(MONTH($A24)=11,1,0) -> 0 | N24: =IF(MONTH($A24)=12,1,0) -> 1 | O24: =$B$5+SUMPRODUCT(C24:N24,$C$5:$N$5) -> 5.5065257 | P24: =B24-O24 -> 1.0407096 | Q24: =P24^2 -> 1.0830765 | R24: =(ROW()-ROW($A$7))/12 -> 1.4166667 | T24: R | U24: =SQRT($U$23) -> 0.74846206 | X24: M2 | Y24: =CORREL($C$7:$C$34,$D$7:$D$34) -> 0.060845544 | Z24: =CORREL($D$7:$D$34,$D$7:$D$34) -> 1 | AA24: =CORREL($E$7:$E$34,$D$7:$D$34) -> -0.076923077 | AB24: =CORREL($F$7:$F$34,$D$7:$D$34) -> -0.076923077 | AC24: =CORREL($G$7:$G$34,$D$7:$D$34) -> -0.076923077 | AD24: =CORREL($H$7:$H$34,$D$7:$D$34) -> -0.076923077 | AE24: =CORREL($I$7:$I$34,$D$7:$D$34) -> -0.076923077 | AF24: =CORREL($J$7:$J$34,$D$7:$D$34) -> -0.096076892 | AG24: =CORREL($K$7:$K$34,$D$7:$D$34) -> -0.096076892 | AH24: =CORREL($L$7:$L$34,$D$7:$D$34) -> -0.096076892 | AI24: =CORREL($M$7:$M$34,$D$7:$D$34) -> -0.096076892 | AJ24: =CORREL($N$7:$N$34,$D$7:$D$34) -> -0.076923077
A25: =Data_Monthly!A26 -> 44953 | B25: =Data_Monthly!K26 -> -2.2944451 | C25: =IF($A25>=$U$5,1,0) -> 1 | D25: =IF(MONTH($A25)=2,1,0) -> 0 | E25: =IF(MONTH($A25)=3,1,0) -> 0 | F25: =IF(MONTH($A25)=4,1,0) -> 0 | G25: =IF(MONTH($A25)=5,1,0) -> 0 | H25: =IF(MONTH($A25)=6,1,0) -> 0 | I25: =IF(MONTH($A25)=7,1,0) -> 0 | J25: =IF(MONTH($A25)=8,1,0) -> 0 | K25: =IF(MONTH($A25)=9,1,0) -> 0 | L25: =IF(MONTH($A25)=10,1,0) -> 0 | M25: =IF(MONTH($A25)=11,1,0) -> 0 | N25: =IF(MONTH($A25)=12,1,0) -> 0 | O25: =$B$5+SUMPRODUCT(C25:N25,$C$5:$N$5) -> -0.31682513 | P25: =B25-O25 -> -1.9776199 | Q25: =P25^2 -> 3.9109806 | R25: =(ROW()-ROW($A$7))/12 -> 1.5 | T25: Residual degrees of freedom | U25: =INDEX(LINEST(B7:B34,C7:N34,TRUE(),TRUE()),4,2) -> 15 | X25: M3 | Y25: =CORREL($C$7:$C$34,$E$7:$E$34) -> 0.060845544 | Z25: =CORREL($D$7:$D$34,$E$7:$E$34) -> -0.076923077 | AA25: =CORREL($E$7:$E$34,$E$7:$E$34) -> 1 | AB25: =CORREL($F$7:$F$34,$E$7:$E$34) -> -0.076923077 | AC25: =CORREL($G$7:$G$34,$E$7:$E$34) -> -0.076923077 | AD25: =CORREL($H$7:$H$34,$E$7:$E$34) -> -0.076923077 | AE25: =CORREL($I$7:$I$34,$E$7:$E$34) -> -0.076923077 | AF25: =CORREL($J$7:$J$34,$E$7:$E$34) -> -0.096076892 | AG25: =CORREL($K$7:$K$34,$E$7:$E$34) -> -0.096076892 | AH25: =CORREL($L$7:$L$34,$E$7:$E$34) -> -0.096076892 | AI25: =CORREL($M$7:$M$34,$E$7:$E$34) -> -0.096076892 | AJ25: =CORREL($N$7:$N$34,$E$7:$E$34) -> -0.076923077
A26: =Data_Monthly!A27 -> 44981 | B26: =Data_Monthly!K27 -> 1.2779078 | C26: =IF($A26>=$U$5,1,0) -> 1 | D26: =IF(MONTH($A26)=2,1,0) -> 1 | E26: =IF(MONTH($A26)=3,1,0) -> 0 | F26: =IF(MONTH($A26)=4,1,0) -> 0 | G26: =IF(MONTH($A26)=5,1,0) -> 0 | H26: =IF(MONTH($A26)=6,1,0) -> 0 | I26: =IF(MONTH($A26)=7,1,0) -> 0 | J26: =IF(MONTH($A26)=8,1,0) -> 0 | K26: =IF(MONTH($A26)=9,1,0) -> 0 | L26: =IF(MONTH($A26)=10,1,0) -> 0 | M26: =IF(MONTH($A26)=11,1,0) -> 0 | N26: =IF(MONTH($A26)=12,1,0) -> 0 | O26: =$B$5+SUMPRODUCT(C26:N26,$C$5:$N$5) -> 0.24236781 | P26: =B26-O26 -> 1.03554 | Q26: =P26^2 -> 1.0723431 | R26: =(ROW()-ROW($A$7))/12 -> 1.5833333 | T26: Adjusted R squared | U26: =1-(1-$U$23)*($U$22-1)/$U$25 -> 0.20835181 | V26: 0.20835181 | X26: M4 | Y26: =CORREL($C$7:$C$34,$F$7:$F$34) -> 0.060845544 | Z26: =CORREL($D$7:$D$34,$F$7:$F$34) -> -0.076923077 | AA26: =CORREL($E$7:$E$34,$F$7:$F$34) -> -0.076923077 | AB26: =CORREL($F$7:$F$34,$F$7:$F$34) -> 1 | AC26: =CORREL($G$7:$G$34,$F$7:$F$34) -> -0.076923077 | AD26: =CORREL($H$7:$H$34,$F$7:$F$34) -> -0.076923077 | AE26: =CORREL($I$7:$I$34,$F$7:$F$34) -> -0.076923077 | AF26: =CORREL($J$7:$J$34,$F$7:$F$34) -> -0.096076892 | AG26: =CORREL($K$7:$K$34,$F$7:$F$34) -> -0.096076892 | AH26: =CORREL($L$7:$L$34,$F$7:$F$34) -> -0.096076892 | AI26: =CORREL($M$7:$M$34,$F$7:$F$34) -> -0.096076892 | AJ26: =CORREL($N$7:$N$34,$F$7:$F$34) -> -0.076923077
A27: =Data_Monthly!A28 -> 45009 | B27: =Data_Monthly!K28 -> -0.2597696 | C27: =IF($A27>=$U$5,1,0) -> 1 | D27: =IF(MONTH($A27)=2,1,0) -> 0 | E27: =IF(MONTH($A27)=3,1,0) -> 1 | F27: =IF(MONTH($A27)=4,1,0) -> 0 | G27: =IF(MONTH($A27)=5,1,0) -> 0 | H27: =IF(MONTH($A27)=6,1,0) -> 0 | I27: =IF(MONTH($A27)=7,1,0) -> 0 | J27: =IF(MONTH($A27)=8,1,0) -> 0 | K27: =IF(MONTH($A27)=9,1,0) -> 0 | L27: =IF(MONTH($A27)=10,1,0) -> 0 | M27: =IF(MONTH($A27)=11,1,0) -> 0 | N27: =IF(MONTH($A27)=12,1,0) -> 0 | O27: =$B$5+SUMPRODUCT(C27:N27,$C$5:$N$5) -> 0.46401145 | P27: =B27-O27 -> -0.72378105 | Q27: =P27^2 -> 0.52385901 | R27: =(ROW()-ROW($A$7))/12 -> 1.6666667 | T27: Standard error of the estimate | U27: =INDEX(LINEST(B7:B34,C7:N34,TRUE(),TRUE()),3,2) -> 2.1152583 | V27: 2.1152583 | X27: M5 | Y27: =CORREL($C$7:$C$34,$G$7:$G$34) -> 0.060845544 | Z27: =CORREL($D$7:$D$34,$G$7:$G$34) -> -0.076923077 | AA27: =CORREL($E$7:$E$34,$G$7:$G$34) -> -0.076923077 | AB27: =CORREL($F$7:$F$34,$G$7:$G$34) -> -0.076923077 | AC27: =CORREL($G$7:$G$34,$G$7:$G$34) -> 1 | AD27: =CORREL($H$7:$H$34,$G$7:$G$34) -> -0.076923077 | AE27: =CORREL($I$7:$I$34,$G$7:$G$34) -> -0.076923077 | AF27: =CORREL($J$7:$J$34,$G$7:$G$34) -> -0.096076892 | AG27: =CORREL($K$7:$K$34,$G$7:$G$34) -> -0.096076892 | AH27: =CORREL($L$7:$L$34,$G$7:$G$34) -> -0.096076892 | AI27: =CORREL($M$7:$M$34,$G$7:$G$34) -> -0.096076892 | AJ27: =CORREL($N$7:$N$34,$G$7:$G$34) -> -0.076923077
A28: =Data_Monthly!A29 -> 45037 | B28: =Data_Monthly!K29 -> 0.1415809 | C28: =IF($A28>=$U$5,1,0) -> 1 | D28: =IF(MONTH($A28)=2,1,0) -> 0 | E28: =IF(MONTH($A28)=3,1,0) -> 0 | F28: =IF(MONTH($A28)=4,1,0) -> 1 | G28: =IF(MONTH($A28)=5,1,0) -> 0 | H28: =IF(MONTH($A28)=6,1,0) -> 0 | I28: =IF(MONTH($A28)=7,1,0) -> 0 | J28: =IF(MONTH($A28)=8,1,0) -> 0 | K28: =IF(MONTH($A28)=9,1,0) -> 0 | L28: =IF(MONTH($A28)=10,1,0) -> 0 | M28: =IF(MONTH($A28)=11,1,0) -> 0 | N28: =IF(MONTH($A28)=12,1,0) -> 0 | O28: =$B$5+SUMPRODUCT(C28:N28,$C$5:$N$5) -> 0.31543884 | P28: =B28-O28 -> -0.17385794 | Q28: =P28^2 -> 0.030226583 | R28: =(ROW()-ROW($A$7))/12 -> 1.75 | X28: M6 | Y28: =CORREL($C$7:$C$34,$H$7:$H$34) -> 0.060845544 | Z28: =CORREL($D$7:$D$34,$H$7:$H$34) -> -0.076923077 | AA28: =CORREL($E$7:$E$34,$H$7:$H$34) -> -0.076923077 | AB28: =CORREL($F$7:$F$34,$H$7:$H$34) -> -0.076923077 | AC28: =CORREL($G$7:$G$34,$H$7:$H$34) -> -0.076923077 | AD28: =CORREL($H$7:$H$34,$H$7:$H$34) -> 1 | AE28: =CORREL($I$7:$I$34,$H$7:$H$34) -> -0.076923077 | AF28: =CORREL($J$7:$J$34,$H$7:$H$34) -> -0.096076892 | AG28: =CORREL($K$7:$K$34,$H$7:$H$34) -> -0.096076892 | AH28: =CORREL($L$7:$L$34,$H$7:$H$34) -> -0.096076892 | AI28: =CORREL($M$7:$M$34,$H$7:$H$34) -> -0.096076892 | AJ28: =CORREL($N$7:$N$34,$H$7:$H$34) -> -0.076923077
